Workbook

Sheet Performance
F2: Health ( INR Lakhs) | G2: M01'19
F3: GWP | G3: =SuM!C8/100000 -> 32.378274
F4: NEP | G4: =SuM!C26/100000 -> 17.107531
F5: Claims (excluding IBNR)-33% of NEP | G5: =((60760+23748)*0.95)/100000 -> 0.802826 | I5: =G5*100000/G9 -> 743.35741
F6: Claims (including IBNR)-95% of NEP | G6: =((60760+23748)*0.95+154370)/100000 -> 2.346526
F7: Claims service cost(3% of claims) | G7: =3%*G6 -> 0.07039578
F8: No. of Policies | G8: 1592
F9: No. of Claims | G9: 108

Sheet SuM
A1: =C41&":" -> A V GLOBAL CORPORATION PRIVATE LIMITED:
A2: Particulars | C2: Number/₹ | D2: 202602
A3: No of Lives Insured | C3: =SUMIF(Details!B:B,$D$2,Details!AD:AD) -> 11
A4: GWP excl GST | C4: =SUMIF(Details!B:B,$D$2,Details!AE:AE) -> 14562.143
A6: Particulars | B6: Details | C6: Total | E6: 45809 | F6: 45839 | G6: 45870 | H6: 45901 | I6: 45931 | J6: 45962 | K6: 45992 | L6: 46023 | M6: 46054 | O6: Recon
A8: GWP | C8: =Details!AE1 -> 3237827.4 | E8: 3079000.2 | F8: 53716.788 | G8: 25267.084 | H8: 4579.028 | I8: 52998.261 | J8: 3191.5687 | K8: 4512.3233 | L8: 0 | M8: =SUMIF(Details!$B:$B,$D$2,Details!$AE:$AE) -> 14562.143 | O8: =$C8-SUM(E8:M8) -> 0
O9: =$C9-SUM(E9:M9) -> 0
A10: GST: | O10: =$C10-SUM(E10:M10) -> 0
A11: SGST/UGST | C11: =Details!AF1 -> 0 | E11: 0 | F11: 0 | G11: 0 | H11: 0 | I11: 0 | J11: 0 | K11: 0 | L11: 0 | M11: =SUMIF(Details!$B:$B,$D$2,Details!$AF:$AF) -> 0 | O11: =$C11-SUM(E11:M11) -> 0
A12: CGST | C12: =Details!AG1 -> 0 | E12: 0 | F12: 0 | G12: 0 | H12: 0 | I12: 0 | J12: 0 | K12: 0 | L12: 0 | M12: =SUMIF(Details!$B:$B,$D$2,Details!$AG:$AG) -> 0 | O12: =$C12-SUM(E12:M12) -> 0
A13: IGST | C13: =Details!AH1 -> 582808.93 | E13: 554220.03 | F13: 9669.0218 | G13: 4548.0751 | H13: 824.22504 | I13: 9539.687 | J13: 574.48236 | K13: 812.21819 | L13: 0 | M13: =SUMIF(Details!$B:$B,$D$2,Details!$AH:$AH) -> 2621.1858 | O13: =$C13-SUM(E13:M13) -> 0
A14: Total GST | C14: =SUM(C11:C13) -> 582808.93 | E14: 554220.03 | F14: 9669.0218 | G14: 4548.0751 | H14: 824.22504 | I14: 9539.687 | J14: 574.48236 | K14: 812.21819 | L14: 0 | M14: =SUM(M11:M13) -> 2621.1858 | O14: =$C14-SUM(E14:M14) -> 0
O15: =$C15-SUM(E15:M15) -> 0
A16: Reinsurance Premium: | O16: =$C16-SUM(E16:M16) -> 0
A17: Reinsurance Premium - Obligatory | C17: =Details!AI1 -> 129513.09 | E17: 123160.01 | F17: 2148.6715 | G17: 1010.6834 | H17: 183.16112 | I17: 2119.9304 | J17: 127.66275 | K17: 180.49293 | L17: 0 | M17: =SUMIF(Details!$B:$B,$D$2,Details!$AI:$AI) -> 582.48572 | O17: =$C17-SUM(E17:M17) -> 0
A18: Reinsurance Premium - Quota Share | C18: =Details!AJ1 -> 728511.16 | E18: 692775.04 | F18: 12086.277 | G18: 5685.0939 | H18: 1030.2813 | I18: 11924.609 | J18: 718.10295 | K18: 1015.2727 | L18: 0 | M18: =SUMIF(Details!$B:$B,$D$2,Details!$AJ:$AJ) -> 3276.4822 | O18: =$C18-SUM(E18:M18) -> 0
O19: =$C19-SUM(E19:M19) -> 0
A20: Commission on Reinsurance Premium: | O20: =$C20-SUM(E20:M20) -> 0
A21: Reinsurance Commission - Obligatory | C21: =ROUND(C17*10%,0) -> 12951 | E21: 12316 | F21: 215 | G21: 101 | H21: 18 | I21: 212 | J21: 13 | K21: 18 | L21: 0 | M21: =ROUND(M17*10%,0) -> 58 | O21: =$C21-SUM(E21:M21) -> 0
A22: Reinsurance Commission - Quota Share | C22: =ROUND(C18*50%,0) -> 364256 | E22: 346388 | F22: 6043 | G22: 2843 | H22: 515 | I22: 5962 | J22: 359 | K22: 508 | L22: 0 | M22: =ROUND(M18*50%,0) -> 1638 | O22: =$C22-SUM(E22:M22) -> 0
E23: 0 | F23: 0 | G23: 0 | H23: 0 | I23: 0 | J23: 0 | K23: 0 | L23: 0 | M23: =ROUND(M19*10%,0) -> 0 | O23: =$C23-SUM(E23:M23) -> 0
A24: GEP | C24: =Details!AK1 -> 2327555.2 | E24: 177147.95 | F24: 266344.88 | G24: 269822 | H24: 259522.77 | I24: 280278.25 | J24: 266764.71 | K24: 275927.86 | L24: 276569.75 | M24: =$C24-SUM($D24:L24) -> 255177 | O24: =$C24-SUM(E24:M24) -> 0
O25: =$C25-SUM(E25:M25) -> 0
A26: NEP | C26: =Details!AL1 -> 1710753.1 | E26: 130203.75 | F26: 195763.49 | G26: 198319.17 | H26: 190749.24 | I26: 206004.51 | J26: 196072.06 | K26: 202806.97 | L26: 203278.77 | M26: =$C26-SUM($D26:L26) -> 187555.1 | O26: =$C26-SUM(E26:M26) -> 0
O27: =$C27-SUM(E27:M27) -> 0
A28: NURR | C28: =C8-C17-C26-C18 -> 669050.05 | E28: 2132861.4 | F28: -156281.65 | G28: -179747.87 | H28: -187383.65 | I28: -167050.79 | J28: -193726.26 | K28: -199490.42 | L28: -203278.77 | M28: =M8-M17-M26-M18 -> -176851.92 | O28: =$C28-SUM(E28:M28) -> 2.7939677e-09
O29: =$C29-SUM(E29:M29) -> 0
A30: Total No of COI/No of Plan Sold | C30: =Details!X1 -> 245 | E30: 232 | F30: 5 | G30: 2 | H30: 3 | I30: 2 | J30: 0 | K30: -1 | L30: 0 | M30: =SUMIF(Details!$B:$B,$D$2,Details!$X:$X) -> 2 | O30: =$C30-SUM(E30:M30) -> 0
O31: =$C31-SUM(E31:M31) -> 0
A32: Total No of Life Cover | C32: =Details!AD1 -> 688 | E32: 645 | F32: 15 | G32: 5 | H32: 3 | I32: 6 | J32: 1 | K32: 2 | L32: 0 | M32: =SUMIF(Details!$B:$B,$D$2,Details!$AD:$AD) -> 11 | O32: =$C32-SUM(E32:M32) -> 0
O33: =$C33-SUM(E33:M33) -> 0
A34: KMD Insurance Brokerage - 9.75% | O34: =$C34-SUM(E34:M34) -> 0
A35: Commission | C35: =9.75%*C8 -> 315688.17 | E35: 300202.52 | F35: 5237.3868 | G35: 2463.5407 | H35: 446.45523 | I35: 5167.3304 | J35: 311.17794 | K35: 439.95152 | L35: 0 | M35: =$C35-SUM($D35:L35) -> 1419.8089 | O35: =$C35-SUM(E35:M35) -> 0
O36: =$C36-SUM(E36:M36) -> 0
A37: Total SA | C37: =Details!W1 -> 79100000 | E37: 73100000 | F37: 1500000 | G37: 600000 | H37: 1600000 | I37: 2000000 | J37: 0 | K37: -300000 | L37: 0 | M37: =$C37-SUM($D37:L37) -> 600000 | O37: =$C37-SUM(E37:M37) -> 0
O38: =$C38-SUM(E38:M38) -> 0
A39: Master Policy No (Passenger) | C39: =Details!C3 -> GMC021090100AV
A40: Period | C40: : 10-06-2025 to 09-06-2026
A41: Proposer Name | C41: =Details!D3 -> A V GLOBAL CORPORATION PRIVATE LIMITED
A43: Name on Premium Summary | B43: A V GLOBAL-GMC-GMC021090100AV
A44: Master Policy No | B44: =Details!C3 -> GMC021090100AV
A45: Master Start Date | B45: =Details!E3 -> 45818
A46: Master End Date | B46: =Details!F3 -> 46182
A47: State | B47: =Details!AB3 -> Delhi
A48: Business Name | B48: Health
A49: Product Name | B49: Health-GMC for Employee
A50: Cost Centre Details | B50: Health
A51: Channel | B51: KMD
A52: Name of Intermediary | B52: NA
A53: Intermediary Type | B53: =B51 -> KMD
A54: Oracle Product Code
A55: Oracle Cost Centre | B55: 706
A56: Oracle Sales Channel
A57: Premium Deposit GL No
A58: Policy Type | B58: Fresh
A59: Cover Type
A60: Sector
A61: Future 1
A62: Future 2
A63: Future 3
A64: Future 4
A65: Future 5

Sheet Details
V1: =ROUND(SUM(V3:V1048576),0) -> 216200000 | W1: =ROUND(SUM(W3:W1048576),0) -> 79100000 | X1: =ROUND(SUM(X3:X1048576),0) -> 245 | Z1: 46081 | AB1: Total | AC1: =ROUND(SUM(AC3:AC1048576),0) -> 3820636 | AD1: =ROUND(SUM(AD3:AD1048576),0) -> 688 | AE1: =SUM(AE3:AE1048576) -> 3237827.4 | AF1: =SUM(AF3:AF1048576) -> 0 | AG1: =SUM(AG3:AG1048576) -> 0 | AH1: =SUM(AH3:AH1048576) -> 582808.93 | AI1: =SUM(AI3:AI1048576) -> 129513.09 | AJ1: =SUM(AJ3:AJ1048576) -> 728511.16 | AK1: =SUM(AK3:AK1048576) -> 2327555.2 | AL1: =SUM(AL3:AL1048576) -> 1710753.1 | AM1: =SUM(AM3:AM1048576) -> 669050.05 | AO1: =ROUND(SUM(AO3:AO1048576),0) -> 3237827
A2: Status | B2: Acct. Month | C2: Master Policy No | D2: Master Policy Holder Name | E2: Master Policy Risk Start Date | F2: Master Policy Risk End Date | G2: Name | H2: Emp ID | I2: DOB | J2: UHID | K2: Policy Risk Start Date | L2: Ri Obligatory | M2: RI Quota | N2: Risk Start Date | O2: Risk End Date | P2: Last Working Day | Q2: Reversal Date | R2: Age | S2: Age Band | T2: Gender | U2: Relationship | V2: Sum Insured | W2: Reporting Sum Insured | X2: No of Policies | Y2: Risk Days | Z2: Base Date | AA2: Used | AB2: State | AC2: Gross Premium | AD2: No of Person Cover Per Day | AE2: GWP | AF2: SGST/UGST | AG2: CGST | AH2: IGST | AI2: Reinsurance Premium -Obligatory | AJ2: Reinsurance Premium -Quota | AK2: GEP | AL2: NEP | AM2: NURR | AN2: Unexpired Premium Date | AO2: Unexpired Premium | AP2: Claim Status
A3: Valid | B3: 202506 | C3: GMC021090100AV | D3: A V GLOBAL CORPORATION PRIVATE LIMITED | E3: 45818 | F3: 46182 | G3: Vijay Mehta | H3: 1001 | I3: 20323 | J3: ACK.F683A520250005.1 | K3: =N3 -> 45818 | L3: =IF(K3>=DATE(2022,4,1),4%,5%) -> 0.04 | M3: 0.225 | N3: 45818 | O3: 46182 | R3: 69 | S3: =VLOOKUP(R3,SA!$B$5:$C$11,2,1) -> 66-70 | T3: Male | U3: Self | V3: 1000000 | W3: =IF(U3="self",V3,0) -> 1000000 | X3: =IF(U3="self",1,0) -> 1 | Y3: =O3-N3+1 -> 365 | Z3: =$Z$1 -> 46081 | AA3: =IF(MIN((Z3-N3)+1,Y3)<0,0,MIN((Z3-N3)+1,Y3)) -> 264 | AB3: Delhi | AC3: =AE3+AF3+AG3+AH3 -> 64504.381 | AD3: 1 | AE3: =IFERROR(INDEX(SA!$C$4:$E$11,MATCH(Details!S3,SA!$C$4:$C$11,0),MATCH(Details!V3,SA!$C$4:$E$4,0)),0)*Y3/(F3-E3+1) -> 54664.73 | AF3: =IF(AB3="Karnataka",AE3*9%,0) -> 0 | AG3: =IF(AB3="Karnataka",AE3*9%,0) -> 0 | AH3: =IF(AF3+AG3>0,0,AE3*18%) -> 9839.6514 | AI3: =AE3*L3 -> 2186.5892 | AJ3: =$AE3*M3 -> 12299.564 | AK3: =(AE3)*AA3/Y3 -> 39538.325 | AL3: =AK3*(1-L3-M3) -> 29060.669 | AM3: =AE3-AI3-AL3-AJ3 -> 11117.907 | AN3: =Z3-366 -> 45715 | AO3: =IF(AND(O3>Z3,N3>AN3),AE3,0) -> 54664.73
A4: Valid | B4: 202506 | C4: GMC021090100AV | D4: A V GLOBAL CORPORATION PRIVATE LIMITED | E4: 45818 | F4: 46182 | G4: Geeta Mehta | H4: 1001 | I4: 22717 | J4: ACK.F683A520250005.2 | K4: =N4 -> 45818 | L4: =IF(K4>=DATE(2022,4,1),4%,5%) -> 0.04 | M4: 0.225 | N4: 45818 | O4: 46182 | R4: 63 | S4: =VLOOKUP(R4,SA!$B$5:$C$11,2,1) -> 56-65 | T4: Female | U4: Spouse | V4: 1000000 | W4: =IF(U4="self",V4,0) -> 0 | X4: =IF(U4="self",1,0) -> 0 | Y4: =O4-N4+1 -> 365 | Z4: =$Z$1 -> 46081 | AA4: =IF(MIN((Z4-N4)+1,Y4)<0,0,MIN((Z4-N4)+1,Y4)) -> 264 | AB4: Delhi | AC4: =AE4+AF4+AG4+AH4 -> 30696.579 | AD4: 1 | AE4: =IFERROR(INDEX(SA!$C$4:$E$11,MATCH(Details!S4,SA!$C$4:$C$11,0),MATCH(Details!V4,SA!$C$4:$E$4,0)),0)*Y4/(F4-E4+1) -> 26014.05 | AF4: =IF(AB4="Karnataka",AE4*9%,0) -> 0 | AG4: =IF(AB4="Karnataka",AE4*9%,0) -> 0 | AH4: =IF(AF4+AG4>0,0,AE4*18%) -> 4682.529 | AI4: =AE4*L4 -> 1040.562 | AJ4: =$AE4*M4 -> 5853.1613 | AK4: =(AE4)*AA4/Y4 -> 18815.642 | AL4: =AK4*(1-L4-M4) -> 13829.497 | AM4: =AE4-AI4-AL4-AJ4 -> 5290.8301 | AN4: =Z4-366 -> 45715 | AO4: =IF(AND(O4>Z4,N4>AN4),AE4,0) -> 26014.05
A5: Valid | B5: 202506 | C5: GMC021090100AV | D5: A V GLOBAL CORPORATION PRIVATE LIMITED | E5: 45818 | F5: 46182 | G5: Ashok Kumar Mehta | H5: 1002 | I5: 19982 | J5: ACK.F683A520250002.1 | K5: =N5 -> 45818 | L5: =IF(K5>=DATE(2022,4,1),4%,5%) -> 0.04 | M5: 0.225 | N5: 45818 | O5: 46182 | R5: 70 | S5: =VLOOKUP(R5,SA!$B$5:$C$11,2,1) -> 66-70 | T5: Male | U5: Self | V5: 1000000 | W5: =IF(U5="self",V5,0) -> 1000000 | X5: =IF(U5="self",1,0) -> 1 | Y5: =O5-N5+1 -> 365 | Z5: =$Z$1 -> 46081 | AA5: =IF(MIN((Z5-N5)+1,Y5)<0,0,MIN((Z5-N5)+1,Y5)) -> 264 | AB5: Delhi | AC5: =AE5+AF5+AG5+AH5 -> 64504.381 | AD5: 1 | AE5: =IFERROR(INDEX(SA!$C$4:$E$11,MATCH(Details!S5,SA!$C$4:$C$11,0),MATCH(Details!V5,SA!$C$4:$E$4,0)),0)*Y5/(F5-E5+1) -> 54664.73 | AF5: =IF(AB5="Karnataka",AE5*9%,0) -> 0 | AG5: =IF(AB5="Karnataka",AE5*9%,0) -> 0 | AH5: =IF(AF5+AG5>0,0,AE5*18%) -> 9839.6514 | AI5: =AE5*L5 -> 2186.5892 | AJ5: =$AE5*M5 -> 12299.564 | AK5: =(AE5)*AA5/Y5 -> 39538.325 | AL5: =AK5*(1-L5-M5) -> 29060.669 | AM5: =AE5-AI5-AL5-AJ5 -> 11117.907 | AN5: =Z5-366 -> 45715 | AO5: =IF(AND(O5>Z5,N5>AN5),AE5,0) -> 54664.73
A6: Valid | B6: 202506 | C6: GMC021090100AV | D6: A V GLOBAL CORPORATION PRIVATE LIMITED | E6: 45818 | F6: 46182 | G6: Ratnesh Kumar Jha | H6: 1004 | I6: 28185 | J6: ACK.F683A520250003.1 | K6: =N6 -> 45818 | L6: =IF(K6>=DATE(2022,4,1),4%,5%) -> 0.04 | M6: 0.225 | N6: 45818 | O6: 46182 | R6: 48 | S6: =VLOOKUP(R6,SA!$B$5:$C$11,2,1) -> 46-55 | T6: Male | U6: Self | V6: 300000 | W6: =IF(U6="self",V6,0) -> 300000 | X6: =IF(U6="self",1,0) -> 1 | Y6: =O6-N6+1 -> 365 | Z6: =$Z$1 -> 46081 | AA6: =IF(MIN((Z6-N6)+1,Y6)<0,0,MIN((Z6-N6)+1,Y6)) -> 264 | AB6: Delhi | AC6: =AE6+AF6+AG6+AH6 -> 9586.9926 | AD6: 1 | AE6: =IFERROR(INDEX(SA!$C$4:$E$11,MATCH(Details!S6,SA!$C$4:$C$11,0),MATCH(Details!V6,SA!$C$4:$E$4,0)),0)*Y6/(F6-E6+1) -> 8124.57 | AF6: =IF(AB6="Karnataka",AE6*9%,0) -> 0 | AG6: =IF(AB6="Karnataka",AE6*9%,0) -> 0 | AH6: =IF(AF6+AG6>0,0,AE6*18%) -> 1462.4226 | AI6: =AE6*L6 -> 324.9828 | AJ6: =$AE6*M6 -> 1828.0283 | AK6: =(AE6)*AA6/Y6 -> 5876.4013 | AL6: =AK6*(1-L6-M6) -> 4319.155 | AM6: =AE6-AI6-AL6-AJ6 -> 1652.404 | AN6: =Z6-366 -> 45715 | AO6: =IF(AND(O6>Z6,N6>AN6),AE6,0) -> 8124.57
A7: Valid | B7: 202506 | C7: GMC021090100AV | D7: A V GLOBAL CORPORATION PRIVATE LIMITED | E7: 45818 | F7: 46182 | G7: Ashwani Kumar Jha | H7: 1004 | I7: 38297 | J7: ACK.F683A520250003.2 | K7: =N7 -> 45818 | L7: =IF(K7>=DATE(2022,4,1),4%,5%) -> 0.04 | M7: 0.225 | N7: 45818 | O7: 46182 | R7: 20 | S7: =VLOOKUP(R7,SA!$B$5:$C$11,2,1) -> 0-35 | T7: Male | U7: Son | V7: 300000 | W7: =IF(U7="self",V7,0) -> 0 | X7: =IF(U7="self",1,0) -> 0 | Y7: =O7-N7+1 -> 365 | Z7: =$Z$1 -> 46081 | AA7: =IF(MIN((Z7-N7)+1,Y7)<0,0,MIN((Z7-N7)+1,Y7)) -> 264 | AB7: Delhi | AC7: =AE7+AF7+AG7+AH7 -> 3874.2114 | AD7: 1 | AE7: =IFERROR(INDEX(SA!$C$4:$E$11,MATCH(Details!S7,SA!$C$4:$C$11,0),MATCH(Details!V7,SA!$C$4:$E$4,0)),0)*Y7/(F7-E7+1) -> 3283.23 | AF7: =IF(AB7="Karnataka",AE7*9%,0) -> 0 | AG7: =IF(AB7="Karnataka",AE7*9%,0) -> 0 | AH7: =IF(AF7+AG7>0,0,AE7*18%) -> 590.9814 | AI7: =AE7*L7 -> 131.3292 | AJ7: =$AE7*M7 -> 738.72675 | AK7: =(AE7)*AA7/Y7 -> 2374.7198 | AL7: =AK7*(1-L7-M7) -> 1745.419 | AM7: =AE7-AI7-AL7-AJ7 -> 667.75501 | AN7: =Z7-366 -> 45715 | AO7: =IF(AND(O7>Z7,N7>AN7),AE7,0) -> 3283.23
A8: Valid | B8: 202506 | C8: GMC021090100AV | D8: A V GLOBAL CORPORATION PRIVATE LIMITED | E8: 45818 | F8: 46182 | G8: Ankit Kumar Jha | H8: 1004 | I8: 39723 | J8: ACK.F683A520250003.3 | K8: =N8 -> 45818 | L8: =IF(K8>=DATE(2022,4,1),4%,5%) -> 0.04 | M8: 0.225 | N8: 45818 | O8: 46182 | R8: 16 | S8: =VLOOKUP(R8,SA!$B$5:$C$11,2,1) -> 0-35 | T8: Male | U8: Son | V8: 300000 | W8: =IF(U8="self",V8,0) -> 0 | X8: =IF(U8="self",1,0) -> 0 | Y8: =O8-N8+1 -> 365 | Z8: =$Z$1 -> 46081 | AA8: =IF(MIN((Z8-N8)+1,Y8)<0,0,MIN((Z8-N8)+1,Y8)) -> 264 | AB8: Delhi | AC8: =AE8+AF8+AG8+AH8 -> 3874.2114 | AD8: 1 | AE8: =IFERROR(INDEX(SA!$C$4:$E$11,MATCH(Details!S8,SA!$C$4:$C$11,0),MATCH(Details!V8,SA!$C$4:$E$4,0)),0)*Y8/(F8-E8+1) -> 3283.23 | AF8: =IF(AB8="Karnataka",AE8*9%,0) -> 0 | AG8: =IF(AB8="Karnataka",AE8*9%,0) -> 0 | AH8: =IF(AF8+AG8>0,0,AE8*18%) -> 590.9814 | AI8: =AE8*L8 -> 131.3292 | AJ8: =$AE8*M8 -> 738.72675 | AK8: =(AE8)*AA8/Y8 -> 2374.7198 | AL8: =AK8*(1-L8-M8) -> 1745.419 | AM8: =AE8-AI8-AL8-AJ8 -> 667.75501 | AN8: =Z8-366 -> 45715 | AO8: =IF(AND(O8>Z8,N8>AN8),AE8,0) -> 3283.23
A9: Valid | B9: 202506 | C9: GMC021090100AV | D9: A V GLOBAL CORPORATION PRIVATE LIMITED | E9: 45818 | F9: 46182 | G9: Gudiya Jha | H9: 1004 | I9: 31215 | J9: ACK.F683A520250003.4 | K9: =N9 -> 45818 | L9: =IF(K9>=DATE(2022,4,1),4%,5%) -> 0.04 | M9: 0.225 | N9: 45818 | O9: 46182 | R9: 39 | S9: =VLOOKUP(R9,SA!$B$5:$C$11,2,1) -> 36-45 | T9: Female | U9: Spouse | V9: 300000 | W9: =IF(U9="self",V9,0) -> 0 | X9: =IF(U9="self",1,0) -> 0 | Y9: =O9-N9+1 -> 365 | Z9: =$Z$1 -> 46081 | AA9: =IF(MIN((Z9-N9)+1,Y9)<0,0,MIN((Z9-N9)+1,Y9)) -> 264 | AB9: Delhi | AC9: =AE9+AF9+AG9+AH9 -> 5017.3246 | AD9: 1 | AE9: =IFERROR(INDEX(SA!$C$4:$E$11,MATCH(Details!S9,SA!$C$4:$C$11,0),MATCH(Details!V9,SA!$C$4:$E$4,0)),0)*Y9/(F9-E9+1) -> 4251.97 | AF9: =IF(AB9="Karnataka",AE9*9%,0) -> 0 | AG9: =IF(AB9="Karnataka",AE9*9%,0) -> 0 | AH9: =IF(AF9+AG9>0,0,AE9*18%) -> 765.3546 | AI9: =AE9*L9 -> 170.0788 | AJ9: =$AE9*M9 -> 956.69325 | AK9: =(AE9)*AA9/Y9 -> 3075.3975 | AL9: =AK9*(1-L9-M9) -> 2260.4171 | AM9: =AE9-AI9-AL9-AJ9 -> 864.7808 | AN9: =Z9-366 -> 45715 | AO9: =IF(AND(O9>Z9,N9>AN9),AE9,0) -> 4251.97
A10: Valid | B10: 202506 | C10: GMC021090100AV | D10: A V GLOBAL CORPORATION PRIVATE LIMITED | E10: 45818 | F10: 46182 | G10: Ritesh Ranjan | H10: 1005 | I10: 27820 | J10: ACK.F683A520250006.1 | K10: =N10 -> 45818 | L10: =IF(K10>=DATE(2022,4,1),4%,5%) -> 0.04 | M10: 0.225 | N10: 45818 | O10: 46182 | R10: 49 | S10: =VLOOKUP(R10,SA!$B$5:$C$11,2,1) -> 46-55 | T10: Male | U10: Self | V10: 300000 | W10: =IF(U10="self",V10,0) -> 300000 | X10: =IF(U10="self",1,0) -> 1 | Y10: =O10-N10+1 -> 365 | Z10: =$Z$1 -> 46081 | AA10: =IF(MIN((Z10-N10)+1,Y10)<0,0,MIN((Z10-N10)+1,Y10)) -> 264 | AB10: Delhi | AC10: =AE10+AF10+AG10+AH10 -> 9586.9926 | AD10: 1 | AE10: =IFERROR(INDEX(SA!$C$4:$E$11,MATCH(Details!S10,SA!$C$4:$C$11,0),MATCH(Details!V10,SA!$C$4:$E$4,0)),0)*Y10/(F10-E10+1) -> 8124.57 | AF10: =IF(AB10="Karnataka",AE10*9%,0) -> 0 | AG10: =IF(AB10="Karnataka",AE10*9%,0) -> 0 | AH10: =IF(AF10+AG10>0,0,AE10*18%) -> 1462.4226 | AI10: =AE10*L10 -> 324.9828 | AJ10: =$AE10*M10 -> 1828.0283 | AK10: =(AE10)*AA10/Y10 -> 5876.4013 | AL10: =AK10*(1-L10-M10) -> 4319.155 | AM10: =AE10-AI10-AL10-AJ10 -> 1652.404 | AN10: =Z10-366 -> 45715 | AO10: =IF(AND(O10>Z10,N10>AN10),AE10,0) -> 8124.57
A11: Valid | B11: 202506 | C11: GMC021090100AV | D11: A V GLOBAL CORPORATION PRIVATE LIMITED | E11: 45818 | F11: 46182 | G11: Neetu Singh | H11: 1005 | I11: 30722 | J11: ACK.F683A520250006.2 | K11: =N11 -> 45818 | L11: =IF(K11>=DATE(2022,4,1),4%,5%) -> 0.04 | M11: 0.225 | N11: 45818 | O11: 46182 | R11: 41 | S11: =VLOOKUP(R11,SA!$B$5:$C$11,2,1) -> 36-45 | T11: Female | U11: Spouse | V11: 300000 | W11: =IF(U11="self",V11,0) -> 0 | X11: =IF(U11="self",1,0) -> 0 | Y11: =O11-N11+1 -> 365 | Z11: =$Z$1 -> 46081 | AA11: =IF(MIN((Z11-N11)+1,Y11)<0,0,MIN((Z11-N11)+1,Y11)) -> 264 | AB11: Delhi | AC11: =AE11+AF11+AG11+AH11 -> 5017.3246 | AD11: 1 | AE11: =IFERROR(INDEX(SA!$C$4:$E$11,MATCH(Details!S11,SA!$C$4:$C$11,0),MATCH(Details!V11,SA!$C$4:$E$4,0)),0)*Y11/(F11-E11+1) -> 4251.97 | AF11: =IF(AB11="Karnataka",AE11*9%,0) -> 0 | AG11: =IF(AB11="Karnataka",AE11*9%,0) -> 0 | AH11: =IF(AF11+AG11>0,0,AE11*18%) -> 765.3546 | AI11: =AE11*L11 -> 170.0788 | AJ11: =$AE11*M11 -> 956.69325 | AK11: =(AE11)*AA11/Y11 -> 3075.3975 | AL11: =AK11*(1-L11-M11) -> 2260.4171 | AM11: =AE11-AI11-AL11-AJ11 -> 864.7808 | AN11: =Z11-366 -> 45715 | AO11: =IF(AND(O11>Z11,N11>AN11),AE11,0) -> 4251.97
A12: Valid | B12: 202506 | C12: GMC021090100AV | D12: A V GLOBAL CORPORATION PRIVATE LIMITED | E12: 45818 | F12: 46182 | G12: Vanshika Singh | H12: 1005 | I12: 38757 | J12: ACK.F683A520250006.3 | K12: =N12 -> 45818 | L12: =IF(K12>=DATE(2022,4,1),4%,5%) -> 0.04 | M12: 0.225 | N12: 45818 | O12: 46182 | R12: 19 | S12: =VLOOKUP(R12,SA!$B$5:$C$11,2,1) -> 0-35 | T12: Female | U12: Daughter | V12: 300000 | W12: =IF(U12="self",V12,0) -> 0 | X12: =IF(U12="self",1,0) -> 0 | Y12: =O12-N12+1 -> 365 | Z12: =$Z$1 -> 46081 | AA12: =IF(MIN((Z12-N12)+1,Y12)<0,0,MIN((Z12-N12)+1,Y12)) -> 264 | AB12: Delhi | AC12: =AE12+AF12+AG12+AH12 -> 3874.2114 | AD12: 1 | AE12: =IFERROR(INDEX(SA!$C$4:$E$11,MATCH(Details!S12,SA!$C$4:$C$11,0),MATCH(Details!V12,SA!$C$4:$E$4,0)),0)*Y12/(F12-E12+1) -> 3283.23 | AF12: =IF(AB12="Karnataka",AE12*9%,0) -> 0 | AG12: =IF(AB12="Karnataka",AE12*9%,0) -> 0 | AH12: =IF(AF12+AG12>0,0,AE12*18%) -> 590.9814 | AI12: =AE12*L12 -> 131.3292 | AJ12: =$AE12*M12 -> 738.72675 | AK12: =(AE12)*AA12/Y12 -> 2374.7198 | AL12: =AK12*(1-L12-M12) -> 1745.419 | AM12: =AE12-AI12-AL12-AJ12 -> 667.75501 | AN12: =Z12-366 -> 45715 | AO12: =IF(AND(O12>Z12,N12>AN12),AE12,0) -> 3283.23
A13: Valid | B13: 202506 | C13: GMC021090100AV | D13: A V GLOBAL CORPORATION PRIVATE LIMITED | E13: 45818 | F13: 46182 | G13: Vaibhav Singh | H13: 1005 | I13: 39150 | J13: ACK.F683A520250006.4 | K13: =N13 -> 45818 | L13: =IF(K13>=DATE(2022,4,1),4%,5%) -> 0.04 | M13: 0.225 | N13: 45818 | O13: 46182 | R13: 18 | S13: =VLOOKUP(R13,SA!$B$5:$C$11,2,1) -> 0-35 | T13: Male | U13: Son | V13: 300000 | W13: =IF(U13="self",V13,0) -> 0 | X13: =IF(U13="self",1,0) -> 0 | Y13: =O13-N13+1 -> 365 | Z13: =$Z$1 -> 46081 | AA13: =IF(MIN((Z13-N13)+1,Y13)<0,0,MIN((Z13-N13)+1,Y13)) -> 264 | AB13: Delhi | AC13: =AE13+AF13+AG13+AH13 -> 3874.2114 | AD13: 1 | AE13: =IFERROR(INDEX(SA!$C$4:$E$11,MATCH(Details!S13,SA!$C$4:$C$11,0),MATCH(Details!V13,SA!$C$4:$E$4,0)),0)*Y13/(F13-E13+1) -> 3283.23 | AF13: =IF(AB13="Karnataka",AE13*9%,0) -> 0 | AG13: =IF(AB13="Karnataka",AE13*9%,0) -> 0 | AH13: =IF(AF13+AG13>0,0,AE13*18%) -> 590.9814 | AI13: =AE13*L13 -> 131.3292 | AJ13: =$AE13*M13 -> 738.72675 | AK13: =(AE13)*AA13/Y13 -> 2374.7198 | AL13: =AK13*(1-L13-M13) -> 1745.419 | AM13: =AE13-AI13-AL13-AJ13 -> 667.75501 | AN13: =Z13-366 -> 45715 | AO13: =IF(AND(O13>Z13,N13>AN13),AE13,0) -> 3283.23
A14: Valid | B14: 202506 | C14: GMC021090100AV | D14: A V GLOBAL CORPORATION PRIVATE LIMITED | E14: 45818 | F14: 46182 | G14: Mini Surendran | H14: 1006 | I14: 25363 | J14: ACK.F683A520250004.1 | K14: =N14 -> 45818 | L14: =IF(K14>=DATE(2022,4,1),4%,5%) -> 0.04 | M14: 0.225 | N14: 45818 | O14: 46182 | R14: 56 | S14: =VLOOKUP(R14,SA!$B$5:$C$11,2,1) -> 56-65 | T14: Female | U14: Self | V14: 300000 | W14: =IF(U14="self",V14,0) -> 300000 | X14: =IF(U14="self",1,0) -> 1 | Y14: =O14-N14+1 -> 365 | Z14: =$Z$1 -> 46081 | AA14: =IF(MIN((Z14-N14)+1,Y14)<0,0,MIN((Z14-N14)+1,Y14)) -> 264 | AB14: Delhi | AC14: =AE14+AF14+AG14+AH14 -> 16811.448 | AD14: 1 | AE14: =IFERROR(INDEX(SA!$C$4:$E$11,MATCH(Details!S14,SA!$C$4:$C$11,0),MATCH(Details!V14,SA!$C$4:$E$4,0)),0)*Y14/(F14-E14+1) -> 14246.99 | AF14: =IF(AB14="Karnataka",AE14*9%,0) -> 0 | AG14: =IF(AB14="Karnataka",AE14*9%,0) -> 0 | AH14: =IF(AF14+AG14>0,0,AE14*18%) -> 2564.4582 | AI14: =AE14*L14 -> 569.8796 | AJ14: =$AE14*M14 -> 3205.5727 | AK14: =(AE14)*AA14/Y14 -> 10304.672 | AL14: =AK14*(1-L14-M14) -> 7573.9341 | AM14: =AE14-AI14-AL14-AJ14 -> 2897.6036 | AN14: =Z14-366 -> 45715 | AO14: =IF(AND(O14>Z14,N14>AN14),AE14,0) -> 14246.99
... A582: Valid | B582: 202506 | C582: GMC021090100AV | D582: A V GLOBAL CORPORATION PRIVATE LIMITED | E582: 45818 | F582: 46182 | G582: S Shazia | H582: 4019 | I582: 44815 | J582: ACK.F683A520250228.4 | K582: =N582 -> 45818 | L582: =IF(K582>=DATE(2022,4,1),4%,5%) -> 0.04 | M582: 0.225 | N582: 45818 | O582: 46182 | R582: 2 | S582: =VLOOKUP(R582,SA!$B$5:$C$11,2,1) -> 0-35 | T582: Female | U582: Daughter | V582: 300000 | W582: =IF(U582="self",V582,0) -> 0 | X582: =IF(U582="self",1,0) -> 0 | Y582: =O582-N582+1 -> 365 | Z582: =$Z$1 -> 46081 | AA582: =IF(MIN((Z582-N582)+1,Y582)<0,0,MIN((Z582-N582)+1,Y582)) -> 264 | AB582: Delhi | AC582: =AE582+AF582+AG582+AH582 -> 3874.2114 | AD582: 1 | AE582: =IFERROR(INDEX(SA!$C$4:$E$11,MATCH(Details!S582,SA!$C$4:$C$11,0),MATCH(Details!V582,SA!$C$4:$E$4,0)),0)*Y582/(F582-E582+1) -> 3283.23 | AF582: =IF(AB582="Karnataka",AE582*9%,0) -> 0 | AG582: =IF(AB582="Karnataka",AE582*9%,0) -> 0 | AH582: =IF(AF582+AG582>0,0,AE582*18%) -> 590.9814 | AI582: =AE582*L582 -> 131.3292 | AJ582: =$AE582*M582 -> 738.72675 | AK582: =(AE582)*AA582/Y582 -> 2374.7198 | AL582: =AK582*(1-L582-M582) -> 1745.419 | AM582: =AE582-AI582-AL582-AJ582 -> 667.75501 | AN582: =Z582-366 -> 45715 | AO582: =IF(AND(O582>Z582,N582>AN582),AE582,0) -> 3283.23
A583: Valid | B583: 202506 | C583: GMC021090100AV | D583: A V GLOBAL CORPORATION PRIVATE LIMITED | E583: 45818 | F583: 46182 | G583: Anand Kumar Jha | H583: AVGCT1 | I583: 34395 | J583: ACK.F683A520250226.1 | K583: =N583 -> 45818 | L583: =IF(K583>=DATE(2022,4,1),4%,5%) -> 0.04 | M583: 0.225 | N583: 45818 | O583: 46182 | R583: 31 | S583: =VLOOKUP(R583,SA!$B$5:$C$11,2,1) -> 0-35 | T583: Male | U583: Self | V583: 300000 | W583: =IF(U583="self",V583,0) -> 300000 | X583: =IF(U583="self",1,0) -> 1 | Y583: =O583-N583+1 -> 365 | Z583: =$Z$1 -> 46081 | AA583: =IF(MIN((Z583-N583)+1,Y583)<0,0,MIN((Z583-N583)+1,Y583)) -> 264 | AB583: Delhi | AC583: =AE583+AF583+AG583+AH583 -> 3874.2114 | AD583: 1 | AE583: =IFERROR(INDEX(SA!$C$4:$E$11,MATCH(Details!S583,SA!$C$4:$C$11,0),MATCH(Details!V583,SA!$C$4:$E$4,0)),0)*Y583/(F583-E583+1) -> 3283.23 | AF583: =IF(AB583="Karnataka",AE583*9%,0) -> 0 | AG583: =IF(AB583="Karnataka",AE583*9%,0) -> 0 | AH583: =IF(AF583+AG583>0,0,AE583*18%) -> 590.9814 | AI583: =AE583*L583 -> 131.3292 | AJ583: =$AE583*M583 -> 738.72675 | AK583: =(AE583)*AA583/Y583 -> 2374.7198 | AL583: =AK583*(1-L583-M583) -> 1745.419 | AM583: =AE583-AI583-AL583-AJ583 -> 667.75501 | AN583: =Z583-366 -> 45715 | AO583: =IF(AND(O583>Z583,N583>AN583),AE583,0) -> 3283.23
A584: Valid | B584: 202506 | C584: GMC021090100AV | D584: A V GLOBAL CORPORATION PRIVATE LIMITED | E584: 45818 | F584: 46182 | G584: Priyadarshani Kumari | H584: AVGCT1 | I584: 35124 | J584: ACK.F683A520250226.2 | K584: =N584 -> 45818 | L584: =IF(K584>=DATE(2022,4,1),4%,5%) -> 0.04 | M584: 0.225 | N584: 45818 | O584: 46182 | R584: 29 | S584: =VLOOKUP(R584,SA!$B$5:$C$11,2,1) -> 0-35 | T584: Female | U584: Spouse | V584: 300000 | W584: =IF(U584="self",V584,0) -> 0 | X584: =IF(U584="self",1,0) -> 0 | Y584: =O584-N584+1 -> 365 | Z584: =$Z$1 -> 46081 | AA584: =IF(MIN((Z584-N584)+1,Y584)<0,0,MIN((Z584-N584)+1,Y584)) -> 264 | AB584: Delhi | AC584: =AE584+AF584+AG584+AH584 -> 3874.2114 | AD584: 1 | AE584: =IFERROR(INDEX(SA!$C$4:$E$11,MATCH(Details!S584,SA!$C$4:$C$11,0),MATCH(Details!V584,SA!$C$4:$E$4,0)),0)*Y584/(F584-E584+1) -> 3283.23 | AF584: =IF(AB584="Karnataka",AE584*9%,0) -> 0 | AG584: =IF(AB584="Karnataka",AE584*9%,0) -> 0 | AH584: =IF(AF584+AG584>0,0,AE584*18%) -> 590.9814 | AI584: =AE584*L584 -> 131.3292 | AJ584: =$AE584*M584 -> 738.72675 | AK584: =(AE584)*AA584/Y584 -> 2374.7198 | AL584: =AK584*(1-L584-M584) -> 1745.419 | AM584: =AE584-AI584-AL584-AJ584 -> 667.75501 | AN584: =Z584-366 -> 45715 | AO584: =IF(AND(O584>Z584,N584>AN584),AE584,0) -> 3283.23
A585: Valid | B585: 202506 | C585: GMC021090100AV | D585: A V GLOBAL CORPORATION PRIVATE LIMITED | E585: 45818 | F585: 46182 | G585: Sanvi Jha | H585: AVGCT1 | I585: 44581 | J585: ACK.F683A520250226.3 | K585: =N585 -> 45818 | L585: =IF(K585>=DATE(2022,4,1),4%,5%) -> 0.04 | M585: 0.225 | N585: 45818 | O585: 46182 | R585: 3 | S585: =VLOOKUP(R585,SA!$B$5:$C$11,2,1) -> 0-35 | T585: Female | U585: Daughter | V585: 300000 | W585: =IF(U585="self",V585,0) -> 0 | X585: =IF(U585="self",1,0) -> 0 | Y585: =O585-N585+1 -> 365 | Z585: =$Z$1 -> 46081 | AA585: =IF(MIN((Z585-N585)+1,Y585)<0,0,MIN((Z585-N585)+1,Y585)) -> 264 | AB585: Delhi | AC585: =AE585+AF585+AG585+AH585 -> 3874.2114 | AD585: 1 | AE585: =IFERROR(INDEX(SA!$C$4:$E$11,MATCH(Details!S585,SA!$C$4:$C$11,0),MATCH(Details!V585,SA!$C$4:$E$4,0)),0)*Y585/(F585-E585+1) -> 3283.23 | AF585: =IF(AB585="Karnataka",AE585*9%,0) -> 0 | AG585: =IF(AB585="Karnataka",AE585*9%,0) -> 0 | AH585: =IF(AF585+AG585>0,0,AE585*18%) -> 590.9814 | AI585: =AE585*L585 -> 131.3292 | AJ585: =$AE585*M585 -> 738.72675 | AK585: =(AE585)*AA585/Y585 -> 2374.7198 | AL585: =AK585*(1-L585-M585) -> 1745.419 | AM585: =AE585-AI585-AL585-AJ585 -> 667.75501 | AN585: =Z585-366 -> 45715 | AO585: =IF(AND(O585>Z585,N585>AN585),AE585,0) -> 3283.23
A586: Valid | B586: 202506 | C586: GMC021090100AV | D586: A V GLOBAL CORPORATION PRIVATE LIMITED | E586: 45818 | F586: 46182 | G586: Rajiv Kumar | H586: AVGCT2 | I586: 29952 | J586: ACK.F683A520250229.1 | K586: =N586 -> 45818 | L586: =IF(K586>=DATE(2022,4,1),4%,5%) -> 0.04 | M586: 0.225 | N586: 45818 | O586: 46182 | R586: 43 | S586: =VLOOKUP(R586,SA!$B$5:$C$11,2,1) -> 36-45 | T586: Male | U586: Self | V586: 300000 | W586: =IF(U586="self",V586,0) -> 300000 | X586: =IF(U586="self",1,0) -> 1 | Y586: =O586-N586+1 -> 365 | Z586: =$Z$1 -> 46081 | AA586: =IF(MIN((Z586-N586)+1,Y586)<0,0,MIN((Z586-N586)+1,Y586)) -> 264 | AB586: Delhi | AC586: =AE586+AF586+AG586+AH586 -> 5017.3246 | AD586: 1 | AE586: =IFERROR(INDEX(SA!$C$4:$E$11,MATCH(Details!S586,SA!$C$4:$C$11,0),MATCH(Details!V586,SA!$C$4:$E$4,0)),0)*Y586/(F586-E586+1) -> 4251.97 | AF586: =IF(AB586="Karnataka",AE586*9%,0) -> 0 | AG586: =IF(AB586="Karnataka",AE586*9%,0) -> 0 | AH586: =IF(AF586+AG586>0,0,AE586*18%) -> 765.3546 | AI586: =AE586*L586 -> 170.0788 | AJ586: =$AE586*M586 -> 956.69325 | AK586: =(AE586)*AA586/Y586 -> 3075.3975 | AL586: =AK586*(1-L586-M586) -> 2260.4171 | AM586: =AE586-AI586-AL586-AJ586 -> 864.7808 | AN586: =Z586-366 -> 45715 | AO586: =IF(AND(O586>Z586,N586>AN586),AE586,0) -> 4251.97
A587: Valid | B587: 202506 | C587: GMC021090100AV | D587: A V GLOBAL CORPORATION PRIVATE LIMITED | E587: 45818 | F587: 46182 | G587: Malti | H587: AVGCT2 | I587: 28950 | J587: ACK.F683A520250229.2 | K587: =N587 -> 45818 | L587: =IF(K587>=DATE(2022,4,1),4%,5%) -> 0.04 | M587: 0.225 | N587: 45818 | O587: 46182 | R587: 46 | S587: =VLOOKUP(R587,SA!$B$5:$C$11,2,1) -> 46-55 | T587: Female | U587: Spouse | V587: 300000 | W587: =IF(U587="self",V587,0) -> 0 | X587: =IF(U587="self",1,0) -> 0 | Y587: =O587-N587+1 -> 365 | Z587: =$Z$1 -> 46081 | AA587: =IF(MIN((Z587-N587)+1,Y587)<0,0,MIN((Z587-N587)+1,Y587)) -> 264 | AB587: Delhi | AC587: =AE587+AF587+AG587+AH587 -> 9586.9926 | AD587: 1 | AE587: =IFERROR(INDEX(SA!$C$4:$E$11,MATCH(Details!S587,SA!$C$4:$C$11,0),MATCH(Details!V587,SA!$C$4:$E$4,0)),0)*Y587/(F587-E587+1) -> 8124.57 | AF587: =IF(AB587="Karnataka",AE587*9%,0) -> 0 | AG587: =IF(AB587="Karnataka",AE587*9%,0) -> 0 | AH587: =IF(AF587+AG587>0,0,AE587*18%) -> 1462.4226 | AI587: =AE587*L587 -> 324.9828 | AJ587: =$AE587*M587 -> 1828.0283 | AK587: =(AE587)*AA587/Y587 -> 5876.4013 | AL587: =AK587*(1-L587-M587) -> 4319.155 | AM587: =AE587-AI587-AL587-AJ587 -> 1652.404 | AN587: =Z587-366 -> 45715 | AO587: =IF(AND(O587>Z587,N587>AN587),AE587,0) -> 8124.57
A588: Valid | B588: 202506 | C588: GMC021090100AV | D588: A V GLOBAL CORPORATION PRIVATE LIMITED | E588: 45818 | F588: 46182 | G588: Philip | H588: AVGCT2 | I588: 36797 | J588: ACK.F683A520250229.3 | K588: =N588 -> 45818 | L588: =IF(K588>=DATE(2022,4,1),4%,5%) -> 0.04 | M588: 0.225 | N588: 45818 | O588: 46182 | R588: 24 | S588: =VLOOKUP(R588,SA!$B$5:$C$11,2,1) -> 0-35 | T588: Male | U588: Son | V588: 300000 | W588: =IF(U588="self",V588,0) -> 0 | X588: =IF(U588="self",1,0) -> 0 | Y588: =O588-N588+1 -> 365 | Z588: =$Z$1 -> 46081 | AA588: =IF(MIN((Z588-N588)+1,Y588)<0,0,MIN((Z588-N588)+1,Y588)) -> 264 | AB588: Delhi | AC588: =AE588+AF588+AG588+AH588 -> 3874.2114 | AD588: 1 | AE588: =IFERROR(INDEX(SA!$C$4:$E$11,MATCH(Details!S588,SA!$C$4:$C$11,0),MATCH(Details!V588,SA!$C$4:$E$4,0)),0)*Y588/(F588-E588+1) -> 3283.23 | AF588: =IF(AB588="Karnataka",AE588*9%,0) -> 0 | AG588: =IF(AB588="Karnataka",AE588*9%,0) -> 0 | AH588: =IF(AF588+AG588>0,0,AE588*18%) -> 590.9814 | AI588: =AE588*L588 -> 131.3292 | AJ588: =$AE588*M588 -> 738.72675 | AK588: =(AE588)*AA588/Y588 -> 2374.7198 | AL588: =AK588*(1-L588-M588) -> 1745.419 | AM588: =AE588-AI588-AL588-AJ588 -> 667.75501 | AN588: =Z588-366 -> 45715 | AO588: =IF(AND(O588>Z588,N588>AN588),AE588,0) -> 3283.23
A589: Valid | B589: 202506 | C589: GMC021090100AV | D589: A V GLOBAL CORPORATION PRIVATE LIMITED | E589: 45818 | F589: 46182 | G589: Joy | H589: AVGCT2 | I589: 39861 | J589: ACK.F683A520250229.4 | K589: =N589 -> 45818 | L589: =IF(K589>=DATE(2022,4,1),4%,5%) -> 0.04 | M589: 0.225 | N589: 45818 | O589: 46182 | R589: 16 | S589: =VLOOKUP(R589,SA!$B$5:$C$11,2,1) -> 0-35 | T589: Male | U589: Son | V589: 300000 | W589: =IF(U589="self",V589,0) -> 0 | X589: =IF(U589="self",1,0) -> 0 | Y589: =O589-N589+1 -> 365 | Z589: =$Z$1 -> 46081 | AA589: =IF(MIN((Z589-N589)+1,Y589)<0,0,MIN((Z589-N589)+1,Y589)) -> 264 | AB589: Delhi | AC589: =AE589+AF589+AG589+AH589 -> 3874.2114 | AD589: 1 | AE589: =IFERROR(INDEX(SA!$C$4:$E$11,MATCH(Details!S589,SA!$C$4:$C$11,0),MATCH(Details!V589,SA!$C$4:$E$4,0)),0)*Y589/(F589-E589+1) -> 3283.23 | AF589: =IF(AB589="Karnataka",AE589*9%,0) -> 0 | AG589: =IF(AB589="Karnataka",AE589*9%,0) -> 0 | AH589: =IF(AF589+AG589>0,0,AE589*18%) -> 590.9814 | AI589: =AE589*L589 -> 131.3292 | AJ589: =$AE589*M589 -> 738.72675 | AK589: =(AE589)*AA589/Y589 -> 2374.7198 | AL589: =AK589*(1-L589-M589) -> 1745.419 | AM589: =AE589-AI589-AL589-AJ589 -> 667.75501 | AN589: =Z589-366 -> 45715 | AO589: =IF(AND(O589>Z589,N589>AN589),AE589,0) -> 3283.23
A590: Valid | B590: 202506 | C590: GMC021090100AV | D590: A V GLOBAL CORPORATION PRIVATE LIMITED | E590: 45818 | F590: 46182 | G590: Poonam | H590: AVGCT3 | I590: 34053 | J590: ACK.F683A520250227.1 | K590: =N590 -> 45818 | L590: =IF(K590>=DATE(2022,4,1),4%,5%) -> 0.04 | M590: 0.225 | N590: 45818 | O590: 46182 | R590: 32 | S590: =VLOOKUP(R590,SA!$B$5:$C$11,2,1) -> 0-35 | T590: Female | U590: Self | V590: 300000 | W590: =IF(U590="self",V590,0) -> 300000 | X590: =IF(U590="self",1,0) -> 1 | Y590: =O590-N590+1 -> 365 | Z590: =$Z$1 -> 46081 | AA590: =IF(MIN((Z590-N590)+1,Y590)<0,0,MIN((Z590-N590)+1,Y590)) -> 264 | AB590: Delhi | AC590: =AE590+AF590+AG590+AH590 -> 3874.2114 | AD590: 1 | AE590: =IFERROR(INDEX(SA!$C$4:$E$11,MATCH(Details!S590,SA!$C$4:$C$11,0),MATCH(Details!V590,SA!$C$4:$E$4,0)),0)*Y590/(F590-E590+1) -> 3283.23 | AF590: =IF(AB590="Karnataka",AE590*9%,0) -> 0 | AG590: =IF(AB590="Karnataka",AE590*9%,0) -> 0 | AH590: =IF(AF590+AG590>0,0,AE590*18%) -> 590.9814 | AI590: =AE590*L590 -> 131.3292 | AJ590: =$AE590*M590 -> 738.72675 | AK590: =(AE590)*AA590/Y590 -> 2374.7198 | AL590: =AK590*(1-L590-M590) -> 1745.419 | AM590: =AE590-AI590-AL590-AJ590 -> 667.75501 | AN590: =Z590-366 -> 45715 | AO590: =IF(AND(O590>Z590,N590>AN590),AE590,0) -> 3283.23
A591: Valid | B591: 202506 | C591: GMC021090100AV | D591: A V GLOBAL CORPORATION PRIVATE LIMITED | E591: 45818 | F591: 46182 | G591: Mukesh | H591: AVGCT4 | I591: 34302 | J591: ACK.F683A520250230.1 | K591: =N591 -> 45818 | L591: =IF(K591>=DATE(2022,4,1),4%,5%) -> 0.04 | M591: 0.225 | N591: 45818 | O591: 46182 | R591: 31 | S591: =VLOOKUP(R591,SA!$B$5:$C$11,2,1) -> 0-35 | T591: Male | U591: Self | V591: 300000 | W591: =IF(U591="self",V591,0) -> 300000 | X591: =IF(U591="self",1,0) -> 1 | Y591: =O591-N591+1 -> 365 | Z591: =$Z$1 -> 46081 | AA591: =IF(MIN((Z591-N591)+1,Y591)<0,0,MIN((Z591-N591)+1,Y591)) -> 264 | AB591: Delhi | AC591: =AE591+AF591+AG591+AH591 -> 3874.2114 | AD591: 1 | AE591: =IFERROR(INDEX(SA!$C$4:$E$11,MATCH(Details!S591,SA!$C$4:$C$11,0),MATCH(Details!V591,SA!$C$4:$E$4,0)),0)*Y591/(F591-E591+1) -> 3283.23 | AF591: =IF(AB591="Karnataka",AE591*9%,0) -> 0 | AG591: =IF(AB591="Karnataka",AE591*9%,0) -> 0 | AH591: =IF(AF591+AG591>0,0,AE591*18%) -> 590.9814 | AI591: =AE591*L591 -> 131.3292 | AJ591: =$AE591*M591 -> 738.72675 | AK591: =(AE591)*AA591/Y591 -> 2374.7198 | AL591: =AK591*(1-L591-M591) -> 1745.419 | AM591: =AE591-AI591-AL591-AJ591 -> 667.75501 | AN591: =Z591-366 -> 45715 | AO591: =IF(AND(O591>Z591,N591>AN591),AE591,0) -> 3283.23
A592: Valid | B592: 202506 | C592: GMC021090100AV | D592: A V GLOBAL CORPORATION PRIVATE LIMITED | E592: 45818 | F592: 46182 | G592: Kanchan | H592: AVGCT4 | I592: 33240 | J592: ACK.F683A520250230.2 | K592: =N592 -> 45818 | L592: =IF(K592>=DATE(2022,4,1),4%,5%) -> 0.04 | M592: 0.225 | N592: 45818 | O592: 46182 | R592: 34 | S592: =VLOOKUP(R592,SA!$B$5:$C$11,2,1) -> 0-35 | T592: Female | U592: Spouse | V592: 300000 | W592: =IF(U592="self",V592,0) -> 0 | X592: =IF(U592="self",1,0) -> 0 | Y592: =O592-N592+1 -> 365 | Z592: =$Z$1 -> 46081 | AA592: =IF(MIN((Z592-N592)+1,Y592)<0,0,MIN((Z592-N592)+1,Y592)) -> 264 | AB592: Delhi | AC592: =AE592+AF592+AG592+AH592 -> 3874.2114 | AD592: 1 | AE592: =IFERROR(INDEX(SA!$C$4:$E$11,MATCH(Details!S592,SA!$C$4:$C$11,0),MATCH(Details!V592,SA!$C$4:$E$4,0)),0)*Y592/(F592-E592+1) -> 3283.23 | AF592: =IF(AB592="Karnataka",AE592*9%,0) -> 0 | AG592: =IF(AB592="Karnataka",AE592*9%,0) -> 0 | AH592: =IF(AF592+AG592>0,0,AE592*18%) -> 590.9814 | AI592: =AE592*L592 -> 131.3292 | AJ592: =$AE592*M592 -> 738.72675 | AK592: =(AE592)*AA592/Y592 -> 2374.7198 | AL592: =AK592*(1-L592-M592) -> 1745.419 | AM592: =AE592-AI592-AL592-AJ592 -> 667.75501 | AN592: =Z592-366 -> 45715 | AO592: =IF(AND(O592>Z592,N592>AN592),AE592,0) -> 3283.23
A593: Valid | B593: 202506 | C593: GMC021090100AV | D593: A V GLOBAL CORPORATION PRIVATE LIMITED | E593: 45818 | F593: 46182 | G593: Pankaj Sharma | H593: AVGCT5 | I593: 31693 | J593: ACK.F683A520250231.1 | K593: =N593 -> 45818 | L593: =IF(K593>=DATE(2022,4,1),4%,5%) -> 0.04 | M593: 0.225 | N593: 45818 | O593: 46182 | R593: 38 | S593: =VLOOKUP(R593,SA!$B$5:$C$11,2,1) -> 36-45 | T593: Male | U593: Self | V593: 300000 | W593: =IF(U593="self",V593,0) -> 300000 | X593: =IF(U593="self",1,0) -> 1 | Y593: =O593-N593+1 -> 365 | Z593: =$Z$1 -> 46081 | AA593: =IF(MIN((Z593-N593)+1,Y593)<0,0,MIN((Z593-N593)+1,Y593)) -> 264 | AB593: Delhi | AC593: =AE593+AF593+AG593+AH593 -> 5017.3246 | AD593: 1 | AE593: =IFERROR(INDEX(SA!$C$4:$E$11,MATCH(Details!S593,SA!$C$4:$C$11,0),MATCH(Details!V593,SA!$C$4:$E$4,0)),0)*Y593/(F593-E593+1) -> 4251.97 | AF593: =IF(AB593="Karnataka",AE593*9%,0) -> 0 | AG593: =IF(AB593="Karnataka",AE593*9%,0) -> 0 | AH593: =IF(AF593+AG593>0,0,AE593*18%) -> 765.3546 | AI593: =AE593*L593 -> 170.0788 | AJ593: =$AE593*M593 -> 956.69325 | AK593: =(AE593)*AA593/Y593 -> 3075.3975 | AL593: =AK593*(1-L593-M593) -> 2260.4171 | AM593: =AE593-AI593-AL593-AJ593 -> 864.7808 | AN593: =Z593-366 -> 45715 | AO593: =IF(AND(O593>Z593,N593>AN593),AE593,0) -> 4251.97
A594: Valid | B594: 202506 | C594: GMC021090100AV | D594: A V GLOBAL CORPORATION PRIVATE LIMITED | E594: 45818 | F594: 46182 | G594: Prakash Kumar | H594: AVGCT6 | I594: 33785 | J594: ACK.F683A520250232.1 | K594: =N594 -> 45818 | L594: =IF(K594>=DATE(2022,4,1),4%,5%) -> 0.04 | M594: 0.225 | N594: 45818 | O594: 46182 | R594: 32 | S594: =VLOOKUP(R594,SA!$B$5:$C$11,2,1) -> 0-35 | T594: Male | U594: Self | V594: 300000 | W594: =IF(U594="self",V594,0) -> 300000 | X594: =IF(U594="self",1,0) -> 1 | Y594: =O594-N594+1 -> 365 | Z594: =$Z$1 -> 46081 | AA594: =IF(MIN((Z594-N594)+1,Y594)<0,0,MIN((Z594-N594)+1,Y594)) -> 264 | AB594: Delhi | AC594: =AE594+AF594+AG594+AH594 -> 3874.2114 | AD594: 1 | AE594: =IFERROR(INDEX(SA!$C$4:$E$11,MATCH(Details!S594,SA!$C$4:$C$11,0),MATCH(Details!V594,SA!$C$4:$E$4,0)),0)*Y594/(F594-E594+1) -> 3283.23 | AF594: =IF(AB594="Karnataka",AE594*9%,0) -> 0 | AG594: =IF(AB594="Karnataka",AE594*9%,0) -> 0 | AH594: =IF(AF594+AG594>0,0,AE594*18%) -> 590.9814 | AI594: =AE594*L594 -> 131.3292 | AJ594: =$AE594*M594 -> 738.72675 | AK594: =(AE594)*AA594/Y594 -> 2374.7198 | AL594: =AK594*(1-L594-M594) -> 1745.419 | AM594: =AE594-AI594-AL594-AJ594 -> 667.75501 | AN594: =Z594-366 -> 45715 | AO594: =IF(AND(O594>Z594,N594>AN594),AE594,0) -> 3283.23
... A596: Valid | B596: 202506 | C596: GMC021090100AV | D596: A V GLOBAL CORPORATION PRIVATE LIMITED | E596: 45818 | F596: 46182 | G596: Viraj Kashyap | H596: AVGCT6 | I596: 45036 | J596: ACK.F683A520250232.3 | K596: =N596 -> 45818 | L596: =IF(K596>=DATE(2022,4,1),4%,5%) -> 0.04 | M596: 0.225 | N596: 45818 | O596: 46182 | R596: 2 | S596: =VLOOKUP(R596,SA!$B$5:$C$11,2,1) -> 0-35 | T596: Male | U596: Son | V596: 300000 | W596: =IF(U596="self",V596,0) -> 0 | X596: =IF(U596="self",1,0) -> 0 | Y596: =O596-N596+1 -> 365 | Z596: =$Z$1 -> 46081 | AA596: =IF(MIN((Z596-N596)+1,Y596)<0,0,MIN((Z596-N596)+1,Y596)) -> 264 | AB596: Delhi | AC596: =AE596+AF596+AG596+AH596 -> 3874.2114 | AD596: 1 | AE596: =IFERROR(INDEX(SA!$C$4:$E$11,MATCH(Details!S596,SA!$C$4:$C$11,0),MATCH(Details!V596,SA!$C$4:$E$4,0)),0)*Y596/(F596-E596+1) -> 3283.23 | AF596: =IF(AB596="Karnataka",AE596*9%,0) -> 0 | AG596: =IF(AB596="Karnataka",AE596*9%,0) -> 0 | AH596: =IF(AF596+AG596>0,0,AE596*18%) -> 590.9814 | AI596: =AE596*L596 -> 131.3292 | AJ596: =$AE596*M596 -> 738.72675 | AK596: =(AE596)*AA596/Y596 -> 2374.7198 | AL596: =AK596*(1-L596-M596) -> 1745.419 | AM596: =AE596-AI596-AL596-AJ596 -> 667.75501 | AN596: =Z596-366 -> 45715 | AO596: =IF(AND(O596>Z596,N596>AN596),AE596,0) -> 3283.23
A597: Valid | B597: 202506 | C597: GMC021090100AV | D597: A V GLOBAL CORPORATION PRIVATE LIMITED | E597: 45818 | F597: 46182 | G597: Sgurusaran | H597: 2327 | I597: 35603 | J597: ACK.F683A520250207.1 | K597: =N597 -> 45818 | L597: =IF(K597>=DATE(2022,4,1),4%,5%) -> 0.04 | M597: 0.225 | N597: 45818 | O597: 46182 | R597: 27 | S597: =VLOOKUP(R597,SA!$B$5:$C$11,2,1) -> 0-35 | T597: Male | U597: Self | V597: 300000 | W597: =IF(U597="self",V597,0) -> 300000 | X597: =IF(U597="self",1,0) -> 1 | Y597: =O597-N597+1 -> 365 | Z597: =$Z$1 -> 46081 | AA597: =IF(MIN((Z597-N597)+1,Y597)<0,0,MIN((Z597-N597)+1,Y597)) -> 264 | AB597: Delhi | AC597: =AE597+AF597+AG597+AH597 -> 3874.2114 | AD597: 1 | AE597: =IFERROR(INDEX(SA!$C$4:$E$11,MATCH(Details!S597,SA!$C$4:$C$11,0),MATCH(Details!V597,SA!$C$4:$E$4,0)),0)*Y597/(F597-E597+1) -> 3283.23 | AF597: =IF(AB597="Karnataka",AE597*9%,0) -> 0 | AG597: =IF(AB597="Karnataka",AE597*9%,0) -> 0 | AH597: =IF(AF597+AG597>0,0,AE597*18%) -> 590.9814 | AI597: =AE597*L597 -> 131.3292 | AJ597: =$AE597*M597 -> 738.72675 | AK597: =(AE597)*AA597/Y597 -> 2374.7198 | AL597: =AK597*(1-L597-M597) -> 1745.419 | AM597: =AE597-AI597-AL597-AJ597 -> 667.75501 | AN597: =Z597-366 -> 45715 | AO597: =IF(AND(O597>Z597,N597>AN597),AE597,0) -> 3283.23
A598: Valid | B598: 202506 | C598: GMC021090100AV | D598: A V GLOBAL CORPORATION PRIVATE LIMITED | E598: 45818 | F598: 46182 | G598: Subbulakshmi Krishnamoorthy | H598: 2327 | I598: 38129 | J598: ACK.F683A520250207.2 | K598: =N598 -> 45818 | L598: =IF(K598>=DATE(2022,4,1),4%,5%) -> 0.04 | M598: 0.225 | N598: 45818 | O598: 46182 | R598: 21 | S598: =VLOOKUP(R598,SA!$B$5:$C$11,2,1) -> 0-35 | T598: Female | U598: Spouse | V598: 300000 | W598: =IF(U598="self",V598,0) -> 0 | X598: =IF(U598="self",1,0) -> 0 | Y598: =O598-N598+1 -> 365 | Z598: =$Z$1 -> 46081 | AA598: =IF(MIN((Z598-N598)+1,Y598)<0,0,MIN((Z598-N598)+1,Y598)) -> 264 | AB598: Delhi | AC598: =AE598+AF598+AG598+AH598 -> 3874.2114 | AD598: 1 | AE598: =IFERROR(INDEX(SA!$C$4:$E$11,MATCH(Details!S598,SA!$C$4:$C$11,0),MATCH(Details!V598,SA!$C$4:$E$4,0)),0)*Y598/(F598-E598+1) -> 3283.23 | AF598: =IF(AB598="Karnataka",AE598*9%,0) -> 0 | AG598: =IF(AB598="Karnataka",AE598*9%,0) -> 0 | AH598: =IF(AF598+AG598>0,0,AE598*18%) -> 590.9814 | AI598: =AE598*L598 -> 131.3292 | AJ598: =$AE598*M598 -> 738.72675 | AK598: =(AE598)*AA598/Y598 -> 2374.7198 | AL598: =AK598*(1-L598-M598) -> 1745.419 | AM598: =AE598-AI598-AL598-AJ598 -> 667.75501 | AN598: =Z598-366 -> 45715 | AO598: =IF(AND(O598>Z598,N598>AN598),AE598,0) -> 3283.23
A599: Valid | B599: 202506 | C599: GMC021090100AV | D599: A V GLOBAL CORPORATION PRIVATE LIMITED | E599: 45818 | F599: 46182 | G599: Abhishek Kumar | H599: 2324 | I599: 35189 | J599: ACK.F683A520250204.1 | K599: =N599 -> 45818 | L599: =IF(K599>=DATE(2022,4,1),4%,5%) -> 0.04 | M599: 0.225 | N599: 45818 | O599: 46182 | R599: 29 | S599: =VLOOKUP(R599,SA!$B$5:$C$11,2,1) -> 0-35 | T599: Male | U599: Self | V599: 300000 | W599: =IF(U599="self",V599,0) -> 300000 | X599: =IF(U599="self",1,0) -> 1 | Y599: =O599-N599+1 -> 365 | Z599: =$Z$1 -> 46081 | AA599: =IF(MIN((Z599-N599)+1,Y599)<0,0,MIN((Z599-N599)+1,Y599)) -> 264 | AB599: Delhi | AC599: =AE599+AF599+AG599+AH599 -> 3874.2114 | AD599: 1 | AE599: =IFERROR(INDEX(SA!$C$4:$E$11,MATCH(Details!S599,SA!$C$4:$C$11,0),MATCH(Details!V599,SA!$C$4:$E$4,0)),0)*Y599/(F599-E599+1) -> 3283.23 | AF599: =IF(AB599="Karnataka",AE599*9%,0) -> 0 | AG599: =IF(AB599="Karnataka",AE599*9%,0) -> 0 | AH599: =IF(AF599+AG599>0,0,AE599*18%) -> 590.9814 | AI599: =AE599*L599 -> 131.3292 | AJ599: =$AE599*M599 -> 738.72675 | AK599: =(AE599)*AA599/Y599 -> 2374.7198 | AL599: =AK599*(1-L599-M599) -> 1745.419 | AM599: =AE599-AI599-AL599-AJ599 -> 667.75501 | AN599: =Z599-366 -> 45715 | AO599: =IF(AND(O599>Z599,N599>AN599),AE599,0) -> 3283.23
A600: Valid | B600: 202506 | C600: GMC021090100AV | D600: A V GLOBAL CORPORATION PRIVATE LIMITED | E600: 45818 | F600: 46182 | G600: Shweta Kumari | H600: 2324 | I600: 36222 | J600: ACK.F683A520250204.2 | K600: =N600 -> 45818 | L600: =IF(K600>=DATE(2022,4,1),4%,5%) -> 0.04 | M600: 0.225 | N600: 45818 | O600: 46182 | R600: 26 | S600: =VLOOKUP(R600,SA!$B$5:$C$11,2,1) -> 0-35 | T600: Female | U600: Spouse | V600: 300000 | W600: =IF(U600="self",V600,0) -> 0 | X600: =IF(U600="self",1,0) -> 0 | Y600: =O600-N600+1 -> 365 | Z600: =$Z$1 -> 46081 | AA600: =IF(MIN((Z600-N600)+1,Y600)<0,0,MIN((Z600-N600)+1,Y600)) -> 264 | AB600: Delhi | AC600: =AE600+AF600+AG600+AH600 -> 3874.2114 | AD600: 1 | AE600: =IFERROR(INDEX(SA!$C$4:$E$11,MATCH(Details!S600,SA!$C$4:$C$11,0),MATCH(Details!V600,SA!$C$4:$E$4,0)),0)*Y600/(F600-E600+1) -> 3283.23 | AF600: =IF(AB600="Karnataka",AE600*9%,0) -> 0 | AG600: =IF(AB600="Karnataka",AE600*9%,0) -> 0 | AH600: =IF(AF600+AG600>0,0,AE600*18%) -> 590.9814 | AI600: =AE600*L600 -> 131.3292 | AJ600: =$AE600*M600 -> 738.72675 | AK600: =(AE600)*AA600/Y600 -> 2374.7198 | AL600: =AK600*(1-L600-M600) -> 1745.419 | AM600: =AE600-AI600-AL600-AJ600 -> 667.75501 | AN600: =Z600-366 -> 45715 | AO600: =IF(AND(O600>Z600,N600>AN600),AE600,0) -> 3283.23
A601: Valid | B601: 202506 | C601: GMC021090100AV | D601: A V GLOBAL CORPORATION PRIVATE LIMITED | E601: 45818 | F601: 46182 | G601: Aradhya Kumari | H601: 2324 | I601: 43084 | J601: ACK.F683A520250204.3 | K601: =N601 -> 45818 | L601: =IF(K601>=DATE(2022,4,1),4%,5%) -> 0.04 | M601: 0.225 | N601: 45818 | O601: 46182 | R601: 7 | S601: =VLOOKUP(R601,SA!$B$5:$C$11,2,1) -> 0-35 | T601: Female | U601: Daughter | V601: 300000 | W601: =IF(U601="self",V601,0) -> 0 | X601: =IF(U601="self",1,0) -> 0 | Y601: =O601-N601+1 -> 365 | Z601: =$Z$1 -> 46081 | AA601: =IF(MIN((Z601-N601)+1,Y601)<0,0,MIN((Z601-N601)+1,Y601)) -> 264 | AB601: Delhi | AC601: =AE601+AF601+AG601+AH601 -> 3874.2114 | AD601: 1 | AE601: =IFERROR(INDEX(SA!$C$4:$E$11,MATCH(Details!S601,SA!$C$4:$C$11,0),MATCH(Details!V601,SA!$C$4:$E$4,0)),0)*Y601/(F601-E601+1) -> 3283.23 | AF601: =IF(AB601="Karnataka",AE601*9%,0) -> 0 | AG601: =IF(AB601="Karnataka",AE601*9%,0) -> 0 | AH601: =IF(AF601+AG601>0,0,AE601*18%) -> 590.9814 | AI601: =AE601*L601 -> 131.3292 | AJ601: =$AE601*M601 -> 738.72675 | AK601: =(AE601)*AA601/Y601 -> 2374.7198 | AL601: =AK601*(1-L601-M601) -> 1745.419 | AM601: =AE601-AI601-AL601-AJ601 -> 667.75501 | AN601: =Z601-366 -> 45715 | AO601: =IF(AND(O601>Z601,N601>AN601),AE601,0) -> 3283.23
A602: Valid | B602: 202506 | C602: GMC021090100AV | D602: A V GLOBAL CORPORATION PRIVATE LIMITED | E602: 45818 | F602: 46182 | G602: Lakshya Kashyap | H602: 2324 | I602: 43860 | J602: ACK.F683A520250204.4 | K602: =N602 -> 45818 | L602: =IF(K602>=DATE(2022,4,1),4%,5%) -> 0.04 | M602: 0.225 | N602: 45818 | O602: 46182 | R602: 5 | S602: =VLOOKUP(R602,SA!$B$5:$C$11,2,1) -> 0-35 | T602: Male | U602: Son | V602: 300000 | W602: =IF(U602="self",V602,0) -> 0 | X602: =IF(U602="self",1,0) -> 0 | Y602: =O602-N602+1 -> 365 | Z602: =$Z$1 -> 46081 | AA602: =IF(MIN((Z602-N602)+1,Y602)<0,0,MIN((Z602-N602)+1,Y602)) -> 264 | AB602: Delhi | AC602: =AE602+AF602+AG602+AH602 -> 3874.2114 | AD602: 1 | AE602: =IFERROR(INDEX(SA!$C$4:$E$11,MATCH(Details!S602,SA!$C$4:$C$11,0),MATCH(Details!V602,SA!$C$4:$E$4,0)),0)*Y602/(F602-E602+1) -> 3283.23 | AF602: =IF(AB602="Karnataka",AE602*9%,0) -> 0 | AG602: =IF(AB602="Karnataka",AE602*9%,0) -> 0 | AH602: =IF(AF602+AG602>0,0,AE602*18%) -> 590.9814 | AI602: =AE602*L602 -> 131.3292 | AJ602: =$AE602*M602 -> 738.72675 | AK602: =(AE602)*AA602/Y602 -> 2374.7198 | AL602: =AK602*(1-L602-M602) -> 1745.419 | AM602: =AE602-AI602-AL602-AJ602 -> 667.75501 | AN602: =Z602-366 -> 45715 | AO602: =IF(AND(O602>Z602,N602>AN602),AE602,0) -> 3283.23
A603: Valid | B603: 202506 | C603: GMC021090100AV | D603: A V GLOBAL CORPORATION PRIVATE LIMITED | E603: 45818 | F603: 46182 | G603: Anand Kumar S | H603: 2215 | I603: 33150 | J603: ACK.F683A520250141.1 | K603: =N603 -> 45818 | L603: =IF(K603>=DATE(2022,4,1),4%,5%) -> 0.04 | M603: 0.225 | N603: 45818 | O603: 46182 | R603: 34 | S603: =VLOOKUP(R603,SA!$B$5:$C$11,2,1) -> 0-35 | T603: Male | U603: Self | V603: 300000 | W603: =IF(U603="self",V603,0) -> 300000 | X603: =IF(U603="self",1,0) -> 1 | Y603: =O603-N603+1 -> 365 | Z603: =$Z$1 -> 46081 | AA603: =IF(MIN((Z603-N603)+1,Y603)<0,0,MIN((Z603-N603)+1,Y603)) -> 264 | AB603: Delhi | AC603: =AE603+AF603+AG603+AH603 -> 3874.2114 | AD603: 1 | AE603: =IFERROR(INDEX(SA!$C$4:$E$11,MATCH(Details!S603,SA!$C$4:$C$11,0),MATCH(Details!V603,SA!$C$4:$E$4,0)),0)*Y603/(F603-E603+1) -> 3283.23 | AF603: =IF(AB603="Karnataka",AE603*9%,0) -> 0 | AG603: =IF(AB603="Karnataka",AE603*9%,0) -> 0 | AH603: =IF(AF603+AG603>0,0,AE603*18%) -> 590.9814 | AI603: =AE603*L603 -> 131.3292 | AJ603: =$AE603*M603 -> 738.72675 | AK603: =(AE603)*AA603/Y603 -> 2374.7198 | AL603: =AK603*(1-L603-M603) -> 1745.419 | AM603: =AE603-AI603-AL603-AJ603 -> 667.75501 | AN603: =Z603-366 -> 45715 | AO603: =IF(AND(O603>Z603,N603>AN603),AE603,0) -> 3283.23
A604: Valid | B604: 202506 | C604: GMC021090100AV | D604: A V GLOBAL CORPORATION PRIVATE LIMITED | E604: 45818 | F604: 46182 | G604: Nagashree N S | H604: 2215 | I604: 34132 | J604: ACK.F683A520250141.2 | K604: =N604 -> 45818 | L604: =IF(K604>=DATE(2022,4,1),4%,5%) -> 0.04 | M604: 0.225 | N604: 45818 | O604: 46182 | R604: 31 | S604: =VLOOKUP(R604,SA!$B$5:$C$11,2,1) -> 0-35 | T604: Female | U604: Spouse | V604: 300000 | W604: =IF(U604="self",V604,0) -> 0 | X604: =IF(U604="self",1,0) -> 0 | Y604: =O604-N604+1 -> 365 | Z604: =$Z$1 -> 46081 | AA604: =IF(MIN((Z604-N604)+1,Y604)<0,0,MIN((Z604-N604)+1,Y604)) -> 264 | AB604: Delhi | AC604: =AE604+AF604+AG604+AH604 -> 3874.2114 | AD604: 1 | AE604: =IFERROR(INDEX(SA!$C$4:$E$11,MATCH(Details!S604,SA!$C$4:$C$11,0),MATCH(Details!V604,SA!$C$4:$E$4,0)),0)*Y604/(F604-E604+1) -> 3283.23 | AF604: =IF(AB604="Karnataka",AE604*9%,0) -> 0 | AG604: =IF(AB604="Karnataka",AE604*9%,0) -> 0 | AH604: =IF(AF604+AG604>0,0,AE604*18%) -> 590.9814 | AI604: =AE604*L604 -> 131.3292 | AJ604: =$AE604*M604 -> 738.72675 | AK604: =(AE604)*AA604/Y604 -> 2374.7198 | AL604: =AK604*(1-L604-M604) -> 1745.419 | AM604: =AE604-AI604-AL604-AJ604 -> 667.75501 | AN604: =Z604-366 -> 45715 | AO604: =IF(AND(O604>Z604,N604>AN604),AE604,0) -> 3283.23
A605: Valid | B605: 202506 | C605: GMC021090100AV | D605: A V GLOBAL CORPORATION PRIVATE LIMITED | E605: 45818 | F605: 46182 | G605: Niharika Anand | H605: 2215 | I605: 43933 | J605: ACK.F683A520250141.3 | K605: =N605 -> 45818 | L605: =IF(K605>=DATE(2022,4,1),4%,5%) -> 0.04 | M605: 0.225 | N605: 45818 | O605: 46182 | R605: 5 | S605: =VLOOKUP(R605,SA!$B$5:$C$11,2,1) -> 0-35 | T605: Female | U605: Daughter | V605: 300000 | W605: =IF(U605="self",V605,0) -> 0 | X605: =IF(U605="self",1,0) -> 0 | Y605: =O605-N605+1 -> 365 | Z605: =$Z$1 -> 46081 | AA605: =IF(MIN((Z605-N605)+1,Y605)<0,0,MIN((Z605-N605)+1,Y605)) -> 264 | AB605: Delhi | AC605: =AE605+AF605+AG605+AH605 -> 3874.2114 | AD605: 1 | AE605: =IFERROR(INDEX(SA!$C$4:$E$11,MATCH(Details!S605,SA!$C$4:$C$11,0),MATCH(Details!V605,SA!$C$4:$E$4,0)),0)*Y605/(F605-E605+1) -> 3283.23 | AF605: =IF(AB605="Karnataka",AE605*9%,0) -> 0 | AG605: =IF(AB605="Karnataka",AE605*9%,0) -> 0 | AH605: =IF(AF605+AG605>0,0,AE605*18%) -> 590.9814 | AI605: =AE605*L605 -> 131.3292 | AJ605: =$AE605*M605 -> 738.72675 | AK605: =(AE605)*AA605/Y605 -> 2374.7198 | AL605: =AK605*(1-L605-M605) -> 1745.419 | AM605: =AE605-AI605-AL605-AJ605 -> 667.75501 | AN605: =Z605-366 -> 45715 | AO605: =IF(AND(O605>Z605,N605>AN605),AE605,0) -> 3283.23
A606: Valid | B606: 202506 | C606: GMC021090100AV | D606: A V GLOBAL CORPORATION PRIVATE LIMITED | E606: 45818 | F606: 46182 | G606: Pradeep N A | H606: 2229 | I606: 32187 | J606: ACK.F683A520250147.1 | K606: =N606 -> 45818 | L606: =IF(K606>=DATE(2022,4,1),4%,5%) -> 0.04 | M606: 0.225 | N606: 45818 | O606: 46182 | R606: 37 | S606: =VLOOKUP(R606,SA!$B$5:$C$11,2,1) -> 36-45 | T606: Male | U606: Self | V606: 300000 | W606: =IF(U606="self",V606,0) -> 300000 | X606: =IF(U606="self",1,0) -> 1 | Y606: =O606-N606+1 -> 365 | Z606: =$Z$1 -> 46081 | AA606: =IF(MIN((Z606-N606)+1,Y606)<0,0,MIN((Z606-N606)+1,Y606)) -> 264 | AB606: Delhi | AC606: =AE606+AF606+AG606+AH606 -> 5017.3246 | AD606: 1 | AE606: =IFERROR(INDEX(SA!$C$4:$E$11,MATCH(Details!S606,SA!$C$4:$C$11,0),MATCH(Details!V606,SA!$C$4:$E$4,0)),0)*Y606/(F606-E606+1) -> 4251.97 | AF606: =IF(AB606="Karnataka",AE606*9%,0) -> 0 | AG606: =IF(AB606="Karnataka",AE606*9%,0) -> 0 | AH606: =IF(AF606+AG606>0,0,AE606*18%) -> 765.3546 | AI606: =AE606*L606 -> 170.0788 | AJ606: =$AE606*M606 -> 956.69325 | AK606: =(AE606)*AA606/Y606 -> 3075.3975 | AL606: =AK606*(1-L606-M606) -> 2260.4171 | AM606: =AE606-AI606-AL606-AJ606 -> 864.7808 | AN606: =Z606-366 -> 45715 | AO606: =IF(AND(O606>Z606,N606>AN606),AE606,0) -> 4251.97
A607: Valid | B607: 202506 | C607: GMC021090100AV | D607: A V GLOBAL CORPORATION PRIVATE LIMITED | E607: 45818 | F607: 46182 | G607: Kavya K | H607: 2229 | I607: 32750 | J607: ACK.F683A520250147.2 | K607: =N607 -> 45818 | L607: =IF(K607>=DATE(2022,4,1),4%,5%) -> 0.04 | M607: 0.225 | N607: 45818 | O607: 46182 | R607: 35 | S607: =VLOOKUP(R607,SA!$B$5:$C$11,2,1) -> 0-35 | T607: Female | U607: Spouse | V607: 300000 | W607: =IF(U607="self",V607,0) -> 0 | X607: =IF(U607="self",1,0) -> 0 | Y607: =O607-N607+1 -> 365 | Z607: =$Z$1 -> 46081 | AA607: =IF(MIN((Z607-N607)+1,Y607)<0,0,MIN((Z607-N607)+1,Y607)) -> 264 | AB607: Delhi | AC607: =AE607+AF607+AG607+AH607 -> 3874.2114 | AD607: 1 | AE607: =IFERROR(INDEX(SA!$C$4:$E$11,MATCH(Details!S607,SA!$C$4:$C$11,0),MATCH(Details!V607,SA!$C$4:$E$4,0)),0)*Y607/(F607-E607+1) -> 3283.23 | AF607: =IF(AB607="Karnataka",AE607*9%,0) -> 0 | AG607: =IF(AB607="Karnataka",AE607*9%,0) -> 0 | AH607: =IF(AF607+AG607>0,0,AE607*18%) -> 590.9814 | AI607: =AE607*L607 -> 131.3292 | AJ607: =$AE607*M607 -> 738.72675 | AK607: =(AE607)*AA607/Y607 -> 2374.7198 | AL607: =AK607*(1-L607-M607) -> 1745.419 | AM607: =AE607-AI607-AL607-AJ607 -> 667.75501 | AN607: =Z607-366 -> 45715 | AO607: =IF(AND(O607>Z607,N607>AN607),AE607,0) -> 3283.23
A608: Valid | B608: 202506 | C608: GMC021090100AV | D608: A V GLOBAL CORPORATION PRIVATE LIMITED | E608: 45818 | F608: 46182 | G608: Rupesh Waman Kadam | H608: 2337 | I608: 30175 | J608: ACK.F683A520250215.1 | K608: =N608 -> 45818 | L608: =IF(K608>=DATE(2022,4,1),4%,5%) -> 0.04 | M608: 0.225 | N608: 45818 | O608: 46182 | R608: 42 | S608: =VLOOKUP(R608,SA!$B$5:$C$11,2,1) -> 36-45 | T608: Male | U608: Self | V608: 300000 | W608: =IF(U608="self",V608,0) -> 300000 | X608: =IF(U608="self",1,0) -> 1 | Y608: =O608-N608+1 -> 365 | Z608: =$Z$1 -> 46081 | AA608: =IF(MIN((Z608-N608)+1,Y608)<0,0,MIN((Z608-N608)+1,Y608)) -> 264 | AB608: Delhi | AC608: =AE608+AF608+AG608+AH608 -> 5017.3246 | AD608: 1 | AE608: =IFERROR(INDEX(SA!$C$4:$E$11,MATCH(Details!S608,SA!$C$4:$C$11,0),MATCH(Details!V608,SA!$C$4:$E$4,0)),0)*Y608/(F608-E608+1) -> 4251.97 | AF608: =IF(AB608="Karnataka",AE608*9%,0) -> 0 | AG608: =IF(AB608="Karnataka",AE608*9%,0) -> 0 | AH608: =IF(AF608+AG608>0,0,AE608*18%) -> 765.3546 | AI608: =AE608*L608 -> 170.0788 | AJ608: =$AE608*M608 -> 956.69325 | AK608: =(AE608)*AA608/Y608 -> 3075.3975 | AL608: =AK608*(1-L608-M608) -> 2260.4171 | AM608: =AE608-AI608-AL608-AJ608 -> 864.7808 | AN608: =Z608-366 -> 45715 | AO608: =IF(AND(O608>Z608,N608>AN608),AE608,0) -> 4251.97
... A661: Valid | B661: 202507 | C661: GMC021090100AV | D661: A V GLOBAL CORPORATION PRIVATE LIMITED | E661: 45818 | F661: 46182 | G661: RISHABH PANDEY | H661: 2277 | I661: 36951 | J661: ACK.F683A520250234.1 | K661: =N661 -> 45839 | L661: =IF(K661>=DATE(2022,4,1),4%,5%) -> 0.04 | M661: 0.225 | N661: 45839 | O661: 46182 | R661: 24 | S661: =VLOOKUP(R661,SA!$B$5:$C$11,2,1) -> 0-35 | T661: Male | U661: Self | V661: 300000 | W661: =IF(U661="self",V661,0) -> 300000 | X661: =IF(U661="self",1,0) -> 1 | Y661: =O661-N661+1 -> 344 | Z661: =$Z$1 -> 46081 | AA661: =IF(MIN((Z661-N661)+1,Y661)<0,0,MIN((Z661-N661)+1,Y661)) -> 243 | AB661: Delhi | AC661: =AE661+AF661+AG661+AH661 -> 3651.3116 | AD661: 1 | AE661: =IFERROR(INDEX(SA!$C$4:$E$11,MATCH(Details!S661,SA!$C$4:$C$11,0),MATCH(Details!V661,SA!$C$4:$E$4,0)),0)*Y661/(F661-E661+1) -> 3094.3318 | AF661: =IF(AB661="Karnataka",AE661*9%,0) -> 0 | AG661: =IF(AB661="Karnataka",AE661*9%,0) -> 0 | AH661: =IF(AF661+AG661>0,0,AE661*18%) -> 556.97973 | AI661: =AE661*L661 -> 123.77327 | AJ661: =$AE661*M661 -> 696.22466 | AK661: =(AE661)*AA661/Y661 -> 2185.8216 | AL661: =AK661*(1-L661-M661) -> 1606.5789 | AM661: =AE661-AI661-AL661-AJ661 -> 667.75501 | AN661: =Z661-366 -> 45715 | AO661: =IF(AND(O661>Z661,N661>AN661),AE661,0) -> 3094.3318
A662: Valid | B662: 202507 | C662: GMC021090100AV | D662: A V GLOBAL CORPORATION PRIVATE LIMITED | E662: 45818 | F662: 46182 | G662: Rajni Kumari | H662: AVGCT5 | I662: 36484 | J662: ACK.F683A520250231.2 | K662: =N662 -> 45839 | L662: =IF(K662>=DATE(2022,4,1),4%,5%) -> 0.04 | M662: 0.225 | N662: 45839 | O662: 46182 | R662: 25 | S662: =VLOOKUP(R662,SA!$B$5:$C$11,2,1) -> 0-35 | T662: Female | U662: Spouse | V662: 300000 | W662: =IF(U662="self",V662,0) -> 0 | X662: =IF(U662="self",1,0) -> 0 | Y662: =O662-N662+1 -> 344 | Z662: =$Z$1 -> 46081 | AA662: =IF(MIN((Z662-N662)+1,Y662)<0,0,MIN((Z662-N662)+1,Y662)) -> 243 | AB662: Delhi | AC662: =AE662+AF662+AG662+AH662 -> 3651.3116 | AD662: 1 | AE662: =IFERROR(INDEX(SA!$C$4:$E$11,MATCH(Details!S662,SA!$C$4:$C$11,0),MATCH(Details!V662,SA!$C$4:$E$4,0)),0)*Y662/(F662-E662+1) -> 3094.3318 | AF662: =IF(AB662="Karnataka",AE662*9%,0) -> 0 | AG662: =IF(AB662="Karnataka",AE662*9%,0) -> 0 | AH662: =IF(AF662+AG662>0,0,AE662*18%) -> 556.97973 | AI662: =AE662*L662 -> 123.77327 | AJ662: =$AE662*M662 -> 696.22466 | AK662: =(AE662)*AA662/Y662 -> 2185.8216 | AL662: =AK662*(1-L662-M662) -> 1606.5789 | AM662: =AE662-AI662-AL662-AJ662 -> 667.75501 | AN662: =Z662-366 -> 45715 | AO662: =IF(AND(O662>Z662,N662>AN662),AE662,0) -> 3094.3318
A663: Valid | B663: 202508 | C663: GMC021090100AV | D663: A V GLOBAL CORPORATION PRIVATE LIMITED | E663: 45818 | F663: 46182 | G663: SATISH SAHADEV PAWNAK | H663: 2220 | I663: 31262 | J663: ACK.F683A520250240.1 | K663: =N663 -> 45856 | L663: =IF(K663>=DATE(2022,4,1),4%,5%) -> 0.04 | M663: 0.225 | N663: 45856 | O663: 46182 | R663: 39 | S663: =VLOOKUP(R663,SA!$B$5:$C$11,2,1) -> 36-45 | T663: Male | U663: Self | V663: 300000 | W663: =IF(U663="self",V663,0) -> 300000 | X663: =IF(U663="self",1,0) -> 1 | Y663: =O663-N663+1 -> 327 | Z663: =$Z$1 -> 46081 | AA663: =IF(MIN((Z663-N663)+1,Y663)<0,0,MIN((Z663-N663)+1,Y663)) -> 226 | AB663: Delhi | AC663: =AE663+AF663+AG663+AH663 -> 4494.973 | AD663: 1 | AE663: =IFERROR(INDEX(SA!$C$4:$E$11,MATCH(Details!S663,SA!$C$4:$C$11,0),MATCH(Details!V663,SA!$C$4:$E$4,0)),0)*Y663/(F663-E663+1) -> 3809.2992 | AF663: =IF(AB663="Karnataka",AE663*9%,0) -> 0 | AG663: =IF(AB663="Karnataka",AE663*9%,0) -> 0 | AH663: =IF(AF663+AG663>0,0,AE663*18%) -> 685.67385 | AI663: =AE663*L663 -> 152.37197 | AJ663: =$AE663*M663 -> 857.09231 | AK663: =(AE663)*AA663/Y663 -> 2632.7266 | AL663: =AK663*(1-L663-M663) -> 1935.0541 | AM663: =AE663-AI663-AL663-AJ663 -> 864.7808 | AN663: =Z663-366 -> 45715 | AO663: =IF(AND(O663>Z663,N663>AN663),AE663,0) -> 3809.2992
A664: Valid | B664: 202508 | C664: GMC021090100AV | D664: A V GLOBAL CORPORATION PRIVATE LIMITED | E664: 45818 | F664: 46182 | G664: Sonakshi Satish Pavnak | H664: 2220 | I664: 33105 | J664: ACK.F683A520250240.2 | K664: =N664 -> 45856 | L664: =IF(K664>=DATE(2022,4,1),4%,5%) -> 0.04 | M664: 0.225 | N664: 45856 | O664: 46182 | R664: 34 | S664: =VLOOKUP(R664,SA!$B$5:$C$11,2,1) -> 0-35 | T664: Female | U664: Spouse | V664: 300000 | W664: =IF(U664="self",V664,0) -> 0 | X664: =IF(U664="self",1,0) -> 0 | Y664: =O664-N664+1 -> 327 | Z664: =$Z$1 -> 46081 | AA664: =IF(MIN((Z664-N664)+1,Y664)<0,0,MIN((Z664-N664)+1,Y664)) -> 226 | AB664: Delhi | AC664: =AE664+AF664+AG664+AH664 -> 3470.8688 | AD664: 1 | AE664: =IFERROR(INDEX(SA!$C$4:$E$11,MATCH(Details!S664,SA!$C$4:$C$11,0),MATCH(Details!V664,SA!$C$4:$E$4,0)),0)*Y664/(F664-E664+1) -> 2941.4143 | AF664: =IF(AB664="Karnataka",AE664*9%,0) -> 0 | AG664: =IF(AB664="Karnataka",AE664*9%,0) -> 0 | AH664: =IF(AF664+AG664>0,0,AE664*18%) -> 529.45457 | AI664: =AE664*L664 -> 117.65657 | AJ664: =$AE664*M664 -> 661.81821 | AK664: =(AE664)*AA664/Y664 -> 2032.9041 | AL664: =AK664*(1-L664-M664) -> 1494.1845 | AM664: =AE664-AI664-AL664-AJ664 -> 667.75501 | AN664: =Z664-366 -> 45715 | AO664: =IF(AND(O664>Z664,N664>AN664),AE664,0) -> 2941.4143
A665: Valid | B665: 202508 | C665: GMC021090100AV | D665: A V GLOBAL CORPORATION PRIVATE LIMITED | E665: 45818 | F665: 46182 | G665: Aaryan Satish Pavnak | H665: 2220 | I665: 41722 | J665: ACK.F683A520250240.3 | K665: =N665 -> 45856 | L665: =IF(K665>=DATE(2022,4,1),4%,5%) -> 0.04 | M665: 0.225 | N665: 45856 | O665: 46182 | R665: 11 | S665: =VLOOKUP(R665,SA!$B$5:$C$11,2,1) -> 0-35 | T665: Male | U665: Son | V665: 300000 | W665: =IF(U665="self",V665,0) -> 0 | X665: =IF(U665="self",1,0) -> 0 | Y665: =O665-N665+1 -> 327 | Z665: =$Z$1 -> 46081 | AA665: =IF(MIN((Z665-N665)+1,Y665)<0,0,MIN((Z665-N665)+1,Y665)) -> 226 | AB665: Delhi | AC665: =AE665+AF665+AG665+AH665 -> 3470.8688 | AD665: 1 | AE665: =IFERROR(INDEX(SA!$C$4:$E$11,MATCH(Details!S665,SA!$C$4:$C$11,0),MATCH(Details!V665,SA!$C$4:$E$4,0)),0)*Y665/(F665-E665+1) -> 2941.4143 | AF665: =IF(AB665="Karnataka",AE665*9%,0) -> 0 | AG665: =IF(AB665="Karnataka",AE665*9%,0) -> 0 | AH665: =IF(AF665+AG665>0,0,AE665*18%) -> 529.45457 | AI665: =AE665*L665 -> 117.65657 | AJ665: =$AE665*M665 -> 661.81821 | AK665: =(AE665)*AA665/Y665 -> 2032.9041 | AL665: =AK665*(1-L665-M665) -> 1494.1845 | AM665: =AE665-AI665-AL665-AJ665 -> 667.75501 | AN665: =Z665-366 -> 45715 | AO665: =IF(AND(O665>Z665,N665>AN665),AE665,0) -> 2941.4143
A666: Valid | B666: 202508 | C666: GMC021090100AV | D666: A V GLOBAL CORPORATION PRIVATE LIMITED | E666: 45818 | F666: 46182 | G666: CHANDRA BALLABH | H666: 2353 | I666: 31959 | J666: ACK.F683A520250241.1 | K666: =N666 -> 45856 | L666: =IF(K666>=DATE(2022,4,1),4%,5%) -> 0.04 | M666: 0.225 | N666: 45856 | O666: 46182 | R666: 38 | S666: =VLOOKUP(R666,SA!$B$5:$C$11,2,1) -> 36-45 | T666: Female | U666: Self | V666: 300000 | W666: =IF(U666="self",V666,0) -> 300000 | X666: =IF(U666="self",1,0) -> 1 | Y666: =O666-N666+1 -> 327 | Z666: =$Z$1 -> 46081 | AA666: =IF(MIN((Z666-N666)+1,Y666)<0,0,MIN((Z666-N666)+1,Y666)) -> 226 | AB666: Delhi | AC666: =AE666+AF666+AG666+AH666 -> 4494.973 | AD666: 1 | AE666: =IFERROR(INDEX(SA!$C$4:$E$11,MATCH(Details!S666,SA!$C$4:$C$11,0),MATCH(Details!V666,SA!$C$4:$E$4,0)),0)*Y666/(F666-E666+1) -> 3809.2992 | AF666: =IF(AB666="Karnataka",AE666*9%,0) -> 0 | AG666: =IF(AB666="Karnataka",AE666*9%,0) -> 0 | AH666: =IF(AF666+AG666>0,0,AE666*18%) -> 685.67385 | AI666: =AE666*L666 -> 152.37197 | AJ666: =$AE666*M666 -> 857.09231 | AK666: =(AE666)*AA666/Y666 -> 2632.7266 | AL666: =AK666*(1-L666-M666) -> 1935.0541 | AM666: =AE666-AI666-AL666-AJ666 -> 864.7808 | AN666: =Z666-366 -> 45715 | AO666: =IF(AND(O666>Z666,N666>AN666),AE666,0) -> 3809.2992
A667: Valid | B667: 202508 | C667: GMC021090100AV | D667: A V GLOBAL CORPORATION PRIVATE LIMITED | E667: 45818 | F667: 46182 | G667: AVNI DOBRIYAL | H667: 2353 | I667: 45061 | J667: ACK.F683A520250241.2 | K667: =N667 -> 45856 | L667: =IF(K667>=DATE(2022,4,1),4%,5%) -> 0.04 | M667: 0.225 | N667: 45856 | O667: 46182 | R667: 2 | S667: =VLOOKUP(R667,SA!$B$5:$C$11,2,1) -> 0-35 | T667: Male | U667: Daughter | V667: 300000 | W667: =IF(U667="self",V667,0) -> 0 | X667: =IF(U667="self",1,0) -> 0 | Y667: =O667-N667+1 -> 327 | Z667: =$Z$1 -> 46081 | AA667: =IF(MIN((Z667-N667)+1,Y667)<0,0,MIN((Z667-N667)+1,Y667)) -> 226 | AB667: Delhi | AC667: =AE667+AF667+AG667+AH667 -> 3470.8688 | AD667: 1 | AE667: =IFERROR(INDEX(SA!$C$4:$E$11,MATCH(Details!S667,SA!$C$4:$C$11,0),MATCH(Details!V667,SA!$C$4:$E$4,0)),0)*Y667/(F667-E667+1) -> 2941.4143 | AF667: =IF(AB667="Karnataka",AE667*9%,0) -> 0 | AG667: =IF(AB667="Karnataka",AE667*9%,0) -> 0 | AH667: =IF(AF667+AG667>0,0,AE667*18%) -> 529.45457 | AI667: =AE667*L667 -> 117.65657 | AJ667: =$AE667*M667 -> 661.81821 | AK667: =(AE667)*AA667/Y667 -> 2032.9041 | AL667: =AK667*(1-L667-M667) -> 1494.1845 | AM667: =AE667-AI667-AL667-AJ667 -> 667.75501 | AN667: =Z667-366 -> 45715 | AO667: =IF(AND(O667>Z667,N667>AN667),AE667,0) -> 2941.4143
A668: Valid | B668: 202508 | C668: GMC021090100AV | D668: A V GLOBAL CORPORATION PRIVATE LIMITED | E668: 45818 | F668: 46182 | G668: ABHINAV DOBRIYAL | H668: 2353 | I668: 43816 | J668: ACK.F683A520250241.3 | K668: =N668 -> 45856 | L668: =IF(K668>=DATE(2022,4,1),4%,5%) -> 0.04 | M668: 0.225 | N668: 45856 | O668: 46182 | R668: 5 | S668: =VLOOKUP(R668,SA!$B$5:$C$11,2,1) -> 0-35 | T668: Female | U668: Son | V668: 300000 | W668: =IF(U668="self",V668,0) -> 0 | X668: =IF(U668="self",1,0) -> 0 | Y668: =O668-N668+1 -> 327 | Z668: =$Z$1 -> 46081 | AA668: =IF(MIN((Z668-N668)+1,Y668)<0,0,MIN((Z668-N668)+1,Y668)) -> 226 | AB668: Delhi | AC668: =AE668+AF668+AG668+AH668 -> 3470.8688 | AD668: 1 | AE668: =IFERROR(INDEX(SA!$C$4:$E$11,MATCH(Details!S668,SA!$C$4:$C$11,0),MATCH(Details!V668,SA!$C$4:$E$4,0)),0)*Y668/(F668-E668+1) -> 2941.4143 | AF668: =IF(AB668="Karnataka",AE668*9%,0) -> 0 | AG668: =IF(AB668="Karnataka",AE668*9%,0) -> 0 | AH668: =IF(AF668+AG668>0,0,AE668*18%) -> 529.45457 | AI668: =AE668*L668 -> 117.65657 | AJ668: =$AE668*M668 -> 661.81821 | AK668: =(AE668)*AA668/Y668 -> 2032.9041 | AL668: =AK668*(1-L668-M668) -> 1494.1845 | AM668: =AE668-AI668-AL668-AJ668 -> 667.75501 | AN668: =Z668-366 -> 45715 | AO668: =IF(AND(O668>Z668,N668>AN668),AE668,0) -> 2941.4143
A669: Valid | B669: 202508 | C669: GMC021090100AV | D669: A V GLOBAL CORPORATION PRIVATE LIMITED | E669: 45818 | F669: 46182 | G669: JYOTI | H669: 2353 | I669: 34974 | J669: ACK.F683A520250241.4 | K669: =N669 -> 45856 | L669: =IF(K669>=DATE(2022,4,1),4%,5%) -> 0.04 | M669: 0.225 | N669: 45856 | O669: 46182 | R669: 29 | S669: =VLOOKUP(R669,SA!$B$5:$C$11,2,1) -> 0-35 | T669: Male | U669: Spouse | V669: 300000 | W669: =IF(U669="self",V669,0) -> 0 | X669: =IF(U669="self",1,0) -> 0 | Y669: =O669-N669+1 -> 327 | Z669: =$Z$1 -> 46081 | AA669: =IF(MIN((Z669-N669)+1,Y669)<0,0,MIN((Z669-N669)+1,Y669)) -> 226 | AB669: Delhi | AC669: =AE669+AF669+AG669+AH669 -> 3470.8688 | AD669: 1 | AE669: =IFERROR(INDEX(SA!$C$4:$E$11,MATCH(Details!S669,SA!$C$4:$C$11,0),MATCH(Details!V669,SA!$C$4:$E$4,0)),0)*Y669/(F669-E669+1) -> 2941.4143 | AF669: =IF(AB669="Karnataka",AE669*9%,0) -> 0 | AG669: =IF(AB669="Karnataka",AE669*9%,0) -> 0 | AH669: =IF(AF669+AG669>0,0,AE669*18%) -> 529.45457 | AI669: =AE669*L669 -> 117.65657 | AJ669: =$AE669*M669 -> 661.81821 | AK669: =(AE669)*AA669/Y669 -> 2032.9041 | AL669: =AK669*(1-L669-M669) -> 1494.1845 | AM669: =AE669-AI669-AL669-AJ669 -> 667.75501 | AN669: =Z669-366 -> 45715 | AO669: =IF(AND(O669>Z669,N669>AN669),AE669,0) -> 2941.4143
A670: Valid | B670: 202508 | C670: GMC021090100AV | D670: A V GLOBAL CORPORATION PRIVATE LIMITED | E670: 45818 | F670: 46182 | G670: VAIBHAV JAGANNATH DESALE | H670: 2352 | I670: 33950 | J670: ACK.F683A520250239.1 | K670: =N670 -> 45856 | L670: =IF(K670>=DATE(2022,4,1),4%,5%) -> 0.04 | M670: 0.225 | N670: 45856 | O670: 46182 | R670: 32 | S670: =VLOOKUP(R670,SA!$B$5:$C$11,2,1) -> 0-35 | T670: Male | U670: Self | V670: 300000 | W670: =IF(U670="self",V670,0) -> 300000 | X670: =IF(U670="self",1,0) -> 1 | Y670: =O670-N670+1 -> 327 | Z670: =$Z$1 -> 46081 | AA670: =IF(MIN((Z670-N670)+1,Y670)<0,0,MIN((Z670-N670)+1,Y670)) -> 226 | AB670: Delhi | AC670: =AE670+AF670+AG670+AH670 -> 3470.8688 | AD670: 1 | AE670: =IFERROR(INDEX(SA!$C$4:$E$11,MATCH(Details!S670,SA!$C$4:$C$11,0),MATCH(Details!V670,SA!$C$4:$E$4,0)),0)*Y670/(F670-E670+1) -> 2941.4143 | AF670: =IF(AB670="Karnataka",AE670*9%,0) -> 0 | AG670: =IF(AB670="Karnataka",AE670*9%,0) -> 0 | AH670: =IF(AF670+AG670>0,0,AE670*18%) -> 529.45457 | AI670: =AE670*L670 -> 117.65657 | AJ670: =$AE670*M670 -> 661.81821 | AK670: =(AE670)*AA670/Y670 -> 2032.9041 | AL670: =AK670*(1-L670-M670) -> 1494.1845 | AM670: =AE670-AI670-AL670-AJ670 -> 667.75501 | AN670: =Z670-366 -> 45715 | AO670: =IF(AND(O670>Z670,N670>AN670),AE670,0) -> 2941.4143
A671: Deletion | B671: 202508 | C671: GMC021090100AV | D671: A V GLOBAL CORPORATION PRIVATE LIMITED | E671: 45818 | F671: 46182 | G671: Rajesh Rajendra Kadam | H671: 2221 | I671: 32502 | J671: ACK.F683A520250144.1 | K671: =N671 -> 45818 | L671: =IF(K671>=DATE(2022,4,1),4%,5%) -> 0.04 | M671: 0.225 | N671: 45818 | O671: 46182 | P671: 45869 | Q671: =P671+1 -> 45870 | R671: 36 | S671: =VLOOKUP(R671,SA!$B$5:$C$11,2,1) -> 36-45 | T671: Male | U671: Self | V671: -300000 | W671: =IF(U671="self",V671,0) -> -300000 | X671: =IF(U671="self",-1,0) -> -1 | Y671: =O671-Q671+1 -> 313 | Z671: =$Z$1 -> 46081 | AA671: =IF(MIN((Z671-Q671)+1,Y671)<0,0,MIN((Z671-Q671)+1,Y671)) -> 212 | AB671: Delhi | AC671: =AE671+AF671+AG671+AH671 -> 0 | AD671: -1 | AE671: =IFERROR(INDEX(SA!$C$4:$E$11,MATCH(Details!S671,SA!$C$4:$C$11,0),MATCH(Details!V671,SA!$C$4:$E$4,0)),0)*Y671/(F671-E671+1)*0 -> 0 | AF671: =IF(AB671="Karnataka",AE671*9%,0) -> 0 | AG671: =IF(AB671="Karnataka",AE671*9%,0) -> 0 | AH671: =IF(AF671+AG671>0,0,AE671*18%) -> 0 | AI671: =AE671*L671 -> 0 | AJ671: =$AE671*M671 -> 0 | AK671: =(AE671)*AA671/Y671 -> 0 | AL671: =AK671*(1-L671-M671) -> 0 | AM671: =AE671-AI671-AL671-AJ671 -> 0 | AN671: =Z671-366 -> 45715 | AO671: =IF(AND(O671>Z671,N671>AN671),AE671,0) -> 0 | AP671: Claim
A672: Deletion | B672: 202508 | C672: GMC021090100AV | D672: A V GLOBAL CORPORATION PRIVATE LIMITED | E672: 45818 | F672: 46182 | G672: Nikita Rajesh Kadam | H672: 2221 | I672: 32976 | J672: ACK.F683A520250144.2 | K672: =N672 -> 45818 | L672: =IF(K672>=DATE(2022,4,1),4%,5%) -> 0.04 | M672: 0.225 | N672: 45818 | O672: 46182 | P672: 45869 | Q672: =P672+1 -> 45870 | R672: 35 | S672: =VLOOKUP(R672,SA!$B$5:$C$11,2,1) -> 0-35 | T672: Female | U672: Spouse | V672: -300000 | W672: =IF(U672="self",V672,0) -> 0 | X672: =IF(U672="self",-1,0) -> 0 | Y672: =O672-Q672+1 -> 313 | Z672: =$Z$1 -> 46081 | AA672: =IF(MIN((Z672-Q672)+1,Y672)<0,0,MIN((Z672-Q672)+1,Y672)) -> 212 | AB672: Delhi | AC672: =AE672+AF672+AG672+AH672 -> 0 | AD672: -1 | AE672: =IFERROR(INDEX(SA!$C$4:$E$11,MATCH(Details!S672,SA!$C$4:$C$11,0),MATCH(Details!V672,SA!$C$4:$E$4,0)),0)*Y672/(F672-E672+1)*0 -> 0 | AF672: =IF(AB672="Karnataka",AE672*9%,0) -> 0 | AG672: =IF(AB672="Karnataka",AE672*9%,0) -> 0 | AH672: =IF(AF672+AG672>0,0,AE672*18%) -> 0 | AI672: =AE672*L672 -> 0 | AJ672: =$AE672*M672 -> 0 | AK672: =(AE672)*AA672/Y672 -> 0 | AL672: =AK672*(1-L672-M672) -> 0 | AM672: =AE672-AI672-AL672-AJ672 -> 0 | AN672: =Z672-366 -> 45715 | AO672: =IF(AND(O672>Z672,N672>AN672),AE672,0) -> 0 | AP672: Claim
A673: Deletion | B673: 202508 | C673: GMC021090100AV | D673: A V GLOBAL CORPORATION PRIVATE LIMITED | E673: 45818 | F673: 46182 | G673: Chitravi Rajesh Kadam | H673: 2221 | I673: 44680 | J673: ACK.F683A520250144.3 | K673: =N673 -> 45818 | L673: =IF(K673>=DATE(2022,4,1),4%,5%) -> 0.04 | M673: 0.225 | N673: 45818 | O673: 46182 | P673: 45869 | Q673: =P673+1 -> 45870 | R673: 3 | S673: =VLOOKUP(R673,SA!$B$5:$C$11,2,1) -> 0-35 | T673: Female | U673: Daughter | V673: -300000 | W673: =IF(U673="self",V673,0) -> 0 | X673: =IF(U673="self",-1,0) -> 0 | Y673: =O673-Q673+1 -> 313 | Z673: =$Z$1 -> 46081 | AA673: =IF(MIN((Z673-Q673)+1,Y673)<0,0,MIN((Z673-Q673)+1,Y673)) -> 212 | AB673: Delhi | AC673: =AE673+AF673+AG673+AH673 -> 0 | AD673: -1 | AE673: =IFERROR(INDEX(SA!$C$4:$E$11,MATCH(Details!S673,SA!$C$4:$C$11,0),MATCH(Details!V673,SA!$C$4:$E$4,0)),0)*Y673/(F673-E673+1)*0 -> 0 | AF673: =IF(AB673="Karnataka",AE673*9%,0) -> 0 | AG673: =IF(AB673="Karnataka",AE673*9%,0) -> 0 | AH673: =IF(AF673+AG673>0,0,AE673*18%) -> 0 | AI673: =AE673*L673 -> 0 | AJ673: =$AE673*M673 -> 0 | AK673: =(AE673)*AA673/Y673 -> 0 | AL673: =AK673*(1-L673-M673) -> 0 | AM673: =AE673-AI673-AL673-AJ673 -> 0 | AN673: =Z673-366 -> 45715 | AO673: =IF(AND(O673>Z673,N673>AN673),AE673,0) -> 0 | AP673: Claim
A674: Valid | B674: 202509 | C674: GMC021090100AV | D674: A V GLOBAL CORPORATION PRIVATE LIMITED | E674: 45818 | F674: 46182 | G674: Tarun Kumar Sharma | H674: 2359 | I674: 31-Mar-1989 | J674: ACK.F683A520250242.1 | K674: =N674 -> 45888 | L674: =IF(K674>=DATE(2022,4,1),4%,5%) -> 0.04 | M674: 0.225 | N674: 45888 | O674: 46182 | R674: 36 | S674: =VLOOKUP(R674,SA!$B$5:$C$11,2,1) -> 36-45 | T674: MALE | U674: Self | V674: 300000 | W674: =IF(U674="self",V674,0) -> 300000 | X674: =IF(U674="self",1,0) -> 1 | Y674: =O674-N674+1 -> 295 | Z674: =$Z$1 -> 46081 | AA674: =IF(MIN((Z674-N674)+1,Y674)<0,0,MIN((Z674-N674)+1,Y674)) -> 194 | AB674: Delhi | AC674: =AE674+AF674+AG674+AH674 -> 4055.098 | AD674: 1 | AE674: =IFERROR(INDEX(SA!$C$4:$E$11,MATCH(Details!S674,SA!$C$4:$C$11,0),MATCH(Details!V674,SA!$C$4:$E$4,0)),0)*Y674/(F674-E674+1) -> 3436.5237 | AF674: =IF(AB674="Karnataka",AE674*9%,0) -> 0 | AG674: =IF(AB674="Karnataka",AE674*9%,0) -> 0 | AH674: =IF(AF674+AG674>0,0,AE674*18%) -> 618.57427 | AI674: =AE674*L674 -> 137.46095 | AJ674: =$AE674*M674 -> 773.21783 | AK674: =(AE674)*AA674/Y674 -> 2259.9512 | AL674: =AK674*(1-L674-M674) -> 1661.0641 | AM674: =AE674-AI674-AL674-AJ674 -> 864.7808 | AN674: =Z674-366 -> 45715 | AO674: =IF(AND(O674>Z674,N674>AN674),AE674,0) -> 3436.5237
A675: Valid | B675: 202509 | C675: GMC021090100AV | D675: A V GLOBAL CORPORATION PRIVATE LIMITED | E675: 45818 | F675: 46182 | G675: Hemlata Sharma | H675: 2359 | I675: 07-Jan-1992 | J675: ACK.F683A520250242.2 | K675: =N675 -> 45888 | L675: =IF(K675>=DATE(2022,4,1),4%,5%) -> 0.04 | M675: 0.225 | N675: 45888 | O675: 46182 | R675: 33 | S675: =VLOOKUP(R675,SA!$B$5:$C$11,2,1) -> 0-35 | T675: FEMALE | U675: Spouse | V675: 300000 | W675: =IF(U675="self",V675,0) -> 0 | X675: =IF(U675="self",1,0) -> 0 | Y675: =O675-N675+1 -> 295 | Z675: =$Z$1 -> 46081 | AA675: =IF(MIN((Z675-N675)+1,Y675)<0,0,MIN((Z675-N675)+1,Y675)) -> 194 | AB675: Delhi | AC675: =AE675+AF675+AG675+AH675 -> 3131.212 | AD675: 1 | AE675: =IFERROR(INDEX(SA!$C$4:$E$11,MATCH(Details!S675,SA!$C$4:$C$11,0),MATCH(Details!V675,SA!$C$4:$E$4,0)),0)*Y675/(F675-E675+1) -> 2653.5695 | AF675: =IF(AB675="Karnataka",AE675*9%,0) -> 0 | AG675: =IF(AB675="Karnataka",AE675*9%,0) -> 0 | AH675: =IF(AF675+AG675>0,0,AE675*18%) -> 477.6425 | AI675: =AE675*L675 -> 106.14278 | AJ675: =$AE675*M675 -> 597.05313 | AK675: =(AE675)*AA675/Y675 -> 1745.0592 | AL675: =AK675*(1-L675-M675) -> 1282.6185 | AM675: =AE675-AI675-AL675-AJ675 -> 667.75501 | AN675: =Z675-366 -> 45715 | AO675: =IF(AND(O675>Z675,N675>AN675),AE675,0) -> 2653.5695
A676: Valid | B676: 202509 | C676: GMC021090100AV | D676: A V GLOBAL CORPORATION PRIVATE LIMITED | E676: 45818 | F676: 46182 | G676: Ayush Sharma | H676: 2359 | I676: 06-Dec-2012 | J676: ACK.F683A520250242.3 | K676: =N676 -> 45888 | L676: =IF(K676>=DATE(2022,4,1),4%,5%) -> 0.04 | M676: 0.225 | N676: 45888 | O676: 46182 | R676: 12 | S676: =VLOOKUP(R676,SA!$B$5:$C$11,2,1) -> 0-35 | T676: MALE | U676: Son | V676: 300000 | W676: =IF(U676="self",V676,0) -> 0 | X676: =IF(U676="self",1,0) -> 0 | Y676: =O676-N676+1 -> 295 | Z676: =$Z$1 -> 46081 | AA676: =IF(MIN((Z676-N676)+1,Y676)<0,0,MIN((Z676-N676)+1,Y676)) -> 194 | AB676: Delhi | AC676: =AE676+AF676+AG676+AH676 -> 3131.212 | AD676: 1 | AE676: =IFERROR(INDEX(SA!$C$4:$E$11,MATCH(Details!S676,SA!$C$4:$C$11,0),MATCH(Details!V676,SA!$C$4:$E$4,0)),0)*Y676/(F676-E676+1) -> 2653.5695 | AF676: =IF(AB676="Karnataka",AE676*9%,0) -> 0 | AG676: =IF(AB676="Karnataka",AE676*9%,0) -> 0 | AH676: =IF(AF676+AG676>0,0,AE676*18%) -> 477.6425 | AI676: =AE676*L676 -> 106.14278 | AJ676: =$AE676*M676 -> 597.05313 | AK676: =(AE676)*AA676/Y676 -> 1745.0592 | AL676: =AK676*(1-L676-M676) -> 1282.6185 | AM676: =AE676-AI676-AL676-AJ676 -> 667.75501 | AN676: =Z676-366 -> 45715 | AO676: =IF(AND(O676>Z676,N676>AN676),AE676,0) -> 2653.5695
A677: Valid | B677: 202509 | C677: GMC021090100AV | D677: A V GLOBAL CORPORATION PRIVATE LIMITED | E677: 45818 | F677: 46182 | G677: Devanshi Sharma | H677: 2359 | I677: 26-Dec-2017 | J677: ACK.F683A520250242.4 | K677: =N677 -> 45888 | L677: =IF(K677>=DATE(2022,4,1),4%,5%) -> 0.04 | M677: 0.225 | N677: 45888 | O677: 46182 | R677: 7 | S677: =VLOOKUP(R677,SA!$B$5:$C$11,2,1) -> 0-35 | T677: FEMALE | U677: Daughter | V677: 300000 | W677: =IF(U677="self",V677,0) -> 0 | X677: =IF(U677="self",1,0) -> 0 | Y677: =O677-N677+1 -> 295 | Z677: =$Z$1 -> 46081 | AA677: =IF(MIN((Z677-N677)+1,Y677)<0,0,MIN((Z677-N677)+1,Y677)) -> 194 | AB677: Delhi | AC677: =AE677+AF677+AG677+AH677 -> 3131.212 | AD677: 1 | AE677: =IFERROR(INDEX(SA!$C$4:$E$11,MATCH(Details!S677,SA!$C$4:$C$11,0),MATCH(Details!V677,SA!$C$4:$E$4,0)),0)*Y677/(F677-E677+1) -> 2653.5695 | AF677: =IF(AB677="Karnataka",AE677*9%,0) -> 0 | AG677: =IF(AB677="Karnataka",AE677*9%,0) -> 0 | AH677: =IF(AF677+AG677>0,0,AE677*18%) -> 477.6425 | AI677: =AE677*L677 -> 106.14278 | AJ677: =$AE677*M677 -> 597.05313 | AK677: =(AE677)*AA677/Y677 -> 1745.0592 | AL677: =AK677*(1-L677-M677) -> 1282.6185 | AM677: =AE677-AI677-AL677-AJ677 -> 667.75501 | AN677: =Z677-366 -> 45715 | AO677: =IF(AND(O677>Z677,N677>AN677),AE677,0) -> 2653.5695
A678: Deletion | B678: 202509 | C678: GMC021090100AV | D678: A V GLOBAL CORPORATION PRIVATE LIMITED | E678: 45818 | F678: 46182 | G678: Tarun Kumar Sharma | H678: 2359 | I678: 31-Mar-1989 | J678: ACK.F683A520250242.1 | K678: =N678 -> 45888 | L678: =IF(K678>=DATE(2022,4,1),4%,5%) -> 0.04 | M678: 0.225 | N678: 45888 | O678: 46182 | P678: 45887 | Q678: =P678+1 -> 45888 | R678: 36 | S678: =VLOOKUP(R678,SA!$B$5:$C$11,2,1) -> 36-45 | T678: MALE | U678: Self | V678: -300000 | W678: =IF(U678="self",V678,0) -> -300000 | X678: =IF(U678="self",-1,0) -> -1 | Y678: =O678-Q678+1 -> 295 | Z678: =$Z$1 -> 46081 | AA678: =IF(MIN((Z678-Q678)+1,Y678)<0,0,MIN((Z678-Q678)+1,Y678)) -> 194 | AB678: Delhi | AC678: =AE678+AF678+AG678+AH678 -> -4055.098 | AD678: -1 | AE678: =-IFERROR(INDEX(SA!$C$4:$E$11,MATCH(Details!S678,SA!$C$4:$C$11,0),MATCH(-Details!V678,SA!$C$4:$E$4,0)),0)*Y678/(F678-E678+1) -> -3436.5237 | AF678: =IF(AB678="Karnataka",AE678*9%,0) -> 0 | AG678: =IF(AB678="Karnataka",AE678*9%,0) -> 0 | AH678: =IF(AF678+AG678>0,0,AE678*18%) -> -618.57427 | AI678: =AE678*L678 -> -137.46095 | AJ678: =$AE678*M678 -> -773.21783 | AK678: =(AE678)*AA678/Y678 -> -2259.9512 | AL678: =AK678*(1-L678-M678) -> -1661.0641 | AM678: =AE678-AI678-AL678-AJ678 -> -864.7808 | AN678: =Z678-366 -> 45715 | AO678: =IF(AND(O678>Z678,N678>AN678),AE678,0) -> -3436.5237 | AP678: No claim
A679: Deletion | B679: 202509 | C679: GMC021090100AV | D679: A V GLOBAL CORPORATION PRIVATE LIMITED | E679: 45818 | F679: 46182 | G679: Hemlata Sharma | H679: 2359 | I679: 07-Jan-1992 | J679: ACK.F683A520250242.2 | K679: =N679 -> 45888 | L679: =IF(K679>=DATE(2022,4,1),4%,5%) -> 0.04 | M679: 0.225 | N679: 45888 | O679: 46182 | P679: 45887 | Q679: =P679+1 -> 45888 | R679: 33 | S679: =VLOOKUP(R679,SA!$B$5:$C$11,2,1) -> 0-35 | T679: FEMALE | U679: Spouse | V679: -300000 | W679: =IF(U679="self",V679,0) -> 0 | X679: =IF(U679="self",-1,0) -> 0 | Y679: =O679-Q679+1 -> 295 | Z679: =$Z$1 -> 46081 | AA679: =IF(MIN((Z679-Q679)+1,Y679)<0,0,MIN((Z679-Q679)+1,Y679)) -> 194 | AB679: Delhi | AC679: =AE679+AF679+AG679+AH679 -> -3131.212 | AD679: -1 | AE679: =-IFERROR(INDEX(SA!$C$4:$E$11,MATCH(Details!S679,SA!$C$4:$C$11,0),MATCH(-Details!V679,SA!$C$4:$E$4,0)),0)*Y679/(F679-E679+1) -> -2653.5695 | AF679: =IF(AB679="Karnataka",AE679*9%,0) -> 0 | AG679: =IF(AB679="Karnataka",AE679*9%,0) -> 0 | AH679: =IF(AF679+AG679>0,0,AE679*18%) -> -477.6425 | AI679: =AE679*L679 -> -106.14278 | AJ679: =$AE679*M679 -> -597.05313 | AK679: =(AE679)*AA679/Y679 -> -1745.0592 | AL679: =AK679*(1-L679-M679) -> -1282.6185 | AM679: =AE679-AI679-AL679-AJ679 -> -667.75501 | AN679: =Z679-366 -> 45715 | AO679: =IF(AND(O679>Z679,N679>AN679),AE679,0) -> -2653.5695 | AP679: No claim
A680: Deletion | B680: 202509 | C680: GMC021090100AV | D680: A V GLOBAL CORPORATION PRIVATE LIMITED | E680: 45818 | F680: 46182 | G680: Ayush Sharma | H680: 2359 | I680: 06-Dec-2012 | J680: ACK.F683A520250242.3 | K680: =N680 -> 45888 | L680: =IF(K680>=DATE(2022,4,1),4%,5%) -> 0.04 | M680: 0.225 | N680: 45888 | O680: 46182 | P680: 45887 | Q680: =P680+1 -> 45888 | R680: 12 | S680: =VLOOKUP(R680,SA!$B$5:$C$11,2,1) -> 0-35 | T680: MALE | U680: Son | V680: -300000 | W680: =IF(U680="self",V680,0) -> 0 | X680: =IF(U680="self",-1,0) -> 0 | Y680: =O680-Q680+1 -> 295 | Z680: =$Z$1 -> 46081 | AA680: =IF(MIN((Z680-Q680)+1,Y680)<0,0,MIN((Z680-Q680)+1,Y680)) -> 194 | AB680: Delhi | AC680: =AE680+AF680+AG680+AH680 -> -3131.212 | AD680: -1 | AE680: =-IFERROR(INDEX(SA!$C$4:$E$11,MATCH(Details!S680,SA!$C$4:$C$11,0),MATCH(-Details!V680,SA!$C$4:$E$4,0)),0)*Y680/(F680-E680+1) -> -2653.5695 | AF680: =IF(AB680="Karnataka",AE680*9%,0) -> 0 | AG680: =IF(AB680="Karnataka",AE680*9%,0) -> 0 | AH680: =IF(AF680+AG680>0,0,AE680*18%) -> -477.6425 | AI680: =AE680*L680 -> -106.14278 | AJ680: =$AE680*M680 -> -597.05313 | AK680: =(AE680)*AA680/Y680 -> -1745.0592 | AL680: =AK680*(1-L680-M680) -> -1282.6185 | AM680: =AE680-AI680-AL680-AJ680 -> -667.75501 | AN680: =Z680-366 -> 45715 | AO680: =IF(AND(O680>Z680,N680>AN680),AE680,0) -> -2653.5695 | AP680: No claim
A681: Deletion | B681: 202509 | C681: GMC021090100AV | D681: A V GLOBAL CORPORATION PRIVATE LIMITED | E681: 45818 | F681: 46182 | G681: Devanshi Sharma | H681: 2359 | I681: 26-Dec-2017 | J681: ACK.F683A520250242.4 | K681: =N681 -> 45888 | L681: =IF(K681>=DATE(2022,4,1),4%,5%) -> 0.04 | M681: 0.225 | N681: 45888 | O681: 46182 | P681: 45887 | Q681: =P681+1 -> 45888 | R681: 7 | S681: =VLOOKUP(R681,SA!$B$5:$C$11,2,1) -> 0-35 | T681: FEMALE | U681: Daughter | V681: -300000 | W681: =IF(U681="self",V681,0) -> 0 | X681: =IF(U681="self",-1,0) -> 0 | Y681: =O681-Q681+1 -> 295 | Z681: =$Z$1 -> 46081 | AA681: =IF(MIN((Z681-Q681)+1,Y681)<0,0,MIN((Z681-Q681)+1,Y681)) -> 194 | AB681: Delhi | AC681: =AE681+AF681+AG681+AH681 -> -3131.212 | AD681: -1 | AE681: =-IFERROR(INDEX(SA!$C$4:$E$11,MATCH(Details!S681,SA!$C$4:$C$11,0),MATCH(-Details!V681,SA!$C$4:$E$4,0)),0)*Y681/(F681-E681+1) -> -2653.5695 | AF681: =IF(AB681="Karnataka",AE681*9%,0) -> 0 | AG681: =IF(AB681="Karnataka",AE681*9%,0) -> 0 | AH681: =IF(AF681+AG681>0,0,AE681*18%) -> -477.6425 | AI681: =AE681*L681 -> -106.14278 | AJ681: =$AE681*M681 -> -597.05313 | AK681: =(AE681)*AA681/Y681 -> -1745.0592 | AL681: =AK681*(1-L681-M681) -> -1282.6185 | AM681: =AE681-AI681-AL681-AJ681 -> -667.75501 | AN681: =Z681-366 -> 45715 | AO681: =IF(AND(O681>Z681,N681>AN681),AE681,0) -> -2653.5695 | AP681: No claim
A682: Valid | B682: 202509 | C682: GMC021090100AV | D682: A V GLOBAL CORPORATION PRIVATE LIMITED | E682: 45818 | F682: 46182 | G682: SAANVI SACHIN SURYAVANSHI | H682: 2361 | I682: 31612 | J682: ACK.F683A520250247.1 | K682: =N682 -> 45901 | L682: =IF(K682>=DATE(2022,4,1),4%,5%) -> 0.04 | M682: 0.225 | N682: 45901 | O682: 46182 | R682: 39 | S682: =VLOOKUP(R682,SA!$B$5:$C$11,2,1) -> 36-45 | T682: Female | U682: Self | V682: 300000 | W682: =IF(U682="self",V682,0) -> 300000 | X682: =IF(U682="self",1,0) -> 1 | Y682: =O682-N682+1 -> 282 | Z682: =$Z$1 -> 46081 | AA682: =IF(MIN((Z682-N682)+1,Y682)<0,0,MIN((Z682-N682)+1,Y682)) -> 181 | AB682: Delhi | AC682: =AE682+AF682+AG682+AH682 -> 3876.3987 | AD682: 1 | AE682: =IFERROR(INDEX(SA!$C$4:$E$11,MATCH(Details!S682,SA!$C$4:$C$11,0),MATCH(Details!V682,SA!$C$4:$E$4,0)),0)*Y682/(F682-E682+1) -> 3285.0837 | AF682: =IF(AB682="Karnataka",AE682*9%,0) -> 0 | AG682: =IF(AB682="Karnataka",AE682*9%,0) -> 0 | AH682: =IF(AF682+AG682>0,0,AE682*18%) -> 591.31506 | AI682: =AE682*L682 -> 131.40335 | AJ682: =$AE682*M682 -> 739.14383 | AK682: =(AE682)*AA682/Y682 -> 2108.5112 | AL682: =AK682*(1-L682-M682) -> 1549.7557 | AM682: =AE682-AI682-AL682-AJ682 -> 864.7808 | AN682: =Z682-366 -> 45715 | AO682: =IF(AND(O682>Z682,N682>AN682),AE682,0) -> 3285.0837
A683: Valid | B683: 202509 | C683: GMC021090100AV | D683: A V GLOBAL CORPORATION PRIVATE LIMITED | E683: 45818 | F683: 46182 | G683: SACHIN CHANDRAKANT SURYAVANSHI | H683: 2361 | I683: 33422 | J683: ACK.F683A520250247.2 | K683: =N683 -> 45901 | L683: =IF(K683>=DATE(2022,4,1),4%,5%) -> 0.04 | M683: 0.225 | N683: 45901 | O683: 46182 | R683: 34 | S683: =VLOOKUP(R683,SA!$B$5:$C$11,2,1) -> 0-35 | T683: Male | U683: Spouse | V683: 300000 | W683: =IF(U683="self",V683,0) -> 0 | X683: =IF(U683="self",1,0) -> 0 | Y683: =O683-N683+1 -> 282 | Z683: =$Z$1 -> 46081 | AA683: =IF(MIN((Z683-N683)+1,Y683)<0,0,MIN((Z683-N683)+1,Y683)) -> 181 | AB683: Delhi | AC683: =AE683+AF683+AG683+AH683 -> 2993.2263 | AD683: 1 | AE683: =IFERROR(INDEX(SA!$C$4:$E$11,MATCH(Details!S683,SA!$C$4:$C$11,0),MATCH(Details!V683,SA!$C$4:$E$4,0)),0)*Y683/(F683-E683+1) -> 2536.6325 | AF683: =IF(AB683="Karnataka",AE683*9%,0) -> 0 | AG683: =IF(AB683="Karnataka",AE683*9%,0) -> 0 | AH683: =IF(AF683+AG683>0,0,AE683*18%) -> 456.59385 | AI683: =AE683*L683 -> 101.4653 | AJ683: =$AE683*M683 -> 570.74231 | AK683: =(AE683)*AA683/Y683 -> 1628.1223 | AL683: =AK683*(1-L683-M683) -> 1196.6699 | AM683: =AE683-AI683-AL683-AJ683 -> 667.75501 | AN683: =Z683-366 -> 45715 | AO683: =IF(AND(O683>Z683,N683>AN683),AE683,0) -> 2536.6325
A684: Valid | B684: 202509 | C684: GMC021090100AV | D684: A V GLOBAL CORPORATION PRIVATE LIMITED | E684: 45818 | F684: 46182 | G684: SADHVI SACHIN SURYAVANSHI | H684: 2361 | I684: 44195 | J684: ACK.F683A520250247.3 | K684: =N684 -> 45901 | L684: =IF(K684>=DATE(2022,4,1),4%,5%) -> 0.04 | M684: 0.225 | N684: 45901 | O684: 46182 | R684: 4 | S684: =VLOOKUP(R684,SA!$B$5:$C$11,2,1) -> 0-35 | T684: Female | U684: Daughter | V684: 300000 | W684: =IF(U684="self",V684,0) -> 0 | X684: =IF(U684="self",1,0) -> 0 | Y684: =O684-N684+1 -> 282 | Z684: =$Z$1 -> 46081 | AA684: =IF(MIN((Z684-N684)+1,Y684)<0,0,MIN((Z684-N684)+1,Y684)) -> 181 | AB684: Delhi | AC684: =AE684+AF684+AG684+AH684 -> 2993.2263 | AD684: 1 | AE684: =IFERROR(INDEX(SA!$C$4:$E$11,MATCH(Details!S684,SA!$C$4:$C$11,0),MATCH(Details!V684,SA!$C$4:$E$4,0)),0)*Y684/(F684-E684+1) -> 2536.6325 | AF684: =IF(AB684="Karnataka",AE684*9%,0) -> 0 | AG684: =IF(AB684="Karnataka",AE684*9%,0) -> 0 | AH684: =IF(AF684+AG684>0,0,AE684*18%) -> 456.59385 | AI684: =AE684*L684 -> 101.4653 | AJ684: =$AE684*M684 -> 570.74231 | AK684: =(AE684)*AA684/Y684 -> 1628.1223 | AL684: =AK684*(1-L684-M684) -> 1196.6699 | AM684: =AE684-AI684-AL684-AJ684 -> 667.75501 | AN684: =Z684-366 -> 45715 | AO684: =IF(AND(O684>Z684,N684>AN684),AE684,0) -> 2536.6325
A685: Valid | B685: 202509 | C685: GMC021090100AV | D685: A V GLOBAL CORPORATION PRIVATE LIMITED | E685: 45818 | F685: 46182 | G685: KUSH SACHIN SURYAVANSHI | H685: 2361 | I685: 44195 | J685: ACK.F683A520250247.4 | K685: =N685 -> 45901 | L685: =IF(K685>=DATE(2022,4,1),4%,5%) -> 0.04 | M685: 0.225 | N685: 45901 | O685: 46182 | R685: 4 | S685: =VLOOKUP(R685,SA!$B$5:$C$11,2,1) -> 0-35 | T685: Male | U685: Son | V685: 300000 | W685: =IF(U685="self",V685,0) -> 0 | X685: =IF(U685="self",1,0) -> 0 | Y685: =O685-N685+1 -> 282 | Z685: =$Z$1 -> 46081 | AA685: =IF(MIN((Z685-N685)+1,Y685)<0,0,MIN((Z685-N685)+1,Y685)) -> 181 | AB685: Delhi | AC685: =AE685+AF685+AG685+AH685 -> 2993.2263 | AD685: 1 | AE685: =IFERROR(INDEX(SA!$C$4:$E$11,MATCH(Details!S685,SA!$C$4:$C$11,0),MATCH(Details!V685,SA!$C$4:$E$4,0)),0)*Y685/(F685-E685+1) -> 2536.6325 | AF685: =IF(AB685="Karnataka",AE685*9%,0) -> 0 | AG685: =IF(AB685="Karnataka",AE685*9%,0) -> 0 | AH685: =IF(AF685+AG685>0,0,AE685*18%) -> 456.59385 | AI685: =AE685*L685 -> 101.4653 | AJ685: =$AE685*M685 -> 570.74231 | AK685: =(AE685)*AA685/Y685 -> 1628.1223 | AL685: =AK685*(1-L685-M685) -> 1196.6699 | AM685: =AE685-AI685-AL685-AJ685 -> 667.75501 | AN685: =Z685-366 -> 45715 | AO685: =IF(AND(O685>Z685,N685>AN685),AE685,0) -> 2536.6325
A686: Valid | B686: 202509 | C686: GMC021090100AV | D686: A V GLOBAL CORPORATION PRIVATE LIMITED | E686: 45818 | F686: 46182 | G686: MUKESH SINGH RAWAT | H686: 2360 | I686: 35702 | J686: ACK.F683A520250243.1 | K686: =N686 -> 45901 | L686: =IF(K686>=DATE(2022,4,1),4%,5%) -> 0.04 | M686: 0.225 | N686: 45901 | O686: 46182 | R686: 27 | S686: =VLOOKUP(R686,SA!$B$5:$C$11,2,1) -> 0-35 | T686: Male | U686: Self | V686: 300000 | W686: =IF(U686="self",V686,0) -> 300000 | X686: =IF(U686="self",1,0) -> 1 | Y686: =O686-N686+1 -> 282 | Z686: =$Z$1 -> 46081 | AA686: =IF(MIN((Z686-N686)+1,Y686)<0,0,MIN((Z686-N686)+1,Y686)) -> 181 | AB686: Delhi | AC686: =AE686+AF686+AG686+AH686 -> 2993.2263 | AD686: 1 | AE686: =IFERROR(INDEX(SA!$C$4:$E$11,MATCH(Details!S686,SA!$C$4:$C$11,0),MATCH(Details!V686,SA!$C$4:$E$4,0)),0)*Y686/(F686-E686+1) -> 2536.6325 | AF686: =IF(AB686="Karnataka",AE686*9%,0) -> 0 | AG686: =IF(AB686="Karnataka",AE686*9%,0) -> 0 | AH686: =IF(AF686+AG686>0,0,AE686*18%) -> 456.59385 | AI686: =AE686*L686 -> 101.4653 | AJ686: =$AE686*M686 -> 570.74231 | AK686: =(AE686)*AA686/Y686 -> 1628.1223 | AL686: =AK686*(1-L686-M686) -> 1196.6699 | AM686: =AE686-AI686-AL686-AJ686 -> 667.75501 | AN686: =Z686-366 -> 45715 | AO686: =IF(AND(O686>Z686,N686>AN686),AE686,0) -> 2536.6325
A687: Valid | B687: 202509 | C687: GMC021090100AV | D687: A V GLOBAL CORPORATION PRIVATE LIMITED | E687: 45818 | F687: 46182 | G687: VIJAYAKUMAR KRISHNAN | H687: 2362 | I687: 35872 | J687: ACK.F683A520250245.1 | K687: =N687 -> 45901 | L687: =IF(K687>=DATE(2022,4,1),4%,5%) -> 0.04 | M687: 0.225 | N687: 45901 | O687: 46182 | R687: 27 | S687: =VLOOKUP(R687,SA!$B$5:$C$11,2,1) -> 0-35 | T687: Male | U687: Self | V687: 300000 | W687: =IF(U687="self",V687,0) -> 300000 | X687: =IF(U687="self",1,0) -> 1 | Y687: =O687-N687+1 -> 282 | Z687: =$Z$1 -> 46081 | AA687: =IF(MIN((Z687-N687)+1,Y687)<0,0,MIN((Z687-N687)+1,Y687)) -> 181 | AB687: Delhi | AC687: =AE687+AF687+AG687+AH687 -> 2993.2263 | AD687: 1 | AE687: =IFERROR(INDEX(SA!$C$4:$E$11,MATCH(Details!S687,SA!$C$4:$C$11,0),MATCH(Details!V687,SA!$C$4:$E$4,0)),0)*Y687/(F687-E687+1) -> 2536.6325 | AF687: =IF(AB687="Karnataka",AE687*9%,0) -> 0 | AG687: =IF(AB687="Karnataka",AE687*9%,0) -> 0 | AH687: =IF(AF687+AG687>0,0,AE687*18%) -> 456.59385 | AI687: =AE687*L687 -> 101.4653 | AJ687: =$AE687*M687 -> 570.74231 | AK687: =(AE687)*AA687/Y687 -> 1628.1223 | AL687: =AK687*(1-L687-M687) -> 1196.6699 | AM687: =AE687-AI687-AL687-AJ687 -> 667.75501 | AN687: =Z687-366 -> 45715 | AO687: =IF(AND(O687>Z687,N687>AN687),AE687,0) -> 2536.6325
A688: Valid | B688: 202509 | C688: GMC021090100AV | D688: A V GLOBAL CORPORATION PRIVATE LIMITED | E688: 45818 | F688: 46182 | G688: RUCHIR RAMESH PALAVAKAR | H688: 2363 | I688: 33743 | J688: ACK.F683A520250244.1 | K688: =N688 -> 45903 | L688: =IF(K688>=DATE(2022,4,1),4%,5%) -> 0.04 | M688: 0.225 | N688: 45903 | O688: 46182 | R688: 33 | S688: =VLOOKUP(R688,SA!$B$5:$C$11,2,1) -> 0-35 | T688: Male | U688: Self | V688: 300000 | W688: =IF(U688="self",V688,0) -> 300000 | X688: =IF(U688="self",1,0) -> 1 | Y688: =O688-N688+1 -> 280 | Z688: =$Z$1 -> 46081 | AA688: =IF(MIN((Z688-N688)+1,Y688)<0,0,MIN((Z688-N688)+1,Y688)) -> 179 | AB688: Delhi | AC688: =AE688+AF688+AG688+AH688 -> 2971.9978 | AD688: 1 | AE688: =IFERROR(INDEX(SA!$C$4:$E$11,MATCH(Details!S688,SA!$C$4:$C$11,0),MATCH(Details!V688,SA!$C$4:$E$4,0)),0)*Y688/(F688-E688+1) -> 2518.6422 | AF688: =IF(AB688="Karnataka",AE688*9%,0) -> 0 | AG688: =IF(AB688="Karnataka",AE688*9%,0) -> 0 | AH688: =IF(AF688+AG688>0,0,AE688*18%) -> 453.35559 | AI688: =AE688*L688 -> 100.74569 | AJ688: =$AE688*M688 -> 566.69449 | AK688: =(AE688)*AA688/Y688 -> 1610.132 | AL688: =AK688*(1-L688-M688) -> 1183.447 | AM688: =AE688-AI688-AL688-AJ688 -> 667.75501 | AN688: =Z688-366 -> 45715 | AO688: =IF(AND(O688>Z688,N688>AN688),AE688,0) -> 2518.6422
A689: Valid | B689: 202509 | C689: GMC021090100AV | D689: A V GLOBAL CORPORATION PRIVATE LIMITED | E689: 45818 | F689: 46182 | G689: SAYALI HARISHCHANDRA BHAGAT | H689: 2363 | I689: 35720 | J689: ACK.F683A520250244.2 | K689: =N689 -> 45903 | L689: =IF(K689>=DATE(2022,4,1),4%,5%) -> 0.04 | M689: 0.225 | N689: 45903 | O689: 46182 | R689: 27 | S689: =VLOOKUP(R689,SA!$B$5:$C$11,2,1) -> 0-35 | T689: Female | U689: Spouse | V689: 300000 | W689: =IF(U689="self",V689,0) -> 0 | X689: =IF(U689="self",1,0) -> 0 | Y689: =O689-N689+1 -> 280 | Z689: =$Z$1 -> 46081 | AA689: =IF(MIN((Z689-N689)+1,Y689)<0,0,MIN((Z689-N689)+1,Y689)) -> 179 | AB689: Delhi | AC689: =AE689+AF689+AG689+AH689 -> 2971.9978 | AD689: 1 | AE689: =IFERROR(INDEX(SA!$C$4:$E$11,MATCH(Details!S689,SA!$C$4:$C$11,0),MATCH(Details!V689,SA!$C$4:$E$4,0)),0)*Y689/(F689-E689+1) -> 2518.6422 | AF689: =IF(AB689="Karnataka",AE689*9%,0) -> 0 | AG689: =IF(AB689="Karnataka",AE689*9%,0) -> 0 | AH689: =IF(AF689+AG689>0,0,AE689*18%) -> 453.35559 | AI689: =AE689*L689 -> 100.74569 | AJ689: =$AE689*M689 -> 566.69449 | AK689: =(AE689)*AA689/Y689 -> 1610.132 | AL689: =AK689*(1-L689-M689) -> 1183.447 | AM689: =AE689-AI689-AL689-AJ689 -> 667.75501 | AN689: =Z689-366 -> 45715 | AO689: =IF(AND(O689>Z689,N689>AN689),AE689,0) -> 2518.6422
A690: Valid | B690: 202509 | C690: GMC021090100AV | D690: A V GLOBAL CORPORATION PRIVATE LIMITED | E690: 45818 | F690: 46182 | G690: SENTHIL KUMAR M | H690: 2364 | I690: 33962 | J690: ACK.F683A520250248.1 | K690: =N690 -> 45901 | L690: =IF(K690>=DATE(2022,4,1),4%,5%) -> 0.04 | M690: 0.225 | N690: 45901 | O690: 46182 | R690: 32 | S690: =VLOOKUP(R690,SA!$B$5:$C$11,2,1) -> 0-35 | T690: Male | U690: Self | V690: 300000 | W690: =IF(U690="self",V690,0) -> 300000 | X690: =IF(U690="self",1,0) -> 1 | Y690: =O690-N690+1 -> 282 | Z690: =$Z$1 -> 46081 | AA690: =IF(MIN((Z690-N690)+1,Y690)<0,0,MIN((Z690-N690)+1,Y690)) -> 181 | AB690: Delhi | AC690: =AE690+AF690+AG690+AH690 -> 2993.2263 | AD690: 1 | AE690: =IFERROR(INDEX(SA!$C$4:$E$11,MATCH(Details!S690,SA!$C$4:$C$11,0),MATCH(Details!V690,SA!$C$4:$E$4,0)),0)*Y690/(F690-E690+1) -> 2536.6325 | AF690: =IF(AB690="Karnataka",AE690*9%,0) -> 0 | AG690: =IF(AB690="Karnataka",AE690*9%,0) -> 0 | AH690: =IF(AF690+AG690>0,0,AE690*18%) -> 456.59385 | AI690: =AE690*L690 -> 101.4653 | AJ690: =$AE690*M690 -> 570.74231 | AK690: =(AE690)*AA690/Y690 -> 1628.1223 | AL690: =AK690*(1-L690-M690) -> 1196.6699 | AM690: =AE690-AI690-AL690-AJ690 -> 667.75501 | AN690: =Z690-366 -> 45715 | AO690: =IF(AND(O690>Z690,N690>AN690),AE690,0) -> 2536.6325
A691: Valid | B691: 202509 | C691: GMC021090100AV | D691: A V GLOBAL CORPORATION PRIVATE LIMITED | E691: 45818 | F691: 46182 | G691: Tarun Kumar Sharma | H691: 2359 | I691: 32598 | J691: ACK.F683A520250246.1 | K691: =N691 -> 45888 | L691: =IF(K691>=DATE(2022,4,1),4%,5%) -> 0.04 | M691: 0.225 | N691: 45888 | O691: 46182 | R691: 36 | S691: =VLOOKUP(R691,SA!$B$5:$C$11,2,1) -> 36-45 | T691: Male | U691: Self | V691: 300000 | W691: =IF(U691="self",V691,0) -> 300000 | X691: =IF(U691="self",1,0) -> 1 | Y691: =O691-N691+1 -> 295 | Z691: =$Z$1 -> 46081 | AA691: =IF(MIN((Z691-N691)+1,Y691)<0,0,MIN((Z691-N691)+1,Y691)) -> 194 | AB691: Delhi | AC691: =AE691+AF691+AG691+AH691 -> 4055.098 | AD691: 1 | AE691: =IFERROR(INDEX(SA!$C$4:$E$11,MATCH(Details!S691,SA!$C$4:$C$11,0),MATCH(Details!V691,SA!$C$4:$E$4,0)),0)*Y691/(F691-E691+1) -> 3436.5237 | AF691: =IF(AB691="Karnataka",AE691*9%,0) -> 0 | AG691: =IF(AB691="Karnataka",AE691*9%,0) -> 0 | AH691: =IF(AF691+AG691>0,0,AE691*18%) -> 618.57427 | AI691: =AE691*L691 -> 137.46095 | AJ691: =$AE691*M691 -> 773.21783 | AK691: =(AE691)*AA691/Y691 -> 2259.9512 | AL691: =AK691*(1-L691-M691) -> 1661.0641 | AM691: =AE691-AI691-AL691-AJ691 -> 864.7808 | AN691: =Z691-366 -> 45715 | AO691: =IF(AND(O691>Z691,N691>AN691),AE691,0) -> 3436.5237
A692: Valid | B692: 202509 | C692: GMC021090100AV | D692: A V GLOBAL CORPORATION PRIVATE LIMITED | E692: 45818 | F692: 46182 | G692: Hemlata Sharma | H692: 2359 | I692: 33610 | J692: ACK.F683A520250246.2 | K692: =N692 -> 45888 | L692: =IF(K692>=DATE(2022,4,1),4%,5%) -> 0.04 | M692: 0.225 | N692: 45888 | O692: 46182 | R692: 33 | S692: =VLOOKUP(R692,SA!$B$5:$C$11,2,1) -> 0-35 | T692: Female | U692: Spouse | V692: 300000 | W692: =IF(U692="self",V692,0) -> 0 | X692: =IF(U692="self",1,0) -> 0 | Y692: =O692-N692+1 -> 295 | Z692: =$Z$1 -> 46081 | AA692: =IF(MIN((Z692-N692)+1,Y692)<0,0,MIN((Z692-N692)+1,Y692)) -> 194 | AB692: Delhi | AC692: =AE692+AF692+AG692+AH692 -> 3131.212 | AD692: 1 | AE692: =IFERROR(INDEX(SA!$C$4:$E$11,MATCH(Details!S692,SA!$C$4:$C$11,0),MATCH(Details!V692,SA!$C$4:$E$4,0)),0)*Y692/(F692-E692+1) -> 2653.5695 | AF692: =IF(AB692="Karnataka",AE692*9%,0) -> 0 | AG692: =IF(AB692="Karnataka",AE692*9%,0) -> 0 | AH692: =IF(AF692+AG692>0,0,AE692*18%) -> 477.6425 | AI692: =AE692*L692 -> 106.14278 | AJ692: =$AE692*M692 -> 597.05313 | AK692: =(AE692)*AA692/Y692 -> 1745.0592 | AL692: =AK692*(1-L692-M692) -> 1282.6185 | AM692: =AE692-AI692-AL692-AJ692 -> 667.75501 | AN692: =Z692-366 -> 45715 | AO692: =IF(AND(O692>Z692,N692>AN692),AE692,0) -> 2653.5695
A693: Valid | B693: 202509 | C693: GMC021090100AV | D693: A V GLOBAL CORPORATION PRIVATE LIMITED | E693: 45818 | F693: 46182 | G693: Ayush Sharma | H693: 2359 | I693: 41249 | J693: ACK.F683A520250246.3 | K693: =N693 -> 45888 | L693: =IF(K693>=DATE(2022,4,1),4%,5%) -> 0.04 | M693: 0.225 | N693: 45888 | O693: 46182 | R693: 12 | S693: =VLOOKUP(R693,SA!$B$5:$C$11,2,1) -> 0-35 | T693: Male | U693: Son | V693: 300000 | W693: =IF(U693="self",V693,0) -> 0 | X693: =IF(U693="self",1,0) -> 0 | Y693: =O693-N693+1 -> 295 | Z693: =$Z$1 -> 46081 | AA693: =IF(MIN((Z693-N693)+1,Y693)<0,0,MIN((Z693-N693)+1,Y693)) -> 194 | AB693: Delhi | AC693: =AE693+AF693+AG693+AH693 -> 3131.212 | AD693: 1 | AE693: =IFERROR(INDEX(SA!$C$4:$E$11,MATCH(Details!S693,SA!$C$4:$C$11,0),MATCH(Details!V693,SA!$C$4:$E$4,0)),0)*Y693/(F693-E693+1) -> 2653.5695 | AF693: =IF(AB693="Karnataka",AE693*9%,0) -> 0 | AG693: =IF(AB693="Karnataka",AE693*9%,0) -> 0 | AH693: =IF(AF693+AG693>0,0,AE693*18%) -> 477.6425 | AI693: =AE693*L693 -> 106.14278 | AJ693: =$AE693*M693 -> 597.05313 | AK693: =(AE693)*AA693/Y693 -> 1745.0592 | AL693: =AK693*(1-L693-M693) -> 1282.6185 | AM693: =AE693-AI693-AL693-AJ693 -> 667.75501 | AN693: =Z693-366 -> 45715 | AO693: =IF(AND(O693>Z693,N693>AN693),AE693,0) -> 2653.5695
A694: Valid | B694: 202509 | C694: GMC021090100AV | D694: A V GLOBAL CORPORATION PRIVATE LIMITED | E694: 45818 | F694: 46182 | G694: Devanshi Sharma | H694: 2359 | I694: 43095 | J694: ACK.F683A520250246.4 | K694: =N694 -> 45888 | L694: =IF(K694>=DATE(2022,4,1),4%,5%) -> 0.04 | M694: 0.225 | N694: 45888 | O694: 46182 | R694: 7 | S694: =VLOOKUP(R694,SA!$B$5:$C$11,2,1) -> 0-35 | T694: Female | U694: Daughter | V694: 300000 | W694: =IF(U694="self",V694,0) -> 0 | X694: =IF(U694="self",1,0) -> 0 | Y694: =O694-N694+1 -> 295 | Z694: =$Z$1 -> 46081 | AA694: =IF(MIN((Z694-N694)+1,Y694)<0,0,MIN((Z694-N694)+1,Y694)) -> 194 | AB694: Delhi | AC694: =AE694+AF694+AG694+AH694 -> 3131.212 | AD694: 1 | AE694: =IFERROR(INDEX(SA!$C$4:$E$11,MATCH(Details!S694,SA!$C$4:$C$11,0),MATCH(Details!V694,SA!$C$4:$E$4,0)),0)*Y694/(F694-E694+1) -> 2653.5695 | AF694: =IF(AB694="Karnataka",AE694*9%,0) -> 0 | AG694: =IF(AB694="Karnataka",AE694*9%,0) -> 0 | AH694: =IF(AF694+AG694>0,0,AE694*18%) -> 477.6425 | AI694: =AE694*L694 -> 106.14278 | AJ694: =$AE694*M694 -> 597.05313 | AK694: =(AE694)*AA694/Y694 -> 1745.0592 | AL694: =AK694*(1-L694-M694) -> 1282.6185 | AM694: =AE694-AI694-AL694-AJ694 -> 667.75501 | AN694: =Z694-366 -> 45715 | AO694: =IF(AND(O694>Z694,N694>AN694),AE694,0) -> 2653.5695
A695: Deletion | B695: 202509 | C695: GMC021090100AV | D695: A V GLOBAL CORPORATION PRIVATE LIMITED | E695: 45818 | F695: 46182 | G695: Mahesh Subramani Nandi | H695: 2082 | I695: 32098 | J695: ACK.F683A520250087.1 | K695: =N695 -> 45818 | L695: =IF(K695>=DATE(2022,4,1),4%,5%) -> 0.04 | M695: 0.225 | N695: 45818 | O695: 46182 | P695: 45892 | Q695: =P695+1 -> 45893 | R695: 37 | S695: =VLOOKUP(R695,SA!$B$5:$C$11,2,1) -> 36-45 | T695: Male | U695: Self | V695: -300000 | W695: =IF(U695="self",V695,0) -> -300000 | X695: =IF(U695="self",-1,0) -> -1 | Y695: =O695-Q695+1 -> 290 | Z695: =$Z$1 -> 46081 | AA695: =IF(MIN((Z695-Q695)+1,Y695)<0,0,MIN((Z695-Q695)+1,Y695)) -> 189 | AB695: Delhi | AC695: =AE695+AF695+AG695+AH695 -> -3986.3675 | AD695: -1 | AE695: =-IFERROR(INDEX(SA!$C$4:$E$11,MATCH(Details!S695,SA!$C$4:$C$11,0),MATCH(-Details!V695,SA!$C$4:$E$4,0)),0)*Y695/(F695-E695+1) -> -3378.2775 | AF695: =IF(AB695="Karnataka",AE695*9%,0) -> 0 | AG695: =IF(AB695="Karnataka",AE695*9%,0) -> 0 | AH695: =IF(AF695+AG695>0,0,AE695*18%) -> -608.08996 | AI695: =AE695*L695 -> -135.1311 | AJ695: =$AE695*M695 -> -760.11245 | AK695: =(AE695)*AA695/Y695 -> -2201.705 | AL695: =AK695*(1-L695-M695) -> -1618.2532 | AM695: =AE695-AI695-AL695-AJ695 -> -864.7808 | AN695: =Z695-366 -> 45715 | AO695: =IF(AND(O695>Z695,N695>AN695),AE695,0) -> -3378.2775 | AP695: No Claim
A696: Deletion | B696: 202509 | C696: GMC021090100AV | D696: A V GLOBAL CORPORATION PRIVATE LIMITED | E696: 45818 | F696: 46182 | G696: Daksh Mahesh Nandi | H696: 2082 | I696: 43751 | J696: ACK.F683A520250087.2 | K696: =N696 -> 45818 | L696: =IF(K696>=DATE(2022,4,1),4%,5%) -> 0.04 | M696: 0.225 | N696: 45818 | O696: 46182 | P696: 45892 | Q696: =P696+1 -> 45893 | R696: 5 | S696: =VLOOKUP(R696,SA!$B$5:$C$11,2,1) -> 0-35 | T696: Male | U696: Son | V696: -300000 | W696: =IF(U696="self",V696,0) -> 0 | X696: =IF(U696="self",-1,0) -> 0 | Y696: =O696-Q696+1 -> 290 | Z696: =$Z$1 -> 46081 | AA696: =IF(MIN((Z696-Q696)+1,Y696)<0,0,MIN((Z696-Q696)+1,Y696)) -> 189 | AB696: Delhi | AC696: =AE696+AF696+AG696+AH696 -> -3078.1406 | AD696: -1 | AE696: =-IFERROR(INDEX(SA!$C$4:$E$11,MATCH(Details!S696,SA!$C$4:$C$11,0),MATCH(-Details!V696,SA!$C$4:$E$4,0)),0)*Y696/(F696-E696+1) -> -2608.5937 | AF696: =IF(AB696="Karnataka",AE696*9%,0) -> 0 | AG696: =IF(AB696="Karnataka",AE696*9%,0) -> 0 | AH696: =IF(AF696+AG696>0,0,AE696*18%) -> -469.54687 | AI696: =AE696*L696 -> -104.34375 | AJ696: =$AE696*M696 -> -586.93358 | AK696: =(AE696)*AA696/Y696 -> -1700.0835 | AL696: =AK696*(1-L696-M696) -> -1249.5614 | AM696: =AE696-AI696-AL696-AJ696 -> -667.75501 | AN696: =Z696-366 -> 45715 | AO696: =IF(AND(O696>Z696,N696>AN696),AE696,0) -> -2608.5937 | AP696: No Claim
A697: Deletion | B697: 202509 | C697: GMC021090100AV | D697: A V GLOBAL CORPORATION PRIVATE LIMITED | E697: 45818 | F697: 46182 | G697: Roja Mahesh Nandi | H697: 2082 | I697: 34355 | J697: ACK.F683A520250087.3 | K697: =N697 -> 45818 | L697: =IF(K697>=DATE(2022,4,1),4%,5%) -> 0.04 | M697: 0.225 | N697: 45818 | O697: 46182 | P697: 45892 | Q697: =P697+1 -> 45893 | R697: 31 | S697: =VLOOKUP(R697,SA!$B$5:$C$11,2,1) -> 0-35 | T697: Female | U697: Spouse | V697: -300000 | W697: =IF(U697="self",V697,0) -> 0 | X697: =IF(U697="self",-1,0) -> 0 | Y697: =O697-Q697+1 -> 290 | Z697: =$Z$1 -> 46081 | AA697: =IF(MIN((Z697-Q697)+1,Y697)<0,0,MIN((Z697-Q697)+1,Y697)) -> 189 | AB697: Delhi | AC697: =AE697+AF697+AG697+AH697 -> -3078.1406 | AD697: -1 | AE697: =-IFERROR(INDEX(SA!$C$4:$E$11,MATCH(Details!S697,SA!$C$4:$C$11,0),MATCH(-Details!V697,SA!$C$4:$E$4,0)),0)*Y697/(F697-E697+1) -> -2608.5937 | AF697: =IF(AB697="Karnataka",AE697*9%,0) -> 0 | AG697: =IF(AB697="Karnataka",AE697*9%,0) -> 0 | AH697: =IF(AF697+AG697>0,0,AE697*18%) -> -469.54687 | AI697: =AE697*L697 -> -104.34375 | AJ697: =$AE697*M697 -> -586.93358 | AK697: =(AE697)*AA697/Y697 -> -1700.0835 | AL697: =AK697*(1-L697-M697) -> -1249.5614 | AM697: =AE697-AI697-AL697-AJ697 -> -667.75501 | AN697: =Z697-366 -> 45715 | AO697: =IF(AND(O697>Z697,N697>AN697),AE697,0) -> -2608.5937 | AP697: No Claim
A698: Deletion | B698: 202509 | C698: GMC021090100AV | D698: A V GLOBAL CORPORATION PRIVATE LIMITED | E698: 45818 | F698: 46182 | G698: Tirth Mahesh Nandi | H698: 2082 | I698: 45702 | J698: ACK.F683A520250087.4 | K698: =N698 -> 45818 | L698: =IF(K698>=DATE(2022,4,1),4%,5%) -> 0.04 | M698: 0.225 | N698: 45818 | O698: 46182 | P698: 45892 | Q698: =P698+1 -> 45893 | R698: 0 | S698: =VLOOKUP(R698,SA!$B$5:$C$11,2,1) -> 0-35 | T698: Male | U698: Son | V698: -300000 | W698: =IF(U698="self",V698,0) -> 0 | X698: =IF(U698="self",-1,0) -> 0 | Y698: =O698-Q698+1 -> 290 | Z698: =$Z$1 -> 46081 | AA698: =IF(MIN((Z698-Q698)+1,Y698)<0,0,MIN((Z698-Q698)+1,Y698)) -> 189 | AB698: Delhi | AC698: =AE698+AF698+AG698+AH698 -> -3078.1406 | AD698: -1 | AE698: =-IFERROR(INDEX(SA!$C$4:$E$11,MATCH(Details!S698,SA!$C$4:$C$11,0),MATCH(-Details!V698,SA!$C$4:$E$4,0)),0)*Y698/(F698-E698+1) -> -2608.5937 | AF698: =IF(AB698="Karnataka",AE698*9%,0) -> 0 | AG698: =IF(AB698="Karnataka",AE698*9%,0) -> 0 | AH698: =IF(AF698+AG698>0,0,AE698*18%) -> -469.54687 | AI698: =AE698*L698 -> -104.34375 | AJ698: =$AE698*M698 -> -586.93358 | AK698: =(AE698)*AA698/Y698 -> -1700.0835 | AL698: =AK698*(1-L698-M698) -> -1249.5614 | AM698: =AE698-AI698-AL698-AJ698 -> -667.75501 | AN698: =Z698-366 -> 45715 | AO698: =IF(AND(O698>Z698,N698>AN698),AE698,0) -> -2608.5937 | AP698: No Claim
A699: Deletion | B699: 202509 | C699: GMC021090100AV | D699: A V GLOBAL CORPORATION PRIVATE LIMITED | E699: 45818 | F699: 46182 | G699: M Rajendiran | H699: 2154 | I699: 32639 | J699: ACK.F683A520250117.1 | K699: =N699 -> 45818 | L699: =IF(K699>=DATE(2022,4,1),4%,5%) -> 0.04 | M699: 0.225 | N699: 45818 | O699: 46182 | P699: 45899 | Q699: =P699+1 -> 45900 | R699: 36 | S699: =VLOOKUP(R699,SA!$B$5:$C$11,2,1) -> 36-45 | T699: Male | U699: Self | V699: -300000 | W699: =IF(U699="self",V699,0) -> -300000 | X699: =IF(U699="self",-1,0) -> -1 | Y699: =O699-Q699+1 -> 283 | Z699: =$Z$1 -> 46081 | AA699: =IF(MIN((Z699-Q699)+1,Y699)<0,0,MIN((Z699-Q699)+1,Y699)) -> 182 | AB699: Delhi | AC699: =AE699+AF699+AG699+AH699 -> -3890.1448 | AD699: -1 | AE699: =-IFERROR(INDEX(SA!$C$4:$E$11,MATCH(Details!S699,SA!$C$4:$C$11,0),MATCH(-Details!V699,SA!$C$4:$E$4,0)),0)*Y699/(F699-E699+1) -> -3296.7329 | AF699: =IF(AB699="Karnataka",AE699*9%,0) -> 0 | AG699: =IF(AB699="Karnataka",AE699*9%,0) -> 0 | AH699: =IF(AF699+AG699>0,0,AE699*18%) -> -593.41192 | AI699: =AE699*L699 -> -131.86932 | AJ699: =$AE699*M699 -> -741.7649 | AK699: =(AE699)*AA699/Y699 -> -2120.1604 | AL699: =AK699*(1-L699-M699) -> -1558.3179 | AM699: =AE699-AI699-AL699-AJ699 -> -864.7808 | AN699: =Z699-366 -> 45715 | AO699: =IF(AND(O699>Z699,N699>AN699),AE699,0) -> -3296.7329 | AP699: No Claim
A700: Deletion | B700: 202509 | C700: GMC021090100AV | D700: A V GLOBAL CORPORATION PRIVATE LIMITED | E700: 45818 | F700: 46182 | G700: Rkrish | H700: 2154 | I700: 42271 | J700: ACK.F683A520250117.2 | K700: =N700 -> 45818 | L700: =IF(K700>=DATE(2022,4,1),4%,5%) -> 0.04 | M700: 0.225 | N700: 45818 | O700: 46182 | P700: 45899 | Q700: =P700+1 -> 45900 | R700: 9 | S700: =VLOOKUP(R700,SA!$B$5:$C$11,2,1) -> 0-35 | T700: Male | U700: Son | V700: -300000 | W700: =IF(U700="self",V700,0) -> 0 | X700: =IF(U700="self",-1,0) -> 0 | Y700: =O700-Q700+1 -> 283 | Z700: =$Z$1 -> 46081 | AA700: =IF(MIN((Z700-Q700)+1,Y700)<0,0,MIN((Z700-Q700)+1,Y700)) -> 182 | AB700: Delhi | AC700: =AE700+AF700+AG700+AH700 -> -3003.8406 | AD700: -1 | AE700: =-IFERROR(INDEX(SA!$C$4:$E$11,MATCH(Details!S700,SA!$C$4:$C$11,0),MATCH(-Details!V700,SA!$C$4:$E$4,0)),0)*Y700/(F700-E700+1) -> -2545.6276 | AF700: =IF(AB700="Karnataka",AE700*9%,0) -> 0 | AG700: =IF(AB700="Karnataka",AE700*9%,0) -> 0 | AH700: =IF(AF700+AG700>0,0,AE700*18%) -> -458.21298 | AI700: =AE700*L700 -> -101.82511 | AJ700: =$AE700*M700 -> -572.76622 | AK700: =(AE700)*AA700/Y700 -> -1637.1174 | AL700: =AK700*(1-L700-M700) -> -1203.2813 | AM700: =AE700-AI700-AL700-AJ700 -> -667.75501 | AN700: =Z700-366 -> 45715 | AO700: =IF(AND(O700>Z700,N700>AN700),AE700,0) -> -2545.6276 | AP700: No Claim
A701: Deletion | B701: 202509 | C701: GMC021090100AV | D701: A V GLOBAL CORPORATION PRIVATE LIMITED | E701: 45818 | F701: 46182 | G701: Rananthi | H701: 2154 | I701: 32316 | J701: ACK.F683A520250117.3 | K701: =N701 -> 45818 | L701: =IF(K701>=DATE(2022,4,1),4%,5%) -> 0.04 | M701: 0.225 | N701: 45818 | O701: 46182 | P701: 45899 | Q701: =P701+1 -> 45900 | R701: 36 | S701: =VLOOKUP(R701,SA!$B$5:$C$11,2,1) -> 36-45 | T701: Female | U701: Spouse | V701: -300000 | W701: =IF(U701="self",V701,0) -> 0 | X701: =IF(U701="self",-1,0) -> 0 | Y701: =O701-Q701+1 -> 283 | Z701: =$Z$1 -> 46081 | AA701: =IF(MIN((Z701-Q701)+1,Y701)<0,0,MIN((Z701-Q701)+1,Y701)) -> 182 | AB701: Delhi | AC701: =AE701+AF701+AG701+AH701 -> -3890.1448 | AD701: -1 | AE701: =-IFERROR(INDEX(SA!$C$4:$E$11,MATCH(Details!S701,SA!$C$4:$C$11,0),MATCH(-Details!V701,SA!$C$4:$E$4,0)),0)*Y701/(F701-E701+1) -> -3296.7329 | AF701: =IF(AB701="Karnataka",AE701*9%,0) -> 0 | AG701: =IF(AB701="Karnataka",AE701*9%,0) -> 0 | AH701: =IF(AF701+AG701>0,0,AE701*18%) -> -593.41192 | AI701: =AE701*L701 -> -131.86932 | AJ701: =$AE701*M701 -> -741.7649 | AK701: =(AE701)*AA701/Y701 -> -2120.1604 | AL701: =AK701*(1-L701-M701) -> -1558.3179 | AM701: =AE701-AI701-AL701-AJ701 -> -864.7808 | AN701: =Z701-366 -> 45715 | AO701: =IF(AND(O701>Z701,N701>AN701),AE701,0) -> -3296.7329 | AP701: No Claim
A702: Deletion | B702: 202509 | C702: GMC021090100AV | D702: A V GLOBAL CORPORATION PRIVATE LIMITED | E702: 45818 | F702: 46182 | G702: Rlekhashree | H702: 2154 | I702: 42770 | J702: ACK.F683A520250117.4 | K702: =N702 -> 45818 | L702: =IF(K702>=DATE(2022,4,1),4%,5%) -> 0.04 | M702: 0.225 | N702: 45818 | O702: 46182 | P702: 45899 | Q702: =P702+1 -> 45900 | R702: 8 | S702: =VLOOKUP(R702,SA!$B$5:$C$11,2,1) -> 0-35 | T702: Female | U702: Daughter | V702: -300000 | W702: =IF(U702="self",V702,0) -> 0 | X702: =IF(U702="self",-1,0) -> 0 | Y702: =O702-Q702+1 -> 283 | Z702: =$Z$1 -> 46081 | AA702: =IF(MIN((Z702-Q702)+1,Y702)<0,0,MIN((Z702-Q702)+1,Y702)) -> 182 | AB702: Delhi | AC702: =AE702+AF702+AG702+AH702 -> -3003.8406 | AD702: -1 | AE702: =-IFERROR(INDEX(SA!$C$4:$E$11,MATCH(Details!S702,SA!$C$4:$C$11,0),MATCH(-Details!V702,SA!$C$4:$E$4,0)),0)*Y702/(F702-E702+1) -> -2545.6276 | AF702: =IF(AB702="Karnataka",AE702*9%,0) -> 0 | AG702: =IF(AB702="Karnataka",AE702*9%,0) -> 0 | AH702: =IF(AF702+AG702>0,0,AE702*18%) -> -458.21298 | AI702: =AE702*L702 -> -101.82511 | AJ702: =$AE702*M702 -> -572.76622 | AK702: =(AE702)*AA702/Y702 -> -1637.1174 | AL702: =AK702*(1-L702-M702) -> -1203.2813 | AM702: =AE702-AI702-AL702-AJ702 -> -667.75501 | AN702: =Z702-366 -> 45715 | AO702: =IF(AND(O702>Z702,N702>AN702),AE702,0) -> -2545.6276 | AP702: No Claim
A703: Deletion | B703: 202509 | C703: GMC021090100AV | D703: A V GLOBAL CORPORATION PRIVATE LIMITED | E703: 45818 | F703: 46182 | G703: Sachin Ghanshyam Neman | H703: 2212 | I703: 28845 | J703: ACK.F683A520250139.1 | K703: =N703 -> 45818 | L703: =IF(K703>=DATE(2022,4,1),4%,5%) -> 0.04 | M703: 0.225 | N703: 45818 | O703: 46182 | P703: 45882 | Q703: =P703+1 -> 45883 | R703: 46 | S703: =VLOOKUP(R703,SA!$B$5:$C$11,2,1) -> 46-55 | T703: Male | U703: Self | V703: -300000 | W703: =IF(U703="self",V703,0) -> -300000 | X703: =IF(U703="self",-1,0) -> -1 | Y703: =O703-Q703+1 -> 300 | Z703: =$Z$1 -> 46081 | AA703: =IF(MIN((Z703-Q703)+1,Y703)<0,0,MIN((Z703-Q703)+1,Y703)) -> 199 | AB703: Delhi | AC703: =AE703+AF703+AG703+AH703 -> -7879.7199 | AD703: -1 | AE703: =-IFERROR(INDEX(SA!$C$4:$E$11,MATCH(Details!S703,SA!$C$4:$C$11,0),MATCH(-Details!V703,SA!$C$4:$E$4,0)),0)*Y703/(F703-E703+1) -> -6677.7288 | AF703: =IF(AB703="Karnataka",AE703*9%,0) -> 0 | AG703: =IF(AB703="Karnataka",AE703*9%,0) -> 0 | AH703: =IF(AF703+AG703>0,0,AE703*18%) -> -1201.9912 | AI703: =AE703*L703 -> -267.10915 | AJ703: =$AE703*M703 -> -1502.489 | AK703: =(AE703)*AA703/Y703 -> -4429.5601 | AL703: =AK703*(1-L703-M703) -> -3255.7267 | AM703: =AE703-AI703-AL703-AJ703 -> -1652.404 | AN703: =Z703-366 -> 45715 | AO703: =IF(AND(O703>Z703,N703>AN703),AE703,0) -> -6677.7288 | AP703: No Claim
A704: Deletion | B704: 202509 | C704: GMC021090100AV | D704: A V GLOBAL CORPORATION PRIVATE LIMITED | E704: 45818 | F704: 46182 | G704: Aparna Sachin Neman | H704: 2212 | I704: 30886 | J704: ACK.F683A520250139.2 | K704: =N704 -> 45818 | L704: =IF(K704>=DATE(2022,4,1),4%,5%) -> 0.04 | M704: 0.225 | N704: 45818 | O704: 46182 | P704: 45882 | Q704: =P704+1 -> 45883 | R704: 40 | S704: =VLOOKUP(R704,SA!$B$5:$C$11,2,1) -> 36-45 | T704: Female | U704: Spouse | V704: -300000 | W704: =IF(U704="self",V704,0) -> 0 | X704: =IF(U704="self",-1,0) -> 0 | Y704: =O704-Q704+1 -> 300 | Z704: =$Z$1 -> 46081 | AA704: =IF(MIN((Z704-Q704)+1,Y704)<0,0,MIN((Z704-Q704)+1,Y704)) -> 199 | AB704: Delhi | AC704: =AE704+AF704+AG704+AH704 -> -4123.8284 | AD704: -1 | AE704: =-IFERROR(INDEX(SA!$C$4:$E$11,MATCH(Details!S704,SA!$C$4:$C$11,0),MATCH(-Details!V704,SA!$C$4:$E$4,0)),0)*Y704/(F704-E704+1) -> -3494.7699 | AF704: =IF(AB704="Karnataka",AE704*9%,0) -> 0 | AG704: =IF(AB704="Karnataka",AE704*9%,0) -> 0 | AH704: =IF(AF704+AG704>0,0,AE704*18%) -> -629.05858 | AI704: =AE704*L704 -> -139.79079 | AJ704: =$AE704*M704 -> -786.32322 | AK704: =(AE704)*AA704/Y704 -> -2318.1973 | AL704: =AK704*(1-L704-M704) -> -1703.875 | AM704: =AE704-AI704-AL704-AJ704 -> -864.7808 | AN704: =Z704-366 -> 45715 | AO704: =IF(AND(O704>Z704,N704>AN704),AE704,0) -> -3494.7699 | AP704: No Claim
A705: Deletion | B705: 202509 | C705: GMC021090100AV | D705: A V GLOBAL CORPORATION PRIVATE LIMITED | E705: 45818 | F705: 46182 | G705: Shubham Sachin Neman | H705: 2212 | I705: 39655 | J705: ACK.F683A520250139.3 | K705: =N705 -> 45818 | L705: =IF(K705>=DATE(2022,4,1),4%,5%) -> 0.04 | M705: 0.225 | N705: 45818 | O705: 46182 | P705: 45882 | Q705: =P705+1 -> 45883 | R705: 16 | S705: =VLOOKUP(R705,SA!$B$5:$C$11,2,1) -> 0-35 | T705: Male | U705: Son | V705: -300000 | W705: =IF(U705="self",V705,0) -> 0 | X705: =IF(U705="self",-1,0) -> 0 | Y705: =O705-Q705+1 -> 300 | Z705: =$Z$1 -> 46081 | AA705: =IF(MIN((Z705-Q705)+1,Y705)<0,0,MIN((Z705-Q705)+1,Y705)) -> 199 | AB705: Delhi | AC705: =AE705+AF705+AG705+AH705 -> -3184.2833 | AD705: -1 | AE705: =-IFERROR(INDEX(SA!$C$4:$E$11,MATCH(Details!S705,SA!$C$4:$C$11,0),MATCH(-Details!V705,SA!$C$4:$E$4,0)),0)*Y705/(F705-E705+1) -> -2698.5452 | AF705: =IF(AB705="Karnataka",AE705*9%,0) -> 0 | AG705: =IF(AB705="Karnataka",AE705*9%,0) -> 0 | AH705: =IF(AF705+AG705>0,0,AE705*18%) -> -485.73814 | AI705: =AE705*L705 -> -107.94181 | AJ705: =$AE705*M705 -> -607.17267 | AK705: =(AE705)*AA705/Y705 -> -1790.035 | AL705: =AK705*(1-L705-M705) -> -1315.6757 | AM705: =AE705-AI705-AL705-AJ705 -> -667.75501 | AN705: =Z705-366 -> 45715 | AO705: =IF(AND(O705>Z705,N705>AN705),AE705,0) -> -2698.5452 | AP705: No Claim
A706: Deletion | B706: 202509 | C706: GMC021090100AV | D706: A V GLOBAL CORPORATION PRIVATE LIMITED | E706: 45818 | F706: 46182 | G706: Chetan Vasant Tandel | H706: 2265 | I706: 34895 | J706: ACK.F683A520250163.1 | K706: =N706 -> 45818 | L706: =IF(K706>=DATE(2022,4,1),4%,5%) -> 0.04 | M706: 0.225 | N706: 45818 | O706: 46182 | P706: 45899 | Q706: =P706+1 -> 45900 | R706: 29 | S706: =VLOOKUP(R706,SA!$B$5:$C$11,2,1) -> 0-35 | T706: Male | U706: Self | V706: -300000 | W706: =IF(U706="self",V706,0) -> -300000 | X706: =IF(U706="self",-1,0) -> -1 | Y706: =O706-Q706+1 -> 283 | Z706: =$Z$1 -> 46081 | AA706: =IF(MIN((Z706-Q706)+1,Y706)<0,0,MIN((Z706-Q706)+1,Y706)) -> 182 | AB706: Delhi | AC706: =AE706+AF706+AG706+AH706 -> -3003.8406 | AD706: -1 | AE706: =-IFERROR(INDEX(SA!$C$4:$E$11,MATCH(Details!S706,SA!$C$4:$C$11,0),MATCH(-Details!V706,SA!$C$4:$E$4,0)),0)*Y706/(F706-E706+1) -> -2545.6276 | AF706: =IF(AB706="Karnataka",AE706*9%,0) -> 0 | AG706: =IF(AB706="Karnataka",AE706*9%,0) -> 0 | AH706: =IF(AF706+AG706>0,0,AE706*18%) -> -458.21298 | AI706: =AE706*L706 -> -101.82511 | AJ706: =$AE706*M706 -> -572.76622 | AK706: =(AE706)*AA706/Y706 -> -1637.1174 | AL706: =AK706*(1-L706-M706) -> -1203.2813 | AM706: =AE706-AI706-AL706-AJ706 -> -667.75501 | AN706: =Z706-366 -> 45715 | AO706: =IF(AND(O706>Z706,N706>AN706),AE706,0) -> -2545.6276 | AP706: No Claim
A707: Valid | B707: 202509 | C707: GMC021090100AV | D707: A V GLOBAL CORPORATION PRIVATE LIMITED | E707: 45818 | F707: 46182 | G707: Vanya Jinal Patel | H707: 2054 | I707: 45907 | J707: ACK.F683A520250077.4 | K707: =N707 -> 45907 | L707: =IF(K707>=DATE(2022,4,1),4%,5%) -> 0.04 | M707: 0.225 | N707: 45907 | O707: 46182 | R707: 0 | S707: =VLOOKUP(R707,SA!$B$5:$C$11,2,1) -> 0-35 | T707: Female | U707: Daughter | V707: 300000 | W707: =IF(U707="self",V707,0) -> 0 | X707: =IF(U707="self",1,0) -> 0 | Y707: =O707-N707+1 -> 276 | Z707: =$Z$1 -> 46081 | AA707: =IF(MIN((Z707-N707)+1,Y707)<0,0,MIN((Z707-N707)+1,Y707)) -> 175 | AB707: Delhi | AC707: =AE707+AF707+AG707+AH707 -> 2929.5407 | AD707: 1 | AE707: =IFERROR(INDEX(SA!$C$4:$E$11,MATCH(Details!S707,SA!$C$4:$C$11,0),MATCH(Details!V707,SA!$C$4:$E$4,0)),0)*Y707/(F707-E707+1) -> 2482.6616 | AF707: =IF(AB707="Karnataka",AE707*9%,0) -> 0 | AG707: =IF(AB707="Karnataka",AE707*9%,0) -> 0 | AH707: =IF(AF707+AG707>0,0,AE707*18%) -> 446.87909 | AI707: =AE707*L707 -> 99.306464 | AJ707: =$AE707*M707 -> 558.59886 | AK707: =(AE707)*AA707/Y707 -> 1574.1514 | AL707: =AK707*(1-L707-M707) -> 1157.0013 | AM707: =AE707-AI707-AL707-AJ707 -> 667.75501 | AN707: =Z707-366 -> 45715 | AO707: =IF(AND(O707>Z707,N707>AN707),AE707,0) -> 2482.6616
A708: Valid | B708: 202509 | C708: GMC021090100AV | D708: A V GLOBAL CORPORATION PRIVATE LIMITED | E708: 45818 | F708: 46182 | G708: HIMANI MEHTA | H708: 2365 | I708: 30938 | J708: ACK.F683A520250249.1 | K708: =N708 -> 45922 | L708: =IF(K708>=DATE(2022,4,1),4%,5%) -> 0.04 | M708: 0.225 | N708: 45922 | O708: 46182 | R708: 41 | S708: =VLOOKUP(R708,SA!$B$5:$C$11,2,1) -> 36-45 | T708: Female | U708: Self | V708: 1000000 | W708: =IF(U708="self",V708,0) -> 1000000 | X708: =IF(U708="self",1,0) -> 1 | Y708: =O708-N708+1 -> 261 | Z708: =$Z$1 -> 46081 | AA708: =IF(MIN((Z708-N708)+1,Y708)<0,0,MIN((Z708-N708)+1,Y708)) -> 160 | AB708: Delhi | AC708: =AE708+AF708+AG708+AH708 -> 6445.6586 | AD708: 1 | AE708: =IFERROR(INDEX(SA!$C$4:$E$11,MATCH(Details!S708,SA!$C$4:$C$11,0),MATCH(Details!V708,SA!$C$4:$E$4,0)),0)*Y708/(F708-E708+1) -> 5462.4225 | AF708: =IF(AB708="Karnataka",AE708*9%,0) -> 0 | AG708: =IF(AB708="Karnataka",AE708*9%,0) -> 0 | AH708: =IF(AF708+AG708>0,0,AE708*18%) -> 983.23605 | AI708: =AE708*L708 -> 218.4969 | AJ708: =$AE708*M708 -> 1229.0451 | AK708: =(AE708)*AA708/Y708 -> 3348.6115 | AL708: =AK708*(1-L708-M708) -> 2461.2295 | AM708: =AE708-AI708-AL708-AJ708 -> 1553.6511 | AN708: =Z708-366 -> 45715 | AO708: =IF(AND(O708>Z708,N708>AN708),AE708,0) -> 5462.4225
A709: Valid | B709: 202510 | C709: GMC021090100AV | D709: A V GLOBAL CORPORATION PRIVATE LIMITED | E709: 45818 | F709: 46182 | G709: NITI MEHTA . | H709: 5002 | I709: 31203 | J709: ACK.F683A520250250.1 | K709: =N709 -> 45901 | L709: =IF(K709>=DATE(2022,4,1),4%,5%) -> 0.04 | M709: 0.225 | N709: 45901 | O709: 46182 | R709: 40 | S709: =VLOOKUP(R709,SA!$B$5:$C$11,2,1) -> 36-45 | T709: Female | U709: Self | V709: 1000000 | W709: =IF(U709="self",V709,0) -> 1000000 | X709: =IF(U709="self",1,0) -> 1 | Y709: =O709-N709+1 -> 282 | Z709: =$Z$1 -> 46081 | AA709: =IF(MIN((Z709-N709)+1,Y709)<0,0,MIN((Z709-N709)+1,Y709)) -> 181 | AB709: Delhi | AC709: =AE709+AF709+AG709+AH709 -> 6964.2748 | AD709: 1 | AE709: =IFERROR(INDEX(SA!$C$4:$E$11,MATCH(Details!S709,SA!$C$4:$C$11,0),MATCH(Details!V709,SA!$C$4:$E$4,0)),0)*Y709/(F709-E709+1) -> 5901.9278 | AF709: =IF(AB709="Karnataka",AE709*9%,0) -> 0 | AG709: =IF(AB709="Karnataka",AE709*9%,0) -> 0 | AH709: =IF(AF709+AG709>0,0,AE709*18%) -> 1062.347 | AI709: =AE709*L709 -> 236.07711 | AJ709: =$AE709*M709 -> 1327.9338 | AK709: =(AE709)*AA709/Y709 -> 3788.1168 | AL709: =AK709*(1-L709-M709) -> 2784.2658 | AM709: =AE709-AI709-AL709-AJ709 -> 1553.6511 | AN709: =Z709-366 -> 45715 | AO709: =IF(AND(O709>Z709,N709>AN709),AE709,0) -> 5901.9278
A710: Valid | B710: 202510 | C710: GMC021090100AV | D710: A V GLOBAL CORPORATION PRIVATE LIMITED | E710: 45818 | F710: 46182 | G710: VENKATACHALAM SRIDHARAN . | H710: 5004 | I710: 22065 | J710: ACK.F683A520250251.1 | K710: =N710 -> 45901 | L710: =IF(K710>=DATE(2022,4,1),4%,5%) -> 0.04 | M710: 0.225 | N710: 45901 | O710: 46182 | R710: 65 | S710: =VLOOKUP(R710,SA!$B$5:$C$11,2,1) -> 56-65 | T710: Male | U710: Self | V710: 1000000 | W710: =IF(U710="self",V710,0) -> 1000000 | X710: =IF(U710="self",1,0) -> 1 | Y710: =O710-N710+1 -> 282 | Z710: =$Z$1 -> 46081 | AA710: =IF(MIN((Z710-N710)+1,Y710)<0,0,MIN((Z710-N710)+1,Y710)) -> 181 | AB710: Delhi | AC710: =AE710+AF710+AG710+AH710 -> 23716.261 | AD710: 1 | AE710: =IFERROR(INDEX(SA!$C$4:$E$11,MATCH(Details!S710,SA!$C$4:$C$11,0),MATCH(Details!V710,SA!$C$4:$E$4,0)),0)*Y710/(F710-E710+1) -> 20098.526 | AF710: =IF(AB710="Karnataka",AE710*9%,0) -> 0 | AG710: =IF(AB710="Karnataka",AE710*9%,0) -> 0 | AH710: =IF(AF710+AG710>0,0,AE710*18%) -> 3617.7347 | AI710: =AE710*L710 -> 803.94105 | AJ710: =$AE710*M710 -> 4522.1684 | AK710: =(AE710)*AA710/Y710 -> 12900.118 | AL710: =AK710*(1-L710-M710) -> 9481.5867 | AM710: =AE710-AI710-AL710-AJ710 -> 5290.8301 | AN710: =Z710-366 -> 45715 | AO710: =IF(AND(O710>Z710,N710>AN710),AE710,0) -> 20098.526
A711: Valid | B711: 202510 | C711: GMC021090100AV | D711: A V GLOBAL CORPORATION PRIVATE LIMITED | E711: 45818 | F711: 46182 | G711: THIRIPURA SUNDARI . | H711: 5004 | I711: 23884 | J711: ACK.F683A520250251.2 | K711: =N711 -> 45901 | L711: =IF(K711>=DATE(2022,4,1),4%,5%) -> 0.04 | M711: 0.225 | N711: 45901 | O711: 46182 | R711: 60 | S711: =VLOOKUP(R711,SA!$B$5:$C$11,2,1) -> 56-65 | T711: Female | U711: Spouse | V711: 1000000 | W711: =IF(U711="self",V711,0) -> 0 | X711: =IF(U711="self",1,0) -> 0 | Y711: =O711-N711+1 -> 282 | Z711: =$Z$1 -> 46081 | AA711: =IF(MIN((Z711-N711)+1,Y711)<0,0,MIN((Z711-N711)+1,Y711)) -> 181 | AB711: Delhi | AC711: =AE711+AF711+AG711+AH711 -> 23716.261 | AD711: 1 | AE711: =IFERROR(INDEX(SA!$C$4:$E$11,MATCH(Details!S711,SA!$C$4:$C$11,0),MATCH(Details!V711,SA!$C$4:$E$4,0)),0)*Y711/(F711-E711+1) -> 20098.526 | AF711: =IF(AB711="Karnataka",AE711*9%,0) -> 0 | AG711: =IF(AB711="Karnataka",AE711*9%,0) -> 0 | AH711: =IF(AF711+AG711>0,0,AE711*18%) -> 3617.7347 | AI711: =AE711*L711 -> 803.94105 | AJ711: =$AE711*M711 -> 4522.1684 | AK711: =(AE711)*AA711/Y711 -> 12900.118 | AL711: =AK711*(1-L711-M711) -> 9481.5867 | AM711: =AE711-AI711-AL711-AJ711 -> 5290.8301 | AN711: =Z711-366 -> 45715 | AO711: =IF(AND(O711>Z711,N711>AN711),AE711,0) -> 20098.526
A712: Valid | B712: 202510 | C712: GMC021090100AV | D712: A V GLOBAL CORPORATION PRIVATE LIMITED | E712: 45818 | F712: 46182 | G712: JASWANT | H712: 2367 | I712: 32852 | J712: ACK.F683A520250253.1 | K712: =N712 -> 45931 | L712: =IF(K712>=DATE(2022,4,1),4%,5%) -> 0.04 | M712: 0.225 | N712: 45931 | O712: 46182 | R712: 35 | S712: =VLOOKUP(R712,SA!$B$5:$C$11,2,1) -> 0-35 | T712: Male | U712: Self | V712: 300000 | W712: =IF(U712="self",V712,0) -> 300000 | X712: =IF(U712="self",1,0) -> 1 | Y712: =O712-N712+1 -> 252 | Z712: =$Z$1 -> 46081 | AA712: =IF(MIN((Z712-N712)+1,Y712)<0,0,MIN((Z712-N712)+1,Y712)) -> 151 | AB712: Delhi | AC712: =AE712+AF712+AG712+AH712 -> 2674.798 | AD712: 1 | AE712: =IFERROR(INDEX(SA!$C$4:$E$11,MATCH(Details!S712,SA!$C$4:$C$11,0),MATCH(Details!V712,SA!$C$4:$E$4,0)),0)*Y712/(F712-E712+1) -> 2266.778 | AF712: =IF(AB712="Karnataka",AE712*9%,0) -> 0 | AG712: =IF(AB712="Karnataka",AE712*9%,0) -> 0 | AH712: =IF(AF712+AG712>0,0,AE712*18%) -> 408.02004 | AI712: =AE712*L712 -> 90.671119 | AJ712: =$AE712*M712 -> 510.02504 | AK712: =(AE712)*AA712/Y712 -> 1358.2678 | AL712: =AK712*(1-L712-M712) -> 998.3268 | AM712: =AE712-AI712-AL712-AJ712 -> 667.75501 | AN712: =Z712-366 -> 45715 | AO712: =IF(AND(O712>Z712,N712>AN712),AE712,0) -> 2266.778
A713: Valid | B713: 202510 | C713: GMC021090100AV | D713: A V GLOBAL CORPORATION PRIVATE LIMITED | E713: 45818 | F713: 46182 | G713: SUKHVINDER KAUR | H713: 2367 | I713: 33579 | J713: ACK.F683A520250253.2 | K713: =N713 -> 45931 | L713: =IF(K713>=DATE(2022,4,1),4%,5%) -> 0.04 | M713: 0.225 | N713: 45931 | O713: 46182 | R713: 33 | S713: =VLOOKUP(R713,SA!$B$5:$C$11,2,1) -> 0-35 | T713: Female | U713: Spouse | V713: 300000 | W713: =IF(U713="self",V713,0) -> 0 | X713: =IF(U713="self",1,0) -> 0 | Y713: =O713-N713+1 -> 252 | Z713: =$Z$1 -> 46081 | AA713: =IF(MIN((Z713-N713)+1,Y713)<0,0,MIN((Z713-N713)+1,Y713)) -> 151 | AB713: Delhi | AC713: =AE713+AF713+AG713+AH713 -> 2674.798 | AD713: 1 | AE713: =IFERROR(INDEX(SA!$C$4:$E$11,MATCH(Details!S713,SA!$C$4:$C$11,0),MATCH(Details!V713,SA!$C$4:$E$4,0)),0)*Y713/(F713-E713+1) -> 2266.778 | AF713: =IF(AB713="Karnataka",AE713*9%,0) -> 0 | AG713: =IF(AB713="Karnataka",AE713*9%,0) -> 0 | AH713: =IF(AF713+AG713>0,0,AE713*18%) -> 408.02004 | AI713: =AE713*L713 -> 90.671119 | AJ713: =$AE713*M713 -> 510.02504 | AK713: =(AE713)*AA713/Y713 -> 1358.2678 | AL713: =AK713*(1-L713-M713) -> 998.3268 | AM713: =AE713-AI713-AL713-AJ713 -> 667.75501 | AN713: =Z713-366 -> 45715 | AO713: =IF(AND(O713>Z713,N713>AN713),AE713,0) -> 2266.778
A714: Valid | B714: 202510 | C714: GMC021090100AV | D714: A V GLOBAL CORPORATION PRIVATE LIMITED | E714: 45818 | F714: 46182 | G714: DIGWANSH SINGH | H714: 2367 | I714: 41974 | J714: ACK.F683A520250253.3 | K714: =N714 -> 45931 | L714: =IF(K714>=DATE(2022,4,1),4%,5%) -> 0.04 | M714: 0.225 | N714: 45931 | O714: 46182 | R714: 10 | S714: =VLOOKUP(R714,SA!$B$5:$C$11,2,1) -> 0-35 | T714: Male | U714: Son | V714: 300000 | W714: =IF(U714="self",V714,0) -> 0 | X714: =IF(U714="self",1,0) -> 0 | Y714: =O714-N714+1 -> 252 | Z714: =$Z$1 -> 46081 | AA714: =IF(MIN((Z714-N714)+1,Y714)<0,0,MIN((Z714-N714)+1,Y714)) -> 151 | AB714: Delhi | AC714: =AE714+AF714+AG714+AH714 -> 2674.798 | AD714: 1 | AE714: =IFERROR(INDEX(SA!$C$4:$E$11,MATCH(Details!S714,SA!$C$4:$C$11,0),MATCH(Details!V714,SA!$C$4:$E$4,0)),0)*Y714/(F714-E714+1) -> 2266.778 | AF714: =IF(AB714="Karnataka",AE714*9%,0) -> 0 | AG714: =IF(AB714="Karnataka",AE714*9%,0) -> 0 | AH714: =IF(AF714+AG714>0,0,AE714*18%) -> 408.02004 | AI714: =AE714*L714 -> 90.671119 | AJ714: =$AE714*M714 -> 510.02504 | AK714: =(AE714)*AA714/Y714 -> 1358.2678 | AL714: =AK714*(1-L714-M714) -> 998.3268 | AM714: =AE714-AI714-AL714-AJ714 -> 667.75501 | AN714: =Z714-366 -> 45715 | AO714: =IF(AND(O714>Z714,N714>AN714),AE714,0) -> 2266.778
A715: Valid | B715: 202510 | C715: GMC021090100AV | D715: A V GLOBAL CORPORATION PRIVATE LIMITED | E715: 45818 | F715: 46182 | G715: SAHIBPREET | H715: 2367 | I715: 41371 | J715: ACK.F683A520250253.4 | K715: =N715 -> 45931 | L715: =IF(K715>=DATE(2022,4,1),4%,5%) -> 0.04 | M715: 0.225 | N715: 45931 | O715: 46182 | R715: 12 | S715: =VLOOKUP(R715,SA!$B$5:$C$11,2,1) -> 0-35 | T715: Male | U715: Son | V715: 300000 | W715: =IF(U715="self",V715,0) -> 0 | X715: =IF(U715="self",1,0) -> 0 | Y715: =O715-N715+1 -> 252 | Z715: =$Z$1 -> 46081 | AA715: =IF(MIN((Z715-N715)+1,Y715)<0,0,MIN((Z715-N715)+1,Y715)) -> 151 | AB715: Delhi | AC715: =AE715+AF715+AG715+AH715 -> 2674.798 | AD715: 1 | AE715: =IFERROR(INDEX(SA!$C$4:$E$11,MATCH(Details!S715,SA!$C$4:$C$11,0),MATCH(Details!V715,SA!$C$4:$E$4,0)),0)*Y715/(F715-E715+1) -> 2266.778 | AF715: =IF(AB715="Karnataka",AE715*9%,0) -> 0 | AG715: =IF(AB715="Karnataka",AE715*9%,0) -> 0 | AH715: =IF(AF715+AG715>0,0,AE715*18%) -> 408.02004 | AI715: =AE715*L715 -> 90.671119 | AJ715: =$AE715*M715 -> 510.02504 | AK715: =(AE715)*AA715/Y715 -> 1358.2678 | AL715: =AK715*(1-L715-M715) -> 998.3268 | AM715: =AE715-AI715-AL715-AJ715 -> 667.75501 | AN715: =Z715-366 -> 45715 | AO715: =IF(AND(O715>Z715,N715>AN715),AE715,0) -> 2266.778
A716: Valid | B716: 202510 | C716: GMC021090100AV | D716: A V GLOBAL CORPORATION PRIVATE LIMITED | E716: 45818 | F716: 46182 | G716: SHIVPRASAD BHENDE | H716: 2373 | I716: 33989 | J716: ACK.F683A520250252.1 | K716: =N716 -> 45931 | L716: =IF(K716>=DATE(2022,4,1),4%,5%) -> 0.04 | M716: 0.225 | N716: 45931 | O716: 46182 | R716: 32 | S716: =VLOOKUP(R716,SA!$B$5:$C$11,2,1) -> 0-35 | T716: Male | U716: Self | V716: 300000 | W716: =IF(U716="self",V716,0) -> 300000 | X716: =IF(U716="self",1,0) -> 1 | Y716: =O716-N716+1 -> 252 | Z716: =$Z$1 -> 46081 | AA716: =IF(MIN((Z716-N716)+1,Y716)<0,0,MIN((Z716-N716)+1,Y716)) -> 151 | AB716: Delhi | AC716: =AE716+AF716+AG716+AH716 -> 2674.798 | AD716: 1 | AE716: =IFERROR(INDEX(SA!$C$4:$E$11,MATCH(Details!S716,SA!$C$4:$C$11,0),MATCH(Details!V716,SA!$C$4:$E$4,0)),0)*Y716/(F716-E716+1) -> 2266.778 | AF716: =IF(AB716="Karnataka",AE716*9%,0) -> 0 | AG716: =IF(AB716="Karnataka",AE716*9%,0) -> 0 | AH716: =IF(AF716+AG716>0,0,AE716*18%) -> 408.02004 | AI716: =AE716*L716 -> 90.671119 | AJ716: =$AE716*M716 -> 510.02504 | AK716: =(AE716)*AA716/Y716 -> 1358.2678 | AL716: =AK716*(1-L716-M716) -> 998.3268 | AM716: =AE716-AI716-AL716-AJ716 -> 667.75501 | AN716: =Z716-366 -> 45715 | AO716: =IF(AND(O716>Z716,N716>AN716),AE716,0) -> 2266.778
A717: Deletion | B717: 202510 | C717: GMC021090100AV | D717: A V GLOBAL CORPORATION PRIVATE LIMITED | E717: 45818 | F717: 46182 | G717: Poonam | H717: AVGCT3 | I717: 34053 | J717: ACK.F683A520250227.1 | K717: =N717 -> 45818 | L717: =IF(K717>=DATE(2022,4,1),4%,5%) -> 0.04 | M717: 0.225 | N717: 45818 | O717: 46182 | P717: 45941 | Q717: =P717+1 -> 45942 | R717: 32 | S717: =VLOOKUP(R717,SA!$B$5:$C$11,2,1) -> 0-35 | T717: Female | U717: Self | V717: -300000 | W717: =IF(U717="self",V717,0) -> -300000 | X717: =IF(U717="self",-1,0) -> -1 | Y717: =O717-Q717+1 -> 241 | Z717: =$Z$1 -> 46081 | AA717: =IF(MIN((Z717-Q717)+1,Y717)<0,0,MIN((Z717-Q717)+1,Y717)) -> 140 | AB717: Delhi | AC717: =AE717+AF717+AG717+AH717 -> -2558.041 | AD717: -1 | AE717: =-IFERROR(INDEX(SA!$C$4:$E$11,MATCH(Details!S717,SA!$C$4:$C$11,0),MATCH(-Details!V717,SA!$C$4:$E$4,0)),0)*Y717/(F717-E717+1) -> -2167.8313 | AF717: =IF(AB717="Karnataka",AE717*9%,0) -> 0 | AG717: =IF(AB717="Karnataka",AE717*9%,0) -> 0 | AH717: =IF(AF717+AG717>0,0,AE717*18%) -> -390.20964 | AI717: =AE717*L717 -> -86.713253 | AJ717: =$AE717*M717 -> -487.76205 | AK717: =(AE717)*AA717/Y717 -> -1259.3211 | AL717: =AK717*(1-L717-M717) -> -925.60101 | AM717: =AE717-AI717-AL717-AJ717 -> -667.75501 | AN717: =Z717-366 -> 45715 | AO717: =IF(AND(O717>Z717,N717>AN717),AE717,0) -> -2167.8313 | AP717: No Claim
A718: Deletion | B718: 202510 | C718: GMC021090100AV | D718: A V GLOBAL CORPORATION PRIVATE LIMITED | E718: 45818 | F718: 46182 | G718: Mrunmay Shrikrishna Ludbe | H718: 2336 | I718: 37698 | J718: ACK.F683A520250214.1 | K718: =N718 -> 45818 | L718: =IF(K718>=DATE(2022,4,1),4%,5%) -> 0.04 | M718: 0.225 | N718: 45818 | O718: 46182 | P718: 45930 | Q718: =P718+1 -> 45931 | R718: 22 | S718: =VLOOKUP(R718,SA!$B$5:$C$11,2,1) -> 0-35 | T718: Male | U718: Self | V718: -300000 | W718: =IF(U718="self",V718,0) -> -300000 | X718: =IF(U718="self",-1,0) -> -1 | Y718: =O718-Q718+1 -> 252 | Z718: =$Z$1 -> 46081 | AA718: =IF(MIN((Z718-Q718)+1,Y718)<0,0,MIN((Z718-Q718)+1,Y718)) -> 151 | AB718: Delhi | AC718: =AE718+AF718+AG718+AH718 -> -2674.798 | AD718: -1 | AE718: =-IFERROR(INDEX(SA!$C$4:$E$11,MATCH(Details!S718,SA!$C$4:$C$11,0),MATCH(-Details!V718,SA!$C$4:$E$4,0)),0)*Y718/(F718-E718+1) -> -2266.778 | AF718: =IF(AB718="Karnataka",AE718*9%,0) -> 0 | AG718: =IF(AB718="Karnataka",AE718*9%,0) -> 0 | AH718: =IF(AF718+AG718>0,0,AE718*18%) -> -408.02004 | AI718: =AE718*L718 -> -90.671119 | AJ718: =$AE718*M718 -> -510.02504 | AK718: =(AE718)*AA718/Y718 -> -1358.2678 | AL718: =AK718*(1-L718-M718) -> -998.3268 | AM718: =AE718-AI718-AL718-AJ718 -> -667.75501 | AN718: =Z718-366 -> 45715 | AO718: =IF(AND(O718>Z718,N718>AN718),AE718,0) -> -2266.778 | AP718: No Claim
A719: Valid | B719: 202511 | C719: GMC021090100AV | D719: A V GLOBAL CORPORATION PRIVATE LIMITED | E719: 45818 | F719: 46182 | G719: Vajr Jain | H719: 2218 | I719: 45967 | J719: ACK.F683A520250143.4 | K719: =N719 -> 45967 | L719: =IF(K719>=DATE(2022,4,1),4%,5%) -> 0.04 | M719: 0.225 | N719: 45967 | O719: 46182 | R719: 0 | S719: =VLOOKUP(R719,SA!$B$5:$C$11,2,1) -> 0-35 | T719: Male | U719: Son | V719: 1000000 | W719: =IF(U719="self",V719,0) -> 0 | X719: =IF(U719="self",1,0) -> 0 | Y719: =O719-N719+1 -> 216 | Z719: =$Z$1 -> 46081 | AA719: =IF(MIN((Z719-N719)+1,Y719)<0,0,MIN((Z719-N719)+1,Y719)) -> 115 | AB719: Delhi | AC719: =AE719+AF719+AG719+AH719 -> 3766.051 | AD719: 1 | AE719: =IFERROR(INDEX(SA!$C$4:$E$11,MATCH(Details!S719,SA!$C$4:$C$11,0),MATCH(Details!V719,SA!$C$4:$E$4,0)),0)*Y719/(F719-E719+1) -> 3191.5687 | AF719: =IF(AB719="Karnataka",AE719*9%,0) -> 0 | AG719: =IF(AB719="Karnataka",AE719*9%,0) -> 0 | AH719: =IF(AF719+AG719>0,0,AE719*18%) -> 574.48236 | AI719: =AE719*L719 -> 127.66275 | AJ719: =$AE719*M719 -> 718.10295 | AK719: =(AE719)*AA719/Y719 -> 1699.2148 | AL719: =AK719*(1-L719-M719) -> 1248.9229 | AM719: =AE719-AI719-AL719-AJ719 -> 1096.8801 | AN719: =Z719-366 -> 45715 | AO719: =IF(AND(O719>Z719,N719>AN719),AE719,0) -> 3191.5687
A720: Valid | B720: 202512 | C720: GMC021090100AV | D720: A V GLOBAL CORPORATION PRIVATE LIMITED | E720: 45818 | F720: 46182 | G720: SANTOSH KUMAR MISHRA | H720: 2374 | I720: 33620 | J720: ACK.F683A520250256.1 | K720: =N720 -> 45992 | L720: =IF(K720>=DATE(2022,4,1),4%,5%) -> 0.04 | M720: 0.225 | N720: 45992 | O720: 46182 | R720: 33 | S720: =VLOOKUP(R720,SA!$B$5:$C$11,2,1) -> 0-35 | T720: Male | U720: Self | V720: 300000 | W720: =IF(U720="self",V720,0) -> 300000 | X720: =IF(U720="self",1,0) -> 1 | Y720: =O720-N720+1 -> 191 | Z720: =$Z$1 -> 46081 | AA720: =IF(MIN((Z720-N720)+1,Y720)<0,0,MIN((Z720-N720)+1,Y720)) -> 90 | AB720: Delhi | AC720: =AE720+AF720+AG720+AH720 -> 2027.3271 | AD720: 1 | AE720: =IFERROR(INDEX(SA!$C$4:$E$11,MATCH(Details!S720,SA!$C$4:$C$11,0),MATCH(Details!V720,SA!$C$4:$E$4,0)),0)*Y720/(F720-E720+1) -> 1718.0738 | AF720: =IF(AB720="Karnataka",AE720*9%,0) -> 0 | AG720: =IF(AB720="Karnataka",AE720*9%,0) -> 0 | AH720: =IF(AF720+AG720>0,0,AE720*18%) -> 309.25328 | AI720: =AE720*L720 -> 68.722951 | AJ720: =$AE720*M720 -> 386.5666 | AK720: =(AE720)*AA720/Y720 -> 809.56356 | AL720: =AK720*(1-L720-M720) -> 595.02922 | AM720: =AE720-AI720-AL720-AJ720 -> 667.75501 | AN720: =Z720-366 -> 45715 | AO720: =IF(AND(O720>Z720,N720>AN720),AE720,0) -> 1718.0738
...

Sheet CD Statement
B5: Acko General Insurance Limited
B6: CD Utilization Statement as on 28th Feb 2026
B7: Date | C7: Premium | D7: Tax Invoice No | E7: Description | F7: APD | G7: Balance
B8: 45815 | E8: HDFCH00289610341/AVGLOBA1/A V GLOBAL CORPORATION P LTD | F8: 3633220 | G8: =F8 -> 3633220
B9: 45828 | C9: 3633220.2 | D9: GMC021090100 | E9: GMC Premium | G9: =G8+F9-C9 -> -0.2006
B10: 45838 | G10: =G9+F10-C10 -> -0.2006
B11: 45856 | E11: HDFCH00372273827/AVGLOBA1/A V GLOBAL CORPORATION P LTD | F11: 100000 | G11: =G10+F11-C11 -> 99999.799
B12: 45867 | C12: 63385.809 | D12: GMC021090101 | E12: GMC Premium | G12: =G11+F12-C12 -> 36613.99
B13: 45869 | G13: =G12+F13-C13 -> 36613.99
B14: 45876 | C14: 29815.159 | D14: GMC021090102 | E14: GMC Premium | G14: =G13+F14-C14 -> 6798.8311
B15: 45889 | C15: 0 | D15: GMC021090103 | E15: GMC Premium | G15: =G14+F15-C15 -> 6798.8311
B16: 45900 | C16: 0 | D16: GMC021090104 | E16: GMC Premium | G16: =G15+F16-C16 -> 6798.8311
B17: 45900 | G17: =G16+F17-C17 -> 6798.8311
B18: 45911 | C18: 0 | D18: GMC021090105 | E18: GMC Premium | G18: =G17+F18-C18 -> 6798.8311
B19: 45911 | C19: -3971.9462 | D19: GMC021090106 | E19: GMC Premium | G19: =G18+F19-C19 -> 10770.777
B20: 45913 | E20: HDFCH00484406051/AVGLOBA1/A V GLOBAL CORPORATION P LTD | F20: 100000 | G20: =G19+F20-C20 -> 110770.78
B21: 45918 | C21: 2929.5407 | D21: GMC021090107 | E21: GMC Premium | G21: =G20+F21-C21 -> 107841.24
B22: 45925 | C22: 6445.6586 | D22: GMC021090108 | E22: GMC Premium | G22: =G21+F22-C22 -> 101395.58
B23: 45930 | G23: =G22+F23-C23 -> 101395.58
B24: 45961 | C24: 62537.948 | D24: GMC021090109 | E24: GMC Premium | G24: =G23+F24-C24 -> 38857.63
B25: 45983 | C25: 3766.051 | D25: GMC021090110 | E25: GMC Premium | G25: =G24+F25-C25 -> 35091.579
B26: 45991 | G26: =G25+F26-C26 -> 35091.579
B27: 46001 | C27: 5324.5415 | D27: GMC021090111 | E27: GMC Premium | G27: =G26+F27-C27 -> 29767.038
B28: 46022 | G28: =G27+F28-C28 -> 29767.038
B29: 46053 | G29: =G28+F29-C29 -> 29767.038
B30: 46062 | C30: 17183.329 | D30: GMC021090112 | E30: GMC Premium | G30: =G29+F30-C30 -> 12583.709
B31: 46081 | G31: =G30+F31-C31 -> 12583.709 | H31: =SuM!C8+SuM!C14-SUM(C8:C36) -> 0

Sheet SA
C4: Age Band/SI | D4: 300000 | E4: 1000000
B5: 0 | C5: 0-35 | D5: 3283.23 | E5: 5393.16
B6: 36 | C6: 36-45 | D6: 4251.97 | E6: 7639.02
B7: 46 | C7: 46-55 | D7: 8124.57 | E7: 14753.81
B8: 56 | C8: 56-65 | D8: 14246.99 | E8: 26014.05
B9: 66 | C9: 66-70 | D9: 29312.24 | E9: 54664.73
B10: 71 | C10: 71-75 | D10: 30115.02 | E10: 56645.56
B11: 76 | C11: 76-80 | D11: 30993.25 | E11: 59709.69

Sheet Check
A4: Emp id | B4: Sum of No of Policies | C4: Sum of No of Person Cover Per Day | D4: a | E4: UHID | F4: Gender | G4: Relationship | H4: Sum of Reporting Sum Insured | I4: Sum of GWP | J4: Sum of No of Person Cover Per Day | K4: aa
A5: 1001 | B5: 1 | C5: 2 | E5: ACK.F683A520250005.1 | F5: Male | G5: Self | H5: 1000000 | I5: 54664.73 | J5: 1
A6: 1002 | B6: 1 | C6: 1 | E6: ACK.F683A520250005.2 | F6: Female | G6: Spouse | H6: 0 | I6: 26014.05 | J6: 1
A7: 1004 | B7: 1 | C7: 4 | E7: ACK.F683A520250002.1 | F7: Male | G7: Self | H7: 1000000 | I7: 54664.73 | J7: 1
A8: 1005 | B8: 1 | C8: 4 | E8: ACK.F683A520250003.1 | F8: Male | G8: Self | H8: 300000 | I8: 8124.57 | J8: 1
A9: 1006 | B9: 1 | C9: 3 | E9: ACK.F683A520250003.2 | F9: Male | G9: Son | H9: 0 | I9: 3283.23 | J9: 1
A10: 1007 | B10: 1 | C10: 4 | E10: ACK.F683A520250003.3 | F10: Male | G10: Son | H10: 0 | I10: 3283.23 | J10: 1
A11: 1008 | B11: 1 | C11: 3 | E11: ACK.F683A520250003.4 | F11: Female | G11: Spouse | H11: 0 | I11: 4251.97 | J11: 1
A12: 1016 | B12: 1 | C12: 3 | E12: ACK.F683A520250006.1 | F12: Male | G12: Self | H12: 300000 | I12: 8124.57 | J12: 1
A13: 1017 | B13: 1 | C13: 2 | E13: ACK.F683A520250006.2 | F13: Female | G13: Spouse | H13: 0 | I13: 4251.97 | J13: 1
A14: 1019 | B14: 1 | C14: 4 | E14: ACK.F683A520250006.3 | F14: Female | G14: Daughter | H14: 0 | I14: 3283.23 | J14: 1
A15: 1022 | B15: 1 | C15: 2 | E15: ACK.F683A520250006.4 | F15: Male | G15: Son | H15: 0 | I15: 3283.23 | J15: 1
A16: 1023 | B16: 1 | C16: 3 | E16: ACK.F683A520250004.1 | F16: Female | G16: Self | H16: 300000 | I16: 14246.99 | J16: 1
... A21: 1032 | B21: 1 | C21: 2 | E21: ACK.F683A520250010.3 | F21: Female | G21: Spouse | H21: 0 | I21: 4251.97 | J21: 1
A22: 1033 | B22: 1 | C22: 1 | E22: ACK.F683A520250010.4 | H22: 0 | I22: 3283.23 | J22: 1
A23: 1035 | B23: 1 | C23: 3 | E23: ACK.F683A520250007.1 | F23: Male | G23: Self | H23: 300000 | I23: 8124.57 | J23: 1
A24: 1036 | B24: 1 | C24: 3 | E24: ACK.F683A520250007.2 | F24: Female | G24: Spouse | H24: 0 | I24: 8124.57 | J24: 1
A25: 1044 | B25: 1 | C25: 3 | E25: ACK.F683A520250007.3 | F25: Female | G25: Daughter | H25: 0 | I25: 3283.23 | J25: 1
A26: 1047 | B26: 1 | C26: 4 | E26: ACK.F683A520250008.1 | F26: Male | G26: Self | H26: 300000 | I26: 8124.57 | J26: 1
A27: 1049 | B27: 1 | C27: 4 | E27: ACK.F683A520250008.2 | F27: Female | G27: Spouse | H27: 0 | I27: 8124.57 | J27: 1
A28: 1055 | B28: 1 | C28: 4 | E28: ACK.F683A520250008.3 | F28: Male | G28: Son | H28: 0 | I28: 3283.23 | J28: 1
A29: 1056 | B29: 1 | C29: 3 | E29: ACK.F683A520250009.1 | F29: Male | G29: Self | H29: 300000 | I29: 8124.57 | J29: 1
A30: 1057 | B30: 1 | C30: 4 | E30: ACK.F683A520250009.2 | F30: Female | G30: Spouse | H30: 0 | I30: 8124.57 | J30: 1
A31: 1059 | B31: 1 | C31: 4 | E31: ACK.F683A520250011.1 | F31: Male | G31: Self | H31: 300000 | I31: 8124.57 | J31: 1
A32: 1060 | B32: 1 | C32: 4 | E32: ACK.F683A520250011.2 | F32: Female | G32: Daughter | H32: 0 | I32: 3283.23 | J32: 1
A33: 1061 | B33: 1 | C33: 4 | E33: ACK.F683A520250011.3 | F33: Female | G33: Daughter | H33: 0 | I33: 3283.23 | J33: 1
A34: 1062 | B34: 1 | C34: 3 | E34: ACK.F683A520250011.4 | F34: Female | G34: Spouse | H34: 0 | I34: 8124.57 | J34: 1
... A202: 4019 | B202: 1 | C202: 4 | E202: ACK.F683A520250065.4 | F202: Male | G202: Son | H202: 0 | I202: 3283.23 | J202: 1
A203: AVGCT1 | B203: 1 | C203: 3 | E203: ACK.F683A520250064.1 | F203: Male | G203: Self | H203: 300000 | I203: 4251.97 | J203: 1
A204: AVGCT2 | B204: 1 | C204: 4 | E204: ACK.F683A520250064.2 | F204: Male | G204: Son | H204: 0 | I204: 3283.23 | J204: 1
A205: AVGCT3 | B205: 0 | C205: 0 | E205: ACK.F683A520250064.3 | F205: Female | G205: Daughter | H205: 0 | I205: 3283.23 | J205: 1
A206: AVGCT4 | B206: 1 | C206: 2 | E206: ACK.F683A520250064.4 | F206: Female | G206: Spouse | H206: 0 | I206: 3283.23 | J206: 1
A207: AVGCT5 | B207: 1 | C207: 2 | E207: ACK.F683A520250066.1 | F207: Male | G207: Self | H207: 300000 | I207: 14246.99 | J207: 1
A208: AVGCT6 | B208: 1 | C208: 3 | E208: ACK.F683A520250066.2 | F208: Male | G208: Son | H208: 0 | I208: 3283.23 | J208: 1
A209: 2327 | B209: 1 | C209: 2 | E209: ACK.F683A520250066.3 | F209: Female | G209: Daughter | H209: 0 | I209: 3283.23 | J209: 1
A210: 2324 | B210: 1 | C210: 4 | E210: ACK.F683A520250066.4 | F210: Female | G210: Spouse | H210: 0 | I210: 4251.97 | J210: 1
A211: 2215 | B211: 1 | C211: 3 | E211: ACK.F683A520250067.1 | F211: Male | G211: Self | H211: 300000 | I211: 4251.97 | J211: 1
A212: 2229 | B212: 1 | C212: 2 | E212: ACK.F683A520250067.2 | F212: Female | G212: Spouse | H212: 0 | I212: 4251.97 | J212: 1
A213: 2337 | B213: 1 | C213: 4 | E213: ACK.F683A520250067.3 | F213: Male | G213: Son | H213: 0 | I213: 3283.23 | J213: 1
A214: 2338 | B214: 1 | C214: 4 | E214: ACK.F683A520250067.4 | F214: Female | G214: Daughter | H214: 0 | I214: 3283.23 | J214: 1
A215: 2339 | B215: 0 | C215: 0 | E215: ACK.F683A520250068.1 | F215: Male | G215: Self | H215: 300000 | I215: 4251.97 | J215: 1
A216: 2219 | B216: 1 | C216: 1 | E216: ACK.F683A520250068.2 | F216: Female | G216: Daughter | H216: 0 | I216: 3283.23 | J216: 1
A217: 2335 | B217: 1 | C217: 4 | E217: ACK.F683A520250068.3 | F217: Female | G217: Spouse | H217: 0 | I217: 4251.97 | J217: 1
A218: 2331 | B218: 0 | C218: 0 | E218: ACK.F683A520250068.4 | F218: Female | G218: Daughter | H218: 0 | I218: 3283.23 | J218: 1
A219: 2250 | B219: 1 | C219: 1 | E219: ACK.F683A520250069.1 | F219: Male | G219: Self | H219: 300000 | I219: 8124.57 | J219: 1
A220: 2345 | B220: 1 | C220: 1 | E220: ACK.F683A520250069.2 | F220: Female | G220: Daughter | H220: 0 | I220: 3283.23 | J220: 1
... A261: 2099 | B261: 1 | C261: 5 | E261: ACK.F683A520250083.2 | F261: Female | G261: Spouse | H261: 0 | I261: 4251.97 | J261: 1
A262: RET02 | B262: 1 | C262: 2 | E262: ACK.F683A520250083.3 | F262: Male | G262: Son | H262: 0 | I262: 3283.23 | J262: 1
A263: RET01 | B263: 1 | C263: 3 | E263: ACK.F683A520250085.1 | F263: Male | G263: Self | H263: 300000 | I263: 4251.97 | J263: 1
A264: RET03 | B264: 1 | C264: 4 | E264: ACK.F683A520250085.2 | F264: Male | G264: Son | H264: 0 | I264: 3283.23 | J264: 1
A265: 2381 | B265: 1 | C265: 2 | E265: ACK.F683A520250085.3 | F265: Male | G265: Son | H265: 0 | I265: 3283.23 | J265: 1
A266: Grand Total | B266: 245 | C266: 688 | E266: ACK.F683A520250085.4 | F266: Female | G266: Spouse | H266: 0 | I266: 4251.97 | J266: 1
E267: ACK.F683A520250084.1 | F267: Male | G267: Self | H267: 300000 | I267: 4251.97 | J267: 1
E268: ACK.F683A520250084.2 | F268: Female | G268: Spouse | H268: 0 | I268: 3283.23 | J268: 1
E269: ACK.F683A520250084.3 | F269: Female | G269: Daughter | H269: 0 | I269: 3283.23 | J269: 1
E270: ACK.F683A520250084.4 | F270: Male | G270: Son | H270: 0 | I270: 3283.23 | J270: 1
E271: ACK.F683A520250086.1 | F271: Male | G271: Self | H271: 300000 | I271: 4251.97 | J271: 1
E272: ACK.F683A520250086.2 | F272: Female | G272: Spouse | H272: 0 | I272: 3283.23 | J272: 1
E273: ACK.F683A520250086.3 | F273: Male | G273: Son | H273: 0 | I273: 3283.23 | J273: 1
E274: ACK.F683A520250087.1 | F274: Male | G274: Self | H274: 0 | I274: 873.69247 | J274: 0
E275: ACK.F683A520250087.2 | F275: Male | G275: Son | H275: 0 | I275: 674.6363 | J275: 0
E276: ACK.F683A520250087.3 | F276: Female | G276: Spouse | H276: 0 | I276: 674.6363 | J276: 0
E277: ACK.F683A520250087.4 | F277: Male | G277: Son | H277: 0 | I277: 674.6363 | J277: 0
E278: ACK.F683A520250088.1 | F278: Male | G278: Self | H278: 300000 | I278: 8124.57 | J278: 1
... E728: ACK.F683A520250263.2 | F728: Female | G728: Spouse | H728: 0 | I728: 1439.2241 | J728: 1
E729: Grand Total | H729: 79100000 | I729: 3237827.4 | J729: 688
