Workbook

Sheet Performance
F2: Health ( INR Lakhs) | G2: M01'19
F3: GWP | G3: =SuM!C8/100000 -> 225.52506
F4: NEP | G4: =SuM!C26/100000 -> 81.101078
F5: Claims (excluding IBNR)-33% of NEP | G5: =((60760+23748)*0.95)/100000 -> 0.802826 | I5: =G5*100000/G9 -> 743.35741
F6: Claims (including IBNR)-95% of NEP | G6: =((60760+23748)*0.95+154370)/100000 -> 2.346526
F7: Claims service cost(3% of claims) | G7: =3%*G6 -> 0.07039578
F8: No. of Policies | G8: 1592
F9: No. of Claims | G9: 108

Sheet SuM
A1: =C41&":" -> CALDERYS INDIA REFRACTORIES LIMITED:
A2: Particulars | C2: Number/₹ | D2: 202602
A3: No of Lives Insured | C3: =SUMIF(Details!B:B,$D$2,Details!AD:AD) -> 45
A4: GWP excl GST | C4: =SUMIF(Details!B:B,$D$2,Details!AE:AE) -> 172165.32
A6: Particulars | B6: Details | C6: Total | E6: 45901 | F6: 45931 | G6: 45962 | H6: 45992 | I6: 46023 | J6: 46054 | K6: 46082 | L6: 46113 | M6: 46143 | N6: 46174 | O6: 46204 | P6: 46235 | Q6: 46266 | R6: 46296 | S6: 46327 | U6: Recon
A8: GWP | C8: =Details!AE1 -> 22552506 | E8: 21745013 | F8: -18739.698 | G8: 448900.47 | H8: 66325.505 | I8: 138841.14 | J8: =SUMIF(Details!$B:$B,$D$2,Details!$AE:$AE) -> 172165.32 | K8: =SUMIF(Details!$B:$B,$D$2,Details!$AE:$AE) -> 172165.32 | L8: =SUMIF(Details!$B:$B,$D$2,Details!$AE:$AE) -> 172165.32 | M8: =SUMIF(Details!$B:$B,$D$2,Details!$AE:$AE) -> 172165.32 | N8: =SUMIF(Details!$B:$B,$D$2,Details!$AE:$AE) -> 172165.32 | O8: =SUMIF(Details!$B:$B,$D$2,Details!$AE:$AE) -> 172165.32 | P8: =SUMIF(Details!$B:$B,$D$2,Details!$AE:$AE) -> 172165.32 | Q8: =SUMIF(Details!$B:$B,$D$2,Details!$AE:$AE) -> 172165.32 | ... S8: =SUMIF(Details!$B:$B,$D$2,Details!$AE:$AE) -> 172165.32 | U8: =$C8-SUM(E8:J8) -> 4.8428774e-08
U9: =$C9-SUM(E9:J9) -> 0
A10: GST: | U10: =$C10-SUM(E10:J10) -> 0
A11: SGST/UGST | C11: =Details!AF1 -> 0 | E11: 0 | F11: 0 | G11: 0 | H11: 0 | I11: 0 | J11: =SUMIF(Details!$B:$B,$D$2,Details!$AF:$AF) -> 0 | K11: =SUMIF(Details!$B:$B,$D$2,Details!$AF:$AF) -> 0 | L11: =SUMIF(Details!$B:$B,$D$2,Details!$AF:$AF) -> 0 | M11: =SUMIF(Details!$B:$B,$D$2,Details!$AF:$AF) -> 0 | N11: =SUMIF(Details!$B:$B,$D$2,Details!$AF:$AF) -> 0 | O11: =SUMIF(Details!$B:$B,$D$2,Details!$AF:$AF) -> 0 | P11: =SUMIF(Details!$B:$B,$D$2,Details!$AF:$AF) -> 0 | Q11: =SUMIF(Details!$B:$B,$D$2,Details!$AF:$AF) -> 0 | ... S11: =SUMIF(Details!$B:$B,$D$2,Details!$AF:$AF) -> 0 | U11: =$C11-SUM(E11:J11) -> 0
A12: CGST | C12: =Details!AG1 -> 0 | E12: 0 | F12: 0 | G12: 0 | H12: 0 | I12: 0 | J12: =SUMIF(Details!$B:$B,$D$2,Details!$AG:$AG) -> 0 | K12: =SUMIF(Details!$B:$B,$D$2,Details!$AG:$AG) -> 0 | L12: =SUMIF(Details!$B:$B,$D$2,Details!$AG:$AG) -> 0 | M12: =SUMIF(Details!$B:$B,$D$2,Details!$AG:$AG) -> 0 | N12: =SUMIF(Details!$B:$B,$D$2,Details!$AG:$AG) -> 0 | O12: =SUMIF(Details!$B:$B,$D$2,Details!$AG:$AG) -> 0 | P12: =SUMIF(Details!$B:$B,$D$2,Details!$AG:$AG) -> 0 | Q12: =SUMIF(Details!$B:$B,$D$2,Details!$AG:$AG) -> 0 | ... S12: =SUMIF(Details!$B:$B,$D$2,Details!$AG:$AG) -> 0 | U12: =$C12-SUM(E12:J12) -> 0
A13: IGST | C13: =Details!AH1 -> 4059451 | E13: 3914102.3 | F13: -3373.1456 | G13: 80802.085 | H13: 11938.591 | I13: 24991.405 | J13: =SUMIF(Details!$B:$B,$D$2,Details!$AH:$AH) -> 30989.757 | K13: =SUMIF(Details!$B:$B,$D$2,Details!$AH:$AH) -> 30989.757 | L13: =SUMIF(Details!$B:$B,$D$2,Details!$AH:$AH) -> 30989.757 | M13: =SUMIF(Details!$B:$B,$D$2,Details!$AH:$AH) -> 30989.757 | N13: =SUMIF(Details!$B:$B,$D$2,Details!$AH:$AH) -> 30989.757 | O13: =SUMIF(Details!$B:$B,$D$2,Details!$AH:$AH) -> 30989.757 | P13: =SUMIF(Details!$B:$B,$D$2,Details!$AH:$AH) -> 30989.757 | Q13: =SUMIF(Details!$B:$B,$D$2,Details!$AH:$AH) -> 30989.757 | ... S13: =SUMIF(Details!$B:$B,$D$2,Details!$AH:$AH) -> 30989.757 | U13: =$C13-SUM(E13:J13) -> 5.5879354e-09
A14: Total GST | C14: =SUM(C11:C13) -> 4059451 | E14: 3914102.3 | F14: -3373.1456 | G14: 80802.085 | H14: 11938.591 | I14: 24991.405 | J14: =SUM(J11:J13) -> 30989.757 | K14: =SUM(K11:K13) -> 30989.757 | L14: =SUM(L11:L13) -> 30989.757 | M14: =SUM(M11:M13) -> 30989.757 | N14: =SUM(N11:N13) -> 30989.757 | O14: =SUM(O11:O13) -> 30989.757 | P14: =SUM(P11:P13) -> 30989.757 | Q14: =SUM(Q11:Q13) -> 30989.757 | ... S14: =SUM(S11:S13) -> 30989.757 | U14: =$C14-SUM(E14:J14) -> 5.5879354e-09
U15: =$C15-SUM(E15:J15) -> 0
A16: Reinsurance Premium: | U16: =$C16-SUM(E16:J16) -> 0
A17: Reinsurance Premium - Obligatory | C17: =Details!AI1 -> 902100.23 | E17: 869800.52 | F17: -749.5879 | G17: 17956.019 | H17: 2653.0202 | I17: 5553.6455 | J17: =SUMIF(Details!$B:$B,$D$2,Details!$AI:$AI) -> 6886.6128 | K17: =SUMIF(Details!$B:$B,$D$2,Details!$AI:$AI) -> 6886.6128 | L17: =SUMIF(Details!$B:$B,$D$2,Details!$AI:$AI) -> 6886.6128 | M17: =SUMIF(Details!$B:$B,$D$2,Details!$AI:$AI) -> 6886.6128 | N17: =SUMIF(Details!$B:$B,$D$2,Details!$AI:$AI) -> 6886.6128 | O17: =SUMIF(Details!$B:$B,$D$2,Details!$AI:$AI) -> 6886.6128 | P17: =SUMIF(Details!$B:$B,$D$2,Details!$AI:$AI) -> 6886.6128 | Q17: =SUMIF(Details!$B:$B,$D$2,Details!$AI:$AI) -> 6886.6128 | ... S17: =SUMIF(Details!$B:$B,$D$2,Details!$AI:$AI) -> 6886.6128 | U17: =$C17-SUM(E17:J17) -> 0
A18: Reinsurance Premium - Quota Share | C18: =Details!AJ1 -> 5074313.8 | E18: 4892627.9 | F18: -4216.432 | G18: 101002.61 | H18: 14923.239 | I18: 31239.256 | J18: =SUMIF(Details!$B:$B,$D$2,Details!$AJ:$AJ) -> 38737.197 | K18: =SUMIF(Details!$B:$B,$D$2,Details!$AJ:$AJ) -> 38737.197 | L18: =SUMIF(Details!$B:$B,$D$2,Details!$AJ:$AJ) -> 38737.197 | M18: =SUMIF(Details!$B:$B,$D$2,Details!$AJ:$AJ) -> 38737.197 | N18: =SUMIF(Details!$B:$B,$D$2,Details!$AJ:$AJ) -> 38737.197 | O18: =SUMIF(Details!$B:$B,$D$2,Details!$AJ:$AJ) -> 38737.197 | P18: =SUMIF(Details!$B:$B,$D$2,Details!$AJ:$AJ) -> 38737.197 | Q18: =SUMIF(Details!$B:$B,$D$2,Details!$AJ:$AJ) -> 38737.197 | ... S18: =SUMIF(Details!$B:$B,$D$2,Details!$AJ:$AJ) -> 38737.197 | U18: =$C18-SUM(E18:J18) -> 0
U19: =$C19-SUM(E19:J19) -> 0
A20: Commission on Reinsurance Premium: | U20: =$C20-SUM(E20:J20) -> 0
A21: Reinsurance Commission - Obligatory | C21: =ROUND(C17*10%,0) -> 90210 | E21: 86980 | F21: -75 | G21: 1796 | H21: 265 | I21: 555 | J21: =ROUND(J17*10%,0) -> 689 | K21: =ROUND(K17*10%,0) -> 689 | L21: =ROUND(L17*10%,0) -> 689 | M21: =ROUND(M17*10%,0) -> 689 | N21: =ROUND(N17*10%,0) -> 689 | O21: =ROUND(O17*10%,0) -> 689 | P21: =ROUND(P17*10%,0) -> 689 | Q21: =ROUND(Q17*10%,0) -> 689 | ... S21: =ROUND(S17*10%,0) -> 689 | U21: =$C21-SUM(E21:J21) -> 0
A22: Reinsurance Commission - Quota Share | C22: =ROUND(C18*50%,0) -> 2537157 | E22: 2446314 | F22: -2108 | G22: 50501 | H22: 7462 | I22: 15620 | J22: =ROUND(J18*50%,0) -> 19369 | K22: =ROUND(K18*50%,0) -> 19369 | L22: =ROUND(L18*50%,0) -> 19369 | M22: =ROUND(M18*50%,0) -> 19369 | N22: =ROUND(N18*50%,0) -> 19369 | O22: =ROUND(O18*50%,0) -> 19369 | P22: =ROUND(P18*50%,0) -> 19369 | Q22: =ROUND(Q18*50%,0) -> 19369 | ... S22: =ROUND(S18*50%,0) -> 19369 | U22: =$C22-SUM(E22:J22) -> -1
E23: 0 | F23: 0 | G23: 0 | H23: 0 | I23: 0 | J23: =ROUND(J19*10%,0) -> 0 | K23: =ROUND(K19*10%,0) -> 0 | L23: =ROUND(L19*10%,0) -> 0 | M23: =ROUND(M19*10%,0) -> 0 | N23: =ROUND(N19*10%,0) -> 0 | O23: =ROUND(O19*10%,0) -> 0 | P23: =ROUND(P19*10%,0) -> 0 | Q23: =ROUND(Q19*10%,0) -> 0 | ... S23: =ROUND(S19*10%,0) -> 0 | U23: =$C23-SUM(E23:J23) -> 0
A24: GEP | C24: =Details!AK1 -> 11034160 | E24: 1782648.8 | F24: 1843675.8 | G24: 1840535.2 | H24: 1898203 | I24: 1918898.3 | J24: =$C24-SUM($D24:I24) -> 1750199.2 | K24: =$C24-SUM($D24:J24) -> 0 | L24: =$C24-SUM($D24:K24) -> 0 | M24: =$C24-SUM($D24:L24) -> 0 | N24: =$C24-SUM($D24:M24) -> 0 | O24: =$C24-SUM($D24:N24) -> 0 | P24: =$C24-SUM($D24:O24) -> 0 | Q24: =$C24-SUM($D24:P24) -> 0 | ... S24: =$C24-SUM($D24:R24) -> 0 | U24: =$C24-SUM(E24:J24) -> 0
U25: =$C25-SUM(E25:J25) -> 0
A26: NEP | C26: =Details!AL1 -> 8110107.8 | E26: 1310246.9 | F26: 1355101.7 | G26: 1352793.3 | H26: 1395179.2 | I26: 1410390.2 | J26: =$C26-SUM($D26:I26) -> 1286396.4 | K26: =$C26-SUM($D26:J26) -> 0 | L26: =$C26-SUM($D26:K26) -> 0 | M26: =$C26-SUM($D26:L26) -> 0 | N26: =$C26-SUM($D26:M26) -> 0 | O26: =$C26-SUM($D26:N26) -> 0 | P26: =$C26-SUM($D26:O26) -> 0 | Q26: =$C26-SUM($D26:P26) -> 0 | ... S26: =$C26-SUM($D26:R26) -> 0 | U26: =$C26-SUM(E26:J26) -> 0
U27: =$C27-SUM(E27:J27) -> 0
A28: NURR | C28: =C8-C17-C26-C18 -> 8465983.8 | E28: 14672338 | F28: -1368875.4 | G28: -1022851.5 | H28: -1346429.9 | I28: -1308342 | J28: =J8-J17-J26-J18 -> -1159854.9 | K28: =K8-K17-K26-K18 -> 126541.51 | L28: =L8-L17-L26-L18 -> 126541.51 | M28: =M8-M17-M26-M18 -> 126541.51 | N28: =N8-N17-N26-N18 -> 126541.51 | O28: =O8-O17-O26-O18 -> 126541.51 | P28: =P8-P17-P26-P18 -> 126541.51 | Q28: =Q8-Q17-Q26-Q18 -> 126541.51 | ... S28: =S8-S17-S26-S18 -> 126541.51 | U28: =$C28-SUM(E28:J28) -> 4.2840838e-08
U29: =$C29-SUM(E29:J29) -> 0
A30: Total No of COI/No of Plan Sold | C30: =Details!X1 -> 759 | E30: 706 | F30: 0 | G30: 25 | H30: 5 | I30: 10 | J30: =SUMIF(Details!$B:$B,$D$2,Details!$X:$X) -> 13 | K30: =SUMIF(Details!$B:$B,$D$2,Details!$X:$X) -> 13 | L30: =SUMIF(Details!$B:$B,$D$2,Details!$X:$X) -> 13 | M30: =SUMIF(Details!$B:$B,$D$2,Details!$X:$X) -> 13 | N30: =SUMIF(Details!$B:$B,$D$2,Details!$X:$X) -> 13 | O30: =SUMIF(Details!$B:$B,$D$2,Details!$X:$X) -> 13 | P30: =SUMIF(Details!$B:$B,$D$2,Details!$X:$X) -> 13 | Q30: =SUMIF(Details!$B:$B,$D$2,Details!$X:$X) -> 13 | ... S30: =SUMIF(Details!$B:$B,$D$2,Details!$X:$X) -> 13 | U30: =$C30-SUM(E30:J30) -> 0
U31: =$C31-SUM(E31:J31) -> 0
A32: Total No of Life Cover | C32: =Details!AD1 -> 3167 | E32: 2963 | F32: 19 | G32: 86 | H32: 18 | I32: 36 | J32: =SUMIF(Details!$B:$B,$D$2,Details!$AD:$AD) -> 45 | K32: =SUMIF(Details!$B:$B,$D$2,Details!$AD:$AD) -> 45 | L32: =SUMIF(Details!$B:$B,$D$2,Details!$AD:$AD) -> 45 | M32: =SUMIF(Details!$B:$B,$D$2,Details!$AD:$AD) -> 45 | N32: =SUMIF(Details!$B:$B,$D$2,Details!$AD:$AD) -> 45 | O32: =SUMIF(Details!$B:$B,$D$2,Details!$AD:$AD) -> 45 | P32: =SUMIF(Details!$B:$B,$D$2,Details!$AD:$AD) -> 45 | Q32: =SUMIF(Details!$B:$B,$D$2,Details!$AD:$AD) -> 45 | ... S32: =SUMIF(Details!$B:$B,$D$2,Details!$AD:$AD) -> 45 | U32: =$C32-SUM(E32:J32) -> 0
U33: =$C33-SUM(E33:J33) -> 0
A34: Prudent Insurance Brokerage - 2.38% | U34: =$C34-SUM(E34:J34) -> 0
A35: Commission | C35: =2.38%*C8 -> 536749.63 | E35: 517531.31 | F35: -446.0048 | G35: 10683.831 | H35: 1578.547 | I35: 3304.4191 | J35: =$C35-SUM($D35:I35) -> 4097.5346 | K35: =$C35-SUM($D35:J35) -> 0 | L35: =$C35-SUM($D35:K35) -> 0 | M35: =$C35-SUM($D35:L35) -> 0 | N35: =$C35-SUM($D35:M35) -> 0 | O35: =$C35-SUM($D35:N35) -> 0 | P35: =$C35-SUM($D35:O35) -> 0 | Q35: =$C35-SUM($D35:P35) -> 0 | ... S35: =$C35-SUM($D35:R35) -> 0 | U35: =$C35-SUM(E35:J35) -> 0
U36: =$C36-SUM(E36:J36) -> 0
A37: Total SA | C37: =Details!W1 -> 300500000 | E37: 281100000 | F37: 0 | G37: 10100000 | H37: 1700000 | I37: 3400000 | J37: =$C37-SUM($D37:I37) -> 4200000 | K37: =$C37-SUM($D37:J37) -> 0 | L37: =$C37-SUM($D37:K37) -> 0 | M37: =$C37-SUM($D37:L37) -> 0 | N37: =$C37-SUM($D37:M37) -> 0 | O37: =$C37-SUM($D37:N37) -> 0 | P37: =$C37-SUM($D37:O37) -> 0 | Q37: =$C37-SUM($D37:P37) -> 0 | ... S37: =$C37-SUM($D37:R37) -> 0 | U37: =$C37-SUM(E37:J37) -> 0
U38: =$C38-SUM(E38:J38) -> 0
A39: Master Policy No (Passenger) | C39: =Details!C3 -> GMC023220100CALDERYS
A40: Period | C40: : 01-09-2025 to 31-08-2026
A41: Proposer Name | C41: =Details!D3 -> CALDERYS INDIA REFRACTORIES LIMITED
A43: Name on Premium Summary | B43: CALDERYS-GMC-GMC023220100CALDERYS
A44: Master Policy No | B44: =Details!C3 -> GMC023220100CALDERYS
A45: Master Start Date | B45: =Details!E3 -> 45901
A46: Master End Date | B46: =Details!F3 -> 46265
A47: State | B47: =Details!AB3 -> Maharashtra
A48: Business Name | B48: Health
A49: Product Name | B49: Health-GMC for Employee
A50: Cost Centre Details | B50: Health
A51: Channel | B51: Prudent
A52: Name of Intermediary | B52: NA
A53: Intermediary Type | B53: =B51 -> Prudent
A54: Oracle Product Code
A55: Oracle Cost Centre | B55: 706
A56: Oracle Sales Channel
A57: Premium Deposit GL No
A58: Policy Type | B58: Renewal
A59: Cover Type
A60: Sector
A61: Future 1
A62: Future 2
A63: Future 3
A64: Future 4
A65: Future 5

Sheet Details
H1: 652569 | V1: =ROUND(SUM(V3:V1048576),0) -> 1261100000 | W1: =ROUND(SUM(W3:W1048576),0) -> 300500000 | X1: =ROUND(SUM(X3:X1048576),0) -> 759 | Z1: 46081 | AB1: Total | AC1: =ROUND(SUM(AC3:AC1048576),0) -> 26611957 | AD1: =ROUND(SUM(AD3:AD1048576),0) -> 3167 | AE1: =SUM(AE3:AE1048576) -> 22552506 | AF1: =SUM(AF3:AF1048576) -> 0 | AG1: =SUM(AG3:AG1048576) -> 0 | AH1: =SUM(AH3:AH1048576) -> 4059451 | AI1: =SUM(AI3:AI1048576) -> 902100.23 | AJ1: =SUM(AJ3:AJ1048576) -> 5074313.8 | AK1: =SUM(AK3:AK1048576) -> 11034160 | AL1: =SUM(AL3:AL1048576) -> 8110107.8 | AM1: =SUM(AM3:AM1048576) -> 8465983.8 | AO1: =ROUND(SUM(AO3:AO1048576),0) -> 22552506
A2: Status | B2: Acct. Month | C2: Master Policy No | D2: Master Policy Holder Name | E2: Master Policy Risk Start Date | F2: Master Policy Risk End Date | G2: Name | H2: Emp ID | I2: DOB | J2: UHID | K2: Policy Risk Start Date | L2: Ri Obligatory | M2: RI Quota | N2: Risk Start Date | O2: Risk End Date | P2: Last Working Day | Q2: Reversal Date | R2: Age | S2: Age Band | T2: Gender | U2: Relationship | V2: Sum Insured | W2: Reporting Sum Insured | X2: No of Policies | Y2: Risk Days | Z2: Base Date | AA2: Used | AB2: State | AC2: Gross Premium | AD2: No of Person Cover Per Day | AE2: GWP | AF2: SGST/UGST | AG2: CGST | AH2: IGST | AI2: Reinsurance Premium -Obligatory | AJ2: Reinsurance Premium -Quota | AK2: GEP | AL2: NEP | AM2: NURR | AN2: Unexpired Premium Date | AO2: Unexpired Premium | AP2: Claim Status
A3: Valid | B3: 202509 | C3: GMC023220100CALDERYS | D3: CALDERYS INDIA REFRACTORIES LIMITED | E3: 45901 | F3: 46265 | G3: Kanchana Chakraborty | H3: 11350 | I3: 24166 | J3: ACK.4A9F3020250658.1 | K3: =N3 -> 45901 | L3: =IF(K3>=DATE(2022,4,1),4%,5%) -> 0.04 | M3: 0.225 | N3: 45901 | O3: 46265 | R3: 59 | S3: =VLOOKUP(R3,SA!$B$3:$C$11,2,1) -> 56-65 | T3: Female | U3: Spouse | V3: 600000 | W3: =IF(U3="self",V3,0) -> 0 | X3: =IF(U3="self",1,0) -> 0 | Y3: =O3-N3+1 -> 365 | Z3: =$Z$1 -> 46081 | AA3: =IF(MIN((Z3-N3)+1,Y3)<0,0,MIN((Z3-N3)+1,Y3)) -> 181 | AB3: Maharashtra | AC3: =AE3+AF3+AG3+AH3 -> 14410.797 | AD3: 1 | AE3: =INDEX(SA!$C$2:$G$11,MATCH(Details!S3,SA!$C$2:$C$11,0),MATCH(Details!V3,SA!$C$2:$G$2,0))*Y3/(F3-E3+1) -> 12212.54 | AF3: =IF(AB3="Karnataka",AE3*9%,0) -> 0 | AG3: =IF(AB3="Karnataka",AE3*9%,0) -> 0 | AH3: =IF(AF3+AG3>0,0,AE3*18%) -> 2198.2572 | AI3: =AE3*L3 -> 488.5016 | AJ3: =$AE3*M3 -> 2747.8215 | AK3: =(AE3)*AA3/Y3 -> 6056.0815 | AL3: =AK3*(1-L3-M3) -> 4451.2199 | AM3: =AE3-AI3-AL3-AJ3 -> 4524.997 | AN3: =Z3-366 -> 45715 | AO3: =IF(AND(O3>Z3,N3>AN3),AE3,0) -> 12212.54
A4: Valid | B4: 202509 | C4: GMC023220100CALDERYS | D4: CALDERYS INDIA REFRACTORIES LIMITED | E4: 45901 | F4: 46265 | G4: Indra Nath Chakraborty | H4: 11350 | I4: 20846 | J4: ACK.4A9F3020250658.2 | K4: =N4 -> 45901 | L4: =IF(K4>=DATE(2022,4,1),4%,5%) -> 0.04 | M4: 0.225 | N4: 45901 | O4: 46265 | R4: 68 | S4: =VLOOKUP(R4,SA!$B$3:$C$11,2,1) -> 66-70 | T4: Male | U4: Self | V4: 600000 | W4: =IF(U4="self",V4,0) -> 600000 | X4: =IF(U4="self",1,0) -> 1 | Y4: =O4-N4+1 -> 365 | Z4: =$Z$1 -> 46081 | AA4: =IF(MIN((Z4-N4)+1,Y4)<0,0,MIN((Z4-N4)+1,Y4)) -> 181 | AB4: Maharashtra | AC4: =AE4+AF4+AG4+AH4 -> 20584.357 | AD4: 1 | AE4: =INDEX(SA!$C$2:$G$11,MATCH(Details!S4,SA!$C$2:$C$11,0),MATCH(Details!V4,SA!$C$2:$G$2,0))*Y4/(F4-E4+1) -> 17444.37 | AF4: =IF(AB4="Karnataka",AE4*9%,0) -> 0 | AG4: =IF(AB4="Karnataka",AE4*9%,0) -> 0 | AH4: =IF(AF4+AG4>0,0,AE4*18%) -> 3139.9866 | AI4: =AE4*L4 -> 697.7748 | AJ4: =$AE4*M4 -> 3924.9832 | AK4: =(AE4)*AA4/Y4 -> 8650.4958 | AL4: =AK4*(1-L4-M4) -> 6358.1144 | AM4: =AE4-AI4-AL4-AJ4 -> 6463.4975 | AN4: =Z4-366 -> 45715 | AO4: =IF(AND(O4>Z4,N4>AN4),AE4,0) -> 17444.37
A5: Valid | B5: 202509 | C5: GMC023220100CALDERYS | D5: CALDERYS INDIA REFRACTORIES LIMITED | E5: 45901 | F5: 46265 | G5: Manisha Bajpai | H5: 41022 | I5: 27546 | J5: ACK.4A9F3020250661.1 | K5: =N5 -> 45901 | L5: =IF(K5>=DATE(2022,4,1),4%,5%) -> 0.04 | M5: 0.225 | N5: 45901 | O5: 46265 | R5: 50 | S5: =VLOOKUP(R5,SA!$B$3:$C$11,2,1) -> 46-55 | T5: Female | U5: Spouse | V5: 300000 | W5: =IF(U5="self",V5,0) -> 0 | X5: =IF(U5="self",1,0) -> 0 | Y5: =O5-N5+1 -> 365 | Z5: =$Z$1 -> 46081 | AA5: =IF(MIN((Z5-N5)+1,Y5)<0,0,MIN((Z5-N5)+1,Y5)) -> 181 | AB5: Maharashtra | AC5: =AE5+AF5+AG5+AH5 -> 7373.466 | AD5: 1 | AE5: =INDEX(SA!$C$2:$G$11,MATCH(Details!S5,SA!$C$2:$C$11,0),MATCH(Details!V5,SA!$C$2:$G$2,0))*Y5/(F5-E5+1) -> 6248.7 | AF5: =IF(AB5="Karnataka",AE5*9%,0) -> 0 | AG5: =IF(AB5="Karnataka",AE5*9%,0) -> 0 | AH5: =IF(AF5+AG5>0,0,AE5*18%) -> 1124.766 | AI5: =AE5*L5 -> 249.948 | AJ5: =$AE5*M5 -> 1405.9575 | AK5: =(AE5)*AA5/Y5 -> 3098.6704 | AL5: =AK5*(1-L5-M5) -> 2277.5228 | AM5: =AE5-AI5-AL5-AJ5 -> 2315.2717 | AN5: =Z5-366 -> 45715 | AO5: =IF(AND(O5>Z5,N5>AN5),AE5,0) -> 6248.7
A6: Valid | B6: 202509 | C6: GMC023220100CALDERYS | D6: CALDERYS INDIA REFRACTORIES LIMITED | E6: 45901 | F6: 46265 | G6: Devi Prasad Bajpai | H6: 41022 | I6: 16560 | J6: ACK.4A9F3020250661.2 | K6: =N6 -> 45901 | L6: =IF(K6>=DATE(2022,4,1),4%,5%) -> 0.04 | M6: 0.225 | N6: 45901 | O6: 46265 | R6: 80 | S6: =VLOOKUP(R6,SA!$B$3:$C$11,2,1) -> 76-80 | T6: Male | U6: Father | V6: 300000 | W6: =IF(U6="self",V6,0) -> 0 | X6: =IF(U6="self",1,0) -> 0 | Y6: =O6-N6+1 -> 365 | Z6: =$Z$1 -> 46081 | AA6: =IF(MIN((Z6-N6)+1,Y6)<0,0,MIN((Z6-N6)+1,Y6)) -> 181 | AB6: Maharashtra | AC6: =AE6+AF6+AG6+AH6 -> 24649.079 | AD6: 1 | AE6: =INDEX(SA!$C$2:$G$11,MATCH(Details!S6,SA!$C$2:$C$11,0),MATCH(Details!V6,SA!$C$2:$G$2,0))*Y6/(F6-E6+1) -> 20889.05 | AF6: =IF(AB6="Karnataka",AE6*9%,0) -> 0 | AG6: =IF(AB6="Karnataka",AE6*9%,0) -> 0 | AH6: =IF(AF6+AG6>0,0,AE6*18%) -> 3760.029 | AI6: =AE6*L6 -> 835.562 | AJ6: =$AE6*M6 -> 4700.0363 | AK6: =(AE6)*AA6/Y6 -> 10358.68 | AL6: =AK6*(1-L6-M6) -> 7613.6295 | AM6: =AE6-AI6-AL6-AJ6 -> 7739.8223 | AN6: =Z6-366 -> 45715 | AO6: =IF(AND(O6>Z6,N6>AN6),AE6,0) -> 20889.05
A7: Valid | B7: 202509 | C7: GMC023220100CALDERYS | D7: CALDERYS INDIA REFRACTORIES LIMITED | E7: 45901 | F7: 46265 | G7: Abishek Bajpai | H7: 41022 | I7: 38528 | J7: ACK.4A9F3020250661.3 | K7: =N7 -> 45901 | L7: =IF(K7>=DATE(2022,4,1),4%,5%) -> 0.04 | M7: 0.225 | N7: 45901 | O7: 46265 | R7: 20 | S7: =VLOOKUP(R7,SA!$B$3:$C$11,2,1) -> 0-25 | T7: Male | U7: Son | V7: 300000 | W7: =IF(U7="self",V7,0) -> 0 | X7: =IF(U7="self",1,0) -> 0 | Y7: =O7-N7+1 -> 365 | Z7: =$Z$1 -> 46081 | AA7: =IF(MIN((Z7-N7)+1,Y7)<0,0,MIN((Z7-N7)+1,Y7)) -> 181 | AB7: Maharashtra | AC7: =AE7+AF7+AG7+AH7 -> 3690.3792 | AD7: 1 | AE7: =INDEX(SA!$C$2:$G$11,MATCH(Details!S7,SA!$C$2:$C$11,0),MATCH(Details!V7,SA!$C$2:$G$2,0))*Y7/(F7-E7+1) -> 3127.44 | AF7: =IF(AB7="Karnataka",AE7*9%,0) -> 0 | AG7: =IF(AB7="Karnataka",AE7*9%,0) -> 0 | AH7: =IF(AF7+AG7>0,0,AE7*18%) -> 562.9392 | AI7: =AE7*L7 -> 125.0976 | AJ7: =$AE7*M7 -> 703.674 | AK7: =(AE7)*AA7/Y7 -> 1550.8675 | AL7: =AK7*(1-L7-M7) -> 1139.8876 | AM7: =AE7-AI7-AL7-AJ7 -> 1158.7808 | AN7: =Z7-366 -> 45715 | AO7: =IF(AND(O7>Z7,N7>AN7),AE7,0) -> 3127.44
A8: Valid | B8: 202509 | C8: GMC023220100CALDERYS | D8: CALDERYS INDIA REFRACTORIES LIMITED | E8: 45901 | F8: 46265 | G8: Priya Bajpai | H8: 41022 | I8: 36381 | J8: ACK.4A9F3020250661.4 | K8: =N8 -> 45901 | L8: =IF(K8>=DATE(2022,4,1),4%,5%) -> 0.04 | M8: 0.225 | N8: 45901 | O8: 46265 | R8: 26 | S8: =VLOOKUP(R8,SA!$B$3:$C$11,2,1) -> 26-35 | T8: Female | U8: Daughter | V8: 300000 | W8: =IF(U8="self",V8,0) -> 0 | X8: =IF(U8="self",1,0) -> 0 | Y8: =O8-N8+1 -> 365 | Z8: =$Z$1 -> 46081 | AA8: =IF(MIN((Z8-N8)+1,Y8)<0,0,MIN((Z8-N8)+1,Y8)) -> 181 | AB8: Maharashtra | AC8: =AE8+AF8+AG8+AH8 -> 4124.4658 | AD8: 1 | AE8: =INDEX(SA!$C$2:$G$11,MATCH(Details!S8,SA!$C$2:$C$11,0),MATCH(Details!V8,SA!$C$2:$G$2,0))*Y8/(F8-E8+1) -> 3495.31 | AF8: =IF(AB8="Karnataka",AE8*9%,0) -> 0 | AG8: =IF(AB8="Karnataka",AE8*9%,0) -> 0 | AH8: =IF(AF8+AG8>0,0,AE8*18%) -> 629.1558 | AI8: =AE8*L8 -> 139.8124 | AJ8: =$AE8*M8 -> 786.44475 | AK8: =(AE8)*AA8/Y8 -> 1733.2907 | AL8: =AK8*(1-L8-M8) -> 1273.9687 | AM8: =AE8-AI8-AL8-AJ8 -> 1295.0842 | AN8: =Z8-366 -> 45715 | AO8: =IF(AND(O8>Z8,N8>AN8),AE8,0) -> 3495.31
A9: Valid | B9: 202509 | C9: GMC023220100CALDERYS | D9: CALDERYS INDIA REFRACTORIES LIMITED | E9: 45901 | F9: 46265 | G9: Ravi Shanker Bajpai | H9: 41022 | I9: 25660 | J9: ACK.4A9F3020250661.5 | K9: =N9 -> 45901 | L9: =IF(K9>=DATE(2022,4,1),4%,5%) -> 0.04 | M9: 0.225 | N9: 45901 | O9: 46265 | R9: 55 | S9: =VLOOKUP(R9,SA!$B$3:$C$11,2,1) -> 46-55 | T9: Male | U9: Self | V9: 300000 | W9: =IF(U9="self",V9,0) -> 300000 | X9: =IF(U9="self",1,0) -> 1 | Y9: =O9-N9+1 -> 365 | Z9: =$Z$1 -> 46081 | AA9: =IF(MIN((Z9-N9)+1,Y9)<0,0,MIN((Z9-N9)+1,Y9)) -> 181 | AB9: Maharashtra | AC9: =AE9+AF9+AG9+AH9 -> 7373.466 | AD9: 1 | AE9: =INDEX(SA!$C$2:$G$11,MATCH(Details!S9,SA!$C$2:$C$11,0),MATCH(Details!V9,SA!$C$2:$G$2,0))*Y9/(F9-E9+1) -> 6248.7 | AF9: =IF(AB9="Karnataka",AE9*9%,0) -> 0 | AG9: =IF(AB9="Karnataka",AE9*9%,0) -> 0 | AH9: =IF(AF9+AG9>0,0,AE9*18%) -> 1124.766 | AI9: =AE9*L9 -> 249.948 | AJ9: =$AE9*M9 -> 1405.9575 | AK9: =(AE9)*AA9/Y9 -> 3098.6704 | AL9: =AK9*(1-L9-M9) -> 2277.5228 | AM9: =AE9-AI9-AL9-AJ9 -> 2315.2717 | AN9: =Z9-366 -> 45715 | AO9: =IF(AND(O9>Z9,N9>AN9),AE9,0) -> 6248.7
A10: Valid | B10: 202509 | C10: GMC023220100CALDERYS | D10: CALDERYS INDIA REFRACTORIES LIMITED | E10: 45901 | F10: 46265 | G10: Shiv Prasad Tripathi | H10: 41023 | I10: 18737 | J10: ACK.4A9F3020250078.1 | K10: =N10 -> 45901 | L10: =IF(K10>=DATE(2022,4,1),4%,5%) -> 0.04 | M10: 0.225 | N10: 45901 | O10: 46265 | R10: 74 | S10: =VLOOKUP(R10,SA!$B$3:$C$11,2,1) -> 71-75 | T10: Male | U10: Father | V10: 400000 | W10: =IF(U10="self",V10,0) -> 0 | X10: =IF(U10="self",1,0) -> 0 | Y10: =O10-N10+1 -> 365 | Z10: =$Z$1 -> 46081 | AA10: =IF(MIN((Z10-N10)+1,Y10)<0,0,MIN((Z10-N10)+1,Y10)) -> 181 | AB10: Maharashtra | AC10: =AE10+AF10+AG10+AH10 -> 21578.035 | AD10: 1 | AE10: =INDEX(SA!$C$2:$G$11,MATCH(Details!S10,SA!$C$2:$C$11,0),MATCH(Details!V10,SA!$C$2:$G$2,0))*Y10/(F10-E10+1) -> 18286.47 | AF10: =IF(AB10="Karnataka",AE10*9%,0) -> 0 | AG10: =IF(AB10="Karnataka",AE10*9%,0) -> 0 | AH10: =IF(AF10+AG10>0,0,AE10*18%) -> 3291.5646 | AI10: =AE10*L10 -> 731.4588 | AJ10: =$AE10*M10 -> 4114.4558 | AK10: =(AE10)*AA10/Y10 -> 9068.0851 | AL10: =AK10*(1-L10-M10) -> 6665.0426 | AM10: =AE10-AI10-AL10-AJ10 -> 6775.5129 | AN10: =Z10-366 -> 45715 | AO10: =IF(AND(O10>Z10,N10>AN10),AE10,0) -> 18286.47
A11: Valid | B11: 202509 | C11: GMC023220100CALDERYS | D11: CALDERYS INDIA REFRACTORIES LIMITED | E11: 45901 | F11: 46265 | G11: Anita Tripathi | H11: 41023 | I11: 28732 | J11: ACK.4A9F3020250078.2 | K11: =N11 -> 45901 | L11: =IF(K11>=DATE(2022,4,1),4%,5%) -> 0.04 | M11: 0.225 | N11: 45901 | O11: 46265 | R11: 47 | S11: =VLOOKUP(R11,SA!$B$3:$C$11,2,1) -> 46-55 | T11: Female | U11: Spouse | V11: 400000 | W11: =IF(U11="self",V11,0) -> 0 | X11: =IF(U11="self",1,0) -> 0 | Y11: =O11-N11+1 -> 365 | Z11: =$Z$1 -> 46081 | AA11: =IF(MIN((Z11-N11)+1,Y11)<0,0,MIN((Z11-N11)+1,Y11)) -> 181 | AB11: Maharashtra | AC11: =AE11+AF11+AG11+AH11 -> 8108.2166 | AD11: 1 | AE11: =INDEX(SA!$C$2:$G$11,MATCH(Details!S11,SA!$C$2:$C$11,0),MATCH(Details!V11,SA!$C$2:$G$2,0))*Y11/(F11-E11+1) -> 6871.37 | AF11: =IF(AB11="Karnataka",AE11*9%,0) -> 0 | AG11: =IF(AB11="Karnataka",AE11*9%,0) -> 0 | AH11: =IF(AF11+AG11>0,0,AE11*18%) -> 1236.8466 | AI11: =AE11*L11 -> 274.8548 | AJ11: =$AE11*M11 -> 1546.0583 | AK11: =(AE11)*AA11/Y11 -> 3407.4465 | AL11: =AK11*(1-L11-M11) -> 2504.4732 | AM11: =AE11-AI11-AL11-AJ11 -> 2545.9838 | AN11: =Z11-366 -> 45715 | AO11: =IF(AND(O11>Z11,N11>AN11),AE11,0) -> 6871.37
A12: Valid | B12: 202509 | C12: GMC023220100CALDERYS | D12: CALDERYS INDIA REFRACTORIES LIMITED | E12: 45901 | F12: 46265 | G12: Shakun Tripathi | H12: 41023 | I12: 19207 | J12: ACK.4A9F3020250078.3 | K12: =N12 -> 45901 | L12: =IF(K12>=DATE(2022,4,1),4%,5%) -> 0.04 | M12: 0.225 | N12: 45901 | O12: 46265 | R12: 73 | S12: =VLOOKUP(R12,SA!$B$3:$C$11,2,1) -> 71-75 | T12: Female | U12: Mother | V12: 400000 | W12: =IF(U12="self",V12,0) -> 0 | X12: =IF(U12="self",1,0) -> 0 | Y12: =O12-N12+1 -> 365 | Z12: =$Z$1 -> 46081 | AA12: =IF(MIN((Z12-N12)+1,Y12)<0,0,MIN((Z12-N12)+1,Y12)) -> 181 | AB12: Maharashtra | AC12: =AE12+AF12+AG12+AH12 -> 21578.035 | AD12: 1 | AE12: =INDEX(SA!$C$2:$G$11,MATCH(Details!S12,SA!$C$2:$C$11,0),MATCH(Details!V12,SA!$C$2:$G$2,0))*Y12/(F12-E12+1) -> 18286.47 | AF12: =IF(AB12="Karnataka",AE12*9%,0) -> 0 | AG12: =IF(AB12="Karnataka",AE12*9%,0) -> 0 | AH12: =IF(AF12+AG12>0,0,AE12*18%) -> 3291.5646 | AI12: =AE12*L12 -> 731.4588 | AJ12: =$AE12*M12 -> 4114.4558 | AK12: =(AE12)*AA12/Y12 -> 9068.0851 | AL12: =AK12*(1-L12-M12) -> 6665.0426 | AM12: =AE12-AI12-AL12-AJ12 -> 6775.5129 | AN12: =Z12-366 -> 45715 | AO12: =IF(AND(O12>Z12,N12>AN12),AE12,0) -> 18286.47
A13: Valid | B13: 202509 | C13: GMC023220100CALDERYS | D13: CALDERYS INDIA REFRACTORIES LIMITED | E13: 45901 | F13: 46265 | G13: Kedar Prasad | H13: 41023 | I13: 27207 | J13: ACK.4A9F3020250078.4 | K13: =N13 -> 45901 | L13: =IF(K13>=DATE(2022,4,1),4%,5%) -> 0.04 | M13: 0.225 | N13: 45901 | O13: 46265 | R13: 51 | S13: =VLOOKUP(R13,SA!$B$3:$C$11,2,1) -> 46-55 | T13: Male | U13: Self | V13: 400000 | W13: =IF(U13="self",V13,0) -> 400000 | X13: =IF(U13="self",1,0) -> 1 | Y13: =O13-N13+1 -> 365 | Z13: =$Z$1 -> 46081 | AA13: =IF(MIN((Z13-N13)+1,Y13)<0,0,MIN((Z13-N13)+1,Y13)) -> 181 | AB13: Maharashtra | AC13: =AE13+AF13+AG13+AH13 -> 8108.2166 | AD13: 1 | AE13: =INDEX(SA!$C$2:$G$11,MATCH(Details!S13,SA!$C$2:$C$11,0),MATCH(Details!V13,SA!$C$2:$G$2,0))*Y13/(F13-E13+1) -> 6871.37 | AF13: =IF(AB13="Karnataka",AE13*9%,0) -> 0 | AG13: =IF(AB13="Karnataka",AE13*9%,0) -> 0 | AH13: =IF(AF13+AG13>0,0,AE13*18%) -> 1236.8466 | AI13: =AE13*L13 -> 274.8548 | AJ13: =$AE13*M13 -> 1546.0583 | AK13: =(AE13)*AA13/Y13 -> 3407.4465 | AL13: =AK13*(1-L13-M13) -> 2504.4732 | AM13: =AE13-AI13-AL13-AJ13 -> 2545.9838 | AN13: =Z13-366 -> 45715 | AO13: =IF(AND(O13>Z13,N13>AN13),AE13,0) -> 6871.37
A14: Valid | B14: 202509 | C14: GMC023220100CALDERYS | D14: CALDERYS INDIA REFRACTORIES LIMITED | E14: 45901 | F14: 46265 | G14: Prabhakar Singh | H14: 41024 | I14: 32319 | J14: ACK.4A9F3020250659.1 | K14: =N14 -> 45901 | L14: =IF(K14>=DATE(2022,4,1),4%,5%) -> 0.04 | M14: 0.225 | N14: 45901 | O14: 46265 | R14: 37 | S14: =VLOOKUP(R14,SA!$B$3:$C$11,2,1) -> 36-45 | T14: Male | U14: Son | V14: 300000 | W14: =IF(U14="self",V14,0) -> 0 | X14: =IF(U14="self",1,0) -> 0 | Y14: =O14-N14+1 -> 365 | Z14: =$Z$1 -> 46081 | AA14: =IF(MIN((Z14-N14)+1,Y14)<0,0,MIN((Z14-N14)+1,Y14)) -> 181 | AB14: Maharashtra | AC14: =AE14+AF14+AG14+AH14 -> 5119.5716 | AD14: 1 | AE14: =INDEX(SA!$C$2:$G$11,MATCH(Details!S14,SA!$C$2:$C$11,0),MATCH(Details!V14,SA!$C$2:$G$2,0))*Y14/(F14-E14+1) -> 4338.62 | AF14: =IF(AB14="Karnataka",AE14*9%,0) -> 0 | AG14: =IF(AB14="Karnataka",AE14*9%,0) -> 0 | AH14: =IF(AF14+AG14>0,0,AE14*18%) -> 780.9516 | AI14: =AE14*L14 -> 173.5448 | AJ14: =$AE14*M14 -> 976.1895 | AK14: =(AE14)*AA14/Y14 -> 2151.4801 | AL14: =AK14*(1-L14-M14) -> 1581.3378 | AM14: =AE14-AI14-AL14-AJ14 -> 1607.5479 | AN14: =Z14-366 -> 45715 | AO14: =IF(AND(O14>Z14,N14>AN14),AE14,0) -> 4338.62
... A2876: Valid | B2876: 202509 | C2876: GMC023220100CALDERYS | D2876: CALDERYS INDIA REFRACTORIES LIMITED | E2876: 45901 | F2876: 46265 | G2876: Devraj Parauha | H2876: 45017 | I2876: 35664 | J2876: ACK.4A9F3020250698.2 | K2876: =N2876 -> 45901 | L2876: =IF(K2876>=DATE(2022,4,1),4%,5%) -> 0.04 | M2876: 0.225 | N2876: 45901 | O2876: 46265 | R2876: 28 | S2876: =VLOOKUP(R2876,SA!$B$3:$C$11,2,1) -> 26-35 | T2876: Male | U2876: Self | V2876: 300000 | W2876: =IF(U2876="self",V2876,0) -> 300000 | X2876: =IF(U2876="self",1,0) -> 1 | Y2876: =O2876-N2876+1 -> 365 | Z2876: =$Z$1 -> 46081 | AA2876: =IF(MIN((Z2876-N2876)+1,Y2876)<0,0,MIN((Z2876-N2876)+1,Y2876)) -> 181 | AB2876: Maharashtra | AC2876: =AE2876+AF2876+AG2876+AH2876 -> 4124.4658 | AD2876: 1 | AE2876: =INDEX(SA!$C$2:$G$11,MATCH(Details!S2876,SA!$C$2:$C$11,0),MATCH(Details!V2876,SA!$C$2:$G$2,0))*Y2876/(F2876-E2876+1) -> 3495.31 | AF2876: =IF(AB2876="Karnataka",AE2876*9%,0) -> 0 | AG2876: =IF(AB2876="Karnataka",AE2876*9%,0) -> 0 | AH2876: =IF(AF2876+AG2876>0,0,AE2876*18%) -> 629.1558 | AI2876: =AE2876*L2876 -> 139.8124 | AJ2876: =$AE2876*M2876 -> 786.44475 | AK2876: =(AE2876)*AA2876/Y2876 -> 1733.2907 | AL2876: =AK2876*(1-L2876-M2876) -> 1273.9687 | AM2876: =AE2876-AI2876-AL2876-AJ2876 -> 1295.0842 | AN2876: =Z2876-366 -> 45715 | AO2876: =IF(AND(O2876>Z2876,N2876>AN2876),AE2876,0) -> 3495.31
A2877: Valid | B2877: 202509 | C2877: GMC023220100CALDERYS | D2877: CALDERYS INDIA REFRACTORIES LIMITED | E2877: 45901 | F2877: 46265 | G2877: Kiran Bai | H2877: 44921 | I2877: 27395 | J2877: ACK.4A9F3020250679.1 | K2877: =N2877 -> 45901 | L2877: =IF(K2877>=DATE(2022,4,1),4%,5%) -> 0.04 | M2877: 0.225 | N2877: 45901 | O2877: 46265 | R2877: 50 | S2877: =VLOOKUP(R2877,SA!$B$3:$C$11,2,1) -> 46-55 | T2877: Female | U2877: Mother | V2877: 300000 | W2877: =IF(U2877="self",V2877,0) -> 0 | X2877: =IF(U2877="self",1,0) -> 0 | Y2877: =O2877-N2877+1 -> 365 | Z2877: =$Z$1 -> 46081 | AA2877: =IF(MIN((Z2877-N2877)+1,Y2877)<0,0,MIN((Z2877-N2877)+1,Y2877)) -> 181 | AB2877: Maharashtra | AC2877: =AE2877+AF2877+AG2877+AH2877 -> 7373.466 | AD2877: 1 | AE2877: =INDEX(SA!$C$2:$G$11,MATCH(Details!S2877,SA!$C$2:$C$11,0),MATCH(Details!V2877,SA!$C$2:$G$2,0))*Y2877/(F2877-E2877+1) -> 6248.7 | AF2877: =IF(AB2877="Karnataka",AE2877*9%,0) -> 0 | AG2877: =IF(AB2877="Karnataka",AE2877*9%,0) -> 0 | AH2877: =IF(AF2877+AG2877>0,0,AE2877*18%) -> 1124.766 | AI2877: =AE2877*L2877 -> 249.948 | AJ2877: =$AE2877*M2877 -> 1405.9575 | AK2877: =(AE2877)*AA2877/Y2877 -> 3098.6704 | AL2877: =AK2877*(1-L2877-M2877) -> 2277.5228 | AM2877: =AE2877-AI2877-AL2877-AJ2877 -> 2315.2717 | AN2877: =Z2877-366 -> 45715 | AO2877: =IF(AND(O2877>Z2877,N2877>AN2877),AE2877,0) -> 6248.7
A2878: Valid | B2878: 202509 | C2878: GMC023220100CALDERYS | D2878: CALDERYS INDIA REFRACTORIES LIMITED | E2878: 45901 | F2878: 46265 | G2878: Ritu Dubey | H2878: 44921 | I2878: 34905 | J2878: ACK.4A9F3020250679.2 | K2878: =N2878 -> 45901 | L2878: =IF(K2878>=DATE(2022,4,1),4%,5%) -> 0.04 | M2878: 0.225 | N2878: 45901 | O2878: 46265 | R2878: 30 | S2878: =VLOOKUP(R2878,SA!$B$3:$C$11,2,1) -> 26-35 | T2878: Female | U2878: Spouse | V2878: 300000 | W2878: =IF(U2878="self",V2878,0) -> 0 | X2878: =IF(U2878="self",1,0) -> 0 | Y2878: =O2878-N2878+1 -> 365 | Z2878: =$Z$1 -> 46081 | AA2878: =IF(MIN((Z2878-N2878)+1,Y2878)<0,0,MIN((Z2878-N2878)+1,Y2878)) -> 181 | AB2878: Maharashtra | AC2878: =AE2878+AF2878+AG2878+AH2878 -> 4124.4658 | AD2878: 1 | AE2878: =INDEX(SA!$C$2:$G$11,MATCH(Details!S2878,SA!$C$2:$C$11,0),MATCH(Details!V2878,SA!$C$2:$G$2,0))*Y2878/(F2878-E2878+1) -> 3495.31 | AF2878: =IF(AB2878="Karnataka",AE2878*9%,0) -> 0 | AG2878: =IF(AB2878="Karnataka",AE2878*9%,0) -> 0 | AH2878: =IF(AF2878+AG2878>0,0,AE2878*18%) -> 629.1558 | AI2878: =AE2878*L2878 -> 139.8124 | AJ2878: =$AE2878*M2878 -> 786.44475 | AK2878: =(AE2878)*AA2878/Y2878 -> 1733.2907 | AL2878: =AK2878*(1-L2878-M2878) -> 1273.9687 | AM2878: =AE2878-AI2878-AL2878-AJ2878 -> 1295.0842 | AN2878: =Z2878-366 -> 45715 | AO2878: =IF(AND(O2878>Z2878,N2878>AN2878),AE2878,0) -> 3495.31
A2879: Valid | B2879: 202509 | C2879: GMC023220100CALDERYS | D2879: CALDERYS INDIA REFRACTORIES LIMITED | E2879: 45901 | F2879: 46265 | G2879: Raksha Dubey | H2879: 44921 | I2879: 45523 | J2879: ACK.4A9F3020250679.3 | K2879: =N2879 -> 45901 | L2879: =IF(K2879>=DATE(2022,4,1),4%,5%) -> 0.04 | M2879: 0.225 | N2879: 45901 | O2879: 46265 | R2879: 1 | S2879: =VLOOKUP(R2879,SA!$B$3:$C$11,2,1) -> 0-25 | T2879: Female | U2879: Daughter | V2879: 300000 | W2879: =IF(U2879="self",V2879,0) -> 0 | X2879: =IF(U2879="self",1,0) -> 0 | Y2879: =O2879-N2879+1 -> 365 | Z2879: =$Z$1 -> 46081 | AA2879: =IF(MIN((Z2879-N2879)+1,Y2879)<0,0,MIN((Z2879-N2879)+1,Y2879)) -> 181 | AB2879: Maharashtra | AC2879: =AE2879+AF2879+AG2879+AH2879 -> 3690.3792 | AD2879: 1 | AE2879: =INDEX(SA!$C$2:$G$11,MATCH(Details!S2879,SA!$C$2:$C$11,0),MATCH(Details!V2879,SA!$C$2:$G$2,0))*Y2879/(F2879-E2879+1) -> 3127.44 | AF2879: =IF(AB2879="Karnataka",AE2879*9%,0) -> 0 | AG2879: =IF(AB2879="Karnataka",AE2879*9%,0) -> 0 | AH2879: =IF(AF2879+AG2879>0,0,AE2879*18%) -> 562.9392 | AI2879: =AE2879*L2879 -> 125.0976 | AJ2879: =$AE2879*M2879 -> 703.674 | AK2879: =(AE2879)*AA2879/Y2879 -> 1550.8675 | AL2879: =AK2879*(1-L2879-M2879) -> 1139.8876 | AM2879: =AE2879-AI2879-AL2879-AJ2879 -> 1158.7808 | AN2879: =Z2879-366 -> 45715 | AO2879: =IF(AND(O2879>Z2879,N2879>AN2879),AE2879,0) -> 3127.44
A2880: Valid | B2880: 202509 | C2880: GMC023220100CALDERYS | D2880: CALDERYS INDIA REFRACTORIES LIMITED | E2880: 45901 | F2880: 46265 | G2880: Rajendra Prasad | H2880: 44921 | I2880: 22384 | J2880: ACK.4A9F3020250679.4 | K2880: =N2880 -> 45901 | L2880: =IF(K2880>=DATE(2022,4,1),4%,5%) -> 0.04 | M2880: 0.225 | N2880: 45901 | O2880: 46265 | R2880: 64 | S2880: =VLOOKUP(R2880,SA!$B$3:$C$11,2,1) -> 56-65 | T2880: Male | U2880: Father | V2880: 300000 | W2880: =IF(U2880="self",V2880,0) -> 0 | X2880: =IF(U2880="self",1,0) -> 0 | Y2880: =O2880-N2880+1 -> 365 | Z2880: =$Z$1 -> 46081 | AA2880: =IF(MIN((Z2880-N2880)+1,Y2880)<0,0,MIN((Z2880-N2880)+1,Y2880)) -> 181 | AB2880: Maharashtra | AC2880: =AE2880+AF2880+AG2880+AH2880 -> 10831.751 | AD2880: 1 | AE2880: =INDEX(SA!$C$2:$G$11,MATCH(Details!S2880,SA!$C$2:$C$11,0),MATCH(Details!V2880,SA!$C$2:$G$2,0))*Y2880/(F2880-E2880+1) -> 9179.45 | AF2880: =IF(AB2880="Karnataka",AE2880*9%,0) -> 0 | AG2880: =IF(AB2880="Karnataka",AE2880*9%,0) -> 0 | AH2880: =IF(AF2880+AG2880>0,0,AE2880*18%) -> 1652.301 | AI2880: =AE2880*L2880 -> 367.178 | AJ2880: =$AE2880*M2880 -> 2065.3763 | AK2880: =(AE2880)*AA2880/Y2880 -> 4552.0012 | AL2880: =AK2880*(1-L2880-M2880) -> 3345.7209 | AM2880: =AE2880-AI2880-AL2880-AJ2880 -> 3401.1748 | AN2880: =Z2880-366 -> 45715 | AO2880: =IF(AND(O2880>Z2880,N2880>AN2880),AE2880,0) -> 9179.45
A2881: Valid | B2881: 202509 | C2881: GMC023220100CALDERYS | D2881: CALDERYS INDIA REFRACTORIES LIMITED | E2881: 45901 | F2881: 46265 | G2881: Sateesh Kumar | H2881: 44921 | I2881: 32838 | J2881: ACK.4A9F3020250679.5 | K2881: =N2881 -> 45901 | L2881: =IF(K2881>=DATE(2022,4,1),4%,5%) -> 0.04 | M2881: 0.225 | N2881: 45901 | O2881: 46265 | R2881: 35 | S2881: =VLOOKUP(R2881,SA!$B$3:$C$11,2,1) -> 26-35 | T2881: Male | U2881: Self | V2881: 300000 | W2881: =IF(U2881="self",V2881,0) -> 300000 | X2881: =IF(U2881="self",1,0) -> 1 | Y2881: =O2881-N2881+1 -> 365 | Z2881: =$Z$1 -> 46081 | AA2881: =IF(MIN((Z2881-N2881)+1,Y2881)<0,0,MIN((Z2881-N2881)+1,Y2881)) -> 181 | AB2881: Maharashtra | AC2881: =AE2881+AF2881+AG2881+AH2881 -> 4124.4658 | AD2881: 1 | AE2881: =INDEX(SA!$C$2:$G$11,MATCH(Details!S2881,SA!$C$2:$C$11,0),MATCH(Details!V2881,SA!$C$2:$G$2,0))*Y2881/(F2881-E2881+1) -> 3495.31 | AF2881: =IF(AB2881="Karnataka",AE2881*9%,0) -> 0 | AG2881: =IF(AB2881="Karnataka",AE2881*9%,0) -> 0 | AH2881: =IF(AF2881+AG2881>0,0,AE2881*18%) -> 629.1558 | AI2881: =AE2881*L2881 -> 139.8124 | AJ2881: =$AE2881*M2881 -> 786.44475 | AK2881: =(AE2881)*AA2881/Y2881 -> 1733.2907 | AL2881: =AK2881*(1-L2881-M2881) -> 1273.9687 | AM2881: =AE2881-AI2881-AL2881-AJ2881 -> 1295.0842 | AN2881: =Z2881-366 -> 45715 | AO2881: =IF(AND(O2881>Z2881,N2881>AN2881),AE2881,0) -> 3495.31
A2882: Valid | B2882: 202509 | C2882: GMC023220100CALDERYS | D2882: CALDERYS INDIA REFRACTORIES LIMITED | E2882: 45901 | F2882: 46265 | G2882: Kundan Devi | H2882: 45011 | I2882: 31778 | J2882: ACK.4A9F3020250695.1 | K2882: =N2882 -> 45901 | L2882: =IF(K2882>=DATE(2022,4,1),4%,5%) -> 0.04 | M2882: 0.225 | N2882: 45901 | O2882: 46265 | R2882: 38 | S2882: =VLOOKUP(R2882,SA!$B$3:$C$11,2,1) -> 36-45 | T2882: Female | U2882: Mother | V2882: 400000 | W2882: =IF(U2882="self",V2882,0) -> 0 | X2882: =IF(U2882="self",1,0) -> 0 | Y2882: =O2882-N2882+1 -> 365 | Z2882: =$Z$1 -> 46081 | AA2882: =IF(MIN((Z2882-N2882)+1,Y2882)<0,0,MIN((Z2882-N2882)+1,Y2882)) -> 181 | AB2882: Maharashtra | AC2882: =AE2882+AF2882+AG2882+AH2882 -> 5496.5226 | AD2882: 1 | AE2882: =INDEX(SA!$C$2:$G$11,MATCH(Details!S2882,SA!$C$2:$C$11,0),MATCH(Details!V2882,SA!$C$2:$G$2,0))*Y2882/(F2882-E2882+1) -> 4658.07 | AF2882: =IF(AB2882="Karnataka",AE2882*9%,0) -> 0 | AG2882: =IF(AB2882="Karnataka",AE2882*9%,0) -> 0 | AH2882: =IF(AF2882+AG2882>0,0,AE2882*18%) -> 838.4526 | AI2882: =AE2882*L2882 -> 186.3228 | AJ2882: =$AE2882*M2882 -> 1048.0657 | AK2882: =(AE2882)*AA2882/Y2882 -> 2309.8922 | AL2882: =AK2882*(1-L2882-M2882) -> 1697.7708 | AM2882: =AE2882-AI2882-AL2882-AJ2882 -> 1725.9106 | AN2882: =Z2882-366 -> 45715 | AO2882: =IF(AND(O2882>Z2882,N2882>AN2882),AE2882,0) -> 4658.07
A2883: Valid | B2883: 202509 | C2883: GMC023220100CALDERYS | D2883: CALDERYS INDIA REFRACTORIES LIMITED | E2883: 45901 | F2883: 46265 | G2883: Priti Priya | H2883: 45011 | I2883: 37363 | J2883: ACK.4A9F3020250695.2 | K2883: =N2883 -> 45901 | L2883: =IF(K2883>=DATE(2022,4,1),4%,5%) -> 0.04 | M2883: 0.225 | N2883: 45901 | O2883: 46265 | R2883: 23 | S2883: =VLOOKUP(R2883,SA!$B$3:$C$11,2,1) -> 0-25 | T2883: Female | U2883: Self | V2883: 400000 | W2883: =IF(U2883="self",V2883,0) -> 400000 | X2883: =IF(U2883="self",1,0) -> 1 | Y2883: =O2883-N2883+1 -> 365 | Z2883: =$Z$1 -> 46081 | AA2883: =IF(MIN((Z2883-N2883)+1,Y2883)<0,0,MIN((Z2883-N2883)+1,Y2883)) -> 181 | AB2883: Maharashtra | AC2883: =AE2883+AF2883+AG2883+AH2883 -> 4043.8364 | AD2883: 1 | AE2883: =INDEX(SA!$C$2:$G$11,MATCH(Details!S2883,SA!$C$2:$C$11,0),MATCH(Details!V2883,SA!$C$2:$G$2,0))*Y2883/(F2883-E2883+1) -> 3426.98 | AF2883: =IF(AB2883="Karnataka",AE2883*9%,0) -> 0 | AG2883: =IF(AB2883="Karnataka",AE2883*9%,0) -> 0 | AH2883: =IF(AF2883+AG2883>0,0,AE2883*18%) -> 616.8564 | AI2883: =AE2883*L2883 -> 137.0792 | AJ2883: =$AE2883*M2883 -> 771.0705 | AK2883: =(AE2883)*AA2883/Y2883 -> 1699.4065 | AL2883: =AK2883*(1-L2883-M2883) -> 1249.0638 | AM2883: =AE2883-AI2883-AL2883-AJ2883 -> 1269.7665 | AN2883: =Z2883-366 -> 45715 | AO2883: =IF(AND(O2883>Z2883,N2883>AN2883),AE2883,0) -> 3426.98
A2884: Valid | B2884: 202509 | C2884: GMC023220100CALDERYS | D2884: CALDERYS INDIA REFRACTORIES LIMITED | E2884: 45901 | F2884: 46265 | G2884: Arun Ray | H2884: 45011 | I2884: 31079 | J2884: ACK.4A9F3020250695.3 | K2884: =N2884 -> 45901 | L2884: =IF(K2884>=DATE(2022,4,1),4%,5%) -> 0.04 | M2884: 0.225 | N2884: 45901 | O2884: 46265 | R2884: 40 | S2884: =VLOOKUP(R2884,SA!$B$3:$C$11,2,1) -> 36-45 | T2884: Male | U2884: Father | V2884: 400000 | W2884: =IF(U2884="self",V2884,0) -> 0 | X2884: =IF(U2884="self",1,0) -> 0 | Y2884: =O2884-N2884+1 -> 365 | Z2884: =$Z$1 -> 46081 | AA2884: =IF(MIN((Z2884-N2884)+1,Y2884)<0,0,MIN((Z2884-N2884)+1,Y2884)) -> 181 | AB2884: Maharashtra | AC2884: =AE2884+AF2884+AG2884+AH2884 -> 5496.5226 | AD2884: 1 | AE2884: =INDEX(SA!$C$2:$G$11,MATCH(Details!S2884,SA!$C$2:$C$11,0),MATCH(Details!V2884,SA!$C$2:$G$2,0))*Y2884/(F2884-E2884+1) -> 4658.07 | AF2884: =IF(AB2884="Karnataka",AE2884*9%,0) -> 0 | AG2884: =IF(AB2884="Karnataka",AE2884*9%,0) -> 0 | AH2884: =IF(AF2884+AG2884>0,0,AE2884*18%) -> 838.4526 | AI2884: =AE2884*L2884 -> 186.3228 | AJ2884: =$AE2884*M2884 -> 1048.0657 | AK2884: =(AE2884)*AA2884/Y2884 -> 2309.8922 | AL2884: =AK2884*(1-L2884-M2884) -> 1697.7708 | AM2884: =AE2884-AI2884-AL2884-AJ2884 -> 1725.9106 | AN2884: =Z2884-366 -> 45715 | AO2884: =IF(AND(O2884>Z2884,N2884>AN2884),AE2884,0) -> 4658.07
A2885: Valid | B2885: 202509 | C2885: GMC023220100CALDERYS | D2885: CALDERYS INDIA REFRACTORIES LIMITED | E2885: 45901 | F2885: 46265 | G2885: Ranjan Niranjan Amte | H2885: 45020 | I2885: 18785 | J2885: ACK.4A9F3020250703.1 | K2885: =N2885 -> 45901 | L2885: =IF(K2885>=DATE(2022,4,1),4%,5%) -> 0.04 | M2885: 0.225 | N2885: 45901 | O2885: 46265 | R2885: 74 | S2885: =VLOOKUP(R2885,SA!$B$3:$C$11,2,1) -> 71-75 | T2885: Female | U2885: Mother | V2885: 500000 | W2885: =IF(U2885="self",V2885,0) -> 0 | X2885: =IF(U2885="self",1,0) -> 0 | Y2885: =O2885-N2885+1 -> 365 | Z2885: =$Z$1 -> 46081 | AA2885: =IF(MIN((Z2885-N2885)+1,Y2885)<0,0,MIN((Z2885-N2885)+1,Y2885)) -> 181 | AB2885: Maharashtra | AC2885: =AE2885+AF2885+AG2885+AH2885 -> 23735.924 | AD2885: 1 | AE2885: =INDEX(SA!$C$2:$G$11,MATCH(Details!S2885,SA!$C$2:$C$11,0),MATCH(Details!V2885,SA!$C$2:$G$2,0))*Y2885/(F2885-E2885+1) -> 20115.19 | AF2885: =IF(AB2885="Karnataka",AE2885*9%,0) -> 0 | AG2885: =IF(AB2885="Karnataka",AE2885*9%,0) -> 0 | AH2885: =IF(AF2885+AG2885>0,0,AE2885*18%) -> 3620.7342 | AI2885: =AE2885*L2885 -> 804.6076 | AJ2885: =$AE2885*M2885 -> 4525.9177 | AK2885: =(AE2885)*AA2885/Y2885 -> 9974.9298 | AL2885: =AK2885*(1-L2885-M2885) -> 7331.5734 | AM2885: =AE2885-AI2885-AL2885-AJ2885 -> 7453.0912 | AN2885: =Z2885-366 -> 45715 | AO2885: =IF(AND(O2885>Z2885,N2885>AN2885),AE2885,0) -> 20115.19
A2886: Valid | B2886: 202509 | C2886: GMC023220100CALDERYS | D2886: CALDERYS INDIA REFRACTORIES LIMITED | E2886: 45901 | F2886: 46265 | G2886: Aparna Amte | H2886: 45020 | I2886: 30936 | J2886: ACK.4A9F3020250703.2 | K2886: =N2886 -> 45901 | L2886: =IF(K2886>=DATE(2022,4,1),4%,5%) -> 0.04 | M2886: 0.225 | N2886: 45901 | O2886: 46265 | R2886: 40 | S2886: =VLOOKUP(R2886,SA!$B$3:$C$11,2,1) -> 36-45 | T2886: Female | U2886: Self | V2886: 500000 | W2886: =IF(U2886="self",V2886,0) -> 500000 | X2886: =IF(U2886="self",1,0) -> 1 | Y2886: =O2886-N2886+1 -> 365 | Z2886: =$Z$1 -> 46081 | AA2886: =IF(MIN((Z2886-N2886)+1,Y2886)<0,0,MIN((Z2886-N2886)+1,Y2886)) -> 181 | AB2886: Maharashtra | AC2886: =AE2886+AF2886+AG2886+AH2886 -> 6046.1902 | AD2886: 1 | AE2886: =INDEX(SA!$C$2:$G$11,MATCH(Details!S2886,SA!$C$2:$C$11,0),MATCH(Details!V2886,SA!$C$2:$G$2,0))*Y2886/(F2886-E2886+1) -> 5123.89 | AF2886: =IF(AB2886="Karnataka",AE2886*9%,0) -> 0 | AG2886: =IF(AB2886="Karnataka",AE2886*9%,0) -> 0 | AH2886: =IF(AF2886+AG2886>0,0,AE2886*18%) -> 922.3002 | AI2886: =AE2886*L2886 -> 204.9556 | AJ2886: =$AE2886*M2886 -> 1152.8753 | AK2886: =(AE2886)*AA2886/Y2886 -> 2540.8879 | AL2886: =AK2886*(1-L2886-M2886) -> 1867.5526 | AM2886: =AE2886-AI2886-AL2886-AJ2886 -> 1898.5065 | AN2886: =Z2886-366 -> 45715 | AO2886: =IF(AND(O2886>Z2886,N2886>AN2886),AE2886,0) -> 5123.89
A2887: Valid | B2887: 202509 | C2887: GMC023220100CALDERYS | D2887: CALDERYS INDIA REFRACTORIES LIMITED | E2887: 45901 | F2887: 46265 | G2887: Niranjan Narayan Amte | H2887: 45020 | I2887: 18471 | J2887: ACK.4A9F3020250703.3 | K2887: =N2887 -> 45901 | L2887: =IF(K2887>=DATE(2022,4,1),4%,5%) -> 0.04 | M2887: 0.225 | N2887: 45901 | O2887: 46265 | R2887: 75 | S2887: =VLOOKUP(R2887,SA!$B$3:$C$11,2,1) -> 71-75 | T2887: Male | U2887: Father | V2887: 500000 | W2887: =IF(U2887="self",V2887,0) -> 0 | X2887: =IF(U2887="self",1,0) -> 0 | Y2887: =O2887-N2887+1 -> 365 | Z2887: =$Z$1 -> 46081 | AA2887: =IF(MIN((Z2887-N2887)+1,Y2887)<0,0,MIN((Z2887-N2887)+1,Y2887)) -> 181 | AB2887: Maharashtra | AC2887: =AE2887+AF2887+AG2887+AH2887 -> 23735.924 | AD2887: 1 | AE2887: =INDEX(SA!$C$2:$G$11,MATCH(Details!S2887,SA!$C$2:$C$11,0),MATCH(Details!V2887,SA!$C$2:$G$2,0))*Y2887/(F2887-E2887+1) -> 20115.19 | AF2887: =IF(AB2887="Karnataka",AE2887*9%,0) -> 0 | AG2887: =IF(AB2887="Karnataka",AE2887*9%,0) -> 0 | AH2887: =IF(AF2887+AG2887>0,0,AE2887*18%) -> 3620.7342 | AI2887: =AE2887*L2887 -> 804.6076 | AJ2887: =$AE2887*M2887 -> 4525.9177 | AK2887: =(AE2887)*AA2887/Y2887 -> 9974.9298 | AL2887: =AK2887*(1-L2887-M2887) -> 7331.5734 | AM2887: =AE2887-AI2887-AL2887-AJ2887 -> 7453.0912 | AN2887: =Z2887-366 -> 45715 | AO2887: =IF(AND(O2887>Z2887,N2887>AN2887),AE2887,0) -> 20115.19
A2888: Valid | B2888: 202509 | C2888: GMC023220100CALDERYS | D2888: CALDERYS INDIA REFRACTORIES LIMITED | E2888: 45901 | F2888: 46265 | G2888: Gaurav Bhatnagar | H2888: 45020 | I2888: 29321 | J2888: ACK.4A9F3020250703.4 | K2888: =N2888 -> 45901 | L2888: =IF(K2888>=DATE(2022,4,1),4%,5%) -> 0.04 | M2888: 0.225 | N2888: 45901 | O2888: 46265 | R2888: 45 | S2888: =VLOOKUP(R2888,SA!$B$3:$C$11,2,1) -> 36-45 | T2888: Male | U2888: Spouse | V2888: 500000 | W2888: =IF(U2888="self",V2888,0) -> 0 | X2888: =IF(U2888="self",1,0) -> 0 | Y2888: =O2888-N2888+1 -> 365 | Z2888: =$Z$1 -> 46081 | AA2888: =IF(MIN((Z2888-N2888)+1,Y2888)<0,0,MIN((Z2888-N2888)+1,Y2888)) -> 181 | AB2888: Maharashtra | AC2888: =AE2888+AF2888+AG2888+AH2888 -> 6046.1902 | AD2888: 1 | AE2888: =INDEX(SA!$C$2:$G$11,MATCH(Details!S2888,SA!$C$2:$C$11,0),MATCH(Details!V2888,SA!$C$2:$G$2,0))*Y2888/(F2888-E2888+1) -> 5123.89 | AF2888: =IF(AB2888="Karnataka",AE2888*9%,0) -> 0 | AG2888: =IF(AB2888="Karnataka",AE2888*9%,0) -> 0 | AH2888: =IF(AF2888+AG2888>0,0,AE2888*18%) -> 922.3002 | AI2888: =AE2888*L2888 -> 204.9556 | AJ2888: =$AE2888*M2888 -> 1152.8753 | AK2888: =(AE2888)*AA2888/Y2888 -> 2540.8879 | AL2888: =AK2888*(1-L2888-M2888) -> 1867.5526 | AM2888: =AE2888-AI2888-AL2888-AJ2888 -> 1898.5065 | AN2888: =Z2888-366 -> 45715 | AO2888: =IF(AND(O2888>Z2888,N2888>AN2888),AE2888,0) -> 5123.89
A2889: Valid | B2889: 202509 | C2889: GMC023220100CALDERYS | D2889: CALDERYS INDIA REFRACTORIES LIMITED | E2889: 45901 | F2889: 46265 | G2889: Gandhari Mahato | H2889: 45012 | I2889: 32136 | J2889: ACK.4A9F3020250697.1 | K2889: =N2889 -> 45901 | L2889: =IF(K2889>=DATE(2022,4,1),4%,5%) -> 0.04 | M2889: 0.225 | N2889: 45901 | O2889: 46265 | R2889: 37 | S2889: =VLOOKUP(R2889,SA!$B$3:$C$11,2,1) -> 36-45 | T2889: Female | U2889: Mother | V2889: 400000 | W2889: =IF(U2889="self",V2889,0) -> 0 | X2889: =IF(U2889="self",1,0) -> 0 | Y2889: =O2889-N2889+1 -> 365 | Z2889: =$Z$1 -> 46081 | AA2889: =IF(MIN((Z2889-N2889)+1,Y2889)<0,0,MIN((Z2889-N2889)+1,Y2889)) -> 181 | AB2889: Maharashtra | AC2889: =AE2889+AF2889+AG2889+AH2889 -> 5496.5226 | AD2889: 1 | AE2889: =INDEX(SA!$C$2:$G$11,MATCH(Details!S2889,SA!$C$2:$C$11,0),MATCH(Details!V2889,SA!$C$2:$G$2,0))*Y2889/(F2889-E2889+1) -> 4658.07 | AF2889: =IF(AB2889="Karnataka",AE2889*9%,0) -> 0 | AG2889: =IF(AB2889="Karnataka",AE2889*9%,0) -> 0 | AH2889: =IF(AF2889+AG2889>0,0,AE2889*18%) -> 838.4526 | AI2889: =AE2889*L2889 -> 186.3228 | AJ2889: =$AE2889*M2889 -> 1048.0657 | AK2889: =(AE2889)*AA2889/Y2889 -> 2309.8922 | AL2889: =AK2889*(1-L2889-M2889) -> 1697.7708 | AM2889: =AE2889-AI2889-AL2889-AJ2889 -> 1725.9106 | AN2889: =Z2889-366 -> 45715 | AO2889: =IF(AND(O2889>Z2889,N2889>AN2889),AE2889,0) -> 4658.07
A2890: Valid | B2890: 202509 | C2890: GMC023220100CALDERYS | D2890: CALDERYS INDIA REFRACTORIES LIMITED | E2890: 45901 | F2890: 46265 | G2890: Roshni Mahato | H2890: 45012 | I2890: 38576 | J2890: ACK.4A9F3020250697.2 | K2890: =N2890 -> 45901 | L2890: =IF(K2890>=DATE(2022,4,1),4%,5%) -> 0.04 | M2890: 0.225 | N2890: 45901 | O2890: 46265 | R2890: 20 | S2890: =VLOOKUP(R2890,SA!$B$3:$C$11,2,1) -> 0-25 | T2890: Female | U2890: Self | V2890: 400000 | W2890: =IF(U2890="self",V2890,0) -> 400000 | X2890: =IF(U2890="self",1,0) -> 1 | Y2890: =O2890-N2890+1 -> 365 | Z2890: =$Z$1 -> 46081 | AA2890: =IF(MIN((Z2890-N2890)+1,Y2890)<0,0,MIN((Z2890-N2890)+1,Y2890)) -> 181 | AB2890: Maharashtra | AC2890: =AE2890+AF2890+AG2890+AH2890 -> 4043.8364 | AD2890: 1 | AE2890: =INDEX(SA!$C$2:$G$11,MATCH(Details!S2890,SA!$C$2:$C$11,0),MATCH(Details!V2890,SA!$C$2:$G$2,0))*Y2890/(F2890-E2890+1) -> 3426.98 | AF2890: =IF(AB2890="Karnataka",AE2890*9%,0) -> 0 | AG2890: =IF(AB2890="Karnataka",AE2890*9%,0) -> 0 | AH2890: =IF(AF2890+AG2890>0,0,AE2890*18%) -> 616.8564 | AI2890: =AE2890*L2890 -> 137.0792 | AJ2890: =$AE2890*M2890 -> 771.0705 | AK2890: =(AE2890)*AA2890/Y2890 -> 1699.4065 | AL2890: =AK2890*(1-L2890-M2890) -> 1249.0638 | AM2890: =AE2890-AI2890-AL2890-AJ2890 -> 1269.7665 | AN2890: =Z2890-366 -> 45715 | AO2890: =IF(AND(O2890>Z2890,N2890>AN2890),AE2890,0) -> 3426.98
A2891: Valid | B2891: 202509 | C2891: GMC023220100CALDERYS | D2891: CALDERYS INDIA REFRACTORIES LIMITED | E2891: 45901 | F2891: 46265 | G2891: Subhas Mahato | H2891: 45012 | I2891: 30127 | J2891: ACK.4A9F3020250697.3 | K2891: =N2891 -> 45901 | L2891: =IF(K2891>=DATE(2022,4,1),4%,5%) -> 0.04 | M2891: 0.225 | N2891: 45901 | O2891: 46265 | R2891: 43 | S2891: =VLOOKUP(R2891,SA!$B$3:$C$11,2,1) -> 36-45 | T2891: Male | U2891: Father | V2891: 400000 | W2891: =IF(U2891="self",V2891,0) -> 0 | X2891: =IF(U2891="self",1,0) -> 0 | Y2891: =O2891-N2891+1 -> 365 | Z2891: =$Z$1 -> 46081 | AA2891: =IF(MIN((Z2891-N2891)+1,Y2891)<0,0,MIN((Z2891-N2891)+1,Y2891)) -> 181 | AB2891: Maharashtra | AC2891: =AE2891+AF2891+AG2891+AH2891 -> 5496.5226 | AD2891: 1 | AE2891: =INDEX(SA!$C$2:$G$11,MATCH(Details!S2891,SA!$C$2:$C$11,0),MATCH(Details!V2891,SA!$C$2:$G$2,0))*Y2891/(F2891-E2891+1) -> 4658.07 | AF2891: =IF(AB2891="Karnataka",AE2891*9%,0) -> 0 | AG2891: =IF(AB2891="Karnataka",AE2891*9%,0) -> 0 | AH2891: =IF(AF2891+AG2891>0,0,AE2891*18%) -> 838.4526 | AI2891: =AE2891*L2891 -> 186.3228 | AJ2891: =$AE2891*M2891 -> 1048.0657 | AK2891: =(AE2891)*AA2891/Y2891 -> 2309.8922 | AL2891: =AK2891*(1-L2891-M2891) -> 1697.7708 | AM2891: =AE2891-AI2891-AL2891-AJ2891 -> 1725.9106 | AN2891: =Z2891-366 -> 45715 | AO2891: =IF(AND(O2891>Z2891,N2891>AN2891),AE2891,0) -> 4658.07
A2892: Valid | B2892: 202509 | C2892: GMC023220100CALDERYS | D2892: CALDERYS INDIA REFRACTORIES LIMITED | E2892: 45901 | F2892: 46265 | G2892: Prabha Deshmukh | H2892: 45056 | I2892: 20580 | J2892: ACK.4A9F3020250708.1 | K2892: =N2892 -> 45901 | L2892: =IF(K2892>=DATE(2022,4,1),4%,5%) -> 0.04 | M2892: 0.225 | N2892: 45901 | O2892: 46265 | R2892: 69 | S2892: =VLOOKUP(R2892,SA!$B$3:$C$11,2,1) -> 66-70 | T2892: Female | U2892: Mother | V2892: 500000 | W2892: =IF(U2892="self",V2892,0) -> 0 | X2892: =IF(U2892="self",1,0) -> 0 | Y2892: =O2892-N2892+1 -> 365 | Z2892: =$Z$1 -> 46081 | AA2892: =IF(MIN((Z2892-N2892)+1,Y2892)<0,0,MIN((Z2892-N2892)+1,Y2892)) -> 181 | AB2892: Maharashtra | AC2892: =AE2892+AF2892+AG2892+AH2892 -> 18713.136 | AD2892: 1 | AE2892: =INDEX(SA!$C$2:$G$11,MATCH(Details!S2892,SA!$C$2:$C$11,0),MATCH(Details!V2892,SA!$C$2:$G$2,0))*Y2892/(F2892-E2892+1) -> 15858.59 | AF2892: =IF(AB2892="Karnataka",AE2892*9%,0) -> 0 | AG2892: =IF(AB2892="Karnataka",AE2892*9%,0) -> 0 | AH2892: =IF(AF2892+AG2892>0,0,AE2892*18%) -> 2854.5462 | AI2892: =AE2892*L2892 -> 634.3436 | AJ2892: =$AE2892*M2892 -> 3568.1827 | AK2892: =(AE2892)*AA2892/Y2892 -> 7864.1227 | AL2892: =AK2892*(1-L2892-M2892) -> 5780.1302 | AM2892: =AE2892-AI2892-AL2892-AJ2892 -> 5875.9335 | AN2892: =Z2892-366 -> 45715 | AO2892: =IF(AND(O2892>Z2892,N2892>AN2892),AE2892,0) -> 15858.59
A2893: Valid | B2893: 202509 | C2893: GMC023220100CALDERYS | D2893: CALDERYS INDIA REFRACTORIES LIMITED | E2893: 45901 | F2893: 46265 | G2893: Ashwini Deshmukh | H2893: 45056 | I2893: 32278 | J2893: ACK.4A9F3020250708.2 | K2893: =N2893 -> 45901 | L2893: =IF(K2893>=DATE(2022,4,1),4%,5%) -> 0.04 | M2893: 0.225 | N2893: 45901 | O2893: 46265 | R2893: 37 | S2893: =VLOOKUP(R2893,SA!$B$3:$C$11,2,1) -> 36-45 | T2893: Female | U2893: Spouse | V2893: 500000 | W2893: =IF(U2893="self",V2893,0) -> 0 | X2893: =IF(U2893="self",1,0) -> 0 | Y2893: =O2893-N2893+1 -> 365 | Z2893: =$Z$1 -> 46081 | AA2893: =IF(MIN((Z2893-N2893)+1,Y2893)<0,0,MIN((Z2893-N2893)+1,Y2893)) -> 181 | AB2893: Maharashtra | AC2893: =AE2893+AF2893+AG2893+AH2893 -> 6046.1902 | AD2893: 1 | AE2893: =INDEX(SA!$C$2:$G$11,MATCH(Details!S2893,SA!$C$2:$C$11,0),MATCH(Details!V2893,SA!$C$2:$G$2,0))*Y2893/(F2893-E2893+1) -> 5123.89 | AF2893: =IF(AB2893="Karnataka",AE2893*9%,0) -> 0 | AG2893: =IF(AB2893="Karnataka",AE2893*9%,0) -> 0 | AH2893: =IF(AF2893+AG2893>0,0,AE2893*18%) -> 922.3002 | AI2893: =AE2893*L2893 -> 204.9556 | AJ2893: =$AE2893*M2893 -> 1152.8753 | AK2893: =(AE2893)*AA2893/Y2893 -> 2540.8879 | AL2893: =AK2893*(1-L2893-M2893) -> 1867.5526 | AM2893: =AE2893-AI2893-AL2893-AJ2893 -> 1898.5065 | AN2893: =Z2893-366 -> 45715 | AO2893: =IF(AND(O2893>Z2893,N2893>AN2893),AE2893,0) -> 5123.89
... A2897: Valid | B2897: 202509 | C2897: GMC023220100CALDERYS | D2897: CALDERYS INDIA REFRACTORIES LIMITED | E2897: 45901 | F2897: 46265 | G2897: Rahul Deshmukh | H2897: 45056 | I2897: 30980 | J2897: ACK.4A9F3020250708.6 | K2897: =N2897 -> 45901 | L2897: =IF(K2897>=DATE(2022,4,1),4%,5%) -> 0.04 | M2897: 0.225 | N2897: 45901 | O2897: 46265 | R2897: 40 | S2897: =VLOOKUP(R2897,SA!$B$3:$C$11,2,1) -> 36-45 | T2897: Male | U2897: Self | V2897: 500000 | W2897: =IF(U2897="self",V2897,0) -> 500000 | X2897: =IF(U2897="self",1,0) -> 1 | Y2897: =O2897-N2897+1 -> 365 | Z2897: =$Z$1 -> 46081 | AA2897: =IF(MIN((Z2897-N2897)+1,Y2897)<0,0,MIN((Z2897-N2897)+1,Y2897)) -> 181 | AB2897: Maharashtra | AC2897: =AE2897+AF2897+AG2897+AH2897 -> 6046.1902 | AD2897: 1 | AE2897: =INDEX(SA!$C$2:$G$11,MATCH(Details!S2897,SA!$C$2:$C$11,0),MATCH(Details!V2897,SA!$C$2:$G$2,0))*Y2897/(F2897-E2897+1) -> 5123.89 | AF2897: =IF(AB2897="Karnataka",AE2897*9%,0) -> 0 | AG2897: =IF(AB2897="Karnataka",AE2897*9%,0) -> 0 | AH2897: =IF(AF2897+AG2897>0,0,AE2897*18%) -> 922.3002 | AI2897: =AE2897*L2897 -> 204.9556 | AJ2897: =$AE2897*M2897 -> 1152.8753 | AK2897: =(AE2897)*AA2897/Y2897 -> 2540.8879 | AL2897: =AK2897*(1-L2897-M2897) -> 1867.5526 | AM2897: =AE2897-AI2897-AL2897-AJ2897 -> 1898.5065 | AN2897: =Z2897-366 -> 45715 | AO2897: =IF(AND(O2897>Z2897,N2897>AN2897),AE2897,0) -> 5123.89
A2898: Valid | B2898: 202509 | C2898: GMC023220100CALDERYS | D2898: CALDERYS INDIA REFRACTORIES LIMITED | E2898: 45901 | F2898: 46265 | G2898: Premlata singh | H2898: 45029 | I2898: 24842 | J2898: ACK.4A9F3020250709.1 | K2898: =N2898 -> 45901 | L2898: =IF(K2898>=DATE(2022,4,1),4%,5%) -> 0.04 | M2898: 0.225 | N2898: 45901 | O2898: 46265 | R2898: 57 | S2898: =VLOOKUP(R2898,SA!$B$3:$C$11,2,1) -> 56-65 | T2898: Female | U2898: Mother | V2898: 400000 | W2898: =IF(U2898="self",V2898,0) -> 0 | X2898: =IF(U2898="self",1,0) -> 0 | Y2898: =O2898-N2898+1 -> 365 | Z2898: =$Z$1 -> 46081 | AA2898: =IF(MIN((Z2898-N2898)+1,Y2898)<0,0,MIN((Z2898-N2898)+1,Y2898)) -> 181 | AB2898: Maharashtra | AC2898: =AE2898+AF2898+AG2898+AH2898 -> 11909.728 | AD2898: 1 | AE2898: =INDEX(SA!$C$2:$G$11,MATCH(Details!S2898,SA!$C$2:$C$11,0),MATCH(Details!V2898,SA!$C$2:$G$2,0))*Y2898/(F2898-E2898+1) -> 10092.99 | AF2898: =IF(AB2898="Karnataka",AE2898*9%,0) -> 0 | AG2898: =IF(AB2898="Karnataka",AE2898*9%,0) -> 0 | AH2898: =IF(AF2898+AG2898>0,0,AE2898*18%) -> 1816.7382 | AI2898: =AE2898*L2898 -> 403.7196 | AJ2898: =$AE2898*M2898 -> 2270.9228 | AK2898: =(AE2898)*AA2898/Y2898 -> 5005.017 | AL2898: =AK2898*(1-L2898-M2898) -> 3678.6875 | AM2898: =AE2898-AI2898-AL2898-AJ2898 -> 3739.6602 | AN2898: =Z2898-366 -> 45715 | AO2898: =IF(AND(O2898>Z2898,N2898>AN2898),AE2898,0) -> 10092.99
A2899: Valid | B2899: 202509 | C2899: GMC023220100CALDERYS | D2899: CALDERYS INDIA REFRACTORIES LIMITED | E2899: 45901 | F2899: 46265 | G2899: samar bahadur singh | H2899: 45029 | I2899: 25223 | J2899: ACK.4A9F3020250709.2 | K2899: =N2899 -> 45901 | L2899: =IF(K2899>=DATE(2022,4,1),4%,5%) -> 0.04 | M2899: 0.225 | N2899: 45901 | O2899: 46265 | R2899: 56 | S2899: =VLOOKUP(R2899,SA!$B$3:$C$11,2,1) -> 56-65 | T2899: Male | U2899: Father | V2899: 400000 | W2899: =IF(U2899="self",V2899,0) -> 0 | X2899: =IF(U2899="self",1,0) -> 0 | Y2899: =O2899-N2899+1 -> 365 | Z2899: =$Z$1 -> 46081 | AA2899: =IF(MIN((Z2899-N2899)+1,Y2899)<0,0,MIN((Z2899-N2899)+1,Y2899)) -> 181 | AB2899: Maharashtra | AC2899: =AE2899+AF2899+AG2899+AH2899 -> 11909.728 | AD2899: 1 | AE2899: =INDEX(SA!$C$2:$G$11,MATCH(Details!S2899,SA!$C$2:$C$11,0),MATCH(Details!V2899,SA!$C$2:$G$2,0))*Y2899/(F2899-E2899+1) -> 10092.99 | AF2899: =IF(AB2899="Karnataka",AE2899*9%,0) -> 0 | AG2899: =IF(AB2899="Karnataka",AE2899*9%,0) -> 0 | AH2899: =IF(AF2899+AG2899>0,0,AE2899*18%) -> 1816.7382 | AI2899: =AE2899*L2899 -> 403.7196 | AJ2899: =$AE2899*M2899 -> 2270.9228 | AK2899: =(AE2899)*AA2899/Y2899 -> 5005.017 | AL2899: =AK2899*(1-L2899-M2899) -> 3678.6875 | AM2899: =AE2899-AI2899-AL2899-AJ2899 -> 3739.6602 | AN2899: =Z2899-366 -> 45715 | AO2899: =IF(AND(O2899>Z2899,N2899>AN2899),AE2899,0) -> 10092.99
A2900: Valid | B2900: 202509 | C2900: GMC023220100CALDERYS | D2900: CALDERYS INDIA REFRACTORIES LIMITED | E2900: 45901 | F2900: 46265 | G2900: Rupesh Singh | H2900: 45029 | I2900: 36435 | J2900: ACK.4A9F3020250709.3 | K2900: =N2900 -> 45901 | L2900: =IF(K2900>=DATE(2022,4,1),4%,5%) -> 0.04 | M2900: 0.225 | N2900: 45901 | O2900: 46265 | R2900: 25 | S2900: =VLOOKUP(R2900,SA!$B$3:$C$11,2,1) -> 0-25 | T2900: Male | U2900: Self | V2900: 400000 | W2900: =IF(U2900="self",V2900,0) -> 400000 | X2900: =IF(U2900="self",1,0) -> 1 | Y2900: =O2900-N2900+1 -> 365 | Z2900: =$Z$1 -> 46081 | AA2900: =IF(MIN((Z2900-N2900)+1,Y2900)<0,0,MIN((Z2900-N2900)+1,Y2900)) -> 181 | AB2900: Maharashtra | AC2900: =AE2900+AF2900+AG2900+AH2900 -> 4043.8364 | AD2900: 1 | AE2900: =INDEX(SA!$C$2:$G$11,MATCH(Details!S2900,SA!$C$2:$C$11,0),MATCH(Details!V2900,SA!$C$2:$G$2,0))*Y2900/(F2900-E2900+1) -> 3426.98 | AF2900: =IF(AB2900="Karnataka",AE2900*9%,0) -> 0 | AG2900: =IF(AB2900="Karnataka",AE2900*9%,0) -> 0 | AH2900: =IF(AF2900+AG2900>0,0,AE2900*18%) -> 616.8564 | AI2900: =AE2900*L2900 -> 137.0792 | AJ2900: =$AE2900*M2900 -> 771.0705 | AK2900: =(AE2900)*AA2900/Y2900 -> 1699.4065 | AL2900: =AK2900*(1-L2900-M2900) -> 1249.0638 | AM2900: =AE2900-AI2900-AL2900-AJ2900 -> 1269.7665 | AN2900: =Z2900-366 -> 45715 | AO2900: =IF(AND(O2900>Z2900,N2900>AN2900),AE2900,0) -> 3426.98
A2901: Valid | B2901: 202509 | C2901: GMC023220100CALDERYS | D2901: CALDERYS INDIA REFRACTORIES LIMITED | E2901: 45901 | F2901: 46265 | G2901: Nitu Kumari | H2901: 652602 | I2901: 36319 | J2901: ACK.4A9F3020250714.1 | K2901: =N2901 -> 45901 | L2901: =IF(K2901>=DATE(2022,4,1),4%,5%) -> 0.04 | M2901: 0.225 | N2901: 45901 | O2901: 46265 | R2901: 26 | S2901: =VLOOKUP(R2901,SA!$B$3:$C$11,2,1) -> 26-35 | T2901: Female | U2901: Self | V2901: 400000 | W2901: =IF(U2901="self",V2901,0) -> 400000 | X2901: =IF(U2901="self",1,0) -> 1 | Y2901: =O2901-N2901+1 -> 365 | Z2901: =$Z$1 -> 46081 | AA2901: =IF(MIN((Z2901-N2901)+1,Y2901)<0,0,MIN((Z2901-N2901)+1,Y2901)) -> 181 | AB2901: Maharashtra | AC2901: =AE2901+AF2901+AG2901+AH2901 -> 4533.029 | AD2901: 1 | AE2901: =INDEX(SA!$C$2:$G$11,MATCH(Details!S2901,SA!$C$2:$C$11,0),MATCH(Details!V2901,SA!$C$2:$G$2,0))*Y2901/(F2901-E2901+1) -> 3841.55 | AF2901: =IF(AB2901="Karnataka",AE2901*9%,0) -> 0 | AG2901: =IF(AB2901="Karnataka",AE2901*9%,0) -> 0 | AH2901: =IF(AF2901+AG2901>0,0,AE2901*18%) -> 691.479 | AI2901: =AE2901*L2901 -> 153.662 | AJ2901: =$AE2901*M2901 -> 864.34875 | AK2901: =(AE2901)*AA2901/Y2901 -> 1904.9878 | AL2901: =AK2901*(1-L2901-M2901) -> 1400.166 | AM2901: =AE2901-AI2901-AL2901-AJ2901 -> 1423.3732 | AN2901: =Z2901-366 -> 45715 | AO2901: =IF(AND(O2901>Z2901,N2901>AN2901),AE2901,0) -> 3841.55
A2902: Valid | B2902: 202509 | C2902: GMC023220100CALDERYS | D2902: CALDERYS INDIA REFRACTORIES LIMITED | E2902: 45901 | F2902: 46265 | G2902: Umesh Ram | H2902: 652602 | I2902: 25934 | J2902: ACK.4A9F3020250714.2 | K2902: =N2902 -> 45901 | L2902: =IF(K2902>=DATE(2022,4,1),4%,5%) -> 0.04 | M2902: 0.225 | N2902: 45901 | O2902: 46265 | R2902: 54 | S2902: =VLOOKUP(R2902,SA!$B$3:$C$11,2,1) -> 46-55 | T2902: Male | U2902: Father | V2902: 400000 | W2902: =IF(U2902="self",V2902,0) -> 0 | X2902: =IF(U2902="self",1,0) -> 0 | Y2902: =O2902-N2902+1 -> 365 | Z2902: =$Z$1 -> 46081 | AA2902: =IF(MIN((Z2902-N2902)+1,Y2902)<0,0,MIN((Z2902-N2902)+1,Y2902)) -> 181 | AB2902: Maharashtra | AC2902: =AE2902+AF2902+AG2902+AH2902 -> 8108.2166 | AD2902: 1 | AE2902: =INDEX(SA!$C$2:$G$11,MATCH(Details!S2902,SA!$C$2:$C$11,0),MATCH(Details!V2902,SA!$C$2:$G$2,0))*Y2902/(F2902-E2902+1) -> 6871.37 | AF2902: =IF(AB2902="Karnataka",AE2902*9%,0) -> 0 | AG2902: =IF(AB2902="Karnataka",AE2902*9%,0) -> 0 | AH2902: =IF(AF2902+AG2902>0,0,AE2902*18%) -> 1236.8466 | AI2902: =AE2902*L2902 -> 274.8548 | AJ2902: =$AE2902*M2902 -> 1546.0583 | AK2902: =(AE2902)*AA2902/Y2902 -> 3407.4465 | AL2902: =AK2902*(1-L2902-M2902) -> 2504.4732 | AM2902: =AE2902-AI2902-AL2902-AJ2902 -> 2545.9838 | AN2902: =Z2902-366 -> 45715 | AO2902: =IF(AND(O2902>Z2902,N2902>AN2902),AE2902,0) -> 6871.37
A2903: Valid | B2903: 202509 | C2903: GMC023220100CALDERYS | D2903: CALDERYS INDIA REFRACTORIES LIMITED | E2903: 45901 | F2903: 46265 | G2903: Shail Kumari Rai | H2903: 652603 | I2903: 21772 | J2903: ACK.4A9F3020250716.1 | K2903: =N2903 -> 45901 | L2903: =IF(K2903>=DATE(2022,4,1),4%,5%) -> 0.04 | M2903: 0.225 | N2903: 45901 | O2903: 46265 | R2903: 66 | S2903: =VLOOKUP(R2903,SA!$B$3:$C$11,2,1) -> 66-70 | T2903: Female | U2903: Mother | V2903: 400000 | W2903: =IF(U2903="self",V2903,0) -> 0 | X2903: =IF(U2903="self",1,0) -> 0 | Y2903: =O2903-N2903+1 -> 365 | Z2903: =$Z$1 -> 46081 | AA2903: =IF(MIN((Z2903-N2903)+1,Y2903)<0,0,MIN((Z2903-N2903)+1,Y2903)) -> 181 | AB2903: Maharashtra | AC2903: =AE2903+AF2903+AG2903+AH2903 -> 17021.972 | AD2903: 1 | AE2903: =INDEX(SA!$C$2:$G$11,MATCH(Details!S2903,SA!$C$2:$C$11,0),MATCH(Details!V2903,SA!$C$2:$G$2,0))*Y2903/(F2903-E2903+1) -> 14425.4 | AF2903: =IF(AB2903="Karnataka",AE2903*9%,0) -> 0 | AG2903: =IF(AB2903="Karnataka",AE2903*9%,0) -> 0 | AH2903: =IF(AF2903+AG2903>0,0,AE2903*18%) -> 2596.572 | AI2903: =AE2903*L2903 -> 577.016 | AJ2903: =$AE2903*M2903 -> 3245.715 | AK2903: =(AE2903)*AA2903/Y2903 -> 7153.4175 | AL2903: =AK2903*(1-L2903-M2903) -> 5257.7619 | AM2903: =AE2903-AI2903-AL2903-AJ2903 -> 5344.9071 | AN2903: =Z2903-366 -> 45715 | AO2903: =IF(AND(O2903>Z2903,N2903>AN2903),AE2903,0) -> 14425.4
A2904: Valid | B2904: 202509 | C2904: GMC023220100CALDERYS | D2904: CALDERYS INDIA REFRACTORIES LIMITED | E2904: 45901 | F2904: 46265 | G2904: Dipti Pandey | H2904: 652603 | I2904: 35452 | J2904: ACK.4A9F3020250716.2 | K2904: =N2904 -> 45901 | L2904: =IF(K2904>=DATE(2022,4,1),4%,5%) -> 0.04 | M2904: 0.225 | N2904: 45901 | O2904: 46265 | R2904: 28 | S2904: =VLOOKUP(R2904,SA!$B$3:$C$11,2,1) -> 26-35 | T2904: Female | U2904: Spouse | V2904: 400000 | W2904: =IF(U2904="self",V2904,0) -> 0 | X2904: =IF(U2904="self",1,0) -> 0 | Y2904: =O2904-N2904+1 -> 365 | Z2904: =$Z$1 -> 46081 | AA2904: =IF(MIN((Z2904-N2904)+1,Y2904)<0,0,MIN((Z2904-N2904)+1,Y2904)) -> 181 | AB2904: Maharashtra | AC2904: =AE2904+AF2904+AG2904+AH2904 -> 4533.029 | AD2904: 1 | AE2904: =INDEX(SA!$C$2:$G$11,MATCH(Details!S2904,SA!$C$2:$C$11,0),MATCH(Details!V2904,SA!$C$2:$G$2,0))*Y2904/(F2904-E2904+1) -> 3841.55 | AF2904: =IF(AB2904="Karnataka",AE2904*9%,0) -> 0 | AG2904: =IF(AB2904="Karnataka",AE2904*9%,0) -> 0 | AH2904: =IF(AF2904+AG2904>0,0,AE2904*18%) -> 691.479 | AI2904: =AE2904*L2904 -> 153.662 | AJ2904: =$AE2904*M2904 -> 864.34875 | AK2904: =(AE2904)*AA2904/Y2904 -> 1904.9878 | AL2904: =AK2904*(1-L2904-M2904) -> 1400.166 | AM2904: =AE2904-AI2904-AL2904-AJ2904 -> 1423.3732 | AN2904: =Z2904-366 -> 45715 | AO2904: =IF(AND(O2904>Z2904,N2904>AN2904),AE2904,0) -> 3841.55
A2905: Valid | B2905: 202509 | C2905: GMC023220100CALDERYS | D2905: CALDERYS INDIA REFRACTORIES LIMITED | E2905: 45901 | F2905: 46265 | G2905: Bhagwan Rai | H2905: 652603 | I2905: 20059 | J2905: ACK.4A9F3020250716.3 | K2905: =N2905 -> 45901 | L2905: =IF(K2905>=DATE(2022,4,1),4%,5%) -> 0.04 | M2905: 0.225 | N2905: 45901 | O2905: 46265 | R2905: 70 | S2905: =VLOOKUP(R2905,SA!$B$3:$C$11,2,1) -> 66-70 | T2905: Male | U2905: Father | V2905: 400000 | W2905: =IF(U2905="self",V2905,0) -> 0 | X2905: =IF(U2905="self",1,0) -> 0 | Y2905: =O2905-N2905+1 -> 365 | Z2905: =$Z$1 -> 46081 | AA2905: =IF(MIN((Z2905-N2905)+1,Y2905)<0,0,MIN((Z2905-N2905)+1,Y2905)) -> 181 | AB2905: Maharashtra | AC2905: =AE2905+AF2905+AG2905+AH2905 -> 17021.972 | AD2905: 1 | AE2905: =INDEX(SA!$C$2:$G$11,MATCH(Details!S2905,SA!$C$2:$C$11,0),MATCH(Details!V2905,SA!$C$2:$G$2,0))*Y2905/(F2905-E2905+1) -> 14425.4 | AF2905: =IF(AB2905="Karnataka",AE2905*9%,0) -> 0 | AG2905: =IF(AB2905="Karnataka",AE2905*9%,0) -> 0 | AH2905: =IF(AF2905+AG2905>0,0,AE2905*18%) -> 2596.572 | AI2905: =AE2905*L2905 -> 577.016 | AJ2905: =$AE2905*M2905 -> 3245.715 | AK2905: =(AE2905)*AA2905/Y2905 -> 7153.4175 | AL2905: =AK2905*(1-L2905-M2905) -> 5257.7619 | AM2905: =AE2905-AI2905-AL2905-AJ2905 -> 5344.9071 | AN2905: =Z2905-366 -> 45715 | AO2905: =IF(AND(O2905>Z2905,N2905>AN2905),AE2905,0) -> 14425.4
A2906: Valid | B2906: 202509 | C2906: GMC023220100CALDERYS | D2906: CALDERYS INDIA REFRACTORIES LIMITED | E2906: 45901 | F2906: 46265 | G2906: Sandeep Kumar Rai | H2906: 652603 | I2906: 32339 | J2906: ACK.4A9F3020250716.4 | K2906: =N2906 -> 45901 | L2906: =IF(K2906>=DATE(2022,4,1),4%,5%) -> 0.04 | M2906: 0.225 | N2906: 45901 | O2906: 46265 | R2906: 37 | S2906: =VLOOKUP(R2906,SA!$B$3:$C$11,2,1) -> 36-45 | T2906: Male | U2906: Self | V2906: 400000 | W2906: =IF(U2906="self",V2906,0) -> 400000 | X2906: =IF(U2906="self",1,0) -> 1 | Y2906: =O2906-N2906+1 -> 365 | Z2906: =$Z$1 -> 46081 | AA2906: =IF(MIN((Z2906-N2906)+1,Y2906)<0,0,MIN((Z2906-N2906)+1,Y2906)) -> 181 | AB2906: Maharashtra | AC2906: =AE2906+AF2906+AG2906+AH2906 -> 5496.5226 | AD2906: 1 | AE2906: =INDEX(SA!$C$2:$G$11,MATCH(Details!S2906,SA!$C$2:$C$11,0),MATCH(Details!V2906,SA!$C$2:$G$2,0))*Y2906/(F2906-E2906+1) -> 4658.07 | AF2906: =IF(AB2906="Karnataka",AE2906*9%,0) -> 0 | AG2906: =IF(AB2906="Karnataka",AE2906*9%,0) -> 0 | AH2906: =IF(AF2906+AG2906>0,0,AE2906*18%) -> 838.4526 | AI2906: =AE2906*L2906 -> 186.3228 | AJ2906: =$AE2906*M2906 -> 1048.0657 | AK2906: =(AE2906)*AA2906/Y2906 -> 2309.8922 | AL2906: =AK2906*(1-L2906-M2906) -> 1697.7708 | AM2906: =AE2906-AI2906-AL2906-AJ2906 -> 1725.9106 | AN2906: =Z2906-366 -> 45715 | AO2906: =IF(AND(O2906>Z2906,N2906>AN2906),AE2906,0) -> 4658.07
A2907: Valid | B2907: 202509 | C2907: GMC023220100CALDERYS | D2907: CALDERYS INDIA REFRACTORIES LIMITED | E2907: 45901 | F2907: 46265 | G2907: Aarav Rai | H2907: 652603 | I2907: 43388 | J2907: ACK.4A9F3020250716.5 | K2907: =N2907 -> 45901 | L2907: =IF(K2907>=DATE(2022,4,1),4%,5%) -> 0.04 | M2907: 0.225 | N2907: 45901 | O2907: 46265 | R2907: 6 | S2907: =VLOOKUP(R2907,SA!$B$3:$C$11,2,1) -> 0-25 | T2907: Male | U2907: Son | V2907: 400000 | W2907: =IF(U2907="self",V2907,0) -> 0 | X2907: =IF(U2907="self",1,0) -> 0 | Y2907: =O2907-N2907+1 -> 365 | Z2907: =$Z$1 -> 46081 | AA2907: =IF(MIN((Z2907-N2907)+1,Y2907)<0,0,MIN((Z2907-N2907)+1,Y2907)) -> 181 | AB2907: Maharashtra | AC2907: =AE2907+AF2907+AG2907+AH2907 -> 4043.8364 | AD2907: 1 | AE2907: =INDEX(SA!$C$2:$G$11,MATCH(Details!S2907,SA!$C$2:$C$11,0),MATCH(Details!V2907,SA!$C$2:$G$2,0))*Y2907/(F2907-E2907+1) -> 3426.98 | AF2907: =IF(AB2907="Karnataka",AE2907*9%,0) -> 0 | AG2907: =IF(AB2907="Karnataka",AE2907*9%,0) -> 0 | AH2907: =IF(AF2907+AG2907>0,0,AE2907*18%) -> 616.8564 | AI2907: =AE2907*L2907 -> 137.0792 | AJ2907: =$AE2907*M2907 -> 771.0705 | AK2907: =(AE2907)*AA2907/Y2907 -> 1699.4065 | AL2907: =AK2907*(1-L2907-M2907) -> 1249.0638 | AM2907: =AE2907-AI2907-AL2907-AJ2907 -> 1269.7665 | AN2907: =Z2907-366 -> 45715 | AO2907: =IF(AND(O2907>Z2907,N2907>AN2907),AE2907,0) -> 3426.98
A2908: Valid | B2908: 202509 | C2908: GMC023220100CALDERYS | D2908: CALDERYS INDIA REFRACTORIES LIMITED | E2908: 45901 | F2908: 46265 | G2908: Indu Sharma | H2908: 45018 | I2908: 23609 | J2908: ACK.4A9F3020250701.1 | K2908: =N2908 -> 45901 | L2908: =IF(K2908>=DATE(2022,4,1),4%,5%) -> 0.04 | M2908: 0.225 | N2908: 45901 | O2908: 46265 | R2908: 61 | S2908: =VLOOKUP(R2908,SA!$B$3:$C$11,2,1) -> 56-65 | T2908: Female | U2908: Mother | V2908: 500000 | W2908: =IF(U2908="self",V2908,0) -> 0 | X2908: =IF(U2908="self",1,0) -> 0 | Y2908: =O2908-N2908+1 -> 365 | Z2908: =$Z$1 -> 46081 | AA2908: =IF(MIN((Z2908-N2908)+1,Y2908)<0,0,MIN((Z2908-N2908)+1,Y2908)) -> 181 | AB2908: Maharashtra | AC2908: =AE2908+AF2908+AG2908+AH2908 -> 13100.714 | AD2908: 1 | AE2908: =INDEX(SA!$C$2:$G$11,MATCH(Details!S2908,SA!$C$2:$C$11,0),MATCH(Details!V2908,SA!$C$2:$G$2,0))*Y2908/(F2908-E2908+1) -> 11102.3 | AF2908: =IF(AB2908="Karnataka",AE2908*9%,0) -> 0 | AG2908: =IF(AB2908="Karnataka",AE2908*9%,0) -> 0 | AH2908: =IF(AF2908+AG2908>0,0,AE2908*18%) -> 1998.414 | AI2908: =AE2908*L2908 -> 444.092 | AJ2908: =$AE2908*M2908 -> 2498.0175 | AK2908: =(AE2908)*AA2908/Y2908 -> 5505.5241 | AL2908: =AK2908*(1-L2908-M2908) -> 4046.5602 | AM2908: =AE2908-AI2908-AL2908-AJ2908 -> 4113.6303 | AN2908: =Z2908-366 -> 45715 | AO2908: =IF(AND(O2908>Z2908,N2908>AN2908),AE2908,0) -> 11102.3
A2909: Valid | B2909: 202509 | C2909: GMC023220100CALDERYS | D2909: CALDERYS INDIA REFRACTORIES LIMITED | E2909: 45901 | F2909: 46265 | G2909: Sonali Singh | H2909: 45018 | I2909: 35662 | J2909: ACK.4A9F3020250701.2 | K2909: =N2909 -> 45901 | L2909: =IF(K2909>=DATE(2022,4,1),4%,5%) -> 0.04 | M2909: 0.225 | N2909: 45901 | O2909: 46265 | R2909: 28 | S2909: =VLOOKUP(R2909,SA!$B$3:$C$11,2,1) -> 26-35 | T2909: Female | U2909: Spouse | V2909: 500000 | W2909: =IF(U2909="self",V2909,0) -> 0 | X2909: =IF(U2909="self",1,0) -> 0 | Y2909: =O2909-N2909+1 -> 365 | Z2909: =$Z$1 -> 46081 | AA2909: =IF(MIN((Z2909-N2909)+1,Y2909)<0,0,MIN((Z2909-N2909)+1,Y2909)) -> 181 | AB2909: Maharashtra | AC2909: =AE2909+AF2909+AG2909+AH2909 -> 4986.3142 | AD2909: 1 | AE2909: =INDEX(SA!$C$2:$G$11,MATCH(Details!S2909,SA!$C$2:$C$11,0),MATCH(Details!V2909,SA!$C$2:$G$2,0))*Y2909/(F2909-E2909+1) -> 4225.69 | AF2909: =IF(AB2909="Karnataka",AE2909*9%,0) -> 0 | AG2909: =IF(AB2909="Karnataka",AE2909*9%,0) -> 0 | AH2909: =IF(AF2909+AG2909>0,0,AE2909*18%) -> 760.6242 | AI2909: =AE2909*L2909 -> 169.0276 | AJ2909: =$AE2909*M2909 -> 950.78025 | AK2909: =(AE2909)*AA2909/Y2909 -> 2095.4792 | AL2909: =AK2909*(1-L2909-M2909) -> 1540.1772 | AM2909: =AE2909-AI2909-AL2909-AJ2909 -> 1565.705 | AN2909: =Z2909-366 -> 45715 | AO2909: =IF(AND(O2909>Z2909,N2909>AN2909),AE2909,0) -> 4225.69
A2910: Valid | B2910: 202509 | C2910: GMC023220100CALDERYS | D2910: CALDERYS INDIA REFRACTORIES LIMITED | E2910: 45901 | F2910: 46265 | G2910: Vijay Kumar Sharma | H2910: 45018 | I2910: 22798 | J2910: ACK.4A9F3020250701.3 | K2910: =N2910 -> 45901 | L2910: =IF(K2910>=DATE(2022,4,1),4%,5%) -> 0.04 | M2910: 0.225 | N2910: 45901 | O2910: 46265 | R2910: 63 | S2910: =VLOOKUP(R2910,SA!$B$3:$C$11,2,1) -> 56-65 | T2910: Male | U2910: Father | V2910: 500000 | W2910: =IF(U2910="self",V2910,0) -> 0 | X2910: =IF(U2910="self",1,0) -> 0 | Y2910: =O2910-N2910+1 -> 365 | Z2910: =$Z$1 -> 46081 | AA2910: =IF(MIN((Z2910-N2910)+1,Y2910)<0,0,MIN((Z2910-N2910)+1,Y2910)) -> 181 | AB2910: Maharashtra | AC2910: =AE2910+AF2910+AG2910+AH2910 -> 13100.714 | AD2910: 1 | AE2910: =INDEX(SA!$C$2:$G$11,MATCH(Details!S2910,SA!$C$2:$C$11,0),MATCH(Details!V2910,SA!$C$2:$G$2,0))*Y2910/(F2910-E2910+1) -> 11102.3 | AF2910: =IF(AB2910="Karnataka",AE2910*9%,0) -> 0 | AG2910: =IF(AB2910="Karnataka",AE2910*9%,0) -> 0 | AH2910: =IF(AF2910+AG2910>0,0,AE2910*18%) -> 1998.414 | AI2910: =AE2910*L2910 -> 444.092 | AJ2910: =$AE2910*M2910 -> 2498.0175 | AK2910: =(AE2910)*AA2910/Y2910 -> 5505.5241 | AL2910: =AK2910*(1-L2910-M2910) -> 4046.5602 | AM2910: =AE2910-AI2910-AL2910-AJ2910 -> 4113.6303 | AN2910: =Z2910-366 -> 45715 | AO2910: =IF(AND(O2910>Z2910,N2910>AN2910),AE2910,0) -> 11102.3
A2911: Valid | B2911: 202509 | C2911: GMC023220100CALDERYS | D2911: CALDERYS INDIA REFRACTORIES LIMITED | E2911: 45901 | F2911: 46265 | G2911: Prashant Sharma | H2911: 45018 | I2911: 33615 | J2911: ACK.4A9F3020250701.4 | K2911: =N2911 -> 45901 | L2911: =IF(K2911>=DATE(2022,4,1),4%,5%) -> 0.04 | M2911: 0.225 | N2911: 45901 | O2911: 46265 | R2911: 33 | S2911: =VLOOKUP(R2911,SA!$B$3:$C$11,2,1) -> 26-35 | T2911: Male | U2911: Self | V2911: 500000 | W2911: =IF(U2911="self",V2911,0) -> 500000 | X2911: =IF(U2911="self",1,0) -> 1 | Y2911: =O2911-N2911+1 -> 365 | Z2911: =$Z$1 -> 46081 | AA2911: =IF(MIN((Z2911-N2911)+1,Y2911)<0,0,MIN((Z2911-N2911)+1,Y2911)) -> 181 | AB2911: Maharashtra | AC2911: =AE2911+AF2911+AG2911+AH2911 -> 4986.3142 | AD2911: 1 | AE2911: =INDEX(SA!$C$2:$G$11,MATCH(Details!S2911,SA!$C$2:$C$11,0),MATCH(Details!V2911,SA!$C$2:$G$2,0))*Y2911/(F2911-E2911+1) -> 4225.69 | AF2911: =IF(AB2911="Karnataka",AE2911*9%,0) -> 0 | AG2911: =IF(AB2911="Karnataka",AE2911*9%,0) -> 0 | AH2911: =IF(AF2911+AG2911>0,0,AE2911*18%) -> 760.6242 | AI2911: =AE2911*L2911 -> 169.0276 | AJ2911: =$AE2911*M2911 -> 950.78025 | AK2911: =(AE2911)*AA2911/Y2911 -> 2095.4792 | AL2911: =AK2911*(1-L2911-M2911) -> 1540.1772 | AM2911: =AE2911-AI2911-AL2911-AJ2911 -> 1565.705 | AN2911: =Z2911-366 -> 45715 | AO2911: =IF(AND(O2911>Z2911,N2911>AN2911),AE2911,0) -> 4225.69
A2912: Valid | B2912: 202509 | C2912: GMC023220100CALDERYS | D2912: CALDERYS INDIA REFRACTORIES LIMITED | E2912: 45901 | F2912: 46265 | G2912: Urbasi Mallick | H2912: 44810 | I2912: 30503 | J2912: ACK.4A9F3020250684.1 | K2912: =N2912 -> 45901 | L2912: =IF(K2912>=DATE(2022,4,1),4%,5%) -> 0.04 | M2912: 0.225 | N2912: 45901 | O2912: 46265 | R2912: 42 | S2912: =VLOOKUP(R2912,SA!$B$3:$C$11,2,1) -> 36-45 | T2912: Female | U2912: Mother | V2912: 400000 | W2912: =IF(U2912="self",V2912,0) -> 0 | X2912: =IF(U2912="self",1,0) -> 0 | Y2912: =O2912-N2912+1 -> 365 | Z2912: =$Z$1 -> 46081 | AA2912: =IF(MIN((Z2912-N2912)+1,Y2912)<0,0,MIN((Z2912-N2912)+1,Y2912)) -> 181 | AB2912: Maharashtra | AC2912: =AE2912+AF2912+AG2912+AH2912 -> 5496.5226 | AD2912: 1 | AE2912: =INDEX(SA!$C$2:$G$11,MATCH(Details!S2912,SA!$C$2:$C$11,0),MATCH(Details!V2912,SA!$C$2:$G$2,0))*Y2912/(F2912-E2912+1) -> 4658.07 | AF2912: =IF(AB2912="Karnataka",AE2912*9%,0) -> 0 | AG2912: =IF(AB2912="Karnataka",AE2912*9%,0) -> 0 | AH2912: =IF(AF2912+AG2912>0,0,AE2912*18%) -> 838.4526 | AI2912: =AE2912*L2912 -> 186.3228 | AJ2912: =$AE2912*M2912 -> 1048.0657 | AK2912: =(AE2912)*AA2912/Y2912 -> 2309.8922 | AL2912: =AK2912*(1-L2912-M2912) -> 1697.7708 | AM2912: =AE2912-AI2912-AL2912-AJ2912 -> 1725.9106 | AN2912: =Z2912-366 -> 45715 | AO2912: =IF(AND(O2912>Z2912,N2912>AN2912),AE2912,0) -> 4658.07
... A3011: Valid | B3011: 202509 | C3011: GMC023220100CALDERYS | D3011: CALDERYS INDIA REFRACTORIES LIMITED | E3011: 45901 | F3011: 46265 | G3011: Dhyan Solanki | H3011: 752021 | I3011: 45901 | J3011: ACK.4A9F3020250574.6 | K3011: =N3011 -> 45901 | L3011: =IF(K3011>=DATE(2022,4,1),4%,5%) -> 0.04 | M3011: 0.225 | N3011: 45901 | O3011: 46265 | R3011: 0 | S3011: =VLOOKUP(R3011,SA!$B$3:$C$11,2,1) -> 0-25 | T3011: MALE | U3011: Son | V3011: 300000 | W3011: =IF(U3011="self",V3011,0) -> 0 | X3011: =IF(U3011="self",1,0) -> 0 | Y3011: =O3011-N3011+1 -> 365 | Z3011: =$Z$1 -> 46081 | AA3011: =IF(MIN((Z3011-N3011)+1,Y3011)<0,0,MIN((Z3011-N3011)+1,Y3011)) -> 181 | AB3011: Maharashtra | AC3011: =AE3011+AF3011+AG3011+AH3011 -> 3690.3792 | AD3011: 1 | AE3011: =INDEX(SA!$C$2:$G$11,MATCH(Details!S3011,SA!$C$2:$C$11,0),MATCH(Details!V3011,SA!$C$2:$G$2,0))*Y3011/(F3011-E3011+1) -> 3127.44 | AF3011: =IF(AB3011="Karnataka",AE3011*9%,0) -> 0 | AG3011: =IF(AB3011="Karnataka",AE3011*9%,0) -> 0 | AH3011: =IF(AF3011+AG3011>0,0,AE3011*18%) -> 562.9392 | AI3011: =AE3011*L3011 -> 125.0976 | AJ3011: =$AE3011*M3011 -> 703.674 | AK3011: =(AE3011)*AA3011/Y3011 -> 1550.8675 | AL3011: =AK3011*(1-L3011-M3011) -> 1139.8876 | AM3011: =AE3011-AI3011-AL3011-AJ3011 -> 1158.7808 | AN3011: =Z3011-366 -> 45715 | AO3011: =IF(AND(O3011>Z3011,N3011>AN3011),AE3011,0) -> 3127.44
A3012: Deletion | B3012: 202509 | C3012: GMC023220100CALDERYS | D3012: CALDERYS INDIA REFRACTORIES LIMITED | E3012: 45901 | F3012: 46265 | G3012: Sayyed Ahmed Ali | H3012: 42350 | I3012: 36108 | J3012: ACK.4A9F3020250208.1 | K3012: =N3012 -> 45901 | L3012: =IF(K3012>=DATE(2022,4,1),4%,5%) -> 0.04 | M3012: 0.225 | N3012: 45901 | O3012: 46265 | P3012: 45900 | Q3012: =P3012+1 -> 45901 | R3012: 26 | S3012: =VLOOKUP(R3012,SA!$B$3:$C$11,2,1) -> 26-35 | T3012: Male | U3012: Self | V3012: -400000 | W3012: =IF(U3012="self",V3012,0) -> -400000 | X3012: =IF(U3012="self",-1,0) -> -1 | Y3012: =O3012-Q3012+1 -> 365 | Z3012: =$Z$1 -> 46081 | AA3012: =IF(MIN((Z3012-Q3012)+1,Y3012)<0,0,MIN((Z3012-Q3012)+1,Y3012)) -> 181 | AB3012: Maharashtra | AC3012: =AE3012+AF3012+AG3012+AH3012 -> -4533.029 | AD3012: -1 | AE3012: =-INDEX(SA!$C$2:$G$11,MATCH(Details!S3012,SA!$C$2:$C$11,0),MATCH(-Details!V3012,SA!$C$2:$G$2,0))*Y3012/(F3012-E3012+1) -> -3841.55 | AF3012: =IF(AB3012="Karnataka",AE3012*9%,0) -> 0 | AG3012: =IF(AB3012="Karnataka",AE3012*9%,0) -> 0 | AH3012: =IF(AF3012+AG3012>0,0,AE3012*18%) -> -691.479 | AI3012: =AE3012*L3012 -> -153.662 | AJ3012: =$AE3012*M3012 -> -864.34875 | AK3012: =(AE3012)*AA3012/Y3012 -> -1904.9878 | AL3012: =AK3012*(1-L3012-M3012) -> -1400.166 | AM3012: =AE3012-AI3012-AL3012-AJ3012 -> -1423.3732 | AN3012: =Z3012-366 -> 45715 | AO3012: =IF(AND(O3012>Z3012,N3012>AN3012),AE3012,0) -> -3841.55 | AP3012: No claim
A3013: Deletion | B3013: 202509 | C3013: GMC023220100CALDERYS | D3013: CALDERYS INDIA REFRACTORIES LIMITED | E3013: 45901 | F3013: 46265 | G3013: Azra Yasmin | H3013: 42350 | I3013: 25356 | J3013: ACK.4A9F3020250208.2 | K3013: =N3013 -> 45901 | L3013: =IF(K3013>=DATE(2022,4,1),4%,5%) -> 0.04 | M3013: 0.225 | N3013: 45901 | O3013: 46265 | P3013: 45900 | Q3013: =P3013+1 -> 45901 | R3013: 56 | S3013: =VLOOKUP(R3013,SA!$B$3:$C$11,2,1) -> 56-65 | T3013: Female | U3013: Mother | V3013: -400000 | W3013: =IF(U3013="self",V3013,0) -> 0 | X3013: =IF(U3013="self",-1,0) -> 0 | Y3013: =O3013-Q3013+1 -> 365 | Z3013: =$Z$1 -> 46081 | AA3013: =IF(MIN((Z3013-Q3013)+1,Y3013)<0,0,MIN((Z3013-Q3013)+1,Y3013)) -> 181 | AB3013: Maharashtra | AC3013: =AE3013+AF3013+AG3013+AH3013 -> -11909.728 | AD3013: -1 | AE3013: =-INDEX(SA!$C$2:$G$11,MATCH(Details!S3013,SA!$C$2:$C$11,0),MATCH(-Details!V3013,SA!$C$2:$G$2,0))*Y3013/(F3013-E3013+1) -> -10092.99 | AF3013: =IF(AB3013="Karnataka",AE3013*9%,0) -> 0 | AG3013: =IF(AB3013="Karnataka",AE3013*9%,0) -> 0 | AH3013: =IF(AF3013+AG3013>0,0,AE3013*18%) -> -1816.7382 | AI3013: =AE3013*L3013 -> -403.7196 | AJ3013: =$AE3013*M3013 -> -2270.9228 | AK3013: =(AE3013)*AA3013/Y3013 -> -5005.017 | AL3013: =AK3013*(1-L3013-M3013) -> -3678.6875 | AM3013: =AE3013-AI3013-AL3013-AJ3013 -> -3739.6602 | AN3013: =Z3013-366 -> 45715 | AO3013: =IF(AND(O3013>Z3013,N3013>AN3013),AE3013,0) -> -10092.99 | AP3013: No claim
A3014: Deletion | B3014: 202509 | C3014: GMC023220100CALDERYS | D3014: CALDERYS INDIA REFRACTORIES LIMITED | E3014: 45901 | F3014: 46265 | G3014: Amlan Kumar Kar | H3014: 362124 | I3014: 16819 | J3014: ACK.4A9F3020250055.1 | K3014: =N3014 -> 45901 | L3014: =IF(K3014>=DATE(2022,4,1),4%,5%) -> 0.04 | M3014: 0.225 | N3014: 45901 | O3014: 46265 | P3014: 45900 | Q3014: =P3014+1 -> 45901 | R3014: 79 | S3014: =VLOOKUP(R3014,SA!$B$3:$C$11,2,1) -> 76-80 | T3014: Male | U3014: Father | V3014: -500000 | W3014: =IF(U3014="self",V3014,0) -> 0 | X3014: =IF(U3014="self",-1,0) -> 0 | Y3014: =O3014-Q3014+1 -> 365 | Z3014: =$Z$1 -> 46081 | AA3014: =IF(MIN((Z3014-Q3014)+1,Y3014)<0,0,MIN((Z3014-Q3014)+1,Y3014)) -> 181 | AB3014: Maharashtra | AC3014: =AE3014+AF3014+AG3014+AH3014 -> -29821.09 | AD3014: -1 | AE3014: =-INDEX(SA!$C$2:$G$11,MATCH(Details!S3014,SA!$C$2:$C$11,0),MATCH(-Details!V3014,SA!$C$2:$G$2,0))*Y3014/(F3014-E3014+1) -> -25272.11 | AF3014: =IF(AB3014="Karnataka",AE3014*9%,0) -> 0 | AG3014: =IF(AB3014="Karnataka",AE3014*9%,0) -> 0 | AH3014: =IF(AF3014+AG3014>0,0,AE3014*18%) -> -4548.9798 | AI3014: =AE3014*L3014 -> -1010.8844 | AJ3014: =$AE3014*M3014 -> -5686.2248 | AK3014: =(AE3014)*AA3014/Y3014 -> -12532.197 | AL3014: =AK3014*(1-L3014-M3014) -> -9211.1648 | AM3014: =AE3014-AI3014-AL3014-AJ3014 -> -9363.836 | AN3014: =Z3014-366 -> 45715 | AO3014: =IF(AND(O3014>Z3014,N3014>AN3014),AE3014,0) -> -25272.11 | AP3014: No claim
A3015: Deletion | B3015: 202509 | C3015: GMC023220100CALDERYS | D3015: CALDERYS INDIA REFRACTORIES LIMITED | E3015: 45901 | F3015: 46265 | G3015: Milan Kar | H3015: 362124 | I3015: 20471 | J3015: ACK.4A9F3020250055.2 | K3015: =N3015 -> 45901 | L3015: =IF(K3015>=DATE(2022,4,1),4%,5%) -> 0.04 | M3015: 0.225 | N3015: 45901 | O3015: 46265 | P3015: 45900 | Q3015: =P3015+1 -> 45901 | R3015: 69 | S3015: =VLOOKUP(R3015,SA!$B$3:$C$11,2,1) -> 66-70 | T3015: Female | U3015: Mother | V3015: -500000 | W3015: =IF(U3015="self",V3015,0) -> 0 | X3015: =IF(U3015="self",-1,0) -> 0 | Y3015: =O3015-Q3015+1 -> 365 | Z3015: =$Z$1 -> 46081 | AA3015: =IF(MIN((Z3015-Q3015)+1,Y3015)<0,0,MIN((Z3015-Q3015)+1,Y3015)) -> 181 | AB3015: Maharashtra | AC3015: =AE3015+AF3015+AG3015+AH3015 -> -18713.136 | AD3015: -1 | AE3015: =-INDEX(SA!$C$2:$G$11,MATCH(Details!S3015,SA!$C$2:$C$11,0),MATCH(-Details!V3015,SA!$C$2:$G$2,0))*Y3015/(F3015-E3015+1) -> -15858.59 | AF3015: =IF(AB3015="Karnataka",AE3015*9%,0) -> 0 | AG3015: =IF(AB3015="Karnataka",AE3015*9%,0) -> 0 | AH3015: =IF(AF3015+AG3015>0,0,AE3015*18%) -> -2854.5462 | AI3015: =AE3015*L3015 -> -634.3436 | AJ3015: =$AE3015*M3015 -> -3568.1827 | AK3015: =(AE3015)*AA3015/Y3015 -> -7864.1227 | AL3015: =AK3015*(1-L3015-M3015) -> -5780.1302 | AM3015: =AE3015-AI3015-AL3015-AJ3015 -> -5875.9335 | AN3015: =Z3015-366 -> 45715 | AO3015: =IF(AND(O3015>Z3015,N3015>AN3015),AE3015,0) -> -15858.59 | AP3015: No claim
A3016: Deletion | B3016: 202509 | C3016: GMC023220100CALDERYS | D3016: CALDERYS INDIA REFRACTORIES LIMITED | E3016: 45901 | F3016: 46265 | G3016: Amit Kar | H3016: 362124 | I3016: 31147 | J3016: ACK.4A9F3020250055.3 | K3016: =N3016 -> 45901 | L3016: =IF(K3016>=DATE(2022,4,1),4%,5%) -> 0.04 | M3016: 0.225 | N3016: 45901 | O3016: 46265 | P3016: 45900 | Q3016: =P3016+1 -> 45901 | R3016: 40 | S3016: =VLOOKUP(R3016,SA!$B$3:$C$11,2,1) -> 36-45 | T3016: Male | U3016: Self | V3016: -500000 | W3016: =IF(U3016="self",V3016,0) -> -500000 | X3016: =IF(U3016="self",-1,0) -> -1 | Y3016: =O3016-Q3016+1 -> 365 | Z3016: =$Z$1 -> 46081 | AA3016: =IF(MIN((Z3016-Q3016)+1,Y3016)<0,0,MIN((Z3016-Q3016)+1,Y3016)) -> 181 | AB3016: Maharashtra | AC3016: =AE3016+AF3016+AG3016+AH3016 -> -6046.1902 | AD3016: -1 | AE3016: =-INDEX(SA!$C$2:$G$11,MATCH(Details!S3016,SA!$C$2:$C$11,0),MATCH(-Details!V3016,SA!$C$2:$G$2,0))*Y3016/(F3016-E3016+1) -> -5123.89 | AF3016: =IF(AB3016="Karnataka",AE3016*9%,0) -> 0 | AG3016: =IF(AB3016="Karnataka",AE3016*9%,0) -> 0 | AH3016: =IF(AF3016+AG3016>0,0,AE3016*18%) -> -922.3002 | AI3016: =AE3016*L3016 -> -204.9556 | AJ3016: =$AE3016*M3016 -> -1152.8753 | AK3016: =(AE3016)*AA3016/Y3016 -> -2540.8879 | AL3016: =AK3016*(1-L3016-M3016) -> -1867.5526 | AM3016: =AE3016-AI3016-AL3016-AJ3016 -> -1898.5065 | AN3016: =Z3016-366 -> 45715 | AO3016: =IF(AND(O3016>Z3016,N3016>AN3016),AE3016,0) -> -5123.89 | AP3016: No claim
A3017: Deletion | B3017: 202509 | C3017: GMC023220100CALDERYS | D3017: CALDERYS INDIA REFRACTORIES LIMITED | E3017: 45901 | F3017: 46265 | G3017: Ramesh Mohariya | H3017: 362136 | I3017: 23683 | J3017: ACK.4A9F3020250061.1 | K3017: =N3017 -> 45901 | L3017: =IF(K3017>=DATE(2022,4,1),4%,5%) -> 0.04 | M3017: 0.225 | N3017: 45901 | O3017: 46265 | P3017: 45900 | Q3017: =P3017+1 -> 45901 | R3017: 60 | S3017: =VLOOKUP(R3017,SA!$B$3:$C$11,2,1) -> 56-65 | T3017: Male | U3017: Father | V3017: -400000 | W3017: =IF(U3017="self",V3017,0) -> 0 | X3017: =IF(U3017="self",-1,0) -> 0 | Y3017: =O3017-Q3017+1 -> 365 | Z3017: =$Z$1 -> 46081 | AA3017: =IF(MIN((Z3017-Q3017)+1,Y3017)<0,0,MIN((Z3017-Q3017)+1,Y3017)) -> 181 | AB3017: Maharashtra | AC3017: =AE3017+AF3017+AG3017+AH3017 -> -11909.728 | AD3017: -1 | AE3017: =-INDEX(SA!$C$2:$G$11,MATCH(Details!S3017,SA!$C$2:$C$11,0),MATCH(-Details!V3017,SA!$C$2:$G$2,0))*Y3017/(F3017-E3017+1) -> -10092.99 | AF3017: =IF(AB3017="Karnataka",AE3017*9%,0) -> 0 | AG3017: =IF(AB3017="Karnataka",AE3017*9%,0) -> 0 | AH3017: =IF(AF3017+AG3017>0,0,AE3017*18%) -> -1816.7382 | AI3017: =AE3017*L3017 -> -403.7196 | AJ3017: =$AE3017*M3017 -> -2270.9228 | AK3017: =(AE3017)*AA3017/Y3017 -> -5005.017 | AL3017: =AK3017*(1-L3017-M3017) -> -3678.6875 | AM3017: =AE3017-AI3017-AL3017-AJ3017 -> -3739.6602 | AN3017: =Z3017-366 -> 45715 | AO3017: =IF(AND(O3017>Z3017,N3017>AN3017),AE3017,0) -> -10092.99 | AP3017: No claim
A3018: Deletion | B3018: 202509 | C3018: GMC023220100CALDERYS | D3018: CALDERYS INDIA REFRACTORIES LIMITED | E3018: 45901 | F3018: 46265 | G3018: Aruna Ramesh Mohariya | H3018: 362136 | I3018: 27030 | J3018: ACK.4A9F3020250061.2 | K3018: =N3018 -> 45901 | L3018: =IF(K3018>=DATE(2022,4,1),4%,5%) -> 0.04 | M3018: 0.225 | N3018: 45901 | O3018: 46265 | P3018: 45900 | Q3018: =P3018+1 -> 45901 | R3018: 51 | S3018: =VLOOKUP(R3018,SA!$B$3:$C$11,2,1) -> 46-55 | T3018: Female | U3018: Mother | V3018: -400000 | W3018: =IF(U3018="self",V3018,0) -> 0 | X3018: =IF(U3018="self",-1,0) -> 0 | Y3018: =O3018-Q3018+1 -> 365 | Z3018: =$Z$1 -> 46081 | AA3018: =IF(MIN((Z3018-Q3018)+1,Y3018)<0,0,MIN((Z3018-Q3018)+1,Y3018)) -> 181 | AB3018: Maharashtra | AC3018: =AE3018+AF3018+AG3018+AH3018 -> -8108.2166 | AD3018: -1 | AE3018: =-INDEX(SA!$C$2:$G$11,MATCH(Details!S3018,SA!$C$2:$C$11,0),MATCH(-Details!V3018,SA!$C$2:$G$2,0))*Y3018/(F3018-E3018+1) -> -6871.37 | AF3018: =IF(AB3018="Karnataka",AE3018*9%,0) -> 0 | AG3018: =IF(AB3018="Karnataka",AE3018*9%,0) -> 0 | AH3018: =IF(AF3018+AG3018>0,0,AE3018*18%) -> -1236.8466 | AI3018: =AE3018*L3018 -> -274.8548 | AJ3018: =$AE3018*M3018 -> -1546.0583 | AK3018: =(AE3018)*AA3018/Y3018 -> -3407.4465 | AL3018: =AK3018*(1-L3018-M3018) -> -2504.4732 | AM3018: =AE3018-AI3018-AL3018-AJ3018 -> -2545.9838 | AN3018: =Z3018-366 -> 45715 | AO3018: =IF(AND(O3018>Z3018,N3018>AN3018),AE3018,0) -> -6871.37 | AP3018: No claim
A3019: Deletion | B3019: 202509 | C3019: GMC023220100CALDERYS | D3019: CALDERYS INDIA REFRACTORIES LIMITED | E3019: 45901 | F3019: 46265 | G3019: Shubham Ramesh Mohariya | H3019: 362136 | I3019: 35778 | J3019: ACK.4A9F3020250061.3 | K3019: =N3019 -> 45901 | L3019: =IF(K3019>=DATE(2022,4,1),4%,5%) -> 0.04 | M3019: 0.225 | N3019: 45901 | O3019: 46265 | P3019: 45900 | Q3019: =P3019+1 -> 45901 | R3019: 27 | S3019: =VLOOKUP(R3019,SA!$B$3:$C$11,2,1) -> 26-35 | T3019: Male | U3019: Self | V3019: -400000 | W3019: =IF(U3019="self",V3019,0) -> -400000 | X3019: =IF(U3019="self",-1,0) -> -1 | Y3019: =O3019-Q3019+1 -> 365 | Z3019: =$Z$1 -> 46081 | AA3019: =IF(MIN((Z3019-Q3019)+1,Y3019)<0,0,MIN((Z3019-Q3019)+1,Y3019)) -> 181 | AB3019: Maharashtra | AC3019: =AE3019+AF3019+AG3019+AH3019 -> -4533.029 | AD3019: -1 | AE3019: =-INDEX(SA!$C$2:$G$11,MATCH(Details!S3019,SA!$C$2:$C$11,0),MATCH(-Details!V3019,SA!$C$2:$G$2,0))*Y3019/(F3019-E3019+1) -> -3841.55 | AF3019: =IF(AB3019="Karnataka",AE3019*9%,0) -> 0 | AG3019: =IF(AB3019="Karnataka",AE3019*9%,0) -> 0 | AH3019: =IF(AF3019+AG3019>0,0,AE3019*18%) -> -691.479 | AI3019: =AE3019*L3019 -> -153.662 | AJ3019: =$AE3019*M3019 -> -864.34875 | AK3019: =(AE3019)*AA3019/Y3019 -> -1904.9878 | AL3019: =AK3019*(1-L3019-M3019) -> -1400.166 | AM3019: =AE3019-AI3019-AL3019-AJ3019 -> -1423.3732 | AN3019: =Z3019-366 -> 45715 | AO3019: =IF(AND(O3019>Z3019,N3019>AN3019),AE3019,0) -> -3841.55 | AP3019: No claim
A3020: Deletion | B3020: 202509 | C3020: GMC023220100CALDERYS | D3020: CALDERYS INDIA REFRACTORIES LIMITED | E3020: 45901 | F3020: 46265 | G3020: Patel Kamleshbhai Chimanlal | H3020: 652248 | I3020: 25097 | J3020: ACK.4A9F3020250356.1 | K3020: =N3020 -> 45901 | L3020: =IF(K3020>=DATE(2022,4,1),4%,5%) -> 0.04 | M3020: 0.225 | N3020: 45901 | O3020: 46265 | P3020: 45900 | Q3020: =P3020+1 -> 45901 | R3020: 56 | S3020: =VLOOKUP(R3020,SA!$B$3:$C$11,2,1) -> 56-65 | T3020: Male | U3020: Father | V3020: -300000 | W3020: =IF(U3020="self",V3020,0) -> 0 | X3020: =IF(U3020="self",-1,0) -> 0 | Y3020: =O3020-Q3020+1 -> 365 | Z3020: =$Z$1 -> 46081 | AA3020: =IF(MIN((Z3020-Q3020)+1,Y3020)<0,0,MIN((Z3020-Q3020)+1,Y3020)) -> 181 | AB3020: Maharashtra | AC3020: =AE3020+AF3020+AG3020+AH3020 -> -10831.751 | AD3020: -1 | AE3020: =-INDEX(SA!$C$2:$G$11,MATCH(Details!S3020,SA!$C$2:$C$11,0),MATCH(-Details!V3020,SA!$C$2:$G$2,0))*Y3020/(F3020-E3020+1) -> -9179.45 | AF3020: =IF(AB3020="Karnataka",AE3020*9%,0) -> 0 | AG3020: =IF(AB3020="Karnataka",AE3020*9%,0) -> 0 | AH3020: =IF(AF3020+AG3020>0,0,AE3020*18%) -> -1652.301 | AI3020: =AE3020*L3020 -> -367.178 | AJ3020: =$AE3020*M3020 -> -2065.3763 | AK3020: =(AE3020)*AA3020/Y3020 -> -4552.0012 | AL3020: =AK3020*(1-L3020-M3020) -> -3345.7209 | AM3020: =AE3020-AI3020-AL3020-AJ3020 -> -3401.1748 | AN3020: =Z3020-366 -> 45715 | AO3020: =IF(AND(O3020>Z3020,N3020>AN3020),AE3020,0) -> -9179.45 | AP3020: No claim
A3021: Deletion | B3021: 202509 | C3021: GMC023220100CALDERYS | D3021: CALDERYS INDIA REFRACTORIES LIMITED | E3021: 45901 | F3021: 46265 | G3021: Patel Krish Vishalbhai | H3021: 652248 | I3021: 44277 | J3021: ACK.4A9F3020250356.2 | K3021: =N3021 -> 45901 | L3021: =IF(K3021>=DATE(2022,4,1),4%,5%) -> 0.04 | M3021: 0.225 | N3021: 45901 | O3021: 46265 | P3021: 45900 | Q3021: =P3021+1 -> 45901 | R3021: 4 | S3021: =VLOOKUP(R3021,SA!$B$3:$C$11,2,1) -> 0-25 | T3021: Male | U3021: Son | V3021: -300000 | W3021: =IF(U3021="self",V3021,0) -> 0 | X3021: =IF(U3021="self",-1,0) -> 0 | Y3021: =O3021-Q3021+1 -> 365 | Z3021: =$Z$1 -> 46081 | AA3021: =IF(MIN((Z3021-Q3021)+1,Y3021)<0,0,MIN((Z3021-Q3021)+1,Y3021)) -> 181 | AB3021: Maharashtra | AC3021: =AE3021+AF3021+AG3021+AH3021 -> -3690.3792 | AD3021: -1 | AE3021: =-INDEX(SA!$C$2:$G$11,MATCH(Details!S3021,SA!$C$2:$C$11,0),MATCH(-Details!V3021,SA!$C$2:$G$2,0))*Y3021/(F3021-E3021+1) -> -3127.44 | AF3021: =IF(AB3021="Karnataka",AE3021*9%,0) -> 0 | AG3021: =IF(AB3021="Karnataka",AE3021*9%,0) -> 0 | AH3021: =IF(AF3021+AG3021>0,0,AE3021*18%) -> -562.9392 | AI3021: =AE3021*L3021 -> -125.0976 | AJ3021: =$AE3021*M3021 -> -703.674 | AK3021: =(AE3021)*AA3021/Y3021 -> -1550.8675 | AL3021: =AK3021*(1-L3021-M3021) -> -1139.8876 | AM3021: =AE3021-AI3021-AL3021-AJ3021 -> -1158.7808 | AN3021: =Z3021-366 -> 45715 | AO3021: =IF(AND(O3021>Z3021,N3021>AN3021),AE3021,0) -> -3127.44 | AP3021: No claim
A3022: Deletion | B3022: 202509 | C3022: GMC023220100CALDERYS | D3022: CALDERYS INDIA REFRACTORIES LIMITED | E3022: 45901 | F3022: 46265 | G3022: Patel Dimpal Vishalbhai | H3022: 652248 | I3022: 36664 | J3022: ACK.4A9F3020250356.3 | K3022: =N3022 -> 45901 | L3022: =IF(K3022>=DATE(2022,4,1),4%,5%) -> 0.04 | M3022: 0.225 | N3022: 45901 | O3022: 46265 | P3022: 45900 | Q3022: =P3022+1 -> 45901 | R3022: 25 | S3022: =VLOOKUP(R3022,SA!$B$3:$C$11,2,1) -> 0-25 | T3022: Female | U3022: Spouse | V3022: -300000 | W3022: =IF(U3022="self",V3022,0) -> 0 | X3022: =IF(U3022="self",-1,0) -> 0 | Y3022: =O3022-Q3022+1 -> 365 | Z3022: =$Z$1 -> 46081 | AA3022: =IF(MIN((Z3022-Q3022)+1,Y3022)<0,0,MIN((Z3022-Q3022)+1,Y3022)) -> 181 | AB3022: Maharashtra | AC3022: =AE3022+AF3022+AG3022+AH3022 -> -3690.3792 | AD3022: -1 | AE3022: =-INDEX(SA!$C$2:$G$11,MATCH(Details!S3022,SA!$C$2:$C$11,0),MATCH(-Details!V3022,SA!$C$2:$G$2,0))*Y3022/(F3022-E3022+1) -> -3127.44 | AF3022: =IF(AB3022="Karnataka",AE3022*9%,0) -> 0 | AG3022: =IF(AB3022="Karnataka",AE3022*9%,0) -> 0 | AH3022: =IF(AF3022+AG3022>0,0,AE3022*18%) -> -562.9392 | AI3022: =AE3022*L3022 -> -125.0976 | AJ3022: =$AE3022*M3022 -> -703.674 | AK3022: =(AE3022)*AA3022/Y3022 -> -1550.8675 | AL3022: =AK3022*(1-L3022-M3022) -> -1139.8876 | AM3022: =AE3022-AI3022-AL3022-AJ3022 -> -1158.7808 | AN3022: =Z3022-366 -> 45715 | AO3022: =IF(AND(O3022>Z3022,N3022>AN3022),AE3022,0) -> -3127.44 | AP3022: No claim
A3023: Deletion | B3023: 202509 | C3023: GMC023220100CALDERYS | D3023: CALDERYS INDIA REFRACTORIES LIMITED | E3023: 45901 | F3023: 46265 | G3023: Patel Vishal Kamleshbhai | H3023: 652248 | I3023: 34149 | J3023: ACK.4A9F3020250356.4 | K3023: =N3023 -> 45901 | L3023: =IF(K3023>=DATE(2022,4,1),4%,5%) -> 0.04 | M3023: 0.225 | N3023: 45901 | O3023: 46265 | P3023: 45900 | Q3023: =P3023+1 -> 45901 | R3023: 32 | S3023: =VLOOKUP(R3023,SA!$B$3:$C$11,2,1) -> 26-35 | T3023: Male | U3023: Self | V3023: -300000 | W3023: =IF(U3023="self",V3023,0) -> -300000 | X3023: =IF(U3023="self",-1,0) -> -1 | Y3023: =O3023-Q3023+1 -> 365 | Z3023: =$Z$1 -> 46081 | AA3023: =IF(MIN((Z3023-Q3023)+1,Y3023)<0,0,MIN((Z3023-Q3023)+1,Y3023)) -> 181 | AB3023: Maharashtra | AC3023: =AE3023+AF3023+AG3023+AH3023 -> -4124.4658 | AD3023: -1 | AE3023: =-INDEX(SA!$C$2:$G$11,MATCH(Details!S3023,SA!$C$2:$C$11,0),MATCH(-Details!V3023,SA!$C$2:$G$2,0))*Y3023/(F3023-E3023+1) -> -3495.31 | AF3023: =IF(AB3023="Karnataka",AE3023*9%,0) -> 0 | AG3023: =IF(AB3023="Karnataka",AE3023*9%,0) -> 0 | AH3023: =IF(AF3023+AG3023>0,0,AE3023*18%) -> -629.1558 | AI3023: =AE3023*L3023 -> -139.8124 | AJ3023: =$AE3023*M3023 -> -786.44475 | AK3023: =(AE3023)*AA3023/Y3023 -> -1733.2907 | AL3023: =AK3023*(1-L3023-M3023) -> -1273.9687 | AM3023: =AE3023-AI3023-AL3023-AJ3023 -> -1295.0842 | AN3023: =Z3023-366 -> 45715 | AO3023: =IF(AND(O3023>Z3023,N3023>AN3023),AE3023,0) -> -3495.31 | AP3023: No claim
... A3057: Deletion | B3057: 202509 | C3057: GMC023220100CALDERYS | D3057: CALDERYS INDIA REFRACTORIES LIMITED | E3057: 45901 | F3057: 46265 | G3057: Sandeep | H3057: 550062 | I3057: 36347 | J3057: ACK.4A9F3020250667.1 | K3057: =N3057 -> 45901 | L3057: =IF(K3057>=DATE(2022,4,1),4%,5%) -> 0.04 | M3057: 0.225 | N3057: 45901 | O3057: 46265 | P3057: 45900 | Q3057: =P3057+1 -> 45901 | R3057: 26 | S3057: =VLOOKUP(R3057,SA!$B$3:$C$11,2,1) -> 26-35 | T3057: Male | U3057: Son | V3057: -300000 | W3057: =IF(U3057="self",V3057,0) -> 0 | X3057: =IF(U3057="self",-1,0) -> 0 | Y3057: =O3057-Q3057+1 -> 365 | Z3057: =$Z$1 -> 46081 | AA3057: =IF(MIN((Z3057-Q3057)+1,Y3057)<0,0,MIN((Z3057-Q3057)+1,Y3057)) -> 181 | AB3057: Maharashtra | AC3057: =AE3057+AF3057+AG3057+AH3057 -> -4124.4658 | AD3057: -1 | AE3057: =-INDEX(SA!$C$2:$G$11,MATCH(Details!S3057,SA!$C$2:$C$11,0),MATCH(-Details!V3057,SA!$C$2:$G$2,0))*Y3057/(F3057-E3057+1) -> -3495.31 | AF3057: =IF(AB3057="Karnataka",AE3057*9%,0) -> 0 | AG3057: =IF(AB3057="Karnataka",AE3057*9%,0) -> 0 | AH3057: =IF(AF3057+AG3057>0,0,AE3057*18%) -> -629.1558 | AI3057: =AE3057*L3057 -> -139.8124 | AJ3057: =$AE3057*M3057 -> -786.44475 | AK3057: =(AE3057)*AA3057/Y3057 -> -1733.2907 | AL3057: =AK3057*(1-L3057-M3057) -> -1273.9687 | AM3057: =AE3057-AI3057-AL3057-AJ3057 -> -1295.0842 | AN3057: =Z3057-366 -> 45715 | AO3057: =IF(AND(O3057>Z3057,N3057>AN3057),AE3057,0) -> -3495.31 | AP3057: No claim
A3058: SI Enhancement | B3058: 202510 | C3058: GMC023220100CALDERYS | D3058: CALDERYS INDIA REFRACTORIES LIMITED | E3058: 45901 | F3058: 46265 | G3058: Chhuttan Lal Laharia | H3058: 60697 | I3058: 18048 | J3058: ACK.4A9F3020250284.3 | K3058: =N3058 -> 45901 | L3058: =IF(K3058>=DATE(2022,4,1),4%,5%) -> 0.04 | M3058: 0.225 | N3058: 45901 | O3058: 46265 | R3058: 86 | S3058: =VLOOKUP(R3058,SA!$B$3:$C$11,2,1) -> 81-100 | T3058: Male | U3058: Father | V3058: 600000 | W3058: 0 | X3058: 0 | Y3058: =O3058-N3058+1 -> 365 | Z3058: =$Z$1 -> 46081 | AA3058: =IF(MIN((Z3058-N3058)+1,Y3058)<0,0,MIN((Z3058-N3058)+1,Y3058)) -> 181 | AB3058: Maharashtra | AC3058: =AE3058+AF3058+AG3058+AH3058 -> 3012.2332 | AD3058: 0 | AE3058: 2552.74 | AF3058: =IF(AB3058="Karnataka",AE3058*9%,0) -> 0 | AG3058: =IF(AB3058="Karnataka",AE3058*9%,0) -> 0 | AH3058: =IF(AF3058+AG3058>0,0,AE3058*18%) -> 459.4932 | AI3058: =AE3058*L3058 -> 102.1096 | AJ3058: =$AE3058*M3058 -> 574.3665 | AK3058: =(AE3058)*AA3058/Y3058 -> 1265.8793 | AL3058: =AK3058*(1-L3058-M3058) -> 930.42128 | AM3058: =AE3058-AI3058-AL3058-AJ3058 -> 945.84262 | AN3058: =Z3058-366 -> 45715 | AO3058: =IF(AND(O3058>Z3058,N3058>AN3058),AE3058,0) -> 2552.74
A3059: SI Enhancement | B3059: 202510 | C3059: GMC023220100CALDERYS | D3059: CALDERYS INDIA REFRACTORIES LIMITED | E3059: 45901 | F3059: 46265 | G3059: Suman Pandurang Kadu | H3059: 362031 | I3059: 20626 | J3059: ACK.4A9F3020250011.6 | K3059: =N3059 -> 45901 | L3059: =IF(K3059>=DATE(2022,4,1),4%,5%) -> 0.04 | M3059: 0.225 | N3059: 45901 | O3059: 46265 | R3059: 74 | S3059: =VLOOKUP(R3059,SA!$B$3:$C$11,2,1) -> 71-75 | T3059: Female | U3059: Mother | V3059: 300000 | W3059: 0 | X3059: 0 | Y3059: =O3059-N3059+1 -> 365 | Z3059: =$Z$1 -> 46081 | AA3059: =IF(MIN((Z3059-N3059)+1,Y3059)<0,0,MIN((Z3059-N3059)+1,Y3059)) -> 181 | AB3059: Maharashtra | AC3059: =AE3059+AF3059+AG3059+AH3059 -> 4152.243 | AD3059: 0 | AE3059: 3518.85 | AF3059: =IF(AB3059="Karnataka",AE3059*9%,0) -> 0 | AG3059: =IF(AB3059="Karnataka",AE3059*9%,0) -> 0 | AH3059: =IF(AF3059+AG3059>0,0,AE3059*18%) -> 633.393 | AI3059: =AE3059*L3059 -> 140.754 | AJ3059: =$AE3059*M3059 -> 791.74125 | AK3059: =(AE3059)*AA3059/Y3059 -> 1744.964 | AL3059: =AK3059*(1-L3059-M3059) -> 1282.5485 | AM3059: =AE3059-AI3059-AL3059-AJ3059 -> 1303.8062 | AN3059: =Z3059-366 -> 45715 | AO3059: =IF(AND(O3059>Z3059,N3059>AN3059),AE3059,0) -> 3518.85
A3060: SI Enhancement | B3060: 202510 | C3060: GMC023220100CALDERYS | D3060: CALDERYS INDIA REFRACTORIES LIMITED | E3060: 45901 | F3060: 46265 | G3060: Laxmi viththal Ambakhaye | H3060: 362112 | I3060: 23788 | J3060: ACK.4A9F3020250046.5 | K3060: =N3060 -> 45901 | L3060: =IF(K3060>=DATE(2022,4,1),4%,5%) -> 0.04 | M3060: 0.225 | N3060: 45901 | O3060: 46265 | R3060: 55 | S3060: =VLOOKUP(R3060,SA!$B$3:$C$11,2,1) -> 46-55 | T3060: Female | U3060: Mother | V3060: 300000 | W3060: 0 | X3060: 0 | Y3060: =O3060-N3060+1 -> 365 | Z3060: =$Z$1 -> 46081 | AA3060: =IF(MIN((Z3060-N3060)+1,Y3060)<0,0,MIN((Z3060-N3060)+1,Y3060)) -> 181 | AB3060: Maharashtra | AC3060: =AE3060+AF3060+AG3060+AH3060 -> -3458.285 | AD3060: 0 | AE3060: -2930.75 | AF3060: =IF(AB3060="Karnataka",AE3060*9%,0) -> 0 | AG3060: =IF(AB3060="Karnataka",AE3060*9%,0) -> 0 | AH3060: =IF(AF3060+AG3060>0,0,AE3060*18%) -> -527.535 | AI3060: =AE3060*L3060 -> -117.23 | AJ3060: =$AE3060*M3060 -> -659.41875 | AK3060: =(AE3060)*AA3060/Y3060 -> -1453.3308 | AL3060: =AK3060*(1-L3060-M3060) -> -1068.1982 | AM3060: =AE3060-AI3060-AL3060-AJ3060 -> -1085.9031 | AN3060: =Z3060-366 -> 45715 | AO3060: =IF(AND(O3060>Z3060,N3060>AN3060),AE3060,0) -> -2930.75
A3061: SI Enhancement | B3061: 202510 | C3061: GMC023220100CALDERYS | D3061: CALDERYS INDIA REFRACTORIES LIMITED | E3061: 45901 | F3061: 46265 | G3061: Layanabai Chandankhede | H3061: 362115 | I3061: 20677 | J3061: ACK.4A9F3020250048.1 | K3061: =N3061 -> 45901 | L3061: =IF(K3061>=DATE(2022,4,1),4%,5%) -> 0.04 | M3061: 0.225 | N3061: 45901 | O3061: 46265 | R3061: 73 | S3061: =VLOOKUP(R3061,SA!$B$3:$C$11,2,1) -> 71-75 | T3061: Female | U3061: Mother | V3061: 300000 | W3061: 0 | X3061: 0 | Y3061: =O3061-N3061+1 -> 365 | Z3061: =$Z$1 -> 46081 | AA3061: =IF(MIN((Z3061-N3061)+1,Y3061)<0,0,MIN((Z3061-N3061)+1,Y3061)) -> 181 | AB3061: Maharashtra | AC3061: =AE3061+AF3061+AG3061+AH3061 -> 4152.243 | AD3061: 0 | AE3061: 3518.85 | AF3061: =IF(AB3061="Karnataka",AE3061*9%,0) -> 0 | AG3061: =IF(AB3061="Karnataka",AE3061*9%,0) -> 0 | AH3061: =IF(AF3061+AG3061>0,0,AE3061*18%) -> 633.393 | AI3061: =AE3061*L3061 -> 140.754 | AJ3061: =$AE3061*M3061 -> 791.74125 | AK3061: =(AE3061)*AA3061/Y3061 -> 1744.964 | AL3061: =AK3061*(1-L3061-M3061) -> 1282.5485 | AM3061: =AE3061-AI3061-AL3061-AJ3061 -> 1303.8062 | AN3061: =Z3061-366 -> 45715 | AO3061: =IF(AND(O3061>Z3061,N3061>AN3061),AE3061,0) -> 3518.85
A3062: SI Enhancement | B3062: 202510 | C3062: GMC023220100CALDERYS | D3062: CALDERYS INDIA REFRACTORIES LIMITED | E3062: 45901 | F3062: 46265 | G3062: Rekhabai Chandrashekhar Gourkar | H3062: 362120 | I3062: 24047 | J3062: ACK.4A9F3020250052.1 | K3062: =N3062 -> 45901 | L3062: =IF(K3062>=DATE(2022,4,1),4%,5%) -> 0.04 | M3062: 0.225 | N3062: 45901 | O3062: 46265 | R3062: 54 | S3062: =VLOOKUP(R3062,SA!$B$3:$C$11,2,1) -> 46-55 | T3062: Female | U3062: Mother | V3062: 300000 | W3062: 0 | X3062: 0 | Y3062: =O3062-N3062+1 -> 365 | Z3062: =$Z$1 -> 46081 | AA3062: =IF(MIN((Z3062-N3062)+1,Y3062)<0,0,MIN((Z3062-N3062)+1,Y3062)) -> 181 | AB3062: Maharashtra | AC3062: =AE3062+AF3062+AG3062+AH3062 -> -3458.285 | AD3062: 0 | AE3062: -2930.75 | AF3062: =IF(AB3062="Karnataka",AE3062*9%,0) -> 0 | AG3062: =IF(AB3062="Karnataka",AE3062*9%,0) -> 0 | AH3062: =IF(AF3062+AG3062>0,0,AE3062*18%) -> -527.535 | AI3062: =AE3062*L3062 -> -117.23 | AJ3062: =$AE3062*M3062 -> -659.41875 | AK3062: =(AE3062)*AA3062/Y3062 -> -1453.3308 | AL3062: =AK3062*(1-L3062-M3062) -> -1068.1982 | AM3062: =AE3062-AI3062-AL3062-AJ3062 -> -1085.9031 | AN3062: =Z3062-366 -> 45715 | AO3062: =IF(AND(O3062>Z3062,N3062>AN3062),AE3062,0) -> -2930.75
A3063: SI Enhancement | B3063: 202510 | C3063: GMC023220100CALDERYS | D3063: CALDERYS INDIA REFRACTORIES LIMITED | E3063: 45901 | F3063: 46265 | G3063: Munni | H3063: 550003 | I3063: 24023 | J3063: ACK.4A9F3020250237.1 | K3063: =N3063 -> 45901 | L3063: =IF(K3063>=DATE(2022,4,1),4%,5%) -> 0.04 | M3063: 0.225 | N3063: 45901 | O3063: 46265 | R3063: 55 | S3063: =VLOOKUP(R3063,SA!$B$3:$C$11,2,1) -> 46-55 | T3063: Female | U3063: Spouse | V3063: 400000 | W3063: 0 | X3063: 0 | Y3063: =O3063-N3063+1 -> 365 | Z3063: =$Z$1 -> 46081 | AA3063: =IF(MIN((Z3063-N3063)+1,Y3063)<0,0,MIN((Z3063-N3063)+1,Y3063)) -> 181 | AB3063: Maharashtra | AC3063: =AE3063+AF3063+AG3063+AH3063 -> -3801.5116 | AD3063: 0 | AE3063: -3221.62 | AF3063: =IF(AB3063="Karnataka",AE3063*9%,0) -> 0 | AG3063: =IF(AB3063="Karnataka",AE3063*9%,0) -> 0 | AH3063: =IF(AF3063+AG3063>0,0,AE3063*18%) -> -579.8916 | AI3063: =AE3063*L3063 -> -128.8648 | AJ3063: =$AE3063*M3063 -> -724.8645 | AK3063: =(AE3063)*AA3063/Y3063 -> -1597.5705 | AL3063: =AK3063*(1-L3063-M3063) -> -1174.2143 | AM3063: =AE3063-AI3063-AL3063-AJ3063 -> -1193.6764 | AN3063: =Z3063-366 -> 45715 | AO3063: =IF(AND(O3063>Z3063,N3063>AN3063),AE3063,0) -> -3221.62
A3064: Valid | B3064: 202510 | C3064: GMC023220100CALDERYS | D3064: CALDERYS INDIA REFRACTORIES LIMITED | E3064: 45901 | F3064: 46265 | G3064: ADVAIT ISHWARKUMAR BHUJADE | H3064: 42163 | I3064: 45424 | J3064: ACK.4A9F3020250100.4 | K3064: =N3064 -> 45901 | L3064: =IF(K3064>=DATE(2022,4,1),4%,5%) -> 0.04 | M3064: 0.225 | N3064: 45901 | O3064: 46265 | R3064: 1 | S3064: =VLOOKUP(R3064,SA!$B$3:$C$11,2,1) -> 0-25 | T3064: MALE | U3064: SON | V3064: 500000 | W3064: =IF(U3064="self",V3064,0) -> 0 | X3064: =IF(U3064="self",1,0) -> 0 | Y3064: =O3064-N3064+1 -> 365 | Z3064: =$Z$1 -> 46081 | AA3064: =IF(MIN((Z3064-N3064)+1,Y3064)<0,0,MIN((Z3064-N3064)+1,Y3064)) -> 181 | AB3064: Maharashtra | AC3064: =AE3064+AF3064+AG3064+AH3064 -> 4448.2106 | AD3064: 1 | AE3064: =INDEX(SA!$C$2:$G$11,MATCH(Details!S3064,SA!$C$2:$C$11,0),MATCH(Details!V3064,SA!$C$2:$G$2,0))*Y3064/(F3064-E3064+1) -> 3769.67 | AF3064: =IF(AB3064="Karnataka",AE3064*9%,0) -> 0 | AG3064: =IF(AB3064="Karnataka",AE3064*9%,0) -> 0 | AH3064: =IF(AF3064+AG3064>0,0,AE3064*18%) -> 678.5406 | AI3064: =AE3064*L3064 -> 150.7868 | AJ3064: =$AE3064*M3064 -> 848.17575 | AK3064: =(AE3064)*AA3064/Y3064 -> 1869.3432 | AL3064: =AK3064*(1-L3064-M3064) -> 1373.9673 | AM3064: =AE3064-AI3064-AL3064-AJ3064 -> 1396.7402 | AN3064: =Z3064-366 -> 45715 | AO3064: =IF(AND(O3064>Z3064,N3064>AN3064),AE3064,0) -> 3769.67
A3065: Valid | B3065: 202510 | C3065: GMC023220100CALDERYS | D3065: CALDERYS INDIA REFRACTORIES LIMITED | E3065: 45901 | F3065: 46265 | G3065: Charu Parmar | H3065: 42256 | I3065: 32997 | J3065: ACK.4A9F3020250139.4 | K3065: =N3065 -> 45901 | L3065: =IF(K3065>=DATE(2022,4,1),4%,5%) -> 0.04 | M3065: 0.225 | N3065: 45901 | O3065: 46265 | R3065: 35 | S3065: =VLOOKUP(R3065,SA!$B$3:$C$11,2,1) -> 26-35 | T3065: FEMALE | U3065: Spouse | V3065: 500000 | W3065: =IF(U3065="self",V3065,0) -> 0 | X3065: =IF(U3065="self",1,0) -> 0 | Y3065: =O3065-N3065+1 -> 365 | Z3065: =$Z$1 -> 46081 | AA3065: =IF(MIN((Z3065-N3065)+1,Y3065)<0,0,MIN((Z3065-N3065)+1,Y3065)) -> 181 | AB3065: Maharashtra | AC3065: =AE3065+AF3065+AG3065+AH3065 -> 4986.3142 | AD3065: 1 | AE3065: =INDEX(SA!$C$2:$G$11,MATCH(Details!S3065,SA!$C$2:$C$11,0),MATCH(Details!V3065,SA!$C$2:$G$2,0))*Y3065/(F3065-E3065+1) -> 4225.69 | AF3065: =IF(AB3065="Karnataka",AE3065*9%,0) -> 0 | AG3065: =IF(AB3065="Karnataka",AE3065*9%,0) -> 0 | AH3065: =IF(AF3065+AG3065>0,0,AE3065*18%) -> 760.6242 | AI3065: =AE3065*L3065 -> 169.0276 | AJ3065: =$AE3065*M3065 -> 950.78025 | AK3065: =(AE3065)*AA3065/Y3065 -> 2095.4792 | AL3065: =AK3065*(1-L3065-M3065) -> 1540.1772 | AM3065: =AE3065-AI3065-AL3065-AJ3065 -> 1565.705 | AN3065: =Z3065-366 -> 45715 | AO3065: =IF(AND(O3065>Z3065,N3065>AN3065),AE3065,0) -> 4225.69
A3066: Valid | B3066: 202510 | C3066: GMC023220100CALDERYS | D3066: CALDERYS INDIA REFRACTORIES LIMITED | E3066: 45901 | F3066: 46265 | G3066: SIDDHI JYOTI RAVINDRA CHAVHAN | H3066: 42292 | I3066: 45798 | J3066: ACK.4A9F3020250165.6 | K3066: =N3066 -> 45901 | L3066: =IF(K3066>=DATE(2022,4,1),4%,5%) -> 0.04 | M3066: 0.225 | N3066: 45901 | O3066: 46265 | R3066: 0 | S3066: =VLOOKUP(R3066,SA!$B$3:$C$11,2,1) -> 0-25 | T3066: FEMALE | U3066: DAUGHTER | V3066: 400000 | W3066: =IF(U3066="self",V3066,0) -> 0 | X3066: =IF(U3066="self",1,0) -> 0 | Y3066: =O3066-N3066+1 -> 365 | Z3066: =$Z$1 -> 46081 | AA3066: =IF(MIN((Z3066-N3066)+1,Y3066)<0,0,MIN((Z3066-N3066)+1,Y3066)) -> 181 | AB3066: Maharashtra | AC3066: =AE3066+AF3066+AG3066+AH3066 -> 4043.8364 | AD3066: 1 | AE3066: =INDEX(SA!$C$2:$G$11,MATCH(Details!S3066,SA!$C$2:$C$11,0),MATCH(Details!V3066,SA!$C$2:$G$2,0))*Y3066/(F3066-E3066+1) -> 3426.98 | AF3066: =IF(AB3066="Karnataka",AE3066*9%,0) -> 0 | AG3066: =IF(AB3066="Karnataka",AE3066*9%,0) -> 0 | AH3066: =IF(AF3066+AG3066>0,0,AE3066*18%) -> 616.8564 | AI3066: =AE3066*L3066 -> 137.0792 | AJ3066: =$AE3066*M3066 -> 771.0705 | AK3066: =(AE3066)*AA3066/Y3066 -> 1699.4065 | AL3066: =AK3066*(1-L3066-M3066) -> 1249.0638 | AM3066: =AE3066-AI3066-AL3066-AJ3066 -> 1269.7665 | AN3066: =Z3066-366 -> 45715 | AO3066: =IF(AND(O3066>Z3066,N3066>AN3066),AE3066,0) -> 3426.98
A3067: Valid | B3067: 202510 | C3067: GMC023220100CALDERYS | D3067: CALDERYS INDIA REFRACTORIES LIMITED | E3067: 45901 | F3067: 46265 | G3067: Amiya Roy | H3067: 42297 | I3067: 34399 | J3067: ACK.4A9F3020250170.4 | K3067: =N3067 -> 45901 | L3067: =IF(K3067>=DATE(2022,4,1),4%,5%) -> 0.04 | M3067: 0.225 | N3067: 45901 | O3067: 46265 | R3067: 31 | S3067: =VLOOKUP(R3067,SA!$B$3:$C$11,2,1) -> 26-35 | T3067: MALE | U3067: Spouse | V3067: 400000 | W3067: =IF(U3067="self",V3067,0) -> 0 | X3067: =IF(U3067="self",1,0) -> 0 | Y3067: =O3067-N3067+1 -> 365 | Z3067: =$Z$1 -> 46081 | AA3067: =IF(MIN((Z3067-N3067)+1,Y3067)<0,0,MIN((Z3067-N3067)+1,Y3067)) -> 181 | AB3067: Maharashtra | AC3067: =AE3067+AF3067+AG3067+AH3067 -> 4533.029 | AD3067: 1 | AE3067: =INDEX(SA!$C$2:$G$11,MATCH(Details!S3067,SA!$C$2:$C$11,0),MATCH(Details!V3067,SA!$C$2:$G$2,0))*Y3067/(F3067-E3067+1) -> 3841.55 | AF3067: =IF(AB3067="Karnataka",AE3067*9%,0) -> 0 | AG3067: =IF(AB3067="Karnataka",AE3067*9%,0) -> 0 | AH3067: =IF(AF3067+AG3067>0,0,AE3067*18%) -> 691.479 | AI3067: =AE3067*L3067 -> 153.662 | AJ3067: =$AE3067*M3067 -> 864.34875 | AK3067: =(AE3067)*AA3067/Y3067 -> 1904.9878 | AL3067: =AK3067*(1-L3067-M3067) -> 1400.166 | AM3067: =AE3067-AI3067-AL3067-AJ3067 -> 1423.3732 | AN3067: =Z3067-366 -> 45715 | AO3067: =IF(AND(O3067>Z3067,N3067>AN3067),AE3067,0) -> 3841.55
A3068: Valid | B3068: 202510 | C3068: GMC023220100CALDERYS | D3068: CALDERYS INDIA REFRACTORIES LIMITED | E3068: 45901 | F3068: 46265 | G3068: Hiba Fatima Dilavarhusen Tai | H3068: 42345 | I3068: 45921 | J3068: ACK.4A9F3020250203.5 | K3068: =N3068 -> 45921 | L3068: =IF(K3068>=DATE(2022,4,1),4%,5%) -> 0.04 | M3068: 0.225 | N3068: 45921 | O3068: 46265 | R3068: 0 | S3068: =VLOOKUP(R3068,SA!$B$3:$C$11,2,1) -> 0-25 | T3068: FEMALE | U3068: DAUGHTER | V3068: 400000 | W3068: =IF(U3068="self",V3068,0) -> 0 | X3068: =IF(U3068="self",1,0) -> 0 | Y3068: =O3068-N3068+1 -> 345 | Z3068: =$Z$1 -> 46081 | AA3068: =IF(MIN((Z3068-N3068)+1,Y3068)<0,0,MIN((Z3068-N3068)+1,Y3068)) -> 161 | AB3068: Maharashtra | AC3068: =AE3068+AF3068+AG3068+AH3068 -> 3822.2563 | AD3068: 1 | AE3068: =INDEX(SA!$C$2:$G$11,MATCH(Details!S3068,SA!$C$2:$C$11,0),MATCH(Details!V3068,SA!$C$2:$G$2,0))*Y3068/(F3068-E3068+1) -> 3239.2003 | AF3068: =IF(AB3068="Karnataka",AE3068*9%,0) -> 0 | AG3068: =IF(AB3068="Karnataka",AE3068*9%,0) -> 0 | AH3068: =IF(AF3068+AG3068>0,0,AE3068*18%) -> 583.05605 | AI3068: =AE3068*L3068 -> 129.56801 | AJ3068: =$AE3068*M3068 -> 728.82006 | AK3068: =(AE3068)*AA3068/Y3068 -> 1511.6268 | AL3068: =AK3068*(1-L3068-M3068) -> 1111.0457 | AM3068: =AE3068-AI3068-AL3068-AJ3068 -> 1269.7665 | AN3068: =Z3068-366 -> 45715 | AO3068: =IF(AND(O3068>Z3068,N3068>AN3068),AE3068,0) -> 3239.2003
A3069: Valid | B3069: 202510 | C3069: GMC023220100CALDERYS | D3069: CALDERYS INDIA REFRACTORIES LIMITED | E3069: 45901 | F3069: 46265 | G3069: Shailesh Barman | H3069: 42352 | I3069: 31041 | J3069: ACK.4A9F3020250209.3 | K3069: =N3069 -> 45901 | L3069: =IF(K3069>=DATE(2022,4,1),4%,5%) -> 0.04 | M3069: 0.225 | N3069: 45901 | O3069: 46265 | R3069: 40 | S3069: =VLOOKUP(R3069,SA!$B$3:$C$11,2,1) -> 36-45 | T3069: MALE | U3069: Spouse | V3069: 300000 | W3069: =IF(U3069="self",V3069,0) -> 0 | X3069: =IF(U3069="self",1,0) -> 0 | Y3069: =O3069-N3069+1 -> 365 | Z3069: =$Z$1 -> 46081 | AA3069: =IF(MIN((Z3069-N3069)+1,Y3069)<0,0,MIN((Z3069-N3069)+1,Y3069)) -> 181 | AB3069: Maharashtra | AC3069: =AE3069+AF3069+AG3069+AH3069 -> 5119.5716 | AD3069: 1 | AE3069: =INDEX(SA!$C$2:$G$11,MATCH(Details!S3069,SA!$C$2:$C$11,0),MATCH(Details!V3069,SA!$C$2:$G$2,0))*Y3069/(F3069-E3069+1) -> 4338.62 | AF3069: =IF(AB3069="Karnataka",AE3069*9%,0) -> 0 | AG3069: =IF(AB3069="Karnataka",AE3069*9%,0) -> 0 | AH3069: =IF(AF3069+AG3069>0,0,AE3069*18%) -> 780.9516 | AI3069: =AE3069*L3069 -> 173.5448 | AJ3069: =$AE3069*M3069 -> 976.1895 | AK3069: =(AE3069)*AA3069/Y3069 -> 2151.4801 | AL3069: =AK3069*(1-L3069-M3069) -> 1581.3378 | AM3069: =AE3069-AI3069-AL3069-AJ3069 -> 1607.5479 | AN3069: =Z3069-366 -> 45715 | AO3069: =IF(AND(O3069>Z3069,N3069>AN3069),AE3069,0) -> 4338.62
A3070: Valid | B3070: 202510 | C3070: GMC023220100CALDERYS | D3070: CALDERYS INDIA REFRACTORIES LIMITED | E3070: 45901 | F3070: 46265 | G3070: Tanushree Jana | H3070: 42357 | I3070: 34988 | J3070: ACK.4A9F3020250214.4 | K3070: =N3070 -> 45901 | L3070: =IF(K3070>=DATE(2022,4,1),4%,5%) -> 0.04 | M3070: 0.225 | N3070: 45901 | O3070: 46265 | R3070: 29 | S3070: =VLOOKUP(R3070,SA!$B$3:$C$11,2,1) -> 26-35 | T3070: FEMALE | U3070: Spouse | V3070: 500000 | W3070: =IF(U3070="self",V3070,0) -> 0 | X3070: =IF(U3070="self",1,0) -> 0 | Y3070: =O3070-N3070+1 -> 365 | Z3070: =$Z$1 -> 46081 | AA3070: =IF(MIN((Z3070-N3070)+1,Y3070)<0,0,MIN((Z3070-N3070)+1,Y3070)) -> 181 | AB3070: Maharashtra | AC3070: =AE3070+AF3070+AG3070+AH3070 -> 4986.3142 | AD3070: 1 | AE3070: =INDEX(SA!$C$2:$G$11,MATCH(Details!S3070,SA!$C$2:$C$11,0),MATCH(Details!V3070,SA!$C$2:$G$2,0))*Y3070/(F3070-E3070+1) -> 4225.69 | AF3070: =IF(AB3070="Karnataka",AE3070*9%,0) -> 0 | AG3070: =IF(AB3070="Karnataka",AE3070*9%,0) -> 0 | AH3070: =IF(AF3070+AG3070>0,0,AE3070*18%) -> 760.6242 | AI3070: =AE3070*L3070 -> 169.0276 | AJ3070: =$AE3070*M3070 -> 950.78025 | AK3070: =(AE3070)*AA3070/Y3070 -> 2095.4792 | AL3070: =AK3070*(1-L3070-M3070) -> 1540.1772 | AM3070: =AE3070-AI3070-AL3070-AJ3070 -> 1565.705 | AN3070: =Z3070-366 -> 45715 | AO3070: =IF(AND(O3070>Z3070,N3070>AN3070),AE3070,0) -> 4225.69
A3071: Valid | B3071: 202510 | C3071: GMC023220100CALDERYS | D3071: CALDERYS INDIA REFRACTORIES LIMITED | E3071: 45901 | F3071: 46265 | G3071: ATHARVA TIWARI | H3071: 42369 | I3071: 45895 | J3071: ACK.4A9F3020250225.5 | K3071: =N3071 -> 45901 | L3071: =IF(K3071>=DATE(2022,4,1),4%,5%) -> 0.04 | M3071: 0.225 | N3071: 45901 | O3071: 46265 | R3071: 0 | S3071: =VLOOKUP(R3071,SA!$B$3:$C$11,2,1) -> 0-25 | T3071: MALE | U3071: SON | V3071: 400000 | W3071: =IF(U3071="self",V3071,0) -> 0 | X3071: =IF(U3071="self",1,0) -> 0 | Y3071: =O3071-N3071+1 -> 365 | Z3071: =$Z$1 -> 46081 | AA3071: =IF(MIN((Z3071-N3071)+1,Y3071)<0,0,MIN((Z3071-N3071)+1,Y3071)) -> 181 | AB3071: Maharashtra | AC3071: =AE3071+AF3071+AG3071+AH3071 -> 4043.8364 | AD3071: 1 | AE3071: =INDEX(SA!$C$2:$G$11,MATCH(Details!S3071,SA!$C$2:$C$11,0),MATCH(Details!V3071,SA!$C$2:$G$2,0))*Y3071/(F3071-E3071+1) -> 3426.98 | AF3071: =IF(AB3071="Karnataka",AE3071*9%,0) -> 0 | AG3071: =IF(AB3071="Karnataka",AE3071*9%,0) -> 0 | AH3071: =IF(AF3071+AG3071>0,0,AE3071*18%) -> 616.8564 | AI3071: =AE3071*L3071 -> 137.0792 | AJ3071: =$AE3071*M3071 -> 771.0705 | AK3071: =(AE3071)*AA3071/Y3071 -> 1699.4065 | AL3071: =AK3071*(1-L3071-M3071) -> 1249.0638 | AM3071: =AE3071-AI3071-AL3071-AJ3071 -> 1269.7665 | AN3071: =Z3071-366 -> 45715 | AO3071: =IF(AND(O3071>Z3071,N3071>AN3071),AE3071,0) -> 3426.98
A3072: Valid | B3072: 202510 | C3072: GMC023220100CALDERYS | D3072: CALDERYS INDIA REFRACTORIES LIMITED | E3072: 45901 | F3072: 46265 | G3072: Suresh Prasad Tiwari | H3072: 42375 | I3072: 18105 | J3072: ACK.4A9F3020250664.8 | K3072: =N3072 -> 45901 | L3072: =IF(K3072>=DATE(2022,4,1),4%,5%) -> 0.04 | M3072: 0.225 | N3072: 45901 | O3072: 46265 | R3072: 76 | S3072: =VLOOKUP(R3072,SA!$B$3:$C$11,2,1) -> 76-80 | T3072: MALE | U3072: FATHER IN LAW | V3072: 500000 | W3072: =IF(U3072="self",V3072,0) -> 0 | X3072: =IF(U3072="self",1,0) -> 0 | Y3072: =O3072-N3072+1 -> 365 | Z3072: =$Z$1 -> 46081 | AA3072: =IF(MIN((Z3072-N3072)+1,Y3072)<0,0,MIN((Z3072-N3072)+1,Y3072)) -> 181 | AB3072: Maharashtra | AC3072: =AE3072+AF3072+AG3072+AH3072 -> 29821.09 | AD3072: 1 | AE3072: =INDEX(SA!$C$2:$G$11,MATCH(Details!S3072,SA!$C$2:$C$11,0),MATCH(Details!V3072,SA!$C$2:$G$2,0))*Y3072/(F3072-E3072+1) -> 25272.11 | AF3072: =IF(AB3072="Karnataka",AE3072*9%,0) -> 0 | AG3072: =IF(AB3072="Karnataka",AE3072*9%,0) -> 0 | AH3072: =IF(AF3072+AG3072>0,0,AE3072*18%) -> 4548.9798 | AI3072: =AE3072*L3072 -> 1010.8844 | AJ3072: =$AE3072*M3072 -> 5686.2248 | AK3072: =(AE3072)*AA3072/Y3072 -> 12532.197 | AL3072: =AK3072*(1-L3072-M3072) -> 9211.1648 | AM3072: =AE3072-AI3072-AL3072-AJ3072 -> 9363.836 | AN3072: =Z3072-366 -> 45715 | AO3072: =IF(AND(O3072>Z3072,N3072>AN3072),AE3072,0) -> 25272.11
A3073: Valid | B3073: 202510 | C3073: GMC023220100CALDERYS | D3073: CALDERYS INDIA REFRACTORIES LIMITED | E3073: 45901 | F3073: 46265 | G3073: Sarla Bai | H3073: 42375 | I3073: 20455 | J3073: ACK.4A9F3020250664.7 | K3073: =N3073 -> 45901 | L3073: =IF(K3073>=DATE(2022,4,1),4%,5%) -> 0.04 | M3073: 0.225 | N3073: 45901 | O3073: 46265 | R3073: 69 | S3073: =VLOOKUP(R3073,SA!$B$3:$C$11,2,1) -> 66-70 | T3073: FEMALE | U3073: MOTHER IN LAW | V3073: 500000 | W3073: =IF(U3073="self",V3073,0) -> 0 | X3073: =IF(U3073="self",1,0) -> 0 | Y3073: =O3073-N3073+1 -> 365 | Z3073: =$Z$1 -> 46081 | AA3073: =IF(MIN((Z3073-N3073)+1,Y3073)<0,0,MIN((Z3073-N3073)+1,Y3073)) -> 181 | AB3073: Maharashtra | AC3073: =AE3073+AF3073+AG3073+AH3073 -> 18713.136 | AD3073: 1 | AE3073: =INDEX(SA!$C$2:$G$11,MATCH(Details!S3073,SA!$C$2:$C$11,0),MATCH(Details!V3073,SA!$C$2:$G$2,0))*Y3073/(F3073-E3073+1) -> 15858.59 | AF3073: =IF(AB3073="Karnataka",AE3073*9%,0) -> 0 | AG3073: =IF(AB3073="Karnataka",AE3073*9%,0) -> 0 | AH3073: =IF(AF3073+AG3073>0,0,AE3073*18%) -> 2854.5462 | AI3073: =AE3073*L3073 -> 634.3436 | AJ3073: =$AE3073*M3073 -> 3568.1827 | AK3073: =(AE3073)*AA3073/Y3073 -> 7864.1227 | AL3073: =AK3073*(1-L3073-M3073) -> 5780.1302 | AM3073: =AE3073-AI3073-AL3073-AJ3073 -> 5875.9335 | AN3073: =Z3073-366 -> 45715 | AO3073: =IF(AND(O3073>Z3073,N3073>AN3073),AE3073,0) -> 15858.59
A3074: Valid | B3074: 202510 | C3074: GMC023220100CALDERYS | D3074: CALDERYS INDIA REFRACTORIES LIMITED | E3074: 45901 | F3074: 46265 | G3074: Neena Gulati | H3074: 44613 | I3074: 25475 | J3074: ACK.4A9F3020250677.3 | K3074: =N3074 -> 45901 | L3074: =IF(K3074>=DATE(2022,4,1),4%,5%) -> 0.04 | M3074: 0.225 | N3074: 45901 | O3074: 46265 | R3074: 55 | S3074: =VLOOKUP(R3074,SA!$B$3:$C$11,2,1) -> 46-55 | T3074: FEMALE | U3074: MOTHER IN LAW | V3074: 500000 | W3074: =IF(U3074="self",V3074,0) -> 0 | X3074: =IF(U3074="self",1,0) -> 0 | Y3074: =O3074-N3074+1 -> 365 | Z3074: =$Z$1 -> 46081 | AA3074: =IF(MIN((Z3074-N3074)+1,Y3074)<0,0,MIN((Z3074-N3074)+1,Y3074)) -> 181 | AB3074: Maharashtra | AC3074: =AE3074+AF3074+AG3074+AH3074 -> 8919.0418 | AD3074: 1 | AE3074: =INDEX(SA!$C$2:$G$11,MATCH(Details!S3074,SA!$C$2:$C$11,0),MATCH(Details!V3074,SA!$C$2:$G$2,0))*Y3074/(F3074-E3074+1) -> 7558.51 | AF3074: =IF(AB3074="Karnataka",AE3074*9%,0) -> 0 | AG3074: =IF(AB3074="Karnataka",AE3074*9%,0) -> 0 | AH3074: =IF(AF3074+AG3074>0,0,AE3074*18%) -> 1360.5318 | AI3074: =AE3074*L3074 -> 302.3404 | AJ3074: =$AE3074*M3074 -> 1700.6647 | AK3074: =(AE3074)*AA3074/Y3074 -> 3748.1926 | AL3074: =AK3074*(1-L3074-M3074) -> 2754.9216 | AM3074: =AE3074-AI3074-AL3074-AJ3074 -> 2800.5833 | AN3074: =Z3074-366 -> 45715 | AO3074: =IF(AND(O3074>Z3074,N3074>AN3074),AE3074,0) -> 7558.51
A3075: Valid | B3075: 202510 | C3075: GMC023220100CALDERYS | D3075: CALDERYS INDIA REFRACTORIES LIMITED | E3075: 45901 | F3075: 46265 | G3075: Komal tukaram Chandankhede | H3075: 362115 | I3075: 36466 | J3075: ACK.4A9F3020250048.4 | K3075: =N3075 -> 45901 | L3075: =IF(K3075>=DATE(2022,4,1),4%,5%) -> 0.04 | M3075: 0.225 | N3075: 45901 | O3075: 46265 | R3075: 25 | S3075: =VLOOKUP(R3075,SA!$B$3:$C$11,2,1) -> 0-25 | T3075: FEMALE | U3075: Spouse | V3075: 300000 | W3075: =IF(U3075="self",V3075,0) -> 0 | X3075: =IF(U3075="self",1,0) -> 0 | Y3075: =O3075-N3075+1 -> 365 | Z3075: =$Z$1 -> 46081 | AA3075: =IF(MIN((Z3075-N3075)+1,Y3075)<0,0,MIN((Z3075-N3075)+1,Y3075)) -> 181 | AB3075: Maharashtra | AC3075: =AE3075+AF3075+AG3075+AH3075 -> 3690.3792 | AD3075: 1 | AE3075: =INDEX(SA!$C$2:$G$11,MATCH(Details!S3075,SA!$C$2:$C$11,0),MATCH(Details!V3075,SA!$C$2:$G$2,0))*Y3075/(F3075-E3075+1) -> 3127.44 | AF3075: =IF(AB3075="Karnataka",AE3075*9%,0) -> 0 | AG3075: =IF(AB3075="Karnataka",AE3075*9%,0) -> 0 | AH3075: =IF(AF3075+AG3075>0,0,AE3075*18%) -> 562.9392 | AI3075: =AE3075*L3075 -> 125.0976 | AJ3075: =$AE3075*M3075 -> 703.674 | AK3075: =(AE3075)*AA3075/Y3075 -> 1550.8675 | AL3075: =AK3075*(1-L3075-M3075) -> 1139.8876 | AM3075: =AE3075-AI3075-AL3075-AJ3075 -> 1158.7808 | AN3075: =Z3075-366 -> 45715 | AO3075: =IF(AND(O3075>Z3075,N3075>AN3075),AE3075,0) -> 3127.44
... A3106: Valid | B3106: 202510 | C3106: GMC023220100CALDERYS | D3106: CALDERYS INDIA REFRACTORIES LIMITED | E3106: 45901 | F3106: 46265 | G3106: Daughter of Shraddha | H3106: 362107 | I3106: 45839 | J3106: ACK.4A9F3020250042.6 | K3106: =N3106 -> 45901 | L3106: =IF(K3106>=DATE(2022,4,1),4%,5%) -> 0.04 | M3106: 0.225 | N3106: 45901 | O3106: 46265 | R3106: 0 | S3106: =VLOOKUP(R3106,SA!$B$3:$C$11,2,1) -> 0-25 | T3106: FEMALE | U3106: DAUGHTER | V3106: 300000 | W3106: =IF(U3106="self",V3106,0) -> 0 | X3106: =IF(U3106="self",1,0) -> 0 | Y3106: =O3106-N3106+1 -> 365 | Z3106: =$Z$1 -> 46081 | AA3106: =IF(MIN((Z3106-N3106)+1,Y3106)<0,0,MIN((Z3106-N3106)+1,Y3106)) -> 181 | AB3106: Maharashtra | AC3106: =AE3106+AF3106+AG3106+AH3106 -> 3690.3792 | AD3106: 1 | AE3106: =INDEX(SA!$C$2:$G$11,MATCH(Details!S3106,SA!$C$2:$C$11,0),MATCH(Details!V3106,SA!$C$2:$G$2,0))*Y3106/(F3106-E3106+1) -> 3127.44 | AF3106: =IF(AB3106="Karnataka",AE3106*9%,0) -> 0 | AG3106: =IF(AB3106="Karnataka",AE3106*9%,0) -> 0 | AH3106: =IF(AF3106+AG3106>0,0,AE3106*18%) -> 562.9392 | AI3106: =AE3106*L3106 -> 125.0976 | AJ3106: =$AE3106*M3106 -> 703.674 | AK3106: =(AE3106)*AA3106/Y3106 -> 1550.8675 | AL3106: =AK3106*(1-L3106-M3106) -> 1139.8876 | AM3106: =AE3106-AI3106-AL3106-AJ3106 -> 1158.7808 | AN3106: =Z3106-366 -> 45715 | AO3106: =IF(AND(O3106>Z3106,N3106>AN3106),AE3106,0) -> 3127.44
A3107: Deletion | B3107: 202510 | C3107: GMC023220100CALDERYS | D3107: CALDERYS INDIA REFRACTORIES LIMITED | E3107: 45901 | F3107: 46265 | G3107: Bidita Basu | H3107: 42033 | I3107: 36496 | J3107: ACK.4A9F3020250084.2 | K3107: =N3107 -> 45901 | L3107: =IF(K3107>=DATE(2022,4,1),4%,5%) -> 0.04 | M3107: 0.225 | N3107: 45901 | O3107: 46265 | P3107: 45900 | Q3107: =P3107+1 -> 45901 | R3107: 25 | S3107: =VLOOKUP(R3107,SA!$B$3:$C$11,2,1) -> 0-25 | T3107: Female | U3107: Daughter | V3107: -600000 | W3107: =IF(U3107="self",V3107,0) -> 0 | X3107: =IF(U3107="self",-1,0) -> 0 | Y3107: =O3107-Q3107+1 -> 365 | Z3107: =$Z$1 -> 46081 | AA3107: =IF(MIN((Z3107-Q3107)+1,Y3107)<0,0,MIN((Z3107-Q3107)+1,Y3107)) -> 181 | AB3107: Maharashtra | AC3107: =AE3107+AF3107+AG3107+AH3107 -> -4893.0234 | AD3107: -1 | AE3107: =-INDEX(SA!$C$2:$G$11,MATCH(Details!S3107,SA!$C$2:$C$11,0),MATCH(-Details!V3107,SA!$C$2:$G$2,0))*Y3107/(F3107-E3107+1) -> -4146.63 | AF3107: =IF(AB3107="Karnataka",AE3107*9%,0) -> 0 | AG3107: =IF(AB3107="Karnataka",AE3107*9%,0) -> 0 | AH3107: =IF(AF3107+AG3107>0,0,AE3107*18%) -> -746.3934 | AI3107: =AE3107*L3107 -> -165.8652 | AJ3107: =$AE3107*M3107 -> -932.99175 | AK3107: =(AE3107)*AA3107/Y3107 -> -2056.2741 | AL3107: =AK3107*(1-L3107-M3107) -> -1511.3614 | AM3107: =AE3107-AI3107-AL3107-AJ3107 -> -1536.4116 | AN3107: =Z3107-366 -> 45715 | AO3107: =IF(AND(O3107>Z3107,N3107>AN3107),AE3107,0) -> -4146.63 | AP3107: No claim
A3108: Deletion | B3108: 202510 | C3108: GMC023220100CALDERYS | D3108: CALDERYS INDIA REFRACTORIES LIMITED | E3108: 45901 | F3108: 46265 | G3108: Harsh Ranglani | H3108: 42126 | I3108: 36454 | J3108: ACK.4A9F3020250089.1 | K3108: =N3108 -> 45901 | L3108: =IF(K3108>=DATE(2022,4,1),4%,5%) -> 0.04 | M3108: 0.225 | N3108: 45901 | O3108: 46265 | P3108: 45900 | Q3108: =P3108+1 -> 45901 | R3108: 25 | S3108: =VLOOKUP(R3108,SA!$B$3:$C$11,2,1) -> 0-25 | T3108: Male | U3108: Son | V3108: -400000 | W3108: =IF(U3108="self",V3108,0) -> 0 | X3108: =IF(U3108="self",-1,0) -> 0 | Y3108: =O3108-Q3108+1 -> 365 | Z3108: =$Z$1 -> 46081 | AA3108: =IF(MIN((Z3108-Q3108)+1,Y3108)<0,0,MIN((Z3108-Q3108)+1,Y3108)) -> 181 | AB3108: Maharashtra | AC3108: =AE3108+AF3108+AG3108+AH3108 -> -4043.8364 | AD3108: -1 | AE3108: =-INDEX(SA!$C$2:$G$11,MATCH(Details!S3108,SA!$C$2:$C$11,0),MATCH(-Details!V3108,SA!$C$2:$G$2,0))*Y3108/(F3108-E3108+1) -> -3426.98 | AF3108: =IF(AB3108="Karnataka",AE3108*9%,0) -> 0 | AG3108: =IF(AB3108="Karnataka",AE3108*9%,0) -> 0 | AH3108: =IF(AF3108+AG3108>0,0,AE3108*18%) -> -616.8564 | AI3108: =AE3108*L3108 -> -137.0792 | AJ3108: =$AE3108*M3108 -> -771.0705 | AK3108: =(AE3108)*AA3108/Y3108 -> -1699.4065 | AL3108: =AK3108*(1-L3108-M3108) -> -1249.0638 | AM3108: =AE3108-AI3108-AL3108-AJ3108 -> -1269.7665 | AN3108: =Z3108-366 -> 45715 | AO3108: =IF(AND(O3108>Z3108,N3108>AN3108),AE3108,0) -> -3426.98 | AP3108: No claim
A3109: Deletion | B3109: 202510 | C3109: GMC023220100CALDERYS | D3109: CALDERYS INDIA REFRACTORIES LIMITED | E3109: 45901 | F3109: 46265 | G3109: Jaya Jaiswal | H3109: 42197 | I3109: 18994 | J3109: ACK.4A9F3020250111.1 | K3109: =N3109 -> 45901 | L3109: =IF(K3109>=DATE(2022,4,1),4%,5%) -> 0.04 | M3109: 0.225 | N3109: 45901 | O3109: 46265 | P3109: 45900 | Q3109: =P3109+1 -> 45901 | R3109: 73 | S3109: =VLOOKUP(R3109,SA!$B$3:$C$11,2,1) -> 71-75 | T3109: Female | U3109: Mother | V3109: -400000 | W3109: =IF(U3109="self",V3109,0) -> 0 | X3109: =IF(U3109="self",-1,0) -> 0 | Y3109: =O3109-Q3109+1 -> 365 | Z3109: =$Z$1 -> 46081 | AA3109: =IF(MIN((Z3109-Q3109)+1,Y3109)<0,0,MIN((Z3109-Q3109)+1,Y3109)) -> 181 | AB3109: Maharashtra | AC3109: =AE3109+AF3109+AG3109+AH3109 -> -21578.035 | AD3109: -1 | AE3109: =-INDEX(SA!$C$2:$G$11,MATCH(Details!S3109,SA!$C$2:$C$11,0),MATCH(-Details!V3109,SA!$C$2:$G$2,0))*Y3109/(F3109-E3109+1) -> -18286.47 | AF3109: =IF(AB3109="Karnataka",AE3109*9%,0) -> 0 | AG3109: =IF(AB3109="Karnataka",AE3109*9%,0) -> 0 | AH3109: =IF(AF3109+AG3109>0,0,AE3109*18%) -> -3291.5646 | AI3109: =AE3109*L3109 -> -731.4588 | AJ3109: =$AE3109*M3109 -> -4114.4558 | AK3109: =(AE3109)*AA3109/Y3109 -> -9068.0851 | AL3109: =AK3109*(1-L3109-M3109) -> -6665.0426 | AM3109: =AE3109-AI3109-AL3109-AJ3109 -> -6775.5129 | AN3109: =Z3109-366 -> 45715 | AO3109: =IF(AND(O3109>Z3109,N3109>AN3109),AE3109,0) -> -18286.47 | AP3109: No claim
A3110: Deletion | B3110: 202510 | C3110: GMC023220100CALDERYS | D3110: CALDERYS INDIA REFRACTORIES LIMITED | E3110: 45901 | F3110: 46265 | G3110: Sant Ram Mishra | H3110: 42258 | I3110: 14977 | J3110: ACK.4A9F3020250141.4 | K3110: =N3110 -> 45901 | L3110: =IF(K3110>=DATE(2022,4,1),4%,5%) -> 0.04 | M3110: 0.225 | N3110: 45901 | O3110: 46265 | P3110: 45900 | Q3110: =P3110+1 -> 45901 | R3110: 84 | S3110: =VLOOKUP(R3110,SA!$B$3:$C$11,2,1) -> 81-100 | T3110: Male | U3110: Father | V3110: -400000 | W3110: =IF(U3110="self",V3110,0) -> 0 | X3110: =IF(U3110="self",-1,0) -> 0 | Y3110: =O3110-Q3110+1 -> 365 | Z3110: =$Z$1 -> 46081 | AA3110: =IF(MIN((Z3110-Q3110)+1,Y3110)<0,0,MIN((Z3110-Q3110)+1,Y3110)) -> 181 | AB3110: Maharashtra | AC3110: =AE3110+AF3110+AG3110+AH3110 -> -29599.474 | AD3110: -1 | AE3110: =-INDEX(SA!$C$2:$G$11,MATCH(Details!S3110,SA!$C$2:$C$11,0),MATCH(-Details!V3110,SA!$C$2:$G$2,0))*Y3110/(F3110-E3110+1) -> -25084.3 | AF3110: =IF(AB3110="Karnataka",AE3110*9%,0) -> 0 | AG3110: =IF(AB3110="Karnataka",AE3110*9%,0) -> 0 | AH3110: =IF(AF3110+AG3110>0,0,AE3110*18%) -> -4515.174 | AI3110: =AE3110*L3110 -> -1003.372 | AJ3110: =$AE3110*M3110 -> -5643.9675 | AK3110: =(AE3110)*AA3110/Y3110 -> -12439.064 | AL3110: =AK3110*(1-L3110-M3110) -> -9142.7119 | AM3110: =AE3110-AI3110-AL3110-AJ3110 -> -9294.2486 | AN3110: =Z3110-366 -> 45715 | AO3110: =IF(AND(O3110>Z3110,N3110>AN3110),AE3110,0) -> -25084.3 | AP3110: No claim
A3111: Deletion | B3111: 202510 | C3111: GMC023220100CALDERYS | D3111: CALDERYS INDIA REFRACTORIES LIMITED | E3111: 45901 | F3111: 46265 | G3111: Gani Bai Mishra | H3111: 42258 | I3111: 19360 | J3111: ACK.4A9F3020250141.5 | K3111: =N3111 -> 45901 | L3111: =IF(K3111>=DATE(2022,4,1),4%,5%) -> 0.04 | M3111: 0.225 | N3111: 45901 | O3111: 46265 | P3111: 45900 | Q3111: =P3111+1 -> 45901 | R3111: 72 | S3111: =VLOOKUP(R3111,SA!$B$3:$C$11,2,1) -> 71-75 | T3111: Female | U3111: Mother | V3111: -400000 | W3111: =IF(U3111="self",V3111,0) -> 0 | X3111: =IF(U3111="self",-1,0) -> 0 | Y3111: =O3111-Q3111+1 -> 365 | Z3111: =$Z$1 -> 46081 | AA3111: =IF(MIN((Z3111-Q3111)+1,Y3111)<0,0,MIN((Z3111-Q3111)+1,Y3111)) -> 181 | AB3111: Maharashtra | AC3111: =AE3111+AF3111+AG3111+AH3111 -> -21578.035 | AD3111: -1 | AE3111: =-INDEX(SA!$C$2:$G$11,MATCH(Details!S3111,SA!$C$2:$C$11,0),MATCH(-Details!V3111,SA!$C$2:$G$2,0))*Y3111/(F3111-E3111+1) -> -18286.47 | AF3111: =IF(AB3111="Karnataka",AE3111*9%,0) -> 0 | AG3111: =IF(AB3111="Karnataka",AE3111*9%,0) -> 0 | AH3111: =IF(AF3111+AG3111>0,0,AE3111*18%) -> -3291.5646 | AI3111: =AE3111*L3111 -> -731.4588 | AJ3111: =$AE3111*M3111 -> -4114.4558 | AK3111: =(AE3111)*AA3111/Y3111 -> -9068.0851 | AL3111: =AK3111*(1-L3111-M3111) -> -6665.0426 | AM3111: =AE3111-AI3111-AL3111-AJ3111 -> -6775.5129 | AN3111: =Z3111-366 -> 45715 | AO3111: =IF(AND(O3111>Z3111,N3111>AN3111),AE3111,0) -> -18286.47 | AP3111: No claim
A3112: Deletion | B3112: 202510 | C3112: GMC023220100CALDERYS | D3112: CALDERYS INDIA REFRACTORIES LIMITED | E3112: 45901 | F3112: 46265 | G3112: Ramavatar Pandey | H3112: 42375 | I3112: 18629 | J3112: ACK.4A9F3020250664.1 | K3112: =N3112 -> 45901 | L3112: =IF(K3112>=DATE(2022,4,1),4%,5%) -> 0.04 | M3112: 0.225 | N3112: 45901 | O3112: 46265 | P3112: 45900 | Q3112: =P3112+1 -> 45901 | R3112: 74 | S3112: =VLOOKUP(R3112,SA!$B$3:$C$11,2,1) -> 71-75 | T3112: Male | U3112: Father | V3112: -500000 | W3112: =IF(U3112="self",V3112,0) -> 0 | X3112: =IF(U3112="self",-1,0) -> 0 | Y3112: =O3112-Q3112+1 -> 365 | Z3112: =$Z$1 -> 46081 | AA3112: =IF(MIN((Z3112-Q3112)+1,Y3112)<0,0,MIN((Z3112-Q3112)+1,Y3112)) -> 181 | AB3112: Maharashtra | AC3112: =AE3112+AF3112+AG3112+AH3112 -> -23735.924 | AD3112: -1 | AE3112: =-INDEX(SA!$C$2:$G$11,MATCH(Details!S3112,SA!$C$2:$C$11,0),MATCH(-Details!V3112,SA!$C$2:$G$2,0))*Y3112/(F3112-E3112+1) -> -20115.19 | AF3112: =IF(AB3112="Karnataka",AE3112*9%,0) -> 0 | AG3112: =IF(AB3112="Karnataka",AE3112*9%,0) -> 0 | AH3112: =IF(AF3112+AG3112>0,0,AE3112*18%) -> -3620.7342 | AI3112: =AE3112*L3112 -> -804.6076 | AJ3112: =$AE3112*M3112 -> -4525.9177 | AK3112: =(AE3112)*AA3112/Y3112 -> -9974.9298 | AL3112: =AK3112*(1-L3112-M3112) -> -7331.5734 | AM3112: =AE3112-AI3112-AL3112-AJ3112 -> -7453.0912 | AN3112: =Z3112-366 -> 45715 | AO3112: =IF(AND(O3112>Z3112,N3112>AN3112),AE3112,0) -> -20115.19 | AP3112: No claim
A3113: Deletion | B3113: 202510 | C3113: GMC023220100CALDERYS | D3113: CALDERYS INDIA REFRACTORIES LIMITED | E3113: 45901 | F3113: 46265 | G3113: Somvati Laharia | H3113: 60697 | I3113: 14733 | J3113: ACK.4A9F3020250284.2 | K3113: =N3113 -> 45901 | L3113: =IF(K3113>=DATE(2022,4,1),4%,5%) -> 0.04 | M3113: 0.225 | N3113: 45901 | O3113: 46265 | P3113: 45900 | Q3113: =P3113+1 -> 45901 | R3113: 85 | S3113: =VLOOKUP(R3113,SA!$B$3:$C$11,2,1) -> 81-100 | T3113: Female | U3113: Mother | V3113: -600000 | W3113: =IF(U3113="self",V3113,0) -> 0 | X3113: =IF(U3113="self",-1,0) -> 0 | Y3113: =O3113-Q3113+1 -> 365 | Z3113: =$Z$1 -> 46081 | AA3113: =IF(MIN((Z3113-Q3113)+1,Y3113)<0,0,MIN((Z3113-Q3113)+1,Y3113)) -> 181 | AB3113: Maharashtra | AC3113: =AE3113+AF3113+AG3113+AH3113 -> -35815.419 | AD3113: -1 | AE3113: =-INDEX(SA!$C$2:$G$11,MATCH(Details!S3113,SA!$C$2:$C$11,0),MATCH(-Details!V3113,SA!$C$2:$G$2,0))*Y3113/(F3113-E3113+1) -> -30352.05 | AF3113: =IF(AB3113="Karnataka",AE3113*9%,0) -> 0 | AG3113: =IF(AB3113="Karnataka",AE3113*9%,0) -> 0 | AH3113: =IF(AF3113+AG3113>0,0,AE3113*18%) -> -5463.369 | AI3113: =AE3113*L3113 -> -1214.082 | AJ3113: =$AE3113*M3113 -> -6829.2113 | AK3113: =(AE3113)*AA3113/Y3113 -> -15051.291 | AL3113: =AK3113*(1-L3113-M3113) -> -11062.699 | AM3113: =AE3113-AI3113-AL3113-AJ3113 -> -11246.058 | AN3113: =Z3113-366 -> 45715 | AO3113: =IF(AND(O3113>Z3113,N3113>AN3113),AE3113,0) -> -30352.05 | AP3113: No claim
A3114: Deletion | B3114: 202510 | C3114: GMC023220100CALDERYS | D3114: CALDERYS INDIA REFRACTORIES LIMITED | E3114: 45901 | F3114: 46265 | G3114: Tulshiram Didase | H3114: 362037 | I3114: 18264 | J3114: ACK.4A9F3020250016.1 | K3114: =N3114 -> 45901 | L3114: =IF(K3114>=DATE(2022,4,1),4%,5%) -> 0.04 | M3114: 0.225 | N3114: 45901 | O3114: 46265 | P3114: 45900 | Q3114: =P3114+1 -> 45901 | R3114: 75 | S3114: =VLOOKUP(R3114,SA!$B$3:$C$11,2,1) -> 71-75 | T3114: Male | U3114: Father | V3114: -300000 | W3114: =IF(U3114="self",V3114,0) -> 0 | X3114: =IF(U3114="self",-1,0) -> 0 | Y3114: =O3114-Q3114+1 -> 365 | Z3114: =$Z$1 -> 46081 | AA3114: =IF(MIN((Z3114-Q3114)+1,Y3114)<0,0,MIN((Z3114-Q3114)+1,Y3114)) -> 181 | AB3114: Maharashtra | AC3114: =AE3114+AF3114+AG3114+AH3114 -> -19621.193 | AD3114: -1 | AE3114: =-INDEX(SA!$C$2:$G$11,MATCH(Details!S3114,SA!$C$2:$C$11,0),MATCH(-Details!V3114,SA!$C$2:$G$2,0))*Y3114/(F3114-E3114+1) -> -16628.13 | AF3114: =IF(AB3114="Karnataka",AE3114*9%,0) -> 0 | AG3114: =IF(AB3114="Karnataka",AE3114*9%,0) -> 0 | AH3114: =IF(AF3114+AG3114>0,0,AE3114*18%) -> -2993.0634 | AI3114: =AE3114*L3114 -> -665.1252 | AJ3114: =$AE3114*M3114 -> -3741.3293 | AK3114: =(AE3114)*AA3114/Y3114 -> -8245.7302 | AL3114: =AK3114*(1-L3114-M3114) -> -6060.6117 | AM3114: =AE3114-AI3114-AL3114-AJ3114 -> -6161.0638 | AN3114: =Z3114-366 -> 45715 | AO3114: =IF(AND(O3114>Z3114,N3114>AN3114),AE3114,0) -> -16628.13 | AP3114: No claim
A3115: Deletion | B3115: 202510 | C3115: GMC023220100CALDERYS | D3115: CALDERYS INDIA REFRACTORIES LIMITED | E3115: 45901 | F3115: 46265 | G3115: Jagannath Chandankhede | H3115: 362115 | I3115: 18838 | J3115: ACK.4A9F3020250048.2 | K3115: =N3115 -> 45901 | L3115: =IF(K3115>=DATE(2022,4,1),4%,5%) -> 0.04 | M3115: 0.225 | N3115: 45901 | O3115: 46265 | P3115: 45900 | Q3115: =P3115+1 -> 45901 | R3115: 74 | S3115: =VLOOKUP(R3115,SA!$B$3:$C$11,2,1) -> 71-75 | T3115: Male | U3115: Father | V3115: -300000 | W3115: =IF(U3115="self",V3115,0) -> 0 | X3115: =IF(U3115="self",-1,0) -> 0 | Y3115: =O3115-Q3115+1 -> 365 | Z3115: =$Z$1 -> 46081 | AA3115: =IF(MIN((Z3115-Q3115)+1,Y3115)<0,0,MIN((Z3115-Q3115)+1,Y3115)) -> 181 | AB3115: Maharashtra | AC3115: =AE3115+AF3115+AG3115+AH3115 -> -19621.193 | AD3115: -1 | AE3115: =-INDEX(SA!$C$2:$G$11,MATCH(Details!S3115,SA!$C$2:$C$11,0),MATCH(-Details!V3115,SA!$C$2:$G$2,0))*Y3115/(F3115-E3115+1) -> -16628.13 | AF3115: =IF(AB3115="Karnataka",AE3115*9%,0) -> 0 | AG3115: =IF(AB3115="Karnataka",AE3115*9%,0) -> 0 | AH3115: =IF(AF3115+AG3115>0,0,AE3115*18%) -> -2993.0634 | AI3115: =AE3115*L3115 -> -665.1252 | AJ3115: =$AE3115*M3115 -> -3741.3293 | AK3115: =(AE3115)*AA3115/Y3115 -> -8245.7302 | AL3115: =AK3115*(1-L3115-M3115) -> -6060.6117 | AM3115: =AE3115-AI3115-AL3115-AJ3115 -> -6161.0638 | AN3115: =Z3115-366 -> 45715 | AO3115: =IF(AND(O3115>Z3115,N3115>AN3115),AE3115,0) -> -16628.13 | AP3115: No claim
A3116: Deletion | B3116: 202510 | C3116: GMC023220100CALDERYS | D3116: CALDERYS INDIA REFRACTORIES LIMITED | E3116: 45901 | F3116: 46265 | G3116: Chandrashekhar Gourkar | H3116: 362120 | I3116: 22324 | J3116: ACK.4A9F3020250052.4 | K3116: =N3116 -> 45901 | L3116: =IF(K3116>=DATE(2022,4,1),4%,5%) -> 0.04 | M3116: 0.225 | N3116: 45901 | O3116: 46265 | P3116: 45900 | Q3116: =P3116+1 -> 45901 | R3116: 64 | S3116: =VLOOKUP(R3116,SA!$B$3:$C$11,2,1) -> 56-65 | T3116: Male | U3116: Father | V3116: -300000 | W3116: =IF(U3116="self",V3116,0) -> 0 | X3116: =IF(U3116="self",-1,0) -> 0 | Y3116: =O3116-Q3116+1 -> 365 | Z3116: =$Z$1 -> 46081 | AA3116: =IF(MIN((Z3116-Q3116)+1,Y3116)<0,0,MIN((Z3116-Q3116)+1,Y3116)) -> 181 | AB3116: Maharashtra | AC3116: =AE3116+AF3116+AG3116+AH3116 -> -10831.751 | AD3116: -1 | AE3116: =-INDEX(SA!$C$2:$G$11,MATCH(Details!S3116,SA!$C$2:$C$11,0),MATCH(-Details!V3116,SA!$C$2:$G$2,0))*Y3116/(F3116-E3116+1) -> -9179.45 | AF3116: =IF(AB3116="Karnataka",AE3116*9%,0) -> 0 | AG3116: =IF(AB3116="Karnataka",AE3116*9%,0) -> 0 | AH3116: =IF(AF3116+AG3116>0,0,AE3116*18%) -> -1652.301 | AI3116: =AE3116*L3116 -> -367.178 | AJ3116: =$AE3116*M3116 -> -2065.3763 | AK3116: =(AE3116)*AA3116/Y3116 -> -4552.0012 | AL3116: =AK3116*(1-L3116-M3116) -> -3345.7209 | AM3116: =AE3116-AI3116-AL3116-AJ3116 -> -3401.1748 | AN3116: =Z3116-366 -> 45715 | AO3116: =IF(AND(O3116>Z3116,N3116>AN3116),AE3116,0) -> -9179.45 | AP3116: No claim
A3117: Deletion | B3117: 202510 | C3117: GMC023220100CALDERYS | D3117: CALDERYS INDIA REFRACTORIES LIMITED | E3117: 45901 | F3117: 46265 | G3117: Chandrakala Namdeo Raut | H3117: 362150 | I3117: 22690 | J3117: ACK.4A9F3020250076.3 | K3117: =N3117 -> 45901 | L3117: =IF(K3117>=DATE(2022,4,1),4%,5%) -> 0.04 | M3117: 0.225 | N3117: 45901 | O3117: 46265 | P3117: 45900 | Q3117: =P3117+1 -> 45901 | R3117: 63 | S3117: =VLOOKUP(R3117,SA!$B$3:$C$11,2,1) -> 56-65 | T3117: Female | U3117: Mother | V3117: -500000 | W3117: =IF(U3117="self",V3117,0) -> 0 | X3117: =IF(U3117="self",-1,0) -> 0 | Y3117: =O3117-Q3117+1 -> 365 | Z3117: =$Z$1 -> 46081 | AA3117: =IF(MIN((Z3117-Q3117)+1,Y3117)<0,0,MIN((Z3117-Q3117)+1,Y3117)) -> 181 | AB3117: Maharashtra | AC3117: =AE3117+AF3117+AG3117+AH3117 -> -13100.714 | AD3117: -1 | AE3117: =-INDEX(SA!$C$2:$G$11,MATCH(Details!S3117,SA!$C$2:$C$11,0),MATCH(-Details!V3117,SA!$C$2:$G$2,0))*Y3117/(F3117-E3117+1) -> -11102.3 | AF3117: =IF(AB3117="Karnataka",AE3117*9%,0) -> 0 | AG3117: =IF(AB3117="Karnataka",AE3117*9%,0) -> 0 | AH3117: =IF(AF3117+AG3117>0,0,AE3117*18%) -> -1998.414 | AI3117: =AE3117*L3117 -> -444.092 | AJ3117: =$AE3117*M3117 -> -2498.0175 | AK3117: =(AE3117)*AA3117/Y3117 -> -5505.5241 | AL3117: =AK3117*(1-L3117-M3117) -> -4046.5602 | AM3117: =AE3117-AI3117-AL3117-AJ3117 -> -4113.6303 | AN3117: =Z3117-366 -> 45715 | AO3117: =IF(AND(O3117>Z3117,N3117>AN3117),AE3117,0) -> -11102.3 | AP3117: No claim
A3118: Deletion | B3118: 202510 | C3118: GMC023220100CALDERYS | D3118: CALDERYS INDIA REFRACTORIES LIMITED | E3118: 45901 | F3118: 46265 | G3118: Anshita Verma | H3118: 550008 | I3118: 36234 | J3118: ACK.4A9F3020250663.2 | K3118: =N3118 -> 45901 | L3118: =IF(K3118>=DATE(2022,4,1),4%,5%) -> 0.04 | M3118: 0.225 | N3118: 45901 | O3118: 46265 | P3118: 45900 | Q3118: =P3118+1 -> 45901 | R3118: 26 | S3118: =VLOOKUP(R3118,SA!$B$3:$C$11,2,1) -> 26-35 | T3118: Female | U3118: Daughter | V3118: -400000 | W3118: =IF(U3118="self",V3118,0) -> 0 | X3118: =IF(U3118="self",-1,0) -> 0 | Y3118: =O3118-Q3118+1 -> 365 | Z3118: =$Z$1 -> 46081 | AA3118: =IF(MIN((Z3118-Q3118)+1,Y3118)<0,0,MIN((Z3118-Q3118)+1,Y3118)) -> 181 | AB3118: Maharashtra | AC3118: =AE3118+AF3118+AG3118+AH3118 -> -4533.029 | AD3118: -1 | AE3118: =-INDEX(SA!$C$2:$G$11,MATCH(Details!S3118,SA!$C$2:$C$11,0),MATCH(-Details!V3118,SA!$C$2:$G$2,0))*Y3118/(F3118-E3118+1) -> -3841.55 | AF3118: =IF(AB3118="Karnataka",AE3118*9%,0) -> 0 | AG3118: =IF(AB3118="Karnataka",AE3118*9%,0) -> 0 | AH3118: =IF(AF3118+AG3118>0,0,AE3118*18%) -> -691.479 | AI3118: =AE3118*L3118 -> -153.662 | AJ3118: =$AE3118*M3118 -> -864.34875 | AK3118: =(AE3118)*AA3118/Y3118 -> -1904.9878 | AL3118: =AK3118*(1-L3118-M3118) -> -1400.166 | AM3118: =AE3118-AI3118-AL3118-AJ3118 -> -1423.3732 | AN3118: =Z3118-366 -> 45715 | AO3118: =IF(AND(O3118>Z3118,N3118>AN3118),AE3118,0) -> -3841.55 | AP3118: No claim
... A3130: Deletion | B3130: 202510 | C3130: GMC023220100CALDERYS | D3130: CALDERYS INDIA REFRACTORIES LIMITED | E3130: 45901 | F3130: 46265 | G3130: Dhyan Solanki | H3130: 752021 | I3130: 45901 | J3130: ACK.4A9F3020250574.6 | K3130: =N3130 -> 45901 | L3130: =IF(K3130>=DATE(2022,4,1),4%,5%) -> 0.04 | M3130: 0.225 | N3130: 45901 | O3130: 46265 | P3130: 45900 | Q3130: =P3130+1 -> 45901 | R3130: 0 | S3130: =VLOOKUP(R3130,SA!$B$3:$C$11,2,1) -> 0-25 | T3130: MALE | U3130: Son | V3130: -300000 | W3130: =IF(U3130="self",V3130,0) -> 0 | X3130: =IF(U3130="self",-1,0) -> 0 | Y3130: =O3130-Q3130+1 -> 365 | Z3130: =$Z$1 -> 46081 | AA3130: =IF(MIN((Z3130-Q3130)+1,Y3130)<0,0,MIN((Z3130-Q3130)+1,Y3130)) -> 181 | AB3130: Maharashtra | AC3130: =AE3130+AF3130+AG3130+AH3130 -> -3690.3792 | AD3130: -1 | AE3130: =-INDEX(SA!$C$2:$G$11,MATCH(Details!S3130,SA!$C$2:$C$11,0),MATCH(-Details!V3130,SA!$C$2:$G$2,0))*Y3130/(F3130-E3130+1) -> -3127.44 | AF3130: =IF(AB3130="Karnataka",AE3130*9%,0) -> 0 | AG3130: =IF(AB3130="Karnataka",AE3130*9%,0) -> 0 | AH3130: =IF(AF3130+AG3130>0,0,AE3130*18%) -> -562.9392 | AI3130: =AE3130*L3130 -> -125.0976 | AJ3130: =$AE3130*M3130 -> -703.674 | AK3130: =(AE3130)*AA3130/Y3130 -> -1550.8675 | AL3130: =AK3130*(1-L3130-M3130) -> -1139.8876 | AM3130: =AE3130-AI3130-AL3130-AJ3130 -> -1158.7808 | AN3130: =Z3130-366 -> 45715 | AO3130: =IF(AND(O3130>Z3130,N3130>AN3130),AE3130,0) -> -3127.44 | AP3130: No claim
A3131: Valid | B3131: 202511 | C3131: GMC023220100CALDERYS | D3131: CALDERYS INDIA REFRACTORIES LIMITED | E3131: 45901 | F3131: 46265 | G3131: Jyoti Ranjan Sahoo | H3131: 45270 | I3131: 33770 | J3131: ACK.4A9F3020250721.1 | K3131: =N3131 -> 45915 | L3131: =IF(K3131>=DATE(2022,4,1),4%,5%) -> 0.04 | M3131: 0.225 | N3131: 45915 | O3131: 46265 | R3131: 33 | S3131: =VLOOKUP(R3131,SA!$B$3:$C$11,2,1) -> 26-35 | T3131: Male | U3131: Self | V3131: 300000 | W3131: =IF(U3131="self",V3131,0) -> 300000 | X3131: =IF(U3131="self",1,0) -> 1 | Y3131: =O3131-N3131+1 -> 351 | Z3131: =$Z$1 -> 46081 | AA3131: =IF(MIN((Z3131-N3131)+1,Y3131)<0,0,MIN((Z3131-N3131)+1,Y3131)) -> 167 | AB3131: Maharashtra | AC3131: =AE3131+AF3131+AG3131+AH3131 -> 3966.2671 | AD3131: 1 | AE3131: =INDEX(SA!$C$2:$G$11,MATCH(Details!S3131,SA!$C$2:$C$11,0),MATCH(Details!V3131,SA!$C$2:$G$2,0))*Y3131/(F3131-E3131+1) -> 3361.2433 | AF3131: =IF(AB3131="Karnataka",AE3131*9%,0) -> 0 | AG3131: =IF(AB3131="Karnataka",AE3131*9%,0) -> 0 | AH3131: =IF(AF3131+AG3131>0,0,AE3131*18%) -> 605.0238 | AI3131: =AE3131*L3131 -> 134.44973 | AJ3131: =$AE3131*M3131 -> 756.27975 | AK3131: =(AE3131)*AA3131/Y3131 -> 1599.224 | AL3131: =AK3131*(1-L3131-M3131) -> 1175.4297 | AM3131: =AE3131-AI3131-AL3131-AJ3131 -> 1295.0842 | AN3131: =Z3131-366 -> 45715 | AO3131: =IF(AND(O3131>Z3131,N3131>AN3131),AE3131,0) -> 3361.2433
A3132: Valid | B3132: 202511 | C3132: GMC023220100CALDERYS | D3132: CALDERYS INDIA REFRACTORIES LIMITED | E3132: 45901 | F3132: 46265 | G3132: Jangyaseni Priyadarsini Sahoo | H3132: 45270 | I3132: 34487 | J3132: ACK.4A9F3020250721.2 | K3132: =N3132 -> 45915 | L3132: =IF(K3132>=DATE(2022,4,1),4%,5%) -> 0.04 | M3132: 0.225 | N3132: 45915 | O3132: 46265 | R3132: 31 | S3132: =VLOOKUP(R3132,SA!$B$3:$C$11,2,1) -> 26-35 | T3132: Female | U3132: Spouse | V3132: 300000 | W3132: =IF(U3132="self",V3132,0) -> 0 | X3132: =IF(U3132="self",1,0) -> 0 | Y3132: =O3132-N3132+1 -> 351 | Z3132: =$Z$1 -> 46081 | AA3132: =IF(MIN((Z3132-N3132)+1,Y3132)<0,0,MIN((Z3132-N3132)+1,Y3132)) -> 167 | AB3132: Maharashtra | AC3132: =AE3132+AF3132+AG3132+AH3132 -> 3966.2671 | AD3132: 1 | AE3132: =INDEX(SA!$C$2:$G$11,MATCH(Details!S3132,SA!$C$2:$C$11,0),MATCH(Details!V3132,SA!$C$2:$G$2,0))*Y3132/(F3132-E3132+1) -> 3361.2433 | AF3132: =IF(AB3132="Karnataka",AE3132*9%,0) -> 0 | AG3132: =IF(AB3132="Karnataka",AE3132*9%,0) -> 0 | AH3132: =IF(AF3132+AG3132>0,0,AE3132*18%) -> 605.0238 | AI3132: =AE3132*L3132 -> 134.44973 | AJ3132: =$AE3132*M3132 -> 756.27975 | AK3132: =(AE3132)*AA3132/Y3132 -> 1599.224 | AL3132: =AK3132*(1-L3132-M3132) -> 1175.4297 | AM3132: =AE3132-AI3132-AL3132-AJ3132 -> 1295.0842 | AN3132: =Z3132-366 -> 45715 | AO3132: =IF(AND(O3132>Z3132,N3132>AN3132),AE3132,0) -> 3361.2433
A3133: Valid | B3133: 202511 | C3133: GMC023220100CALDERYS | D3133: CALDERYS INDIA REFRACTORIES LIMITED | E3133: 45901 | F3133: 46265 | G3133: Sarat Chandra Sahoo | H3133: 45270 | I3133: 23012 | J3133: ACK.4A9F3020250721.3 | K3133: =N3133 -> 45915 | L3133: =IF(K3133>=DATE(2022,4,1),4%,5%) -> 0.04 | M3133: 0.225 | N3133: 45915 | O3133: 46265 | R3133: 62 | S3133: =VLOOKUP(R3133,SA!$B$3:$C$11,2,1) -> 56-65 | T3133: Male | U3133: Father | V3133: 300000 | W3133: =IF(U3133="self",V3133,0) -> 0 | X3133: =IF(U3133="self",1,0) -> 0 | Y3133: =O3133-N3133+1 -> 351 | Z3133: =$Z$1 -> 46081 | AA3133: =IF(MIN((Z3133-N3133)+1,Y3133)<0,0,MIN((Z3133-N3133)+1,Y3133)) -> 167 | AB3133: Maharashtra | AC3133: =AE3133+AF3133+AG3133+AH3133 -> 10416.287 | AD3133: 1 | AE3133: =INDEX(SA!$C$2:$G$11,MATCH(Details!S3133,SA!$C$2:$C$11,0),MATCH(Details!V3133,SA!$C$2:$G$2,0))*Y3133/(F3133-E3133+1) -> 8827.3615 | AF3133: =IF(AB3133="Karnataka",AE3133*9%,0) -> 0 | AG3133: =IF(AB3133="Karnataka",AE3133*9%,0) -> 0 | AH3133: =IF(AF3133+AG3133>0,0,AE3133*18%) -> 1588.9251 | AI3133: =AE3133*L3133 -> 353.09446 | AJ3133: =$AE3133*M3133 -> 1986.1563 | AK3133: =(AE3133)*AA3133/Y3133 -> 4199.9127 | AL3133: =AK3133*(1-L3133-M3133) -> 3086.9359 | AM3133: =AE3133-AI3133-AL3133-AJ3133 -> 3401.1748 | AN3133: =Z3133-366 -> 45715 | AO3133: =IF(AND(O3133>Z3133,N3133>AN3133),AE3133,0) -> 8827.3615
A3134: Valid | B3134: 202511 | C3134: GMC023220100CALDERYS | D3134: CALDERYS INDIA REFRACTORIES LIMITED | E3134: 45901 | F3134: 46265 | G3134: Binodini Sahoo | H3134: 45270 | I3134: 23743 | J3134: ACK.4A9F3020250721.4 | K3134: =N3134 -> 45915 | L3134: =IF(K3134>=DATE(2022,4,1),4%,5%) -> 0.04 | M3134: 0.225 | N3134: 45915 | O3134: 46265 | R3134: 60 | S3134: =VLOOKUP(R3134,SA!$B$3:$C$11,2,1) -> 56-65 | T3134: Female | U3134: Mother | V3134: 300000 | W3134: =IF(U3134="self",V3134,0) -> 0 | X3134: =IF(U3134="self",1,0) -> 0 | Y3134: =O3134-N3134+1 -> 351 | Z3134: =$Z$1 -> 46081 | AA3134: =IF(MIN((Z3134-N3134)+1,Y3134)<0,0,MIN((Z3134-N3134)+1,Y3134)) -> 167 | AB3134: Maharashtra | AC3134: =AE3134+AF3134+AG3134+AH3134 -> 10416.287 | AD3134: 1 | AE3134: =INDEX(SA!$C$2:$G$11,MATCH(Details!S3134,SA!$C$2:$C$11,0),MATCH(Details!V3134,SA!$C$2:$G$2,0))*Y3134/(F3134-E3134+1) -> 8827.3615 | AF3134: =IF(AB3134="Karnataka",AE3134*9%,0) -> 0 | AG3134: =IF(AB3134="Karnataka",AE3134*9%,0) -> 0 | AH3134: =IF(AF3134+AG3134>0,0,AE3134*18%) -> 1588.9251 | AI3134: =AE3134*L3134 -> 353.09446 | AJ3134: =$AE3134*M3134 -> 1986.1563 | AK3134: =(AE3134)*AA3134/Y3134 -> 4199.9127 | AL3134: =AK3134*(1-L3134-M3134) -> 3086.9359 | AM3134: =AE3134-AI3134-AL3134-AJ3134 -> 3401.1748 | AN3134: =Z3134-366 -> 45715 | AO3134: =IF(AND(O3134>Z3134,N3134>AN3134),AE3134,0) -> 8827.3615
A3135: Valid | B3135: 202511 | C3135: GMC023220100CALDERYS | D3135: CALDERYS INDIA REFRACTORIES LIMITED | E3135: 45901 | F3135: 46265 | G3135: Amlesh Kumar | H3135: 45324 | I3135: 33243 | J3135: ACK.4A9F3020250718.1 | K3135: =N3135 -> 45922 | L3135: =IF(K3135>=DATE(2022,4,1),4%,5%) -> 0.04 | M3135: 0.225 | N3135: 45922 | O3135: 46265 | R3135: 34 | S3135: =VLOOKUP(R3135,SA!$B$3:$C$11,2,1) -> 26-35 | T3135: Male | U3135: Self | V3135: 300000 | W3135: =IF(U3135="self",V3135,0) -> 300000 | X3135: =IF(U3135="self",1,0) -> 1 | Y3135: =O3135-N3135+1 -> 344 | Z3135: =$Z$1 -> 46081 | AA3135: =IF(MIN((Z3135-N3135)+1,Y3135)<0,0,MIN((Z3135-N3135)+1,Y3135)) -> 160 | AB3135: Maharashtra | AC3135: =AE3135+AF3135+AG3135+AH3135 -> 3887.1678 | AD3135: 1 | AE3135: =INDEX(SA!$C$2:$G$11,MATCH(Details!S3135,SA!$C$2:$C$11,0),MATCH(Details!V3135,SA!$C$2:$G$2,0))*Y3135/(F3135-E3135+1) -> 3294.21 | AF3135: =IF(AB3135="Karnataka",AE3135*9%,0) -> 0 | AG3135: =IF(AB3135="Karnataka",AE3135*9%,0) -> 0 | AH3135: =IF(AF3135+AG3135>0,0,AE3135*18%) -> 592.9578 | AI3135: =AE3135*L3135 -> 131.7684 | AJ3135: =$AE3135*M3135 -> 741.19724 | AK3135: =(AE3135)*AA3135/Y3135 -> 1532.1907 | AL3135: =AK3135*(1-L3135-M3135) -> 1126.1602 | AM3135: =AE3135-AI3135-AL3135-AJ3135 -> 1295.0842 | AN3135: =Z3135-366 -> 45715 | AO3135: =IF(AND(O3135>Z3135,N3135>AN3135),AE3135,0) -> 3294.21
A3136: Valid | B3136: 202511 | C3136: GMC023220100CALDERYS | D3136: CALDERYS INDIA REFRACTORIES LIMITED | E3136: 45901 | F3136: 46265 | G3136: Amrita Kumari | H3136: 45324 | I3136: 38518 | J3136: ACK.4A9F3020250718.2 | K3136: =N3136 -> 45922 | L3136: =IF(K3136>=DATE(2022,4,1),4%,5%) -> 0.04 | M3136: 0.225 | N3136: 45922 | O3136: 46265 | R3136: 20 | S3136: =VLOOKUP(R3136,SA!$B$3:$C$11,2,1) -> 0-25 | T3136: Female | U3136: Spouse | V3136: 300000 | W3136: =IF(U3136="self",V3136,0) -> 0 | X3136: =IF(U3136="self",1,0) -> 0 | Y3136: =O3136-N3136+1 -> 344 | Z3136: =$Z$1 -> 46081 | AA3136: =IF(MIN((Z3136-N3136)+1,Y3136)<0,0,MIN((Z3136-N3136)+1,Y3136)) -> 160 | AB3136: Maharashtra | AC3136: =AE3136+AF3136+AG3136+AH3136 -> 3478.056 | AD3136: 1 | AE3136: =INDEX(SA!$C$2:$G$11,MATCH(Details!S3136,SA!$C$2:$C$11,0),MATCH(Details!V3136,SA!$C$2:$G$2,0))*Y3136/(F3136-E3136+1) -> 2947.5051 | AF3136: =IF(AB3136="Karnataka",AE3136*9%,0) -> 0 | AG3136: =IF(AB3136="Karnataka",AE3136*9%,0) -> 0 | AH3136: =IF(AF3136+AG3136>0,0,AE3136*18%) -> 530.55092 | AI3136: =AE3136*L3136 -> 117.9002 | AJ3136: =$AE3136*M3136 -> 663.18865 | AK3136: =(AE3136)*AA3136/Y3136 -> 1370.9326 | AL3136: =AK3136*(1-L3136-M3136) -> 1007.6355 | AM3136: =AE3136-AI3136-AL3136-AJ3136 -> 1158.7808 | AN3136: =Z3136-366 -> 45715 | AO3136: =IF(AND(O3136>Z3136,N3136>AN3136),AE3136,0) -> 2947.5051
...

Sheet SA
C2: Age Band SI | D2: 300000 | E2: 400000 | F2: 500000 | G2: 600000
B3: 0 | C3: 0-25 | D3: 3127.44 | E3: 3426.98 | F3: 3769.67 | G3: 4146.63
B4: 26 | C4: 26-35 | D4: 3495.31 | E4: 3841.55 | F4: 4225.69 | G4: 4648.32
B5: 36 | C5: 36-45 | D5: 4338.62 | E5: 4658.07 | F5: 5123.89 | G5: 5636.29
B6: 46 | C6: 46-55 | D6: 6248.7 | E6: 6871.37 | F6: 7558.51 | G6: 8314.37
B7: 56 | C7: 56-65 | D7: 9179.45 | E7: 10092.99 | F7: 11102.3 | G7: 12212.54
B8: 66 | C8: 66-70 | D8: 13109.28 | E8: 14425.4 | F8: 15858.59 | G8: 17444.37
B9: 71 | C9: 71-75 | D9: 16628.13 | E9: 18286.47 | F9: 20115.19 | G9: 22126.45
B10: 76 | C10: 76-80 | D10: 20889.05 | E10: 22974.65 | F10: 25272.11 | G10: 27799.31
B11: 81 | C11: 81-100 | D11: 22807.9 | E11: 25084.3 | F11: 27592.73 | G11: 30352.05

Sheet CD Statement
B5: Acko General Insurance Limited
B6: CD Utilization Statement as on 28th Feb 2026
B7: Date | C7: Premium | D7: Tax Invoice No | E7: Description | F7: APD | G7: Balance
B8: 45899 | E8: BNPAH25242NAEJ12/CALDERY1/CALDERYS INDIA REFRACTORIES LIMITED | F8: 554877 | G8: =F8 -> 554877
B9: 45899 | E9: BNPAR52025083000466965/CALDERY1/CALDERYS INDIA REFRACTORIES LIMITED | F9: 24780000 | G9: =G8+F9-C9 -> 25334877
B10: 45901 | C10: 554877.06 | D10: GPA086900100 | E10: GPA Premium | G10: =G9+F10-C10 -> 24780000
B11: 45904 | E11: BNPAH25247NAKQ24/CALDERY1/CALDERYS INDIA REFRACTORIES LIMITED | F11: 1000000 | G11: =G10+F11-C11 -> 25780000
B12: 45915 | C12: 24780000 | D12: GMC023220100 | E12: GMC Premium | G12: =G11+F12-C12 -> 1000000.1
B13: 45917 | C13: 5367.348 | D13: GPA086900101 | E13: GPA Premium | G13: =G12+F13-C13 -> 994632.75
B14: 45919 | C14: 150501.12 | D14: GMC023220101 | E14: GMC Premium | G14: =G13+F14-C14 -> 844131.64
B15: 45919 | C15: 20518.047 | D15: GPA086900102 | E15: GPA Premium | G15: =G14+F15-C15 -> 823613.59
B16: 45925 | C16: 728614.31 | D16: GMC023220102 | E16: GMC Premium | G16: =G15+F16-C16 -> 94999.283
B17: 45930 | C17: 0 | D17: GMC023220103 | E17: GMC Premium | G17: =G16+F17-C17 -> 94999.283
B18: 45930 | G18: =G17+F18-C18 -> 94999.283
B19: 45938 | E19: Transferred from: GMC017050100CALDERYS | F19: 145497 | G19: =G18+F19-C19 -> 240496.28
B20: 45946 | E20: BNPAR52025101600487495/CALDERY1/CALDERYS INDIA REFRACTORIES LIMITED | F20: 1000000 | G20: =G19+F20-C20 -> 1240496.3
B21: 45957 | C21: -22112.843 | D21: GMC023220104 | E21: GMC Premium | G21: =G20+F21-C21 -> 1262609.1
B22: 45961 | G22: =G21+F22-C22 -> 1262609.1
B23: 45967 | C23: 846.37036 | D23: GPA086900103 | E23: GPA Premium | G23: =G22+F23-C23 -> 1261762.8
B24: 45970 | C24: -7614.0654 | D24: GPA086900104 | E24: GPA Premium | G24: =G23+F24-C24 -> 1269376.8
B25: 45970 | C25: 113233.43 | D25: GMC023220105 | E25: GMC Premium | G25: =G24+F25-C25 -> 1156143.4
B26: 45986 | C26: 8459.2564 | D26: GPA086900105 | E26: GPA Premium | G26: =G25+F26-C26 -> 1147684.1
B27: 45986 | C27: 416469.12 | D27: GMC023220106 | E27: GMC Premium | G27: =G26+F27-C27 -> 731215.01
B28: 45991 | C28: 0 | D28: GPA086900106 | E28: GPA Premium | G28: =G27+F28-C28 -> 731215.01
B29: 45991 | C29: 0 | D29: GMC023220107 | E29: GMC Premium | G29: =G28+F29-C29 -> 731215.01
B30: 45991 | G30: =G29+F30-C30 -> 731215.01
B31: 46007 | C31: 75193.002 | D31: GMC023220108 | E31: GMC Premium | G31: =G30+F31-C31 -> 656022.01
B32: 46007 | C32: 862.40219 | D32: GPA086900107 | E32: GPA Premium | G32: =G31+F32-C32 -> 655159.61
B33: 46007 | C33: 1848.5382 | D33: GPA086900108 | E33: GPA Premium | G33: =G32+F33-C33 -> 653311.07
B34: 46021 | C34: 792.56236 | D34: GPA086900109 | E34: GPA Premium | G34: =G33+F34-C34 -> 652518.51
B35: 46022 | C35: 3071.0933 | D35: GMC023220109 | E35: GMC Premium | G35: =G34+F35-C35 -> 649447.41
B36: 46021 | E36: BNPAR52025123000436980/CALDERY1/CALDERYS INDIA REFRACTORIES LIMITED | F36: 2205433 | G36: =G35+F36-C36 -> 2854880.4
B37: 46022 | G37: =G36+F37-C37 -> 2854880.4
B38: 46042 | C38: 126735.68 | D38: GMC023220110 | E38: GMC Premium | G38: =G37+F38-C38 -> 2728144.7
B39: 46042 | C39: 183.58602 | D39: GPA086900110 | E39: GPA Premium | G39: =G38+F39-C39 -> 2727961.2
B40: 46047 | C40: 704.84795 | D40: GPA086900111 | E40: GPA Premium | G40: =G39+F40-C40 -> 2727256.3
B41: 46047 | C41: 37096.867 | D41: GMC023220111 | E41: GMC Premium | G41: =G40+F41-C41 -> 2690159.4
B42: 46044 | C42: 2224851 | D42: GMC025860100 | E42: Topup Premium | G42: =G41+F42-C42 -> 465308.47
B43: 46053 | G43: =G42+F43-C43 -> 465308.47
B44: 46056 | C44: 0 | D44: GMC023220112 | E44: GMC Premium | G44: =G43+F44-C44 -> 465308.47
B45: 46067 | C45: -19420.098 | D45: GMC025860101 | E45: Topup Premium
B46: 46069 | C46: 708.55799 | D46: GPA086900112 | E46: GPA Premium | G46: =G44+F46-C46 -> 464599.91
B47: 46069 | C47: 1555.2723 | D47: GPA086900113 | E47: GPA Premium | G47: =G46+F47-C47 -> 463044.64
B48: 46069 | C48: 203155.08 | D48: GMC023220113 | E48: GMC Premium | G48: =G47+F48-C48 -> 259889.56 | H48: =SuM!C8+SuM!C14+[1]SuM!$C$8+[1]SuM!$C$14+[2]SuM!$C$8+[2]SuM!$C$14-SUM(C8:C50) -> -9.3132257e-08
B49: 46081 | G49: =G48+F49-C49 -> 259889.56

Sheet Check
A4: Row Labels | B4: Sum of No of Policies | C4: Sum of No of Person Cover Per Day | D4: aa | E4: UHID | F4: Gender | G4: Relationship | H4: Sum of Reporting Sum Insured | I4: Sum of GWP | J4: Sum of No of Person Cover Per Day | K4: aa
A5: 652306 | B5: 1 | C5: 6 | E5: ACK.4A9F3020250658.1 | F5: Female | G5: Spouse | H5: 0 | I5: 12212.54 | J5: 1
A6: 42342 | B6: 1 | C6: 6 | E6: ACK.4A9F3020250658.2 | F6: Male | G6: Self | H6: 600000 | I6: 17444.37 | J6: 1
A7: 362025 | B7: 1 | C7: 4 | E7: ACK.4A9F3020250661.1 | F7: Female | G7: Spouse | H7: 0 | I7: 6248.7 | J7: 1
A8: 42179 | B8: 1 | C8: 5 | E8: ACK.4A9F3020250661.2 | F8: Male | G8: Father | H8: 0 | I8: 20889.05 | J8: 1
A9: 362125 | B9: 1 | C9: 3 | E9: ACK.4A9F3020250661.3 | F9: Male | G9: Son | H9: 0 | I9: 3127.44 | J9: 1
A10: 42131 | B10: 1 | C10: 3 | E10: ACK.4A9F3020250661.4 | F10: Female | G10: Daughter | H10: 0 | I10: 0 | J10: 0
A11: 550049 | B11: 1 | C11: 4 | E11: ACK.4A9F3020250661.5 | F11: Male | G11: Self | H11: 300000 | I11: 6248.7 | J11: 1
A12: 652177 | B12: 1 | C12: 4 | E12: ACK.4A9F3020250078.1 | F12: Male | G12: Father | H12: 0 | I12: 18286.47 | J12: 1
A13: 362107 | B13: 1 | C13: 6 | E13: ACK.4A9F3020250078.2 | F13: Female | G13: Spouse | H13: 0 | I13: 6871.37 | J13: 1
A14: 42246 | B14: 1 | C14: 4 | E14: ACK.4A9F3020250078.3 | F14: Female | G14: Mother | H14: 0 | I14: 18286.47 | J14: 1
A15: 42145 | B15: 1 | C15: 3 | E15: ACK.4A9F3020250078.4 | F15: Male | G15: Self | H15: 400000 | I15: 6871.37 | J15: 1
A16: 42147 | B16: 1 | C16: 4 | E16: ACK.4A9F3020250659.1 | F16: Male | G16: Son | H16: 0 | I16: 0 | J16: 0
... A718: 45101 | B718: 1 | C718: 4 | E718: ACK.4A9F3020250233.3 | F718: Male | G718: Self | H718: 400000 | I718: 3841.55 | J718: 1
A719: 44921 | B719: 1 | C719: 5 | E719: ACK.4A9F3020250234.1 | F719: Male | G719: Self | H719: 400000 | I719: 3841.55 | J719: 1
A720: 45029 | B720: 1 | C720: 3 | E720: ACK.4A9F3020250234.2 | F720: Female | G720: Mother | H720: 0 | I720: 6871.37 | J720: 1
A721: 45270 | B721: 1 | C721: 4 | E721: ACK.4A9F3020250234.3 | F721: Male | G721: Father | H721: 0 | I721: 10092.99 | J721: 1
A722: 45324 | B722: 1 | C722: 2 | E722: ACK.4A9F3020250236.1 | F722: Female | G722: Daughter | H722: 0 | I722: 3127.44 | J722: 1
A723: 45326 | B723: 1 | C723: 3 | E723: ACK.4A9F3020250236.2 | F723: Male | G723: Self | H723: 300000 | I723: 4338.62 | J723: 1
A724: 45363 | B724: 1 | C724: 5 | E724: ACK.4A9F3020250236.3 | F724: Female | G724: Mother | H724: 0 | I724: 13109.28 | J724: 1
A725: 45364 | B725: 1 | C725: 2 | E725: ACK.4A9F3020250236.4 | F725: Female | G725: Spouse | H725: 0 | I725: 3495.31 | J725: 1
A726: 45367 | B726: 1 | C726: 3 | E726: ACK.4A9F3020250236.5 | F726: Male | G726: Son | H726: 0 | I726: 3127.44 | J726: 1
A727: 45325 | B727: 1 | C727: 6 | E727: ACK.4A9F3020250236.6 | F727: Male | G727: Father | H727: 0 | I727: 20889.05 | J727: 1
A728: 45353 | B728: 1 | C728: 3 | E728: ACK.4A9F3020250235.1 | F728: Male | G728: Self | H728: 300000 | I728: 3495.31 | J728: 1
A729: 45362 | B729: 1 | C729: 5 | E729: ACK.4A9F3020250235.2 | F729: Female | G729: Spouse | H729: 0 | I729: 3495.31 | J729: 1
A730: 45338 | B730: 1 | C730: 3 | E730: ACK.4A9F3020250235.3 | F730: Male | G730: Son | H730: 0 | I730: 3127.44 | J730: 1
A731: 45384 | B731: 1 | C731: 3 | E731: ACK.4A9F3020250235.4 | F731: Male | G731: Father | H731: 0 | I731: 9179.45 | J731: 1
A732: 44991 | B732: 1 | C732: 4 | E732: ACK.4A9F3020250235.5 | F732: Female | G732: Mother | H732: 0 | I732: 6248.7 | J732: 1
... A797: 45784 | B797: 1 | C797: 4 | E797: ACK.4A9F3020250016.5 | F797: Female | G797: Spouse | H797: 0 | I797: 4338.62 | J797: 1
A798: Grand Total | B798: 759 | C798: 3167 | E798: ACK.4A9F3020250016.6 | F798: Male | G798: Son | H798: 0 | I798: 3127.44 | J798: 1
E799: ACK.4A9F3020250014.1 | F799: Female | G799: Spouse | H799: 0 | I799: 3168.3617 | J799: 0
E800: ACK.4A9F3020250014.2 | F800: Female | G800: Daughter | H800: 0 | I800: 1580.163 | J800: 0
E801: ACK.4A9F3020250014.3 | F801: Female | G801: Mother | H801: 0 | I801: 11566.268 | J801: 0
E802: ACK.4A9F3020250014.4 | F802: Female | G802: Daughter | H802: 0 | I802: 1580.163 | J802: 0
E803: ACK.4A9F3020250014.5 | F803: Male | G803: Self | H803: 0 | I803: 4653.8408 | J803: 0
E804: ACK.4A9F3020250013.1 | F804: Female | G804: Mother | H804: 0 | I804: 16628.13 | J804: 1
E805: ACK.4A9F3020250013.2 | F805: Female | G805: Spouse | H805: 0 | I805: 6248.7 | J805: 1
E806: ACK.4A9F3020250013.3 | F806: Male | G806: Son | H806: 0 | I806: 3127.44 | J806: 1
E807: ACK.4A9F3020250013.4 | F807: Male | G807: Self | H807: 300000 | I807: 6248.7 | J807: 1
E808: ACK.4A9F3020250015.1 | F808: Female | G808: Spouse | H808: 0 | I808: 6871.37 | J808: 1
E809: ACK.4A9F3020250015.2 | F809: Male | G809: Son | H809: 0 | I809: 3426.98 | J809: 1
E810: ACK.4A9F3020250015.3 | F810: Male | G810: Self | H810: 400000 | I810: 10092.99 | J810: 1
... E3340: ACK.4A9F3020250716.6 | F3340: Female | G3340: Daughter | H3340: 0 | I3340: 1943.5202 | J3340: 1
E3341: Grand Total | H3341: 300500000 | I3341: 22552506 | J3341: 3167
